Workbook

Sheet Brand Experience & Activation
A1: # | B1: Tier | C1: Campaign | D1: Brand | E1: Product/Service | F1: Agency | G1: Country | H1: Subcategory | I1: Image URL | J1: YouTube ID | K1: Campaign Group | L1: Entry URL
A2: 1 | B2: Grand Prix | C2: Caption with Intention | D2: Academy of Motion Picture Arts & Sciences / Chicago Hearing Society | E2: Closed Captioning | F2: FCB Chicago | G2: United States | H2: A05 - Media/Entertainment | I2: https://ascentialcdn.filespin.io/api/v1/conversion/ae51c3c9f04d452e914dba0555d8b029 | J2: F48khKZhKHM | L2: https://www.lovethework.com/work/entries/caption-with-intention-746864
A3: 2 | B3: Gold | C3: ADS Cover Rents | D3: Brahma | E3: Beer | F3: Africa Creative DDB Sao Paulo | G3: Brazil | H3: D02 - Guerrilla Marketing | I3: https://ascentialcdn.filespin.io/api/v1/conversion/17a255fb4a7d40d79616736a9ee7914c | J3: 8R2TckoklzM | L3: https://www.lovethework.com/work/entries/ads-cover-rents-747640
A4: 3 | B4: Gold | C4: Drops of Hope | D4: Kimberly-Clark | E4: Poise | F4: FCB New York | G4: United States | H4: A01 - Consumer Goods | I4: https://ascentialcdn.filespin.io/api/v1/conversion/6b9aa5b716a6476ca0f016a3c2a0dd62 | J4: MnF0kip489Y | L4: https://www.lovethework.com/work/entries/drops-of-hope-748188
A5: 4 | B5: Gold | C5: Drops of Hope | D5: Kimberly-Clark | E5: Poise | F5: FCB New York | G5: United States | H5: E07 - Corporate Purpose | I5: https://ascentialcdn.filespin.io/api/v1/conversion/b6b3814255234c3596fcb99868c0fbb7 | J5: MnF0kip489Y | L5: https://www.lovethework.com/work/entries/drops-of-hope-748188
A6: 5 | B6: Gold | C6: Fictional Insurance | D6: RCN/Prime | E6: Insurance | F6: DDB Colombia Bogota | G6: Colombia | H6: C03 - Customer Acquisition | I6: https://ascentialcdn.filespin.io/api/v1/conversion/8466955db96a4c52b6813e12a8c63226 | J6: OctiVcwaiXI | L6: https://www.lovethework.com/work/entries/fictional-insurance-747450
A7: 6 | B7: Gold | C7: Gulf of Mexico (Bar) | D7: Tecate | E7: Tecate Light | F7: LePub Mexico City | G7: Mexico | H7: E01 - Local Brand | I7: https://ascentialcdn.filespin.io/api/v1/conversion/afa88aa8421b41a18c68b9863bb6926c | J7: TFbAS7weMR8 | L7: https://www.lovethework.com/work/entries/gulf-of-mexico-bar-747778
A8: 7 | B8: Gold | C8: Lessons of Shame | D8: World Vision | E8: Institutional | F8: Havas Costa Rica | G8: Costa Rica | H8: A07 - Not-for-Profit | I8: https://ascentialcdn.filespin.io/api/v1/conversion/71112ff9b2324f9b8f9338c809483684 | J8: YrNH2-6vqZo | L8: https://www.lovethework.com/work/entries/lessons-of-shame-746863
A9: 8 | B9: Gold | C9: Lucky Yatra | D9: Indian Railways | E9: Railway Service | F9: FCB India Mumbai | G9: India | H9: C03 - Customer Acquisition | I9: https://ascentialcdn.filespin.io/api/v1/conversion/2e252d74f69d4889b7886d241255186a | J9: IYJlZRbvMEw | L9: https://www.lovethework.com/work/entries/lucky-yatra-747400
A10: 9 | B10: Gold | C10: Price Packs | D10: Penny | E10: Food/Non-Food | F10: Serviceplan Germany | G10: Germany | H10: E08 - Market Disruption | I10: https://ascentialcdn.filespin.io/api/v1/conversion/67b6df2a0fe64deeb274c91d50040c54 | J10: cnAXR4lk6R0 | L10: https://www.lovethework.com/work/entries/price-packs-748536
A11: 10 | B11: Gold | C11: The Kimberly Price | D11: Plaza Vea | E11: Plaza Vea | F11: Fahrenheit DDB Lima | G11: Peru | H11: B01 - Social Engagement | I11: https://ascentialcdn.filespin.io/api/v1/conversion/dd37e163320440a58d69763c047eec03 | J11: pPAGka7S4_o | L11: https://www.lovethework.com/work/entries/the-kimberly-price-746894
A12: 11 | B12: Gold | C12: Winter Takes on Colors | D12: McDonald's Polska | E12: Drwala Burger | F12: DDB Warsaw | G12: Poland | H12: C01 - Customer Retail | I12: https://ascentialcdn.filespin.io/api/v1/conversion/4ff9778738a146549164d3153acb8808 | J12: qcSHtBgAB6o | L12: https://www.lovethework.com/work/entries/winter-takes-on-colors-747343
A13: 12 | B13: Silver | C13: 855-How-to-Quit-(Opioids) | D13: Anzen Health | E13: 855-How-to-Quit-Helpline | F13: Serviceplan Germany | G13: Germany | H13: A02 - Healthcare | I13: https://ascentialcdn.filespin.io/api/v1/conversion/650a86946acf45c9946d15c4d5f10c86 | J13: I_xvPLZ9DDk | L13: https://www.lovethework.com/work/entries/855-how-to-quit-opioids-746670
... A68: 67 | B68: Bronze | C68: Worst Children's Library | D68: Samsung | E68: Samsung | F68: DDB New Zealand Auckland | G68: New Zealand | H68: E04 - Social Behaviour | I68: https://ascentialcdn.filespin.io/api/v1/conversion/24a4ad960f3c4ac8a1a86823848e8d17 | J68: 2B2-joqRoHc | L68: https://www.lovethework.com/work/entries/worst-childrens-library-748079

Sheet Audio & Radio
A1: # | B1: Tier | C1: Campaign | D1: Brand | E1: Product/Service | F1: Agency | G1: Country | H1: Subcategory | I1: Image URL | J1: YouTube ID | K1: Campaign Group | L1: Entry URL
A2: 1 | B2: Grand Prix | C2: One Second Ads | D2: Budweiser | E2: Beer | F2: Africa Creative DDB | G2: Brazil | H2: B01 - Use of Music | I2: digital-presentation-images/audio-and-radio-budweiser-one-second-ads.webp | J2: RpvlshoKIrE | L2: https://www.lovethework.com/work/entries/one-second-ads-741948
A3: 2 | B3: Gold | C3: Name This Oreo | D3: Oreo | E3: Oreo | F3: VML | G3: United States | H3: A03 - Voice Activation | I3: digital-presentation-images/audio-and-radio-oreo-name-this-oreo.webp | J3: hRp6cBmbfIw | L3: https://www.lovethework.com/work/entries/name-this-oreo-741853
A4: 3 | B4: Gold | C4: One Second Ads | D4: Budweiser | E4: Beer | F4: Africa Creative DDB | G4: Brazil | H4: A06 - Audio-Led Creativity | I4: digital-presentation-images/audio-and-radio-budweiser-one-second-ads.webp | J4: RpvlshoKIrE | L4: https://www.lovethework.com/work/entries/one-second-ads-741888
A5: 4 | B5: Gold | C5: The Second Release | D5: Billboard Arabia | E5: Billboard Magazine | F5: SRMG Labs | G5: Saudi Arabia | H5: C03 - Single-Market Campaign | I5: digital-presentation-images/audio-and-radio-billboard-arabia-the-second-release.webp | J5: gD1XqvQaMR0 | L5: https://www.lovethework.com/work/entries/the-second-release-742149
A6: 5 | B6: Silver | C6: Name This Oreo | D6: Oreo | E6: Oreo | F6: VML | G6: United States | H6: A01 - Use of Audio & Radio as a Medium | I6: digital-presentation-images/audio-and-radio-oreo-name-this-oreo.webp | J6: hRp6cBmbfIw | L6: https://www.lovethework.com/work/entries/name-this-oreo-741778
A7: 6 | B7: Silver | C7: Fishermen Storytellers | D7: Corona | E7: Beer | F7: Africa Creative DDB | G7: Brazil | H7: A04 - Branded Content/Podcasts | I7: digital-presentation-images/audio-and-radio-corona-fishermen-storytellers.webp | J7: LDbcqtL9zP8 | L7: https://www.lovethework.com/work/entries/fishermen-storytellers-764514
A8: 7 | B8: Silver | C8: 1. High Energy Intern | D8: Fusion Energy Drink | E8: Energy Drink | F8: David | G8: Spain | H8: B03 - Script | I8: https://ascentialcdn.filespin.io/api/v1/storyboard/846afe3e468240929823119e42cf3b99/storyboard_000008.jpg | J8: vimeo:1093833122 | L8: https://www.lovethework.com/work/entries/1-high-energy-intern-762404
A9: 8 | B9: Silver | C9: Chill Enough | D9: Coors Light | E9: Coors Light | F9: Alma Advertising Agency | G9: United States | H9: B04 - Casting & Performance | I9: digital-presentation-images/audio-and-radio-coors-light-chill-enough.webp | J9: BqqqBYEADPg | L9: https://www.lovethework.com/work/entries/chill-enough-762433
A10: 9 | B10: Silver | C10: Burger to King | D10: Burger King | E10: Burger King | F10: Happiness, an FCB Alliance | G10: Belgium | H10: C02 - Challenger Brand | I10: digital-presentation-images/audio-and-radio-burger-king-burger-to-king.webp | J10: RQVaoU4CGRk | L10: https://www.lovethework.com/work/entries/burger-to-king-763482
A11: 10 | B11: Silver | C11: The Second Release | D11: Billboard Arabia | E11: Billboard Magazine | F11: SRMG Labs | G11: Saudi Arabia | H11: C04 - Social Behaviour | I11: digital-presentation-images/audio-and-radio-billboard-arabia-the-second-release.webp | J11: gD1XqvQaMR0 | L11: https://www.lovethework.com/work/entries/the-second-release-742142
A12: 11 | B12: Silver | C12: From Hurt to Hit | D12: Brahma | E12: Beer | F12: Africa Creative DDB | G12: Brazil | H12: C05 - Use of Humour | I12: https://ascentialcdn.filespin.io/api/v1/conversion/2c4c0601d34e42cf931304cf072f6fa8 | J12: t10NTUNmF8c | L12: https://www.lovethework.com/work/entries/from-hurt-to-hit-742107
A13: 12 | B13: Silver | C13: Me Feat. Me | D13: Nosotras | E13: Nosotras | F13: DDB Chile | G13: Chile | H13: C09 - Cultural Engagement | I13: https://ascentialcdn.filespin.io/api/v1/conversion/a6ac5c5dd4fc4487966ae01ac52f95ff | J13: KBcSEzHf5DA | L13: https://www.lovethework.com/work/entries/me-feat-me-742031
... A22: 21 | B22: Bronze | C22: Sounds Right | D22: Museum for the United Nations - UN Live, Spotify | E22: Music | F22: AKQA | G22: Denmark | H22: C07 - Corporate Purpose & Social Responsibility | I22: digital-presentation-images/audio-and-radio-museum-for-the-united-nations-sounds-right.webp | J22: 5newTxSZ9bU | L22: https://www.lovethework.com/work/entries/sounds-right-759882

Sheet Film
A1: # | B1: Tier | C1: Campaign | D1: Brand | E1: Product/Service | F1: Agency | G1: Country | H1: Subcategory | I1: Image URL | J1: YouTube ID | K1: Campaign Group | L1: Entry URL
A2: 1 | B2: Grand Prix | C2: Paris Paralympics 2024: Considering What? | D2: CHANNEL 4 | E2: CHANNEL 4 | F2: CHANNEL 4 | G2: United Kingdom | H2: A05 - Media/Entertainment | I2: digital-presentation-images/film-channel-4-paris-paralympic-2024-considering-what.webp | J2: bUs_mNTNwvE | L2: https://www.lovethework.com/work/entries/paris-paralympics-2024-considering-what-738686
A3: 2 | B3: Grand Prix | C3: The Final Copy of Ilon Specht | D3: L'ORÉAL PARIS | E3: L'ORÉAL PARIS | F3: McCANN | G3: France | H3: F07 - Corporate Purpose & Social Responsibility | I3: digital-presentation-images/film-loreal-paris-the-final-copy-of-ilona-specht.webp | J3: -4o8bCc6-GM | L3: https://www.lovethework.com/work/entries/the-final-copy-of-ilon-specht-739568
A4: 3 | B4: Gold | C4: Find Your Friends | D4: APPLE | E4: PRECISION FINDING | F4: APPLE | G4: United States | H4: B01 - Consumer Goods | I4: digital-presentation-images/film-apple-find-your-friends.webp | J4: LO4wamMlCKQ | L4: https://www.lovethework.com/work/entries/find-your-friends-738592
A5: 4 | B5: Gold | C5: Never Just a Period | D5: BODYFORM | E5: BODYFORM | F5: AMV BBDO | G5: United Kingdom | H5: B02 - Healthcare | I5: digital-presentation-images/film-bodyform-never-just-a-period.webp | J5: EQW59KR3c4U | L5: https://www.lovethework.com/work/entries/never-just-a-period-738863
A6: 5 | B6: Gold | C6: Let There Be Cake | D6: KFC THAILAND | E6: KFC 40TH | F6: BANANAS | G6: South Africa | H6: B04 - Travel, Leisure, Retail, Restaurants & Fast-Food Chains | I6: https://ascentialcdn.filespin.io/api/v1/storyboard/880f481b580e4ddbb51427137d8c2233/storyboard_000008.jpg | J6: YDaAgeyVXiw | L6: https://www.lovethework.com/work/entries/let-there-be-cake-759113
A7: 6 | B7: Gold | C7: The Last Birthday | D7: ASSOCIATION VALENTIN HAÜY | E7: Non Profit Organization - Defense of the Rights of Blind and Visually Impaired People | F7: JOSIANE | G7: France | H7: B07 - Not-For-Profit / Charity / Government | I7: digital-presentation-images/film-association-valentin-hauy-the-last-birthday.webp | J7: E4mGmGE8fC0 | L7: https://www.lovethework.com/work/entries/the-last-birthday-739026
A8: 7 | B8: Gold | C8: Telstra - Better on a Better Network | D8: TELSTRA | E8: TELSTRA | F8: BEAR MEETS EAGLE ON FIRE | G8: Australia | H8: F03 - Single-Market Campaign | I8: digital-presentation-images/film-telstra-telstra-better-on-a-better-network.webp | J8: L8wOtakkr28 | L8: https://www.lovethework.com/work/entries/telstra-better-on-a-better-network-739331
A9: 8 | B9: Gold | C9: The Best Place in the World to Have Herpes | D9: NEW ZEALAND HERPES FOUNDATION | E9: NEW ZEALAND HERPES FOUNDATION | F9: FINCH | G9: Australia | H9: F05 - Use of Humour | I9: digital-presentation-images/film-new-zealand-herpes-foundation-the-best-place-in-the-world-to-have-herpes.webp | J9: DvaU3-VCk8I | L9: https://www.lovethework.com/work/entries/the-best-place-in-the-world-to-have-herpes-739431
A10: 9 | B10: Gold | C10: Brian Cox Goes to College | D10: UBER ONE | E10: UBER ONE FOR STUDENTS | F10: SPECIAL | G10: United States | H10: F05 - Use of Humour | I10: digital-presentation-images/film-uber-one-brian-cox-goes-to-college.webp | J10: vimeo:1035756667 | L10: https://www.lovethework.com/work/entries/brian-cox-goes-to-college-739411
A11: 10 | B11: Gold | C11: Group Therapy | D11: AXA | E11: AXA | F11: VML | G11: France | H11: F05 - Use of Humour | I11: digital-presentation-images/film-axa-group-therapy.webp | J11: cH8-sNMfrOM | L11: https://www.lovethework.com/work/entries/group-therapy-739424
A12: 11 | B12: Silver | C12: Flock | D12: APPLE | E12: IPHONE | F12: TBWA\MEDIA ARTS LAB | G12: United States | H12: A01 - Consumer Goods | I12: digital-presentation-images/film-apple-flock.webp | J12: jom8zBix-4c | L12: https://www.lovethework.com/work/entries/flock-738495
A13: 12 | B13: Silver | C13: Jordan Can't Ban Greatness | D13: NIKE | E13: NIKE | F13: WIEDEN+KENNEDY | G13: United States | H13: A01 - Consumer Goods | I13: digital-presentation-images/film-nike-jordan-cant-ban-greatness.webp | J13: L-upphAEYGc | L13: https://www.lovethework.com/work/entries/jordan-cant-ban-greatness-738501
... A53: 52 | B53: Bronze | C53: Skin | D53: RAÇA MAGAZINE | E53: INSTITUTIONAL | F53: LEPUB | G53: Brazil | H53: F09 - Cultural Engagement | I53: digital-presentation-images/film-raca-magazine-skin.webp | J53: vimeo:1088284685 | L53: https://www.lovethework.com/work/entries/skin-739661

Sheet Outdoor
A1: # | B1: Tier | C1: Campaign | D1: Brand | E1: Product/Service | F1: Agency | G1: Country | H1: Subcategory | I1: Image URL | J1: YouTube ID | K1: Campaign Group | L1: Entry URL
A2: 1 | B2: Grand Prix | C2: Crowd | D2: KitKat | E2: KitKat | F2: VML | G2: Czech Republic | H2: A01 - Consumer Goods | I2: https://ascentialcdn.filespin.io/api/v1/conversion/6dc8ee87b55d449f88c8f8a0868b533a | J2: ByGNQ3wEbEY | K2: kitkat-a01-consumer-goods | L2: https://www.lovethework.com/work/entries/crowd-740225
A3: 2 | B3: Grand Prix | C3: Public Transport | D3: KitKat | E3: KitKat | F3: VML | G3: Czech Republic | H3: A01 - Consumer Goods | I3: https://ascentialcdn.filespin.io/api/v1/conversion/9b1fc196d863402282277d81f4bdf031 | J3: ByGNQ3wEbEY | K3: kitkat-a01-consumer-goods | L3: https://www.lovethework.com/work/entries/public-transport-758659
A4: 3 | B4: Grand Prix | C4: Street | D4: KitKat | E4: KitKat | F4: VML | G4: Czech Republic | H4: A01 - Consumer Goods | I4: https://ascentialcdn.filespin.io/api/v1/conversion/ad97fbb0d50649118006eac4d5a902a7 | J4: ByGNQ3wEbEY | K4: kitkat-a01-consumer-goods | L4: https://www.lovethework.com/work/entries/street-758667
A5: 4 | B5: Grand Prix | C5: Olympic Games Opening Ceremony Paris 2024 | D5: Paris 2024 | E5: Paris 2024 | F5: PANAME 24 | G5: France | H5: C04 - Live Advertising and Events | I5: https://ascentialcdn.filespin.io/api/v1/conversion/60aa1888e5b6444381b060dc1801de84 | J5: t8o4ulxT1Cc | L5: https://www.lovethework.com/work/entries/olympic-games-opening-ceremony-paris-2024-740923
A6: 5 | B6: Gold | C6: The Sip of Sanctuary | D6: Stella Artois | E6: Stella Artois | F6: GREY | G6: United Kingdom | H6: A01 - Consumer Goods | I6: https://ascentialcdn.filespin.io/api/v1/conversion/bc046e548975443980453424bc30515a | K6: stella-artois-philosophical | L6: https://www.lovethework.com/work/entries/the-sip-of-sanctuary-740333
A7: 6 | B7: Gold | C7: Protector of the Chalice | D7: Stella Artois | E7: Stella Artois | F7: GREY | G7: United Kingdom | H7: A01 - Consumer Goods | I7: https://ascentialcdn.filespin.io/api/v1/conversion/a33c9462c05d4330895b056745b6a602 | K7: stella-artois-philosophical | L7: https://www.lovethework.com/work/entries/protector-of-the-chalice-740342
A8: 7 | B8: Gold | C8: Happiness Within Chaos | D8: Stella Artois | E8: Stella Artois | F8: GREY | G8: United Kingdom | H8: A01 - Consumer Goods | I8: https://ascentialcdn.filespin.io/api/v1/conversion/882ea591b6fa40b29a529180b71afa65 | K8: stella-artois-philosophical | L8: https://www.lovethework.com/work/entries/happiness-within-chaos-740351
A9: 8 | B9: Gold | C9: Fries | D9: Heinz | E9: Heinz | F9: Wieden+Kennedy | G9: United Kingdom | H9: B01 - Consumer Goods | I9: https://ascentialcdn.filespin.io/api/v1/conversion/9e7a10af468b4293bb13624b6ac695d7 | J9: GR2NjU6fhZw | K9: heinz-b01-consumer-goods | L9: https://www.lovethework.com/work/entries/fries-740416
A10: 9 | B10: Gold | C10: Chips | D10: Heinz | E10: Heinz | F10: Wieden+Kennedy | G10: United Kingdom | H10: B01 - Consumer Goods | I10: https://ascentialcdn.filespin.io/api/v1/conversion/98502860304b486096f96cbacf35f7ac | J10: 9HpJtpvtrhs | K10: heinz-b01-consumer-goods | L10: https://www.lovethework.com/work/entries/chips-740534
A11: 10 | B11: Gold | C11: Toast | D11: Heinz | E11: Heinz | F11: Wieden+Kennedy | G11: United Kingdom | H11: B01 - Consumer Goods | I11: https://ascentialcdn.filespin.io/api/v1/conversion/19b79ceaf445400d88e358d61316e067 | J11: keOaQm6RpBg | K11: heinz-b01-consumer-goods | L11: https://www.lovethework.com/work/entries/toast-740549
A12: 11 | B12: Gold | C12: Scratch & Sniff | D12: Axe/Lynx | E12: Deodorant | F12: LOLA MullenLowe | G12: Spain | H12: C01 - Displays | I12: https://ascentialcdn.filespin.io/api/v1/conversion/a4189a00c22b49558f6796c1b0fdf90c | J12: L5RfU7Jmoug | L12: https://www.lovethework.com/work/entries/scratch-sniff-740665
A13: 12 | B13: Gold | C13: Shades of Red | D13: Coca-Cola | E13: Coca-Cola Company | F13: DAVID | G13: Spain | H13: C03 - Special Build | I13: https://ascentialcdn.filespin.io/api/v1/conversion/b9b1ac806434448cb6648aa308f263db | J13: 7kRgxEIhX38 | K13: coca-cola-shades-of-red | L13: https://www.lovethework.com/work/entries/shades-of-red-740785
A14: 13 | B14: Gold | C14: Missed Birthdays | D14: ITV X CALM | E14: ITV X CALM | F14: adam&eveDDB | G14: United Kingdom | H14: C04 - Live Advertising and Events | I14: https://ascentialcdn.filespin.io/api/v1/conversion/238b3e3f0aab4c3fa9adf2b23d50eab3 | J14: ifZVZ4fX4gg | L14: https://www.lovethework.com/work/entries/missed-birthdays-740958
A15: 14 | B15: Gold | C15: Tracking Bad Bunny | D15: Rimas Music | E15: Bad Bunny | F15: DDB Latina Puerto Rico | G15: Puerto Rico | H15: C05 - Interactive Experiences | I15: https://ascentialcdn.filespin.io/api/v1/conversion/8c433c0437494277a7cb3b8c1148b82c | J15: -3Aq3u6EJZ4 | L15: https://www.lovethework.com/work/entries/tracking-bad-bunny-759229
A16: 15 | B16: Gold | C16: Gulf of Mexico (Bar) | D16: Tecate | E16: Tecate Light | F16: LePub | G16: Mexico | H16: E01 - Local Brand | I16: https://ascentialcdn.filespin.io/api/v1/conversion/afa88aa8421b41a18c68b9863bb6926c | J16: TFbAS7weMR8 | L16: https://www.lovethework.com/work/entries/gulf-of-mexico-bar-741350
A17: 16 | B17: Gold | C17: Price Packs | D17: Penny | E17: Food/Non-Food | F17: Serviceplan Germany | G17: Germany | H17: E02 - Challenger Brand | I17: https://ascentialcdn.filespin.io/api/v1/conversion/67b6df2a0fe64deeb274c91d50040c54 | J17: cnAXR4lk6R0 | L17: https://www.lovethework.com/work/entries/price-packs-741243
A18: 17 | B18: Gold | C18: Lucky Yatra | D18: Indian Railways | E18: Railway Service | F18: FCB India | G18: India | H18: E04 - Social Behaviour | I18: https://ascentialcdn.filespin.io/api/v1/conversion/7771593e59654e55b2c0654f5d61ec8e | J18: IYJlZRbvMEw | L18: https://www.lovethework.com/work/entries/lucky-yatra-741463
A19: 18 | B19: Silver | C19: Windsurf | D19: Cornetto | E19: Cornetto Ice Cream | F19: LOLA MullenLowe | G19: Spain | H19: B01 - Consumer Goods | I19: https://ascentialcdn.filespin.io/api/v1/conversion/2f9ebcc7b9ec4ad9a4dcf79bd56fa88b | J19: hWhvFLwHOlE | K19: cornetto-b01-consumer-goods | L19: https://www.lovethework.com/work/entries/windsurf-740535
A20: 19 | B20: Silver | C20: Surfer | D20: Cornetto | E20: Cornetto Ice Cream | F20: LOLA MullenLowe | G20: Spain | H20: B01 - Consumer Goods | I20: https://ascentialcdn.filespin.io/api/v1/conversion/9ceaf650a007496f90b6d5670786b4df | J20: hWhvFLwHOlE | K20: cornetto-b01-consumer-goods | L20: https://www.lovethework.com/work/entries/surfer-740546
A21: 20 | B21: Silver | C21: Waves | D21: Cornetto | E21: Cornetto Ice Cream | F21: LOLA MullenLowe | G21: Spain | H21: B01 - Consumer Goods | I21: https://ascentialcdn.filespin.io/api/v1/conversion/35c567148f6e40e1a267849bde62ba92 | J21: hWhvFLwHOlE | K21: cornetto-b01-consumer-goods | L21: https://www.lovethework.com/work/entries/waves-740554
A22: 21 | B22: Silver | C22: Boat | D22: Cornetto | E22: Cornetto Ice Cream | F22: LOLA MullenLowe | G22: Spain | H22: B01 - Consumer Goods | I22: https://ascentialcdn.filespin.io/api/v1/conversion/3a177c8b37754037a19ddf0d99c858db | J22: hWhvFLwHOlE | K22: cornetto-b01-consumer-goods | L22: https://www.lovethework.com/work/entries/boat-740365
A23: 22 | B23: Silver | C23: Bundles of Joy OOH2 | D23: Burger King UK | E23: Whopper | F23: BBH | G23: United Kingdom | H23: B04 - Travel, Leisure, Retail, Restaurants & Fast-Food Chains | I23: digital-presentation-images/outdoor-burger-king-bundles-of-joy-ooh2.webp | J23: aVzEfsIC9KQ | K23: burger-king-uk-b04-travel-leisure-retail-restaurants-fast-food-chains | L23: https://www.lovethework.com/work/entries/bundles-of-joy-ooh2-740450
A24: 23 | B24: Silver | C24: Bundles of Joy OOH1 | D24: Burger King UK | E24: Whopper | F24: BBH | G24: United Kingdom | H24: B04 - Travel, Leisure, Retail, Restaurants & Fast-Food Chains | I24: digital-presentation-images/outdoor-burger-king-bundles-of-joy-ooh1.webp | J24: aVzEfsIC9KQ | K24: burger-king-uk-b04-travel-leisure-retail-restaurants-fast-food-chains | L24: https://www.lovethework.com/work/entries/bundles-of-joy-ooh1-740460
A25: 24 | B25: Silver | C25: Bundles of Joy OOH4 | D25: Burger King UK | E25: Whopper | F25: BBH | G25: United Kingdom | H25: B04 - Travel, Leisure, Retail, Restaurants & Fast-Food Chains | I25: digital-presentation-images/outdoor-burger-king-bundles-of-joy-ooh4.webp | J25: aVzEfsIC9KQ | K25: burger-king-uk-b04-travel-leisure-retail-restaurants-fast-food-chains | L25: https://www.lovethework.com/work/entries/bundles-of-joy-ooh4-740466
A26: 25 | B26: Silver | C26: Bundles of Joy OOH3 | D26: Burger King UK | E26: Whopper | F26: BBH | G26: United Kingdom | H26: B04 - Travel, Leisure, Retail, Restaurants & Fast-Food Chains | I26: digital-presentation-images/outdoor-burger-king-bundles-of-joy-ooh3.webp | J26: aVzEfsIC9KQ | K26: burger-king-uk-b04-travel-leisure-retail-restaurants-fast-food-chains | L26: https://www.lovethework.com/work/entries/bundles-of-joy-ooh3-762361
A27: 26 | B27: Silver | C27: 'Til I Died | D27: British Heart Foundation | E27: British Heart Foundation | F27: Saatchi & Saatchi | G27: United Kingdom | H27: C01 - Displays | I27: https://ascentialcdn.filespin.io/api/v1/conversion/7c797fcbd4784d318b810a3e30777a8a | J27: jB_R0uQ_qcg | L27: https://www.lovethework.com/work/entries/til-i-died-740701
A28: 27 | B28: Silver | C28: Winter Takes on Colors | D28: McDonald's Polska | E28: Drwala Burger (Limited Timed Offer) | F28: DDB Warsaw | G28: Poland | H28: C03 - Special Build | I28: https://ascentialcdn.filespin.io/api/v1/conversion/5c6b7faa74e6455a830e3ef1f22b78d7 | J28: qcSHtBgAB6o | L28: https://www.lovethework.com/work/entries/winter-takes-on-colors-740759
A29: 28 | B29: Silver | C29: Night Signals | D29: Chevrolet Dominican Republic | E29: Chevrolet | F29: Ogilvy Dominican Republic | G29: Dominican Republic | H29: C06 - Transit | I29: https://ascentialcdn.filespin.io/api/v1/conversion/08a2258d5d1348b1bc8f6014ff0c6655 | J29: XVCXMuUU9s8 | L29: https://www.lovethework.com/work/entries/night-signals-741104
A30: 29 | B30: Silver | C30: Speed Coupons | D30: Mercado Livre | E30: Mercado Livre | F30: GUT | G30: Brazil | H30: D01 - Standard Sites | I30: https://ascentialcdn.filespin.io/api/v1/conversion/7e353b967fd64b6692fd97647bd4fbd2 | J30: l3Sxq8LCXZA | L30: https://www.lovethework.com/work/entries/speed-coupons-741121
A31: 30 | B31: Silver | C31: Sun Reserve | D31: Corona | E31: Corona | F31: GREY | G31: Brazil | H31: D02 - Ambient Outdoor | I31: https://ascentialcdn.filespin.io/api/v1/conversion/652b705dcecc4cb7a72c76e4e22c80e5 | J31: 7i2fC6qJR2o | L31: https://www.lovethework.com/work/entries/sun-reserve-741012
A32: 31 | B32: Silver | C32: The Philharmonic Prints | D32: Berliner Philharmonie | E32: Berliner Philharmoniker | F32: Scholz & Friends | G32: Germany | H32: E01 - Local Brand | I32: https://ascentialcdn.filespin.io/api/v1/conversion/a41ca6a9e9454bb585e089d1abcf0187 | J32: 6JuPo6BNhqU | L32: https://www.lovethework.com/work/entries/the-philharmonic-prints-741191
A33: 32 | B33: Silver | C33: See Them for Real | D33: Musée de l'Armée | E33: Museum | F33: Buzzman | G33: France | H33: E02 - Challenger Brand | I33: https://ascentialcdn.filespin.io/api/v1/conversion/f23ad7b894c14298b819130d99bc560f | J33: vimeo:1162577214 | L33: https://www.lovethework.com/work/entries/see-them-for-real-741246
A34: 33 | B34: Silver | C34: Bumpboards | D34: Citroen | E34: Citroen | F34: BETC | G34: France | H34: E03 - Single-Market Campaign | I34: https://ascentialcdn.filespin.io/api/v1/conversion/51f7223ae6f6484caace1b6d0e8df74c | J34: Qh8iW06HWYI | L34: https://www.lovethework.com/work/entries/bumpboards-741287
A35: 34 | B35: Silver | C35: Balikbayan Magic: Philippine Oriental Food Market | D35: Coca-Cola | E35: Coca-Cola | F35: VML | G35: Canada | H35: E04 - Social Behaviour | I35: digital-presentation-images/outdoor-coca-cola-balikbayan-magic-philippine-oriental-food-market.webp | J35: 8WbE3jyFeM8 | L35: https://www.lovethework.com/work/entries/balikbayan-magic-philippine-oriental-food-market-741455
A36: 35 | B36: Silver | C36: Meet Me at the Coke Sign | D36: Coca-Cola | E36: Coca-Cola | F36: Ogilvy | G36: Australia | H36: E04 - Social Behaviour | I36: https://ascentialcdn.filespin.io/api/v1/conversion/e4e51d450eb8458dab81e55d80f5d56b | J36: V2RVAsIFjF0 | L36: https://www.lovethework.com/work/entries/meet-me-at-the-coke-sign-741472
A37: 36 | B37: Silver | C37: Nature Shapes Britannia | D37: Britannia Industries Ltd. | E37: Britannia Sustainability | F37: Talented | G37: India | H37: E06 - Breakthrough on a Budget | I37: https://ascentialcdn.filespin.io/api/v1/conversion/716b17d07a0d40d2b7b2a29d2ae9e171 | J37: dEC4Wo3ZlXQ | L37: https://www.lovethework.com/work/entries/nature-shapes-britannia-741532
A38: 37 | B38: Silver | C38: Too Yumm to Cheer\! | D38: Too Yumm\! | E38: Too Yumm\! | F38: FCB Kinnect | G38: India | H38: E06 - Breakthrough on a Budget | I38: https://ascentialcdn.filespin.io/api/v1/conversion/cb9c8fa9b4464dc6bdc84535bb7991d5 | J38: 2Kf-xAN5WCI | L38: https://www.lovethework.com/work/entries/too-yumm-to-cheer-741592
... A44: 43 | B44: Bronze | C44: 'The Shining' | D44: Coca-Cola | E44: Coca-Cola | F44: VML | G44: United States | H44: A01 - Consumer Goods | I44: https://ascentialcdn.filespin.io/api/v1/conversion/44405bf6f33b4e919c5b283211199392 | J44: vimeo:1124237531 | L44: https://www.lovethework.com/work/entries/the-shining-740263
A45: 44 | B45: Bronze | C45: Mimi's Red | D45: Coca-Cola | E45: Coca-Cola Company | F45: DAVID | G45: Spain | H45: A01 - Consumer Goods | I45: https://ascentialcdn.filespin.io/api/v1/conversion/476f91b3c4024d889f9c5a3071d2af7f | J45: ELBlWKeEqQQ | K45: coca-cola-shades-of-red | L45: https://www.lovethework.com/work/entries/mimis-red-740318
A46: 45 | B46: Bronze | C46: Prado's Red | D46: Coca-Cola | E46: Coca-Cola Company | F46: DAVID | G46: Spain | H46: A01 - Consumer Goods | I46: https://ascentialcdn.filespin.io/api/v1/conversion/9d778b6a2550440b9a1b11e17c7ad280 | J46: VGa1imApfdg | K46: coca-cola-shades-of-red | L46: https://www.lovethework.com/work/entries/prados-red-740326
A47: 46 | B47: Bronze | C47: El Campo's Red | D47: Coca-Cola | E47: Coca-Cola Company | F47: DAVID | G47: Spain | H47: A01 - Consumer Goods | I47: https://ascentialcdn.filespin.io/api/v1/conversion/cc0c84dd54874fdea4173e4874a381c3 | J47: WcQDr4HxPKU | K47: coca-cola-shades-of-red | L47: https://www.lovethework.com/work/entries/el-campos-red-740334
A48: 47 | B48: Bronze | C48: Corona Eclipse - Uruguay | D48: Corona | E48: Corona | F48: DAVID | G48: United States | H48: A01 - Consumer Goods | I48: https://ascentialcdn.filespin.io/api/v1/conversion/77eb12aacaf340e1b7d9e79c99556281 | J48: ViJvHO9BxvU | K48: corona-a01-consumer-goods | L48: https://www.lovethework.com/work/entries/corona-eclipse-uruguay-740235
A49: 48 | B49: Bronze | C49: Corona Eclipse - Argentina 1 | D49: Corona | E49: Corona | F49: DAVID | G49: United States | H49: A01 - Consumer Goods | I49: https://ascentialcdn.filespin.io/api/v1/conversion/923c26278b3042ac83d908e11d20b46c | J49: pitw8c1AXpI | K49: corona-a01-consumer-goods | L49: https://www.lovethework.com/work/entries/corona-eclipse-argentina-1-740248
A50: 49 | B50: Bronze | C50: Corona Eclipse - Argentina 2 | D50: Corona | E50: Corona | F50: DAVID | G50: United States | H50: A01 - Consumer Goods | I50: https://ascentialcdn.filespin.io/api/v1/conversion/7a260b4ceb6f4f7c998edf6aa5b09344 | J50: pitw8c1AXpI | K50: corona-a01-consumer-goods | L50: https://www.lovethework.com/work/entries/corona-eclipse-argentina-2-740260
A51: 50 | B51: Bronze | C51: Price Packs - Chips | D51: Penny | E51: Food/Non-Food | F51: Serviceplan Germany | G51: Germany | H51: A04 - Travel, Leisure, Retail, Restaurants & Fast-Food Chains | I51: https://ascentialcdn.filespin.io/api/v1/conversion/27ff97121fa2498480c1c23ae148604d | J51: wXx6z3mDnVc | K51: penny-a04-travel-leisure-retail-restaurants-fast-food-chains | L51: https://www.lovethework.com/work/entries/price-packs-chips-740364
A52: 51 | B52: Bronze | C52: Price Packs - Oatmeal | D52: Penny | E52: Food/Non-Food | F52: Serviceplan Germany | G52: Germany | H52: A04 - Travel, Leisure, Retail, Restaurants & Fast-Food Chains | I52: https://ascentialcdn.filespin.io/api/v1/conversion/c3069b2a659a442aaabf5389719b9fa6 | J52: cnAXR4lk6R0 | K52: penny-a04-travel-leisure-retail-restaurants-fast-food-chains | L52: https://www.lovethework.com/work/entries/price-packs-oatmeal-740376
A53: 52 | B53: Bronze | C53: Price Packs - Toast | D53: Penny | E53: Food/Non-Food | F53: Serviceplan Germany | G53: Germany | H53: A04 - Travel, Leisure, Retail, Restaurants & Fast-Food Chains | I53: https://ascentialcdn.filespin.io/api/v1/conversion/0f62d161bf704e03bcece90e78e11d29 | J53: 7GVxwv6ZNfw | K53: penny-a04-travel-leisure-retail-restaurants-fast-food-chains | L53: https://www.lovethework.com/work/entries/price-packs-toast-740385
A54: 53 | B54: Bronze | C54: The Sip of Sanctuary | D54: Stella Artois | E54: Stella Artois | F54: GREY | G54: United Kingdom | H54: B01 - Consumer Goods | I54: https://ascentialcdn.filespin.io/api/v1/conversion/bc046e548975443980453424bc30515a | K54: stella-artois-philosophical | L54: https://www.lovethework.com/work/entries/the-sip-of-sanctuary-740553
A55: 54 | B55: Bronze | C55: Happiness Within Chaos | D55: Stella Artois | E55: Stella Artois | F55: GREY | G55: United Kingdom | H55: B01 - Consumer Goods | I55: https://ascentialcdn.filespin.io/api/v1/conversion/882ea591b6fa40b29a529180b71afa65 | K55: stella-artois-philosophical | L55: https://www.lovethework.com/work/entries/happiness-within-chaos-740366
A56: 55 | B56: Bronze | C56: Protector of the Chalice | D56: Stella Artois | E56: Stella Artois | F56: GREY | G56: United Kingdom | H56: B01 - Consumer Goods | I56: https://ascentialcdn.filespin.io/api/v1/conversion/a33c9462c05d4330895b056745b6a602 | K56: stella-artois-philosophical | L56: https://www.lovethework.com/work/entries/protector-of-the-chalice-740439
A57: 56 | B57: Bronze | C57: Likes | D57: History Channel | E57: History Channel | F57: Dentsu Creative | G57: Portugal | H57: B05 - Media/Entertainment | I57: https://ascentialcdn.filespin.io/api/v1/conversion/9e6eef6a84b640f9b2da45ad47d321c9 | J57: 5xRoKPmsEDI | K57: history-channel-b05-media-entertainment | L57: https://www.lovethework.com/work/entries/likes-763469
A58: 57 | B58: Bronze | C58: Marches | D58: History Channel | E58: History Channel | F58: Dentsu Creative | G58: Portugal | H58: B05 - Media/Entertainment | I58: https://ascentialcdn.filespin.io/api/v1/conversion/848c6f5fe00a4cc2be171136fcd87b87 | J58: H6qzUSoN2Pc | K58: history-channel-b05-media-entertainment | L58: https://www.lovethework.com/work/entries/marches-763480
A59: 58 | B59: Bronze | C59: Crimes | D59: History Channel | E59: History Channel | F59: Dentsu Creative | G59: Portugal | H59: B05 - Media/Entertainment | I59: https://ascentialcdn.filespin.io/api/v1/conversion/2aba4c2194414c37b9cf328c0dcc193f | J59: SDME83-pHnQ | K59: history-channel-b05-media-entertainment | L59: https://www.lovethework.com/work/entries/crimes-763490
A60: 59 | B60: Bronze | C60: Signs from Heaven | D60: Pangu Cloud | E60: Pangu Meteorological Model | F60: Ogilvy | G60: China | H60: C01 - Displays | I60: https://ascentialcdn.filespin.io/api/v1/conversion/09dbff10bf5e4eaeae2d578fe9cc19b0 | J60: CLTN81ECv6E | L60: https://www.lovethework.com/work/entries/signs-from-heaven-740708
A61: 60 | B61: Bronze | C61: Smile 20 | D61: Goody's Pain Powder | E61: Goody's Pain Powder | F61: FCB Chicago | G61: United States | H61: C02 - Interactive/Dynamic Digital Screens | I61: https://ascentialcdn.filespin.io/api/v1/conversion/102f0d648c284c6e98ed2de341d6a49d | J61: vimeo:1081666376 | L61: https://www.lovethework.com/work/entries/smile-20-740676
A62: 61 | B62: Bronze | C62: Carrefoursa - Ghost Town | D62: Carrefoursa | E62: Retail | F62: TBWA\Istanbul | G62: Turkey | H62: C03 - Special Build | I62: https://ascentialcdn.filespin.io/api/v1/conversion/7aeda253bc4a4f4e8c659c64a4721596 | J62: 0tKFbogECr4 | L62: https://www.lovethework.com/work/entries/carrefoursa-ghost-town-740781
A63: 62 | B63: Bronze | C63: Chai Bansuri - the Tea Flute | D63: Unilever | E63: Brooke Bond Taj Mahal Tea | F63: Ogilvy | G63: India | H63: C04 - Live Advertising and Events | I63: https://ascentialcdn.filespin.io/api/v1/conversion/b79b43804eae486ea54374794321d26f | J63: rUaCL7lrVa4 | L63: https://www.lovethework.com/work/entries/chai-bansuri-the-tea-flute-740791
A64: 63 | B64: Bronze | C64: Worst Children's Library | D64: Samsung | E64: Samsung | F64: DDB New Zealand | G64: New Zealand | H64: C05 - Interactive Experiences | I64: https://ascentialcdn.filespin.io/api/v1/conversion/0e92a3c97dfe4f05b663ae448b0f27d4 | J64: VGa1imApfdg | L64: https://www.lovethework.com/work/entries/worst-childrens-library-740810
A65: 64 | B65: Bronze | C65: Mayo Exchange | D65: Hellmann's | E65: Hellmann's Mayonnaise | F65: Edelman | G65: United Kingdom | H65: C05 - Interactive Experiences | I65: https://ascentialcdn.filespin.io/api/v1/conversion/2f963ba6e5b3402fb58a7907daa78953 | J65: 4NpEnDNRwc0 | L65: https://www.lovethework.com/work/entries/mayo-exchange-740956
A66: 65 | B66: Bronze | C66: Touchboards Discount | D66: Itaú Unibanco | E66: Bank | F66: Africa Creative DDB | G66: Brazil | H66: C05 - Interactive Experiences | I66: https://ascentialcdn.filespin.io/api/v1/conversion/e14b84bfe13a475898db5ad4b54d8a97 | J66: vimeo:1136599182 | L66: https://www.lovethework.com/work/entries/touchboards-discount-740763
A67: 66 | B67: Bronze | C67: Followers Store | D67: New Balance | E67: New Balance | F67: LePub | G67: Brazil | H67: C06 - Transit | I67: https://ascentialcdn.filespin.io/api/v1/conversion/3f6078e96a9a4e17acada7c2ad04d652 | J67: uYskstOPF4U | L67: https://www.lovethework.com/work/entries/followers-store-741098
A68: 67 | B68: Bronze | C68: Lucky Yatra | D68: Indian Railways | E68: Railway Service | F68: FCB India | G68: India | H68: C06 - Transit | I68: https://ascentialcdn.filespin.io/api/v1/conversion/cf238077a73e4204aff7e28913d98b1d | J68: IYJlZRbvMEw | L68: https://www.lovethework.com/work/entries/lucky-yatra-741094
A69: 68 | B69: Bronze | C69: Hidden Message | D69: Heineken | E69: Heineken | F69: LePub | G69: Italy | H69: D03 - Technology | I69: https://ascentialcdn.filespin.io/api/v1/conversion/459dc31c901d4c3385f219939e6621a9 | J69: PPtbr6aJ7_A | L69: https://www.lovethework.com/work/entries/hidden-message-741175
A70: 69 | B70: Bronze | C70: The Shaded Route | D70: HungerStation | E70: HungerStation Delivery App | F70: VML | G70: Saudi Arabia | H70: D03 - Technology | I70: https://ascentialcdn.filespin.io/api/v1/conversion/a5387631458b48648c6dba4b21efb3d0 | J70: NZcCfqEoFoo | L70: https://www.lovethework.com/work/entries/the-shaded-route-741203
A71: 70 | B71: Bronze | C71: Winning Isn't Comfortable | D71: Nike | E71: Nike | F71: Wieden+Kennedy | G71: United States | H71: E04 - Social Behaviour | I71: digital-presentation-images/outdoor-nike-winning-isnt-comfortable.webp | J71: FFFmnfdBrm8 | L71: https://www.lovethework.com/work/entries/winning-isnt-comfortable-741524
... A78: 77 | B78: Bronze | C78: Aeromexicanos | D78: Aeromexico | E78: Aeromexico | F78: Ogilvy | G78: Mexico | H78: E09 - Cultural Engagement | I78: https://ascentialcdn.filespin.io/api/v1/conversion/f9f2a8cb575c498084f110de98272a4a | J78: 6MDBJbej100 | L78: https://www.lovethework.com/work/entries/aeromexicanos-741588

Sheet Design
A1: # | B1: Tier | C1: Campaign | D1: Brand | E1: Product/Service | F1: Agency | G1: Country | H1: Subcategory | I1: Image URL | J1: YouTube ID | K1: Campaign Group | L1: Entry URL
A2: 1 | B2: Grand Prix | C2: Caption with Intention | D2: Academy of Motion Picture Arts & Sciences / Chicago Hearing Society | E2: Closed Captioning | F2: FCB Chicago | G2: United States | H2: B01 - Inclusive Design | I2: https://ascentialcdn.filespin.io/api/v1/conversion/1a22539ff6e94e288d6a3aa1a3a9ace5 | J2: F48khKZhKHM | L2: https://www.lovethework.com/work/entries/caption-with-intention-758922
A3: 2 | B3: Gold | C3: AirPods Pro 2 Hearing Aid Feature | D3: Apple | E3: AirPods Pro 2 | F3: Apple | G3: United States | H3: A04 - Product Design | I3: https://ascentialcdn.filespin.io/api/v1/conversion/d124f3704bf34fe8a63e19e8325d9220 | J3: OzScknoWq6U | L3: https://www.lovethework.com/work/entries/airpods-pro-2-hearing-aid-feature-748829
A4: 3 | B4: Gold | C4: Nigrum Corpus | D4: Idomed | E4: Nigrum Corpus | F4: Artplan | G4: Brazil | H4: A06 - Books | I4: https://ascentialcdn.filespin.io/api/v1/conversion/83e9fc2a93254c029a34755ff3c96853 | J4: RCK4iiCB2P0 | L4: https://www.lovethework.com/work/entries/nigrum-corpus-764511
A5: 4 | B5: Gold | C5: CarrefourSA - Ghost Town | D5: CarrefourSA | E5: Retail | F5: TBWA\Istanbul | G5: Turkey | H5: A08 - Brand Environment & Experience Design | I5: https://ascentialcdn.filespin.io/api/v1/conversion/a8b0865217084e348df3921cebc7c41f | J5: 0tKFbogECr4 | L5: https://www.lovethework.com/work/entries/carrefoursa-ghost-town-748805
A6: 5 | B6: Gold | C6: Spreadbeats | D6: Spotify | E6: Spotify | F6: FCB New York | G6: United States | H6: A09 - Design-Driven Effectiveness | I6: https://ascentialcdn.filespin.io/api/v1/conversion/4ebdb10e5b80456a925dc283ac7e501a | J6: Z_lbVlhO9HE | L6: https://www.lovethework.com/work/entries/spreadbeats-748953
A7: 6 | B7: Silver | C7: Spreadbeats | D7: Spotify | E7: Spotify | F7: FCB New York | G7: United States | H7: A07 - Digital Design | I7: https://ascentialcdn.filespin.io/api/v1/conversion/1cc1b629542a4d1db92e5b0d90116de7 | J7: Z_lbVlhO9HE | L7: https://www.lovethework.com/work/entries/spreadbeats-748925
A8: 7 | B8: Silver | C8: Price Packs | D8: Penny | E8: Food/Non-Food | F8: Serviceplan Germany | G8: Germany | H8: A09 - Design-Driven Effectiveness | I8: https://ascentialcdn.filespin.io/api/v1/conversion/67b6df2a0fe64deeb274c91d50040c54 | J8: cnAXR4lk6R0 | L8: https://www.lovethework.com/work/entries/price-packs-748846
A9: 8 | B9: Silver | C9: The Shakespeare BIC | D9: BIC | E9: BIC Crystal Pen | F9: VML | G9: Brazil | H9: A11 - Special Editions & Bespoke Items | I9: https://ascentialcdn.filespin.io/api/v1/conversion/352257f3d008491e95e0ccbdfe8a4469 | J9: 5ngNVTeyi4g | L9: https://www.lovethework.com/work/entries/the-shakespeare-bic-749146
A10: 9 | B10: Silver | C10: Sounds of the Land | D10: Billboard Arabia | E10: Billboard Arabia | F10: SRMG Labs | G10: Saudi Arabia | H10: A14 - Promotional Items/Promotional Printed Media | I10: https://ascentialcdn.filespin.io/api/v1/conversion/19a407ae77ab4664baed61135cc5ae9f | J10: gD1XqvQaMR0 | L10: https://www.lovethework.com/work/entries/sounds-of-the-land-758892
A11: 10 | B11: Silver | C11: Code My Crown | D11: Dove | E11: Dove | F11: Edelman | G11: United Kingdom | H11: B01 - Inclusive Design | I11: https://ascentialcdn.filespin.io/api/v1/conversion/dc773a5191b947ea85626af886046a69 | J11: stQ442QJ9pg | L11: https://www.lovethework.com/work/entries/code-my-crown-749303
A12: 11 | B12: Silver | C12: 1837 Tiffany Blue Conservation | D12: Tiffany & Co. | E12: Tiffany & Co. | F12: L&C | G12: United States | H12: B02 - Sustainability-Focused Design | I12: https://ascentialcdn.filespin.io/api/v1/conversion/a9e8fdb5892d441587b7c4c55eb3d5fb | J12: npGswWNcZC8 | L12: https://www.lovethework.com/work/entries/1837-tiffany-blue-conservation-749213
A13: 12 | B13: Silver | C13: Fixables | D13: Philips | E13: Philips Personal Care | F13: LePub | G13: Netherlands | H13: B02 - Sustainability-Focused Design | I13: https://ascentialcdn.filespin.io/api/v1/conversion/9e978f653c5c45cf903985a90708656d | J13: grgsxQjK0B4 | L13: https://www.lovethework.com/work/entries/fixables-761443
... A32: 31 | B32: Bronze | C32: Fixables | D32: Philips | E32: Philips Personal Care | F32: LePub | G32: Netherlands | H32: B05 - Design for Behavioural Change | I32: https://ascentialcdn.filespin.io/api/v1/conversion/9e978f653c5c45cf903985a90708656d | J32: grgsxQjK0B4 | L32: https://www.lovethework.com/work/entries/fixables-761474

Sheet Media
A1: # | B1: Tier | C1: Campaign | D1: Brand | E1: Product/Service | F1: Agency | G1: Country | H1: Subcategory | I1: Image URL | J1: YouTube ID | K1: Campaign Group | L1: Entry URL
A2: 1 | B2: Grand Prix | C2: Dove Real Beauty Redefined for the AI Era | D2: Dove | E2: Dove | F2: Mindshare | G2: United States | H2: E01 - Media Insights & Strategy | I2: https://ascentialcdn.filespin.io/api/v1/conversion/da693fd61fc74ddfbb3525f638cd77c6 | J2: 8vYoL8nga-A | L2: https://www.lovethework.com/work/entries/dove-real-beauty-redefined-for-the-ai-era-746537
A3: 2 | B3: Gold | C3: Can't Unsee It | D3: Heinz Ketchup & Mustard | E3: Kraft Heinz | F3: Rethink | G3: Canada | H3: A01 - Consumer Goods | I3: https://ascentialcdn.filespin.io/api/v1/conversion/3db7ec7e31b7459bafa082009489d40e | J3: itiHi3WYcSs | L3: https://www.lovethework.com/work/entries/cant-unsee-it-745091
A4: 3 | B4: Gold | C4: Vaseline Verified | D4: Unilever | E4: Vaseline | F4: Ogilvy | G4: Singapore | H4: A02 - Healthcare | I4: https://ascentialcdn.filespin.io/api/v1/conversion/faf0755b0d4e4594ad93cb75d6288e3d | J4: ApwxlBruV90 | L4: https://www.lovethework.com/work/entries/vaseline-verified-745075
A5: 4 | B5: Gold | C5: Redditor Edit | D5: Skoda | E5: Automotive | F5: PHD | G5: United Kingdom | H5: A03 - Automotive | I5: https://ascentialcdn.filespin.io/api/v1/conversion/fa18cc31eca84cf2a41f8d9f4a3e8e89 | J5: KmLMtKsmwqA | L5: https://www.lovethework.com/work/entries/redditor-edit-744990
A6: 5 | B6: Gold | C6: Coupon Rain | D6: Mercado Livre | E6: Mercado Livre | F6: GUT | G6: Brazil | H6: A04 - Travel, Leisure, Retail, Restaurants & Fast-Food Chains | I6: https://ascentialcdn.filespin.io/api/v1/conversion/5418c22c9d864f579ce966a3f138628e | J6: RXw_xdHILoU | L6: https://www.lovethework.com/work/entries/coupon-rain-745092
A7: 6 | B7: Gold | C7: The Final Exam | D7: Change the Ref | E7: Pro Bono | F7: Energy BBDO | G7: United States | H7: A07 - Not-for-Profit / Charity / Government | I7: https://ascentialcdn.filespin.io/api/v1/conversion/615e3a15eabf457d91d317468a12d825 | J7: Ljsstj4eiko | L7: https://www.lovethework.com/work/entries/the-final-exam-761015
A8: 7 | B8: Gold | C8: Streaming Bars | D8: Heineken | E8: Heineken | F8: LePub | G8: Brazil | H8: B01 - Use of Screens & Audio Visual Platforms | I8: https://ascentialcdn.filespin.io/api/v1/conversion/d0be42343a2e4aaea76238ca95dfcbab | J8: 0izbOb7N73g | L8: https://www.lovethework.com/work/entries/streaming-bars-745041
A9: 8 | B9: Gold | C9: "Raise Your Banners" | D9: HBO | E9: House of the Dragon Season 2 | F9: Giant Spoon | G9: United States | H9: B06 - Large-Scale Media | I9: https://ascentialcdn.filespin.io/api/v1/conversion/8568fb79e86c4ae994a024b682498651 | J9: S-r_T-LZBR0 | L9: https://www.lovethework.com/work/entries/raise-your-banners-745396
A10: 9 | B10: Gold | C10: Retro Influencers | D10: Skol | E10: Skol | F10: GUT | G10: Brazil | H10: B10 - Use of Social Platforms | I10: https://ascentialcdn.filespin.io/api/v1/conversion/8d30857fd8bf46f3ab1b9c9b3d0a50fa | J10: FKLnmbWukt0 | L10: https://www.lovethework.com/work/entries/retro-influencers-745595
A11: 10 | B11: Gold | C11: The Rewards Bag | D11: Tata | E11: Tata | F11: VML | G11: Uruguay | H11: B13 - Retail Media | I11: https://ascentialcdn.filespin.io/api/v1/conversion/9d355715dd4d4857a2f82df5c502290b | J11: RzJQ1TVItHI | L11: https://www.lovethework.com/work/entries/the-rewards-bag-745869
A12: 11 | B12: Gold | C12: Fictional Insurance | D12: RCN/Prime | E12: Insurance | F12: DDB Colombia | G12: Colombia | H12: C02 - Use of Brand or Product Integration into a Programme or Platform | I12: https://ascentialcdn.filespin.io/api/v1/conversion/9f879201572d4cb9aa1e14e89b6a4f2f | J12: OctiVcwaiXI | L12: https://www.lovethework.com/work/entries/fictional-insurance-745946
A13: 12 | B13: Gold | C13: First Ever Live Commercial Crossover | D13: Rocket | E13: Rocket | F13: Zenith | G13: United States | H13: E03 - Media Execution | I13: https://ascentialcdn.filespin.io/api/v1/conversion/c8c6d973823e408c926f4de68327d5df | J13: oF6A79XVZsc | L13: https://www.lovethework.com/work/entries/first-ever-live-commercial-crossover-759386
... A67: 66 | B67: Bronze | C67: Timeout Against Hate | D67: Foundation to Combat Antisemitism | E67: Foundation to Combat Antisemitism | F67: Mindshare | G67: United States | H67: E02 - Media Planning | I67: https://ascentialcdn.filespin.io/api/v1/conversion/e43c43ae03f240ed8fbaf95002d5d795 | J67: vimeo:1083894799 | L67: https://www.lovethework.com/work/entries/timeout-against-hate-746540

Sheet Film Craft
A1: # | B1: Tier | C1: Campaign | D1: Brand | E1: Product/Service | F1: Agency | G1: Country | H1: Subcategory | I1: Image URL | J1: YouTube ID | K1: Campaign Group | L1: Entry URL
A2: 1 | B2: Grand Prix | C2: TELSTRA - BETTER ON A BETTER NETWORK | D2: TELSTRA | E2: TELSTRA | F2: BEAR MEETS EAGLE ON FIRE | G2: Australia | H2: Animation | I2: digital-presentation-images/film-craft-telstra-telstra-better-on-a-better-network.webp | J2: L8wOtakkr28 | K2: telstra-better-on-a-better-network | L2: https://www.lovethework.com/work/entries/telstra-better-on-a-better-network-765315
A3: 2 | B3: Gold | C3: TELSTRA - BETTER ON A BETTER NETWORK | D3: TELSTRA | E3: TELSTRA | F3: BEAR MEETS EAGLE ON FIRE | G3: Australia | H3: Production Design/Art Direction | I3: digital-presentation-images/film-craft-telstra-telstra-better-on-a-better-network.webp | J3: L8wOtakkr28 | K3: telstra-better-on-a-better-network | L3: https://www.lovethework.com/work/entries/telstra-better-on-a-better-network-765311
A4: 3 | B4: Gold | C4: CONSIDERING WHAT? | D4: CHANNEL 4 | E4: PARALYMPICS 2024 | F4: WORK EDITORIAL | G4: United Kingdom | H4: Editing | I4: https://ascentialcdn.filespin.io/api/v1/storyboard/10fba32c76a941749debf9069e930560/storyboard_000008.jpg | J4: bUs_mNTNwvE | L4: https://www.lovethework.com/work/entries/considering-what-765324
A5: 4 | B5: Gold | C5: GUAO GUAO | D5: DESPERADOS | E5: DESPERADOS | F5: LEPUB | G5: Italy | H5: Casting | I5: digital-presentation-images/film-craft-desperados-guao-guao.webp | J5: N58e8-bziA0 | L5: https://www.lovethework.com/work/entries/guao-guao-765356
A6: 5 | B6: Gold | C6: FIND YOUR FRIENDS | D6: APPLE | E6: PRECISION FINDING | F6: APPLE | G6: United States | H6: Use of Licensed/Adapted Music | I6: digital-presentation-images/film-craft-apple-find-your-friends.webp | J6: LO4wamMlCKQ | L6: https://www.lovethework.com/work/entries/find-your-friends-765322
A7: 6 | B7: Gold | C7: PARIS PARALYMPICS 2024: CONSIDERING WHAT? | D7: CHANNEL 4 | E7: CHANNEL 4 | F7: BISCUIT FILMWORKS | G7: United Kingdom | H7: Direction | I7: https://ascentialcdn.filespin.io/api/v1/storyboard/70b14ba69a8a40b7b9b991d15ac41e79/storyboard_000008.jpg | J7: 2np3KfLrA_M | L7: https://www.lovethework.com/work/entries/paris-paralympics-2024-considering-what-765981
A8: 7 | B8: Gold | C8: A TALE AS OLD AS WEBSITES | D8: SQUARESPACE | E8: SQUARESPACE | F8: SQUARESPACE | G8: United States | H8: Direction | I8: digital-presentation-images/film-craft-squarespace-a-tale-as-old-as-websites.webp | J8: LXQtg237SKY | L8: https://www.lovethework.com/work/entries/a-tale-as-old-as-websites-765346
A9: 8 | B9: Gold | C9: DONKEY | D9: TELSTRA | E9: TELSTRA | F9: REVOLVER | G9: Australia | H9: Direction | I9: digital-presentation-images/film-craft-telstra-donkey.webp | J9: vimeo:1028285893 | K9: telstra-donkey | L9: https://www.lovethework.com/work/entries/donkey-765344
A10: 9 | B10: Gold | C10: A$AP ROCKY - TAILOR SWIF | D10: A$AP ROCKY | E10: A$AP ROCKY | F10: ICONOCLAST | G10: United States | H10: Direction | I10: https://ascentialcdn.filespin.io/api/v1/storyboard/7819511744634f7a81824e1b2a278ae1/storyboard_000008.jpg | J10: 5URefVYaJrA | L10: https://www.lovethework.com/work/entries/aap-rocky-tailor-swif-765317
A11: 10 | B11: Gold | C11: RENAULT - ARGENTINA | D11: RENAULT | E11: RENAULT E-TECH | F11: PUBLICIS CONSEIL | G11: France | H11: Cinematography | I11: digital-presentation-images/film-craft-renault-renault-argentina.webp | J11: IQovoot_ZUM | L11: https://www.lovethework.com/work/entries/renault-argentina-766426
A12: 11 | B12: Silver | C12: GUAO GUAO | D12: DESPERADOS | E12: DESPERADOS | F12: LEPUB | G12: Italy | H12: Use of Original Music | I12: digital-presentation-images/film-craft-desperados-guao-guao.webp | J12: N58e8-bziA0 | L12: https://www.lovethework.com/work/entries/guao-guao-765357
A13: 12 | B13: Silver | C13: MOMENTS | D13: VOLVO | E13: VOLVO EX90 | F13: STENDAHLS | G13: Sweden | H13: Editing | I13: https://ascentialcdn.filespin.io/api/v1/storyboard/346a403fc27b4b2db49c84361f4c8081/storyboard_000008.jpg | J13: cQX-QXxwGvA | L13: https://www.lovethework.com/work/entries/moments-765347
A14: 13 | B14: Silver | C14: NIKE "SUNSHINE" | D14: NIKE | F14: TRAFIK | H14: Colour Correction/Grading | I14: https://ascentialcdn.filespin.io/api/v1/storyboard/b9ed0aae1ae84082882cb4a1ec460780/storyboard_000008.jpg | J14: FFFmnfdBrm8 | L14: https://www.lovethework.com/work/entries/nike-sunshine-765328
A15: 14 | B15: Silver | C15: A TALE AS OLD AS WEBSITES | D15: SQUARESPACE | E15: SQUARESPACE | F15: SQUARESPACE | G15: United States | H15: Casting | I15: digital-presentation-images/film-craft-squarespace-a-tale-as-old-as-websites.webp | J15: LXQtg237SKY | L15: https://www.lovethework.com/work/entries/a-tale-as-old-as-websites-765331
A16: 15 | B16: Silver | C16: FLOCK | D16: APPLE | E16: IPHONE | F16: TBWA\MEDIA ARTS LAB | G16: United States | H16: Animation | I16: digital-presentation-images/film-craft-apple-flock.webp | J16: jom8zBix-4c | K16: apple-flock | L16: https://www.lovethework.com/work/entries/flock-765354
A17: 16 | B17: Silver | C17: MOMENTS | D17: VOLVO | E17: VOLVO EX90 | F17: STENDAHLS | G17: Sweden | H17: Cinematography | I17: https://ascentialcdn.filespin.io/api/v1/storyboard/346a403fc27b4b2db49c84361f4c8081/storyboard_000008.jpg | J17: cQX-QXxwGvA | L17: https://www.lovethework.com/work/entries/moments-765347
A18: 17 | B18: Silver | C18: IN HOT WATER | D18: WORLD WILDLIFE FUND (WWF) | E18: WWF | F18: NOMINT | G18: United Kingdom | H18: Animation | I18: digital-presentation-images/film-craft-world-wildlife-fund-wwf-in-hot-water.webp | J18: vimeo:1028875237 | L18: https://www.lovethework.com/work/entries/in-hot-water-765332
A19: 18 | B19: Silver | C19: DONKEY | D19: TELSTRA | E19: TELSTRA | F19: REVOLVER | G19: Australia | H19: Production Design/Art Direction | I19: digital-presentation-images/film-craft-telstra-donkey.webp | J19: vimeo:1028285893 | K19: telstra-donkey | L19: https://www.lovethework.com/work/entries/donkey-765336
A20: 19 | B20: Silver | C20: COFFIN | D20: LIFE360 | E20: LIFE360 | F20: ALTO | G20: United States | H20: Direction | I20: https://ascentialcdn.filespin.io/api/v1/storyboard/3cd320dd9fcd4445a86f756e25d0402e/storyboard_000008.jpg | J20: hlqerWZSCpE | L20: https://www.lovethework.com/work/entries/coffin-765342
A21: 20 | B21: Silver | C21: RENAULT - ARGENTINA | D21: RENAULT | E21: RENAULT E-TECH | F21: PUBLICIS CONSEIL | G21: France | H21: Production Design/Art Direction | I21: digital-presentation-images/film-craft-renault-renault-argentina.webp | J21: IQovoot_ZUM | L21: https://www.lovethework.com/work/entries/renault-argentina-765345
A22: 21 | B22: Silver | C22: A$AP ROCKY - TAILOR SWIF | D22: A$AP ROCKY | E22: A$AP ROCKY | F22: ICONOCLAST | G22: United States | H22: Production Design/Art Direction | I22: https://ascentialcdn.filespin.io/api/v1/storyboard/7819511744634f7a81824e1b2a278ae1/storyboard_000008.jpg | J22: 5URefVYaJrA | L22: https://www.lovethework.com/work/entries/aap-rocky-tailor-swif-765343
A23: 22 | B23: Silver | C23: BELIEVE IN CHICKEN | D23: KFC | E23: FOOD (FRIED CHICKEN) | F23: MOTHER | G23: United Kingdom | H23: Use of Original Music | I23: digital-presentation-images/film-craft-kfc-believe-in-chicken.webp | J23: Pb4SnxpJLyE | L23: https://www.lovethework.com/work/entries/believe-in-chicken-765320
A24: 23 | B24: Bronze | C24: FLOCK | D24: APPLE | E24: IPHONE | F24: TBWA\MEDIA ARTS LAB | G24: United States | H24: Editing | I24: digital-presentation-images/film-craft-apple-flock.webp | J24: jom8zBix-4c | K24: apple-flock | L24: https://www.lovethework.com/work/entries/flock-765363
A25: 24 | B25: Bronze | C25: EVERYTHING OR NOTHING | D25: RIYADH SEASON | E25: BOXING FIGHT | F25: BIGTIME CREATIVE SHOP | G25: Saudi Arabia | H25: Production Design/Art Direction | I25: https://ascentialcdn.filespin.io/api/v1/storyboard/99b51143eb5a45779617eee2310c73e0/storyboard_000008.jpg | J25: vimeo:987240751 | L25: https://www.lovethework.com/work/entries/everything-or-nothing-765340
A26: 25 | B26: Bronze | C26: NEVER JUST A PERIOD | D26: BODYFORM | E26: BODYFORM | F26: AMV BBDO | G26: United Kingdom | H26: Direction | I26: digital-presentation-images/film-craft-bodyform-never-just-a-period.webp | J26: EQW59KR3c4U | L26: https://www.lovethework.com/work/entries/never-just-a-period-765319
A27: 26 | B27: Bronze | C27: 18 MONTHS | D27: SECOND NURTURE | E27: CHARITY | F27: KLICK HEALTH | G27: Canada | H27: Animation | I27: digital-presentation-images/film-craft-second-nurture-18-months.webp | J27: vimeo:1092249009 | L27: https://www.lovethework.com/work/entries/18-months-765335
A28: 27 | B28: Bronze | C28: THE SHOOTING | D28: LA UNIÓN NEWSPAPER / ARTICULO 19 | E28: LA UNIÃN NEWSPAPER / ARTICULO 19 | F28: GREY | G28: Mexico | H28: Direction | I28: digital-presentation-images/film-craft-la-union-newspaper-the-shooting.webp | J28: -saAXmItj_U | L28: https://www.lovethework.com/work/entries/the-shooting-765350
A29: 28 | B29: Bronze | C29: A TALE AS OLD AS WEBSITES | D29: SQUARESPACE | E29: SQUARESPACE | F29: SQUARESPACE | G29: United States | H29: Production Design/Art Direction | I29: digital-presentation-images/film-craft-squarespace-a-tale-as-old-as-websites.webp | J29: LXQtg237SKY | L29: https://www.lovethework.com/work/entries/a-tale-as-old-as-websites-765338
A30: 29 | B30: Bronze | C30: WITH LOVE, ITALY | D30: NESTLE | E30: SANPELLEGRINO CIAO! | F30: OGILVY | G30: United States | H30: Script | I30: digital-presentation-images/film-craft-nestle-with-love-italy.webp | J30: k0CfyHTmb4Q | L30: https://www.lovethework.com/work/entries/with-love-italy-765329
A31: 30 | B31: Bronze | C31: OBSESSION | D31: RIYADH SEASON | E31: BOXING FIGHT | F31: BIGTIME CREATIVE SHOP | G31: Saudi Arabia | H31: Visual Effects | I31: digital-presentation-images/film-craft-riyadh-season-obsession.webp | J31: PdcUQwAtDDs | L31: https://www.lovethework.com/work/entries/obsession-765355
A32: 31 | B32: Bronze | C32: SUBMERGED | D32: APPLE | E32: VISION PRO | F32: APPLE | G32: United States | H32: Achievement in Production | I32: digital-presentation-images/film-craft-apple-submerged.webp | J32: lP8LLIjCe6Q | L32: https://www.lovethework.com/work/entries/submerged-765360
A33: 32 | B33: Bronze | C33: KFC: BELIEVE IN CHICKEN | D33: KFC | E33: FOOD (FRIED CHICKEN) | F33: LUX ARTISTS | G33: United Kingdom | H33: Cinematography | I33: digital-presentation-images/film-craft-kfc-believe-in-chicken.webp | J33: Pb4SnxpJLyE | L33: https://www.lovethework.com/work/entries/kfc-believe-in-chicken-765358
A34: 33 | B34: Bronze | C34: NAME THE BIAS | D34: PEOPLE LIKE US | E34: PEOPLE LIKE US | F34: NEW LAND | G34: Denmark | H34: Cinematography | I34: https://ascentialcdn.filespin.io/api/v1/storyboard/78d81508b5494a40bba8366f2f62eed1/storyboard_000008.jpg | J34: 3uTwt6FYX98 | L34: https://www.lovethework.com/work/entries/name-the-bias-765351
A35: 34 | B35: Bronze | C35: FIGHT FOR THAIS' GUT | D35: DUTCHIE | E35: DUTCHIE | F35: OGILVY | G35: Thailand | H35: Casting | I35: digital-presentation-images/film-craft-dutchie-fight-for-thais-gut.webp | J35: vimeo:1152947690 | L35: https://www.lovethework.com/work/entries/fight-for-thais-gut-765333
A36: 35 | B36: Bronze | C36: WHEN YOU'VE DONE ENOUGH - EVIL'D ENOUGH | D36: UBER EATS | E36: FOOD DELIVERY SERVICE | F36: MOTHER | G36: United Kingdom | H36: Casting | I36: https://ascentialcdn.filespin.io/api/v1/storyboard/9e327b1cbb6d4295ae6a602857eb395c/storyboard_000008.jpg | J36: W3q1PQGXaps | L36: https://www.lovethework.com/work/entries/when-youve-done-enough-evild-enough-765334
... A50: 49 | B50: Bronze | C50: WALRUS WHIZZER | D50: VIRGIN | E50: VIRGIN MEDIA | F50: UNTOLD STUDIOS | G50: United Kingdom | H50: Visual Effects | I50: https://ascentialcdn.filespin.io/api/v1/storyboard/a7d2b86e8d154d35bb56d32c7d6f43ca/storyboard_000008.jpg | J50: VJ2TZs9WJng | L50: https://www.lovethework.com/work/entries/walrus-whizzer-765353

Sheet Summary
A1: Audio & Radio — Cannes Lions 2025
A3: Tier | B3: Count
A4: Grand Prix | B4: =COUNTIF('Audio & Radio'!B:B,"Grand Prix")
A5: Gold | B5: =COUNTIF('Audio & Radio'!B:B,"Gold")
A6: Silver | B6: =COUNTIF('Audio & Radio'!B:B,"Silver")
A7: Bronze | B7: =COUNTIF('Audio & Radio'!B:B,"Bronze")
A8: Total | B8: =SUM(B4:B7)
A10: Brand Experience & Activation — Cannes Lions 2025
A12: Tier | B12: Count
A13: Grand Prix | B13: =COUNTIF('Brand Experience & Activation'!B:B,"Grand Prix")
A14: Gold | B14: =COUNTIF('Brand Experience & Activation'!B:B,"Gold")
A15: Silver | B15: =COUNTIF('Brand Experience & Activation'!B:B,"Silver")
A16: Bronze | B16: =COUNTIF('Brand Experience & Activation'!B:B,"Bronze")
A17: Total | B17: =SUM(B13:B16)
A19: Design — Cannes Lions 2025
A21: Tier | B21: Count
A22: Grand Prix | B22: =COUNTIF('Design'!B:B,"Grand Prix")
A23: Gold | B23: =COUNTIF('Design'!B:B,"Gold")
A24: Silver | B24: =COUNTIF('Design'!B:B,"Silver")
A25: Bronze | B25: =COUNTIF('Design'!B:B,"Bronze")
A26: Total | B26: =SUM(B22:B25)
A28: Film — Cannes Lions 2025
A30: Tier | B30: Count
A31: Grand Prix | B31: =COUNTIF('Film'!B:B,"Grand Prix")
A32: Gold | B32: =COUNTIF('Film'!B:B,"Gold")
A33: Silver | B33: =COUNTIF('Film'!B:B,"Silver")
A34: Bronze | B34: =COUNTIF('Film'!B:B,"Bronze")
A35: Total | B35: =SUM(B31:B34)
A37: Film Craft — Cannes Lions 2025
A39: Tier | B39: Count
A40: Grand Prix | B40: =COUNTIF('Film Craft'!B:B,"Grand Prix")
A41: Gold | B41: =COUNTIF('Film Craft'!B:B,"Gold")
A42: Silver | B42: =COUNTIF('Film Craft'!B:B,"Silver")
A43: Bronze | B43: =COUNTIF('Film Craft'!B:B,"Bronze")
A44: Total | B44: =SUM(B40:B43)
A46: Media — Cannes Lions 2025
A48: Tier | B48: Count
A49: Grand Prix | B49: =COUNTIF('Media'!B:B,"Grand Prix")
A50: Gold | B50: =COUNTIF('Media'!B:B,"Gold")
A51: Silver | B51: =COUNTIF('Media'!B:B,"Silver")
A52: Bronze | B52: =COUNTIF('Media'!B:B,"Bronze")
A53: Total | B53: =SUM(B49:B52)
A55: Outdoor — Cannes Lions 2025
A57: Tier | B57: Count
A58: Grand Prix | B58: =COUNTIF('Outdoor'!B:B,"Grand Prix")
A59: Gold | B59: =COUNTIF('Outdoor'!B:B,"Gold")
A60: Silver | B60: =COUNTIF('Outdoor'!B:B,"Silver")
A61: Bronze | B61: =COUNTIF('Outdoor'!B:B,"Bronze")
A62: Total | B62: =SUM(B58:B61)
A64: Grand Prix for Good — Cannes Lions 2025
A66: Tier | B66: Count
A67: Grand Prix | B67: =COUNTIF('Grand Prix for Good'!B:B,"Grand Prix")
A68: Gold | B68: =COUNTIF('Grand Prix for Good'!B:B,"Gold")
A69: Silver | B69: =COUNTIF('Grand Prix for Good'!B:B,"Silver")
A70: Bronze | B70: =COUNTIF('Grand Prix for Good'!B:B,"Bronze")
A71: Total | B71: =SUM(B67:B70)
A73: Glass - The Lion for Change — Cannes Lions 2025
A75: Tier | B75: Count
A76: Grand Prix | B76: =COUNTIF('Glass - The Lion for Change'!B:B,"Grand Prix")
A77: Gold | B77: =COUNTIF('Glass - The Lion for Change'!B:B,"Gold")
A78: Silver | B78: =COUNTIF('Glass - The Lion for Change'!B:B,"Silver")
A79: Bronze | B79: =COUNTIF('Glass - The Lion for Change'!B:B,"Bronze")
A80: Total | B80: =SUM(B76:B79)
A82: Creative Bus. Transformation — Cannes Lions 2025
A84: Tier | B84: Count
A85: Grand Prix | B85: =COUNTIF('Creative Bus. Transformation'!B:B,"Grand Prix")
A86: Gold | B86: =COUNTIF('Creative Bus. Transformation'!B:B,"Gold")
A87: Silver | B87: =COUNTIF('Creative Bus. Transformation'!B:B,"Silver")
A88: Bronze | B88: =COUNTIF('Creative Bus. Transformation'!B:B,"Bronze")
A89: Total | B89: =SUM(B85:B88)
A91: Luxury — Cannes Lions 2025
A93: Tier | B93: Count
A94: Grand Prix | B94: =COUNTIF('Luxury'!B:B,"Grand Prix")
A95: Gold | B95: =COUNTIF('Luxury'!B:B,"Gold")
A96: Silver | B96: =COUNTIF('Luxury'!B:B,"Silver")
A97: Bronze | B97: =COUNTIF('Luxury'!B:B,"Bronze")
A98: Total | B98: =SUM(B94:B97)
A100: Innovation — Cannes Lions 2025
A102: Tier | B102: Count
A103: Grand Prix | B103: =COUNTIF('Innovation'!B:B,"Grand Prix")
A104: Gold | B104: =COUNTIF('Innovation'!B:B,"Gold")
A105: Silver | B105: =COUNTIF('Innovation'!B:B,"Silver")
A106: Bronze | B106: =COUNTIF('Innovation'!B:B,"Bronze")
A107: Total | B107: =SUM(B103:B106)
A109: Pharma — Cannes Lions 2025
A111: Tier | B111: Count
A112: Grand Prix | B112: =COUNTIF('Pharma'!B:B,"Grand Prix")
A113: Gold | B113: =COUNTIF('Pharma'!B:B,"Gold")
A114: Silver | B114: =COUNTIF('Pharma'!B:B,"Silver")
A115: Bronze | B115: =COUNTIF('Pharma'!B:B,"Bronze")
A116: Total | B116: =SUM(B112:B115)
A118: Entertainment Lions for Gaming — Cannes Lions 2025
A120: Tier | B120: Count
A121: Grand Prix | B121: =COUNTIF('Entertainment Lions for Gaming'!B:B,"Grand Prix")
A122: Gold | B122: =COUNTIF('Entertainment Lions for Gaming'!B:B,"Gold")
A123: Silver | B123: =COUNTIF('Entertainment Lions for Gaming'!B:B,"Silver")
A124: Bronze | B124: =COUNTIF('Entertainment Lions for Gaming'!B:B,"Bronze")
A125: Total | B125: =SUM(B121:B124)
A127: Creative B2B — Cannes Lions 2025
A129: Tier | B129: Count
...

Sheet Grand Prix for Good
A1: # | B1: Tier | C1: Campaign | D1: Brand | E1: Product/Service | F1: Agency | G1: Country | H1: Subcategory | I1: Image URL | J1: YouTube ID | K1: Campaign Group | L1: Entry URL
A2: 1 | B2: Grand Prix | C2: THE BEST PLACE IN THE WORLD TO HAVE HERPES | D2: NEW ZEALAND HERPES FOUNDATION | E2: NEW ZEALAND HERPES FOUNDATION | F2: FINCH | G2: Australia | H2: Grand Prix for Good | I2: digital-presentation-images/grand-prix-for-good-new-zealand-herpes-foundation-the-best-place-in-the-world-to-have-herpes.webp | J2: vimeo:1083074994 | L2: https://www.lovethework.com/work/entries/the-best-place-in-the-world-to-have-herpes-767497

Sheet Glass - The Lion for Change
A1: # | B1: Tier | C1: Campaign | D1: Brand | E1: Product/Service | F1: Agency | G1: Country | H1: Subcategory | I1: Image URL | J1: YouTube ID | K1: Campaign Group | L1: Entry URL
A2: 1 | B2: Grand Prix | C2: REAL BEAUTY: HOW A SOAP BRAND CREATED A GLOBAL SELF-ESTEEM MOVEMENT | D2: DOVE | E2: DOVE | F2: OGILVY UK | G2: United Kingdom | H2: Long-Term Brand Platform | I2: https://ascentialcdn.filespin.io/api/v1/conversion/f68a5a2f3d844f2b9e241462ec640c44 | J2: puQ0PNZ1W-A | L2: https://www.lovethework.com/work/entries/real-beauty-how-a-soap-brand-created-a-global-self-esteem-movement-754479
A3: 2 | B3: Gold | C3: HERALBONY | D3: HERALBONY, HERALBONY CO. | E3: HERALBONY | F3: LTD. | G3: Japan | H3: Product/Service | I3: https://ascentialcdn.filespin.io/api/v1/conversion/88e24a7cf24b40a590af455059ceeaf9 | J3: vimeo:1093399082 | L3: https://www.lovethework.com/work/entries/heralbony-754170
A4: 3 | B4: Silver | C4: THE PEN TO RIGHT HISTORY | D4: LAST PRISONER PROJECT | E4: NON-FOR-PROFIT | F4: McCANN | G4: United States | H4: Initiatives | I4: https://ascentialcdn.filespin.io/api/v1/conversion/5c13816c86fa4023933a56ac6d5c3593 | J4: SDME83-pHnQ | L4: https://www.lovethework.com/work/entries/the-pen-to-right-history-762088
A5: 4 | B5: Silver | C5: AXA - THREE WORDS | D5: AXA | E5: INSURANCE | F5: PUBLICIS CONSEIL | G5: France | H5: Product/Service | I5: https://ascentialcdn.filespin.io/api/v1/conversion/e1a85ff134e545c7b049791151432028 | J5: pY-03zuV7mE | L5: https://www.lovethework.com/work/entries/axa-three-words-754295
A6: 5 | B6: Bronze | C6: DOVE LOVE YOUR HAIR | D6: UNILEVER | E6: DOVE HAIR CARE | F6: EDELMAN | G6: United States | H6: Long-Term Brand Platform | I6: https://ascentialcdn.filespin.io/api/v1/conversion/bb0973df9f0d4e1e83e3c9ef7dc4d714 | J6: vimeo:1093399067 | L6: https://www.lovethework.com/work/entries/dove-love-your-hair-760237
A7: 6 | B7: Bronze | C7: LIVEFEARLESS | D7: BODYFORM | E7: BODYFORM | F7: AMV BBDO | G7: United Kingdom | H7: Long-Term Brand Platform | I7: https://ascentialcdn.filespin.io/api/v1/conversion/fdf9d053919448b2bf6bc7e2604789c5 | J7: vimeo:1093400188 | L7: https://www.lovethework.com/work/entries/livefearless-754488
A8: 7 | B8: Bronze | C8: HER DOME | D8: GOVERNMENT OF THE STATE OF SAO PAULO | E8: GOVERNMENT OF THE STATE OF SÃO PAULO - WOMEN'S SAFETY | F8: DPZ | G8: Brazil | H8: Technology | I8: https://ascentialcdn.filespin.io/api/v1/conversion/785860d791fe410495aecad052809d64 | J8: vimeo:1093399045 | L8: https://www.lovethework.com/work/entries/her-dome-754187
A9: 8 | B9: Bronze | C9: GRAD IN BLACK | D9: VULT | E9: HAIR PRODUCT LINE | F9: GUT | G9: Brazil | H9: Product/Service | I9: https://ascentialcdn.filespin.io/api/v1/conversion/2488030bdfa840c99e3568fe7b1001d2 | J9: vimeo:1033200856 | L9: https://www.lovethework.com/work/entries/grad-in-black-762134

Sheet Creative Bus. Transformation
A1: # | B1: Tier | C1: Campaign | D1: Brand | E1: Product/Service | F1: Agency | G1: Country | H1: Subcategory | I1: Image URL | J1: YouTube ID | K1: Campaign Group | L1: Entry URL
A2: 1 | B2: Grand Prix | C2: AXA - THREE WORDS | D2: AXA | E2: INSURANCE | F2: PUBLICIS CONSEIL | G2: France | H2: Transformative Strategy | I2: digital-presentation-images/creative-business-transformation-axa-axa-three-words.webp | J2: pY-03zuV7mE | L2: https://www.lovethework.com/work/entries/axa-three-words-757718
A3: 2 | B3: Gold | C3: LUCKY YATRA | D3: INDIAN RAILWAYS | E3: RAILWAY SERVICE | F3: FCB INDIA | G3: India | H3: Targeting, Insights & Personalisation | I3: digital-presentation-images/creative-business-transformation-indian-railways-lucky-yatra.webp | J3: 19fzAvuFq0I | L3: https://www.lovethework.com/work/entries/lucky-yatra-757794
A4: 3 | B4: Silver | C4: BUILDING A MORE RESILIENT AUSTRALIA | D4: SUNCORP | E4: INSURANCE | F4: LEO | G4: Australia | H4: Long-Term Brand Platform | I4: digital-presentation-images/creative-business-transformation-suncorp-building-a-more-resilient-australia.webp | J4: vimeo:1094885092 | L4: https://www.lovethework.com/work/entries/building-a-more-resilient-australia-757856
A5: 4 | B5: Silver | C5: RENAULT - LONG-TERM | D5: RENAULT | E5: AUTOMOTIVE | F5: PUBLICIS CONSEIL | G5: France | H5: Long-Term Brand Platform | I5: https://ascentialcdn.filespin.io/api/v1/storyboard/f4d05b0940354e91afbb9acbfc09d056/storyboard_000008.jpg | J5: GYWg2HktW-0 | L5: https://www.lovethework.com/work/entries/renault-long-term-757900
A6: 5 | B6: Bronze | C6: RECIPE FOR GROWTH | D6: IFOOD | E6: IFOOD B2B | F6: DM9 | G6: Brazil | H6: Transformative Strategy | I6: digital-presentation-images/creative-business-transformation-ifood-recipe-for-growth.webp | J6: vimeo:1080197730 | L6: https://www.lovethework.com/work/entries/recipe-for-growth-757609
A7: 6 | B7: Bronze | C7: IT'S A CHEETOS THING | D7: CHEETOS | PEPSICO | E7: CHEETOS | F7: GOODBY SILVERSTEIN & PARTNERS | G7: United States | H7: Long-Term Brand Platform | I7: digital-presentation-images/creative-business-transformation-cheetos-pepsico-its-a-cheetos-thing.webp | J7: vimeo:1094791063 | L7: https://www.lovethework.com/work/entries/its-a-cheetos-thing-765189
A8: 7 | B8: Bronze | C8: BACKING THE BARS | D8: HEINEKEN | E8: HEINEKEN | F8: LEPUB | G8: Italy | H8: Long-Term Brand Platform | I8: https://ascentialcdn.filespin.io/api/v1/conversion/9d89a2d0441e4f1498beb7e41712ebbf | J8: r2mR8LV53PE | L8: https://www.lovethework.com/work/entries/backing-the-bars-762510

Sheet Luxury
A1: # | B1: Tier | C1: Campaign | D1: Brand | E1: Product/Service | F1: Agency | G1: Country | H1: Subcategory | I1: Image URL | J1: YouTube ID | K1: Campaign Group | L1: Entry URL
A2: 1 | B2: Grand Prix | C2: THE PARTNERSHIP THAT CHANGED EVERYTHING | D2: LVMH | E2: LVMH | F2: HAVAS PLAY | G2: France | H2: Partnerships/Collaborations | I2: https://ascentialcdn.filespin.io/api/v1/conversion/618cd520f9a24294b091f0641b1abd65 | J2: vpsibWyRnKw | L2: https://www.lovethework.com/work/entries/the-partnership-that-changed-everything-758515
A3: 2 | B3: Gold | C3: LATE CHECKOUT: A RITZ-CARLTON STORY | D3: THE RITZ-CARLTON, LATE CHECKOUT | E3: LATE CHECKOUT COLLECTION, RITZ-CARLTON HOTELS | F3: LITTLE SPAIN | G3: Spain | H3: Brand Storytelling | I3: https://ascentialcdn.filespin.io/api/v1/conversion/ba8c7874143548279ee2ef8936cfee6d | J3: vimeo:1094659374 | L3: https://www.lovethework.com/work/entries/late-checkout-a-ritz-carlton-story-758432
A4: 3 | B4: Silver | C4: 1837 TIFFANY BLUE CONSERVATION | D4: TIFFANY & CO. | E4: TIFFANY & CO. | F4: L&C | G4: United States | H4: Sustainable Luxury | I4: https://ascentialcdn.filespin.io/api/v1/conversion/a9e8fdb5892d441587b7c4c55eb3d5fb | J4: _JhBOf0OJrQ | L4: https://www.lovethework.com/work/entries/1837-tiffany-blue-conservation-758489
A5: 4 | B5: Bronze | C5: DON'T CALL IT LOVE | D5: YVES SAINT LAURENT BEAUTE | E5: ABUSE IS NOT LOVE | F5: BETC | G5: France | H5: Social Campaign | I5: https://ascentialcdn.filespin.io/api/v1/conversion/b28805c7458d487cbf93d349fcf83dd2 | J5: eBnKDL57i7Y | L5: https://www.lovethework.com/work/entries/dont-call-it-love-762992
A6: 5 | B6: Bronze | C6: PRADA: BEYOND THE LINE | D6: PRADA BEAUTÉ | E6: PRADA LUNA ROSSA OCEAN | F6: McCANN | G6: France | H6: Brand Storytelling | I6: https://ascentialcdn.filespin.io/api/v1/conversion/d6d662c2af9b477e9d70359dc900be0f | J6: rXF9wl0BCWE | L6: https://www.lovethework.com/work/entries/prada-beyond-the-line-758381
A7: 6 | B7: Bronze | C7: THE EVERLASTING LOGO | D7: BOTTEGA VENETA | E7: BOTTEGA VENETA | F7: LEPUB | G7: Italy | H7: Experience | I7: https://ascentialcdn.filespin.io/api/v1/conversion/f0ac97dd3a4547da87ada6ad61058cc1 | J7: ZzT1nS6DJqc | L7: https://www.lovethework.com/work/entries/the-everlasting-logo-758398
A8: 7 | B8: Bronze | C8: LOEWE TIKTOK | D8: LOEWE | E8: LOEWE | F8: LOEWE | G8: Spain | H8: Social Campaign | I8: https://ascentialcdn.filespin.io/api/v1/conversion/d2cfdb97c2fc40fd9ab74040e3daa0a2 | J8: vimeo:1094660435 | L8: https://www.lovethework.com/work/entries/loewe-tiktok-762978

Sheet Innovation
A1: # | B1: Tier | C1: Campaign | D1: Brand | E1: Product/Service | F1: Agency | G1: Country | H1: Subcategory | I1: Image URL | J1: YouTube ID | K1: Campaign Group | L1: Entry URL
A2: 1 | B2: Grand Prix | C2: SOUNDS RIGHT | D2: MUSEUM FOR THE UNITED NATIONS - UN LIVE, SPOTIFY | E2: MUSIC | F2: AKQA | G2: Denmark | H2: Environmental Innovation | I2: https://ascentialcdn.filespin.io/api/v1/conversion/5015b68d24bd481a8fcfefc326f5b154 | J2: vimeo:1094746280 | L2: https://www.lovethework.com/work/entries/sounds-right-761761
A3: 2 | B3: Gold | C3: CAPTION WITH INTENTION | D3: ACADEMY OF MOTION PICTURE ARTS & SCIENCES - RAKISH - CHICAGO HEARING SOCIETY | E3: CLOSED CAPTIONING | F3: FCB CHICAGO | G3: United States | H3: Societal Innovation | I3: https://ascentialcdn.filespin.io/api/v1/conversion/bcb995632e51401e9bb1c27a8f759215 | J3: F48khKZhKHM | L3: https://www.lovethework.com/work/entries/caption-with-intention-752614
A4: 3 | B4: Silver | C4: BABY MINDER | D4: EUROFARMA | E4: BABY MINDER | F4: OGILVY HEALTH | G4: United States | H4: Early-Stage Technology | I4: https://ascentialcdn.filespin.io/api/v1/conversion/57def036fd3c4c41912d570ec8706239 | J4: vimeo:1081167145 | L4: https://www.lovethework.com/work/entries/baby-minder-760278
A5: 4 | B5: Silver | C5: BEER RETIREMENT ACCOUNT | D5: POKER BEER | E5: POKER | F5: MONKS | G5: Colombia | H5: Societal Innovation | I5: https://ascentialcdn.filespin.io/api/v1/conversion/9c0dd0aaa6f044518e70e7d63c0c78dd | J5: YTUf_mLc_5U | L5: https://www.lovethework.com/work/entries/beer-retirement-account-752712
A6: 5 | B6: Bronze | C6: PAINVISIBLE | D6: ARITIUM | E6: PAINVISIBLE | F6: VML | G6: Spain | H6: Product Innovation | I6: https://ascentialcdn.filespin.io/api/v1/conversion/5a1c3d291d1b4a428ebb261bc24b249b | J6: _BKTmzriqgs | L6: https://www.lovethework.com/work/entries/painvisible-752585
A7: 6 | B7: Bronze | C7: DROPS OF HOPE | D7: KIMBERLY-CLARK | E7: POISE | F7: FCB NEW YORK | G7: United States | H7: Early-Stage Technology | I7: https://ascentialcdn.filespin.io/api/v1/conversion/98d0bf51b7764f41a17afc9759c91bfa | J7: vimeo:1092193619 | L7: https://www.lovethework.com/work/entries/drops-of-hope-761643
A8: 7 | B8: Bronze | C8: LIVING FABRIC | D8: UNIVERSIDAD DE LOS ANDES & ATRATUS | E8: LIVING FABRIC | F8: VML | G8: Colombia | H8: Environmental Innovation | I8: https://ascentialcdn.filespin.io/api/v1/conversion/9f8364b5c9b847aa83fb8ea7b62628d8 | L8: https://www.lovethework.com/work/entries/living-fabric-759716

Sheet Pharma
A1: # | B1: Tier | C1: Campaign | D1: Brand | E1: Product/Service | F1: Agency | G1: Country | H1: Subcategory | I1: Image URL | J1: YouTube ID | K1: Campaign Group | L1: Entry URL
A2: 1 | B2: Grand Prix | C2: MAKE LOVE LAST - BEDROOM | D2: VIATRIS | E2: VIAGRA | F2: OGILVY | G2: China | H2: Film Craft: Cinematography - Unbranded Product or Service Promotion | I2: digital-presentation-images/pharma-viatris-make-love-last-bedroom.webp | J2: vimeo:1086963204 | L2: https://www.lovethework.com/work/entries/make-love-last-bedroom-752901
A3: 2 | B3: Gold | C3: FRIEDREICH'S BACK | D3: BIOGEN | E3: SKYCLARIS | F3: 21GRAMS | G3: United States | H3: Entertainment - Product or Service Promotion: Direct to Patient | I3: https://ascentialcdn.filespin.io/api/v1/conversion/fd234ce7b17e4ff083175e878a0dcc9e | J3: 0-vXeXH0PTg | L3: https://www.lovethework.com/work/entries/friedreichs-back-752797
A4: 3 | B4: Silver | C4: GLOWING RELIEF | D4: ALIVIA HEALTH | E4: GLOWING RELIEF | F4: DE LA CRUZ OGILVY | G4: Puerto Rico | H4: Brand Experience & Activation - Branded Product or Service Promotion | I4: https://ascentialcdn.filespin.io/api/v1/conversion/890f5040eb2d4dbdbaa5b4f333e85719 | J4: VqmIS4FkLP0 | L4: https://www.lovethework.com/work/entries/glowing-relief-764131
A5: 4 | B5: Silver | C5: DAWAI READER | D5: ALKEM LABORATORIES | E5: THE DAWAI READER | F5: LOWE LINTAS | G5: India | H5: Healthcare Product Innovation - Healthcare Professional Engagement | I5: https://ascentialcdn.filespin.io/api/v1/conversion/762f141aa6fc442dad023f1af28469d8 | J5: 8bisb8K-apg | L5: https://www.lovethework.com/work/entries/dawai-reader-752957
A6: 5 | B6: Silver | C6: NO MORE HIPPOCRITES | D6: WISP | E6: SEXUAL HEALTHCARE | F6: EVERSANA INTOUCH | G6: United States | H6: Integrated - Healthcare Professional Engagement | I6: https://ascentialcdn.filespin.io/api/v1/conversion/823ab3c84f2544f5ba3ad5839f2d5e4b | J6: vimeo:1093833225 | L6: https://www.lovethework.com/work/entries/no-more-hippocrites-752770
A7: 6 | B7: Bronze | C7: DON'T STOP MOTION | D7: CENABAST | E7: GOBIERNO DE CHILE | F7: VML | G7: Chile | H7: Brand Experience & Activation - Disease Awareness & Understanding: Direct to Patient or Healthcare Professional | I7: https://ascentialcdn.filespin.io/api/v1/conversion/624a82c03eb34a1e8a6359e0f28b8b71 | J7: 8NxoqgLXy2E | L7: https://www.lovethework.com/work/entries/dont-stop-motion-752912
A8: 7 | B8: Bronze | C8: PAINVISIBLE | D8: ARITIUM | E8: PAINVISIBLE | F8: VML | G8: Spain | H8: Mobile - Innovative Use of Technology: Patient or Healthcare Professional | I8: https://ascentialcdn.filespin.io/api/v1/conversion/36a5e9332fc143ed9a375ed95c71f5d7 | J8: _BKTmzriqgs | L8: https://www.lovethework.com/work/entries/painvisible-752908
A9: 8 | B9: Bronze | C9: SCRATCHED OUT | D9: PATIENT ACTIVATION FOR PRURIGO NODULARIS | E9: SANOFI | F9: HAVAS LYNX | G9: United Kingdom | H9: Film Craft: Animation/Visual Effects - Product or Service Promotion: Direct to Patient | I9: digital-presentation-images/pharma-patient-activation-for-prurigo-nodularis-scratched-out.webp | J9: mp4:videos/scratched_out.mp4 | L9: https://www.lovethework.com/work/entries/scratched-out-752900
A10: 9 | B10: Bronze | C10: PICK UP YOUR POOP | D10: COLOGUARD | E10: COLOGUARD | F10: THE COMMUNITY | G10: United States | H10: Use of Technology - Branded Product or Service Promotion | I10: https://ascentialcdn.filespin.io/api/v1/conversion/cd58f44ccf4c418a98a0074ed522d7d6 | J10: vimeo:1093348412 | L10: https://www.lovethework.com/work/entries/pick-up-your-poop-764312

Sheet Entertainment Lions for Gaming
A1: # | B1: Tier | C1: Campaign | D1: Brand | E1: Product/Service | F1: Agency | G1: Country | H1: Subcategory | I1: Image URL | J1: YouTube ID | K1: Campaign Group | L1: Entry URL
A2: 1 | B2: Grand Prix | C2: CALL OF DISCOUNTS | D2: MERCADO LIVRE | E2: MERCADO LIVRE | F2: GUT | G2: Brazil | H2: Use of Gaming/Streaming Platforms | I2: https://ascentialcdn.filespin.io/api/v1/conversion/c70ca73e1b844ab9b17bafdddb08ab43 | J2: vimeo:1093409251 | L2: https://www.lovethework.com/work/entries/call-of-discounts-758175
A3: 2 | B3: Gold | C3: BURGER TO KING | D3: BURGER KING, HAPPINESS | E3: BURGER KING | F3: AN FCB ALLIANCE | G3: Belgium | H3: Challenger Brand | I3: https://ascentialcdn.filespin.io/api/v1/conversion/4f2c314a8b5244938185d763dbbb08a8 | J3: RQVaoU4CGRk | L3: https://www.lovethework.com/work/entries/burger-to-king-763800
A4: 3 | B4: Gold | C4: THE FINAL EXAM | D4: CHANGE THE REF | E4: PRO BONO | F4: ENERGY BBDO | G4: United States | H4: Social Behaviour | I4: https://ascentialcdn.filespin.io/api/v1/conversion/615e3a15eabf457d91d317468a12d825 | J4: y8LkiSNPJUs | L4: https://www.lovethework.com/work/entries/the-final-exam-760339
A5: 4 | B5: Silver | C5: PROJECT: MEMORY CARD | D5: PLAYSTATION | E5: PLAYSTATION | F5: SIX INC | G5: Japan | H5: Audio-Visual Content | I5: digital-presentation-images/entertainment-lions-for-gaming-playstation-project-memory-card.webp | J5: vimeo:1094223404 | L5: https://www.lovethework.com/work/entries/project-memory-card-758330
A6: 5 | B6: Silver | C6: BURGER TO KING | D6: BURGER KING, HAPPINESS | E6: BURGER KING | F6: AN FCB ALLIANCE | G6: Belgium | H6: Brand Integration for Games | I6: https://ascentialcdn.filespin.io/api/v1/conversion/4f2c314a8b5244938185d763dbbb08a8 | J6: RQVaoU4CGRk | L6: https://www.lovethework.com/work/entries/burger-to-king-763798
A7: 6 | B7: Bronze | C7: THE FINAL EXAM | D7: CHANGE THE REF | E7: PRO BONO | F7: ENERGY BBDO | G7: United States | H7: Use of Gaming/Streaming Platforms | I7: https://ascentialcdn.filespin.io/api/v1/conversion/615e3a15eabf457d91d317468a12d825 | J7: y8LkiSNPJUs | L7: https://www.lovethework.com/work/entries/the-final-exam-760178
A8: 7 | B8: Bronze | C8: HAALAND PAYBACK TIME | D8: CLASH OF CLANS | E8: CLASH OF CLANS | F8: DAVID | G8: United States | H8: Partnerships with Gaming Talent | I8: https://ascentialcdn.filespin.io/api/v1/conversion/3b57e93aef504625807daf7e7575162d | J8: TcQ--NtSQ9s | L8: https://www.lovethework.com/work/entries/haaland-payback-time-762429
A9: 8 | B9: Bronze | C9: THE CO-WORKER | D9: IKEA | E9: RECRUITMENT CAMPAIGN FOR CAREERS AT IKEA. | F9: MOTHER | G9: United Kingdom | H9: Brand Integration for Games | I9: https://ascentialcdn.filespin.io/api/v1/conversion/4492f4557e9441408ea283fcb7cd3a12 | J9: VPemXZatDQA | L9: https://www.lovethework.com/work/entries/the-co-worker-758248
A10: 9 | B10: Bronze | C10: FIZZOOKA | D10: PERFETTI VAN MELLE | E10: MENTOS | F10: BBH | G10: United Kingdom | H10: Brand Partnerships, Sponsorships & Collaborations | I10: https://ascentialcdn.filespin.io/api/v1/conversion/f5ffbe1532054f85b7f9f9b7fba1f1ee | J10: TgjfKovV888 | L10: https://www.lovethework.com/work/entries/fizzooka-758263
A11: 10 | B11: Bronze | C11: LAG OR BAD | D11: XTRIM | E11: XTRIM INTERNET SERVICE | F11: PARADAIS DDB | G11: Ecuador | H11: Social Behaviour | I11: https://ascentialcdn.filespin.io/api/v1/conversion/035c1b7183be486fa7ec0efe20c5cfd2 | J11: Zo2096C1HDQ | L11: https://www.lovethework.com/work/entries/lag-or-bad-760347
A12: 11 | B12: Bronze | C12: THE CHEEKY CONTROLLER | D12: XBOX | E12: XBOX CONTROLLER | F12: McCANN | G12: United Kingdom | H12: Use of Humour | I12: https://ascentialcdn.filespin.io/api/v1/conversion/f1c6e266081d4161b8e3ecc7ecb15a78 | J12: vimeo:1034892837 | L12: https://www.lovethework.com/work/entries/the-cheeky-controller-762497

Sheet Creative B2B
A1: # | B1: Tier | C1: Campaign | D1: Brand | E1: Product/Service | F1: Agency | G1: Country | H1: Subcategory | I1: Image URL | J1: YouTube ID | K1: Campaign Group | L1: Entry URL
A2: 1 | B2: Grand Prix | C2: B2B: ACT LIKE YOU KNOW | D2: GODADDY | E2: GODADDY AIRO | F2: GODADDY | G2: United States | H2: Integrated Campaigns | I2: https://ascentialcdn.filespin.io/api/v1/conversion/f0ac3195ac904c3daf13ae2ee67cc31a | J2: w9oF8Uu80Dg | L2: https://www.lovethework.com/work/entries/b2b-act-like-you-know-758347
A3: 2 | B3: Gold | C3: STILL OPEN | D3: JC DECAUX | E3: OOH MEDIA | F3: DAVID | G3: Spain | H3: Market Disruption | I3: https://ascentialcdn.filespin.io/api/v1/conversion/bccb982c43f84748a1973b909b5863d3 | J3: uIR17EmDu7g | L3: https://www.lovethework.com/work/entries/still-open-758077
A4: 3 | B4: Gold | C4: RENAULT - UN.PATENT | D4: RENAULT | E4: INNOVATING TOOLS | F4: PUBLICIS CONSEIL | G4: France | H4: Corporate Purpose & Social Responsibility | I4: https://ascentialcdn.filespin.io/api/v1/conversion/f8592ba04ed4495d8a51757d790e8679 | J4: yuaAtV_VnC0 | L4: https://www.lovethework.com/work/entries/renault-unpatent-757993
A5: 4 | B5: Silver | C5: RECIPE FOR GROWTH | D5: IFOOD | E5: IFOOD B2B | F5: DM9 | G5: Brazil | H5: Effectiveness & Measurement | I5: https://ascentialcdn.filespin.io/api/v1/conversion/06ac79ad1b9840bdb3df3269a42d0933 | J5: vimeo:1080197730 | L5: https://www.lovethework.com/work/entries/recipe-for-growth-757969
A6: 5 | B6: Silver | C6: ESTIBADORES | D6: MIBANCO | E6: FINANCIAL INCLUSION PROGRAM | F6: CIRCUS GREY | G6: Peru | H6: Targeting & Engagement | I6: https://ascentialcdn.filespin.io/api/v1/conversion/5de4650ab9f34ebb8ad0ea4f4bc6b8b5 | J6: ZUXcFSbQ8LA | L6: https://www.lovethework.com/work/entries/estibadores-759626
A7: 6 | B7: Silver | C7: THE DESK BREAK CLAUSE | D7: ASICS | E7: ASICS | F7: GOLIN | G7: United Kingdom | H7: B2B Influencer Marketing | I7: https://ascentialcdn.filespin.io/api/v1/conversion/859a375f4fc94040a6d0deeea1586fae | J7: vimeo:1086029094 | L7: https://www.lovethework.com/work/entries/the-desk-break-clause-758238
A8: 7 | B8: Silver | C8: ANIMAL ALERTS | D8: PETPACE | E8: ANIMAL ALERTS | F8: SERVICEPLAN GERMANY | G8: Germany | H8: Corporate Purpose & Social Responsibility | I8: https://ascentialcdn.filespin.io/api/v1/conversion/4c7f3fc5e9e844a883cf1d4bc94c9d58 | J8: kfnhUWM876k | L8: https://www.lovethework.com/work/entries/animal-alerts-757967
A9: 8 | B9: Bronze | C9: NESCAFÉ - PLANTLETS FOR FUTURE | D9: NESCAFE | E9: COFFEE | F9: PUBLICIS CONSEIL | G9: France | H9: Market Disruption | I9: https://ascentialcdn.filespin.io/api/v1/conversion/84fdb68c2d894cd581682c863718054b | J9: vimeo:1097814176 | L9: https://www.lovethework.com/work/entries/nescaf-plantlets-for-future-758004
A10: 9 | B10: Bronze | C10: CAPTION WITH INTENTION | D10: ACADEMY OF MOTION PICTURE ARTS & SCIENCES - RAKISH - CHICAGO HEARING SOCIETY | E10: CLOSED CAPTIONING | F10: FCB CHICAGO | G10: United States | H10: Innovative use of Content | I10: https://ascentialcdn.filespin.io/api/v1/conversion/8cee05632e994496abdaa28c9c780583 | J10: F48khKZhKHM | L10: https://www.lovethework.com/work/entries/caption-with-intention-757997
A11: 10 | B11: Bronze | C11: EVERYBODY'S BUSINESS | D11: LINKEDIN | E11: EVERYBODY'S BUSINESS | F11: LINKEDIN | G11: Ireland | H11: Craft in B2B | I11: https://ascentialcdn.filespin.io/api/v1/conversion/31d78640c4d74a57a9568f3c2153d239 | J11: vimeo:1094885255 | L11: https://www.lovethework.com/work/entries/everybodys-business-760029
A12: 11 | B12: Bronze | C12: PRESERVED PROMOS | D12: ZIPLOC | E12: ZIPLOC | F12: VML | G12: United States | H12: Market Disruption | I12: https://ascentialcdn.filespin.io/api/v1/conversion/8223f25b769b40e3b665c4ec19e2e12c | J12: F9CTRsV3N7k | L12: https://www.lovethework.com/work/entries/preserved-promos-758130
A13: 12 | B13: Bronze | C13: STARRING BARS | D13: HEINEKEN | E13: HEINEKEN | F13: LEPUB | G13: Italy | H13: Cross-Channel Storytelling | I13: https://ascentialcdn.filespin.io/api/v1/conversion/6544f095e71a47a39d27334e2404e951 | J13: VNq1oogkrYk | L13: https://www.lovethework.com/work/entries/starring-bars-757826
A14: 13 | B14: Bronze | C14: RECIPE FOR CHANGE | D14: ARLA | E14: PUCK | F14: FP7 McCANN | G14: United Arab Emirates | H14: Targeting & Engagement | I14: https://ascentialcdn.filespin.io/api/v1/conversion/47493919a45c464ca5a8228f83685d83 | J14: vimeo:1078926878 | L14: https://www.lovethework.com/work/entries/recipe-for-change-758056

Sheet Sustainable Development Goals
A1: # | B1: Tier | C1: Campaign | D1: Brand | E1: Product/Service | F1: Agency | G1: Country | H1: Subcategory | I1: Image URL | J1: YouTube ID | K1: Campaign Group | L1: Entry URL
A2: 1 | B2: Grand Prix | C2: THE AMAZON GREENVENTORY | D2: NATURA | E2: INSTITUTO NATTURA | F2: AFRICA CREATIVE DDB | G2: Brazil | H2: Life on Land | I2: https://ascentialcdn.filespin.io/api/v1/conversion/8f27d4982c9f44a0ae99fa41531bda8e | J2: vimeo:1094885157 | L2: https://www.lovethework.com/work/entries/the-amazon-greenventory-755993
A3: 2 | B3: Gold | C3: MINEFIELD HONEY: HARVESTING HOPE | D3: KERNEL, MINISTRY OF FOREIGN AFFAIRS OF UKRAINE | E3: AGRICULTURE | F3: SAATCHI & SAATCHI UKRAINE | G3: Ukraine | H3: Decent Work and Economic Growth | I3: https://ascentialcdn.filespin.io/api/v1/conversion/e943553f2152499c8182bfce20e7355d | J3: ABV3K_N7a7k | L3: https://www.lovethework.com/work/entries/minefield-honey-harvesting-hope-755960
A4: 3 | B4: Gold | C4: RESEARCH MY BODY | D4: GRUPO BOTICÁRIO | E4: WOMEN'S RESEARCH CENTER\t | F4: GUT | G4: Brazil | H4: Good Health and Well-being | I4: https://ascentialcdn.filespin.io/api/v1/conversion/01a0aba05ed745cf8b40b9f6719fff6a | J4: vimeo:1091039142 | L4: https://www.lovethework.com/work/entries/research-my-body-755612
A5: 4 | B5: Gold | C5: RECIPE FOR CHANGE | D5: ARLA | E5: PUCK | F5: FP7 McCANN | G5: United Arab Emirates | H5: Poverty | I5: https://ascentialcdn.filespin.io/api/v1/conversion/d51c95f53aaf474ba9faba5a10094bd0 | J5: vimeo:1078926878 | L5: https://www.lovethework.com/work/entries/recipe-for-change-755679
A6: 5 | B6: Gold | C6: SOUNDS RIGHT | D6: MUSEUM FOR THE UNITED NATIONS - UN LIVE, SPOTIFY | E6: MUSIC | F6: AKQA | G6: Denmark | H6: Climate Action | I6: https://ascentialcdn.filespin.io/api/v1/conversion/10360044a9be467286965f70b39a984b | J6: vimeo:1094746280 | L6: https://www.lovethework.com/work/entries/sounds-right-755775
A7: 6 | B7: Silver | C7: ARIEL #SHARETHELOAD (10 YEARS) | D7: ARIEL | E7: ARIEL LAUNDRY DETERGENT | F7: BBDO INDIA | G7: India | H7: Long-Term Brand Platform | I7: https://ascentialcdn.filespin.io/api/v1/conversion/1e1df1c7a74a4897a3f75a7a38e60d27 | J7: AL88aQPBlnU | L7: https://www.lovethework.com/work/entries/ariel-sharetheload-10-years-759693
A8: 7 | B8: Silver | C8: THE DOVE CODE | D8: DOVE, DROGA5 | E8: DOVE | F8: PART OF ACCENTURE SONG | G8: Brazil | H8: Gender Equality | I8: https://ascentialcdn.filespin.io/api/v1/conversion/aab2b49f4bde4aef88d22006ef903d54 | J8: L4o03Hrxgzg | L8: https://www.lovethework.com/work/entries/the-dove-code-755937
A9: 8 | B9: Silver | C9: OMNILIVERY | D9: OMNI | E9: MOBILITY SYSTEM FOR WHEELCHAIR | F9: SAATCHI & SAATCHI FRANCE | G9: France | H9: Reduced Inequalities | I9: https://ascentialcdn.filespin.io/api/v1/conversion/38cbe1a6ee444db186b748c9da630bdc | J9: vimeo:1158377325 | L9: https://www.lovethework.com/work/entries/omnilivery-756098
A10: 9 | B10: Silver | C10: ANIMAL ALERTS | D10: PETPACE | E10: ANIMAL ALERTS | F10: SERVICEPLAN GERMANY | G10: Germany | H10: Good Health and Well-being | I10: https://ascentialcdn.filespin.io/api/v1/conversion/4c7f3fc5e9e844a883cf1d4bc94c9d58 | J10: kfnhUWM876k | L10: https://www.lovethework.com/work/entries/animal-alerts-755614
A11: 10 | B11: Bronze | C11: THE BEST PLACE IN THE WORLD TO HAVE HERPES | D11: NEW ZEALAND HERPES FOUNDATION | E11: NEW ZEALAND HERPES FOUNDATION | F11: FINCH | G11: Australia | H11: Good Health and Well-being | I11: https://ascentialcdn.filespin.io/api/v1/conversion/5d4b1b0582c5428bafb14fcc9670d1dc | J11: vimeo:1083074994 | L11: https://www.lovethework.com/work/entries/the-best-place-in-the-world-to-have-herpes-755748
A12: 11 | B12: Bronze | C12: REEF PROTECTION FACTOR | D12: STREAM2SEA | E12: CORAL CARE & RPF | F12: McCANN DEMAND | G12: United Kingdom | H12: Life Below Water | I12: https://ascentialcdn.filespin.io/api/v1/conversion/632753c2e0e444898a416c5bbd6272fb | J12: vimeo:1083456679 | L12: https://www.lovethework.com/work/entries/reef-protection-factor-755941
A13: 12 | B13: Bronze | C13: WILDFIRE WATCHTOWERS | D13: ROGERS | E13: ROGERS | F13: PUBLICIS CANADA | G13: Canada | H13: Climate Action | I13: https://ascentialcdn.filespin.io/api/v1/conversion/5cc44dd478364c8f89e74997da34c416 | L13: https://www.lovethework.com/work/entries/wildfire-watchtowers-755880
A14: 13 | B14: Bronze | C14: SOS BEES | D14: ABINBEV | E14: Consumer Goods | F14: AFRICA CREATIVE DDB | G14: Brazil | H14: Sustainable Cities and Communities | I14: https://ascentialcdn.filespin.io/api/v1/conversion/43c463221a2f4400b93862d1c5538078 | J14: vimeo:1095117362 | L14: https://www.lovethework.com/work/entries/sos-bees-755943
A15: 14 | B15: Bronze | C15: SALTANAT LIGHT | D15: CITIX | E15: CITIX | F15: GFORCE | G15: Kazakhstan | H15: Gender Equality | I15: https://ascentialcdn.filespin.io/api/v1/conversion/68f2c53ebcea42bd9ab7b58852b5aa95 | J15: POZJDa6y23g | L15: https://www.lovethework.com/work/entries/saltanat-light-758763
A16: 15 | B16: Bronze | C16: NOBODY SHOULD DIE AT XMAS | D16: OPEN ARMS | E16: CHRISTMAS CAMPAIGN | F16: DOUBLEYOU | G16: Spain | H16: Peace, Justice and Strong Institutions | I16: https://ascentialcdn.filespin.io/api/v1/conversion/1b883e0ec2f648dea7bf17849408f188 | J16: vimeo:951451298 | L16: https://www.lovethework.com/work/entries/nobody-should-die-at-xmas-756056
A17: 16 | B17: Bronze | C17: HOW DOVE TOOK ON A NEW ERA OF TOXIC BEAUTY | D17: DOVE | E17: DOVE | F17: OGILVY UK | G17: United Kingdom | H17: Long-Term Brand Platform | I17: digital-presentation-images/sustainable-development-goals-dove-how-dove-took-on-a-new-era-of-toxic-beauty.webp | L17: https://www.lovethework.com/work/entries/how-dove-took-on-a-new-era-of-toxic-beauty-765307

Sheet Entertainment Lions for Music
A1: # | B1: Tier | C1: Campaign | D1: Brand | E1: Product/Service | F1: Agency | G1: Country | H1: Subcategory | I1: Image URL | J1: YouTube ID | K1: Campaign Group | L1: Entry URL
A2: 1 | B2: Grand Prix | C2: TRACKING BAD BUNNY | D2: RIMAS MUSIC | E2: BAD BUNNY | F2: DDB LATINA PUERTO RICO | G2: Puerto Rico | H2: Cultural Engagement | I2: https://ascentialcdn.filespin.io/api/v1/conversion/6d3d67544e4a4fe7baad1c1b50560274 | J2: hPLaT_JT9Zw | L2: https://www.lovethework.com/work/entries/tracking-bad-bunny-760320
A3: 2 | B3: Gold | C3: A$AP ROCKY - TAILOR SWIF | D3: A$AP ROCKY | E3: A$AP ROCKY | F3: ICONOCLAST | G3: United States | H3: Excellence in Music Video | I3: https://ascentialcdn.filespin.io/api/v1/storyboard/7819511744634f7a81824e1b2a278ae1/storyboard_000008.jpg | J3: 5URefVYaJrA | L3: https://www.lovethework.com/work/entries/aap-rocky-tailor-swif-754915
A4: 3 | B4: Gold | C4: HEY JUDE | D4: ADIDAS | E4: ADIDAS | F4: JOHANNES LEONARDO | G4: United States | H4: Use of Licensed/Adapted Music | I4: https://ascentialcdn.filespin.io/api/v1/conversion/c5b4d99a1f714aea8f5124ebd5d701f7 | J4: aoOfn_W8PWg | L4: https://www.lovethework.com/work/entries/hey-jude-754810
A5: 4 | B5: Gold | C5: ABRACADABRA: FROM FAN TO FEATURED | D5: MASTERCARD | E5: MASTERCARD | F5: McCANN XBC | G5: United States | H5: Fan Engagement/Community Building | I5: https://ascentialcdn.filespin.io/api/v1/conversion/0b4f8069282647798e50f403983c1f06 | J5: vimeo:1093143827 | L5: https://www.lovethework.com/work/entries/abracadabra-from-fan-to-featured-759657
A6: 5 | B6: Silver | C6: ME FEAT. ME | D6: NOSOTRAS | E6: NOSOTRAS | F6: DDB CHILE | G6: Chile | H6: Cultural Engagement | I6: https://ascentialcdn.filespin.io/api/v1/conversion/a6ac5c5dd4fc4487966ae01ac52f95ff | J6: vimeo:1093833141 | L6: https://www.lovethework.com/work/entries/me-feat-me-755132
A7: 6 | B7: Silver | C7: "LOVE" | D7: OK GO | F7: SPECIALGUEST | H7: Excellence in Music Video | I7: digital-presentation-images/entertainment-lions-for-music-ok-go-love.webp | J7: gz9BRl7DVSM | L7: https://www.lovethework.com/work/entries/love-754922
A8: 7 | B8: Silver | C8: TENNESSEE SOUND SITES | D8: TENNESSEE DEPARTMENT OF TOURIST DEVELOPMENT | E8: TENNESSEE DEPARTMENT OF TOURIST DEVELOPMENT | F8: VML | G8: United States | H8: Diversity & Inclusion in Music | I8: https://ascentialcdn.filespin.io/api/v1/conversion/eb513fac29984db2811524e932026062 | J8: cE9pTxrtkjk | L8: https://www.lovethework.com/work/entries/tennessee-sound-sites-755015
A9: 8 | B9: Silver | C9: THE GIRL WHO PLAYED THE TUTARI | D9: COCA-COLA | E9: COKE STUDIO BHARAT | F9: VML | G9: India | H9: Cultural Engagement | I9: digital-presentation-images/entertainment-lions-for-music-coca-cola-the-girl-who-played-the-tutari.webp | J9: vimeo:1073423333 | L9: https://www.lovethework.com/work/entries/the-girl-who-played-the-tutari-754967
A10: 9 | B10: Silver | C10: LITTLE SIMZ 'FLOOD' | D10: LITTLE SIMZ | E10: FILM | F10: PRETTYBIRD | G10: United Kingdom | H10: Excellence in Music Video | I10: https://ascentialcdn.filespin.io/api/v1/conversion/17f5e6466cc04660b48ef8ef11bb211e | J10: GvrNPiz7rHw | L10: https://www.lovethework.com/work/entries/little-simz-flood-754835
A11: 10 | B11: Bronze | C11: KENDRICK LAMAR + APPLE MUSIC'S SUPER BOWL HALFTIME SHOW CAMPAIGN | D11: APPLE | E11: APPLE MUSIC | F11: APPLE | G11: United States | H11: Partnerships with Music Talent | I11: https://ascentialcdn.filespin.io/api/v1/conversion/4e38334504284effbc474e7a3273d412 | J11: vimeo:1094223419 | L11: https://www.lovethework.com/work/entries/kendrick-lamar-apple-musics-super-bowl-halftime-show-campaign-755001
A12: 11 | B12: Bronze | C12: THE LAST TIMBIT | D12: TIM HORTONS | E12: TIM HORTONS | F12: GUT | G12: Canada | H12: Use of Original Composition | I12: https://ascentialcdn.filespin.io/api/v1/conversion/f0419f522ab74225a6515a6514c036ec | J12: vimeo:1094221778 | L12: https://www.lovethework.com/work/entries/the-last-timbit-762830
A13: 12 | B13: Bronze | C13: JOVEM MK - MEU KARMA | D13: KONDZILLA | E13: MUSIC | F13: AFRICA CREATIVE DDB | G13: Brazil | H13: Excellence in Music Video | I13: digital-presentation-images/entertainment-lions-for-music-kondzilla-jovem-mk-meu-karma.webp | J13: vimeo:1076470479 | L13: https://www.lovethework.com/work/entries/jovem-mk-meu-karma-754791
A14: 13 | B14: Bronze | C14: LOVE THE RACKS | D14: KITCHENAID | E14: KITCHENAIDÂ® 360Â° MAX JETSâ¢ THIRD RACK DISHWASHERS | F14: WOW STUDIOS | G14: United States | H14: Use of Original Composition | I14: digital-presentation-images/entertainment-lions-for-music-kitchenaid-love-the-racks.webp | J14: 9qlKfY_FCe4 | L14: https://www.lovethework.com/work/entries/love-the-racks-754806
A15: 14 | B15: Bronze | C15: TRACKING BAD BUNNY | D15: RIMAS MUSIC | E15: BAD BUNNY | F15: DDB LATINA PUERTO RICO | G15: Puerto Rico | H15: Partnerships with Music Talent | I15: https://ascentialcdn.filespin.io/api/v1/conversion/6d3d67544e4a4fe7baad1c1b50560274 | J15: hPLaT_JT9Zw | L15: https://www.lovethework.com/work/entries/tracking-bad-bunny-760302
A16: 15 | B16: Bronze | C16: A STONE ONLY ROLLS DOWNHILL | D16: OK GO | E16: OK GO | F16: PARK PICTURES | G16: United States | H16: Excellence in Music Video | I16: https://ascentialcdn.filespin.io/api/v1/storyboard/191cd784934f42e29f332027d298ef62/storyboard_000008.jpg | J16: MOEULOSVNK4 | L16: https://www.lovethework.com/work/entries/a-stone-only-rolls-downhill-754853
A17: 16 | B17: Bronze | C17: BORN TO RUN | D17: DOVE | E17: DOVE | F17: OGILVY UK | G17: United Kingdom | H17: Social Behaviour | I17: https://ascentialcdn.filespin.io/api/v1/conversion/1df87588cc0f4cf58bf77a0ffc045a44 | J17: db2adhodJwc | L17: https://www.lovethework.com/work/entries/born-to-run-755077

Sheet Creative Effectiveness
A1: # | B1: Tier | C1: Campaign | D1: Brand | E1: Product/Service | F1: Agency | G1: Country | H1: Subcategory | I1: Image URL | J1: YouTube ID | K1: Campaign Group | L1: Entry URL
A2: 1 | B2: Grand Prix | C2: SHOT ON IPHONE | D2: APPLE | E2: IPHONE | F2: TBWA\MEDIA ARTS LAB | G2: United States | H2: Long-Term Brand Platform | I2: https://ascentialcdn.filespin.io/api/v1/conversion/c125657ef0f84557825eba78ef7e3d63 | J2: S74jad3ZmUY | L2: https://www.lovethework.com/work/entries/shot-on-iphone-765239
A3: 2 | B3: Gold | C3: THE EVERYDAY TACTICIAN: HOW GETTING A FOOTBALL CLUB PROMOTED HELPED XBOX TAKE A STEP CLOSER TO THE FUTURE OF GAMING | D3: XBOX | E3: XBOX GAME PASS | F3: McCANN | G3: United Kingdom | H3: Launch | I3: https://ascentialcdn.filespin.io/api/v1/conversion/7c2d069dafe1485c9e355a842cdb238d | J3: Kb3nqqwihz0 | L3: https://www.lovethework.com/work/entries/the-everyday-tactician-how-getting-a-football-club-promoted-helped-xbox-take-a-step-closer-to-the-future-of-gaming-764812
A4: 3 | B4: Gold | C4: DON'T DRINK HERTOG JAN | D4: HERTOG JAN | E4: HERTOG JAN | F4: GUT | G4: Netherlands | H4: Single Market | I4: digital-presentation-images/creative-effectiveness-hertog-jan-dont-drink-hertog-jan.webp | J4: vimeo:1003184179 | L4: https://www.lovethework.com/work/entries/dont-drink-hertog-jan-761647
A5: 4 | B5: Gold | C5: THE MISHEARD VERSION | D5: SPECSAVERS | E5: AUDIOLOGY | F5: GOLIN | G5: United Kingdom | H5: Acquisition | I5: https://ascentialcdn.filespin.io/api/v1/conversion/907772d8708748d5b4087c68c1b6fdf9 | J5: EgNb0LQxm84 | L5: https://www.lovethework.com/work/entries/the-misheard-version-751965
A6: 5 | B6: Silver | C6: SAMSUNG THROWBACK DEALS | D6: SAMSUNG BRAZIL | E6: E-COMMERCE | F6: MRM | G6: Brazil | H6: Breakthrough on a Budget | I6: https://ascentialcdn.filespin.io/api/v1/conversion/f046264282904c7b9cf6f37b69173ec2 | J6: dlY3UOVF9OU | L6: https://www.lovethework.com/work/entries/samsung-throwback-deals-752109
A7: 6 | B7: Silver | C7: REAL BEAUTY: HOW A SOAP BRAND CREATED A GLOBAL SELF-ESTEEM MOVEMENT | D7: DOVE | E7: DOVE | F7: OGILVY UK | G7: United Kingdom | H7: Long-Term Brand Platform | I7: https://ascentialcdn.filespin.io/api/v1/conversion/1c2573f5cf2c4b78af5a4b42f75ac2c2 | J7: puQ0PNZ1W-A | L7: https://www.lovethework.com/work/entries/real-beauty-how-a-soap-brand-created-a-global-self-esteem-movement-765245
A8: 7 | B8: Silver | C8: NO SMILES | D8: MCDONALD'S | E8: HIRING | F8: TBWA\HAKUHODO | G8: Japan | H8: Market Disruption | I8: https://ascentialcdn.filespin.io/api/v1/conversion/8bd771cfe9f74489a6ecf874a92cac25 | J8: vimeo:1129136785 | L8: https://www.lovethework.com/work/entries/no-smiles-752049
A9: 8 | B9: Silver | C9: FIND YOUR SUMMER | D9: MAGNUM | E9: MAGNUM ICE CREAM | F9: LOLA MULLENLOWE | G9: Spain | H9: Market Disruption | I9: https://ascentialcdn.filespin.io/api/v1/conversion/fccf3dc65a7040fcbc382da62a1bcf0b | J9: jmf4xjZvwqs | L9: https://www.lovethework.com/work/entries/find-your-summer-761700
A10: 9 | B10: Silver | C10: HANDSHAKE HUNT | D10: MERCADO LIVRE | E10: MERCADO LIVRE | F10: GUT | G10: Brazil | H10: Multi-Market | I10: https://ascentialcdn.filespin.io/api/v1/conversion/79595be993234fda94d72414b4e673e2 | J10: Uc6Xgiizi8Q | L10: https://www.lovethework.com/work/entries/handshake-hunt-761683
A11: 10 | B11: Silver | C11: REFURB | D11: PHILIPS | E11: PHILIPS | F11: LEPUB | G11: Netherlands | H11: Consumer Goods | I11: https://ascentialcdn.filespin.io/api/v1/conversion/0f9e4316f9644aad87356635e8f39cf3 | J11: sJXFLk5wvcQ | L11: https://www.lovethework.com/work/entries/refurb-761714
A12: 11 | B12: Bronze | C12: A PIECE OF ME | D12: KPN | E12: KPN | F12: DENTSU CREATIVE | G12: Netherlands | H12: Creative Effectiveness for Good | I12: https://ascentialcdn.filespin.io/api/v1/conversion/d2ae25cdfd9c418185c6cac4e75b98fe | J12: LwH85eFmveQ | L12: https://www.lovethework.com/work/entries/a-piece-of-me-752147
A13: 12 | B13: Bronze | C13: MICHAEL CERAVE | D13: CERAVE | E13: CERAVE | F13: OGILVY PR | G13: United States | H13: Healthcare | I13: https://ascentialcdn.filespin.io/api/v1/conversion/a30647b18cf146969ce30881a640aca9 | J13: vimeo:924148167 | L13: https://www.lovethework.com/work/entries/michael-cerave-751766
... A18: 17 | B18: Bronze | C18: THE EVERYDAY TACTICIAN: HOW GETTING A FOOTBALL CLUB PROMOTED HELPED XBOX TAKE A STEP CLOSER TO THE FUTURE OF GAMING | D18: XBOX | E18: XBOX GAME PASS | F18: McCANN | G18: United Kingdom | H18: Collaboration | I18: https://ascentialcdn.filespin.io/api/v1/conversion/7c2d069dafe1485c9e355a842cdb238d | J18: Kb3nqqwihz0 | L18: https://www.lovethework.com/work/entries/the-everyday-tactician-how-getting-a-football-club-promoted-helped-xbox-take-a-step-closer-to-the-future-of-gaming-764822

Sheet Creative Data
A1: # | B1: Tier | C1: Campaign | D1: Brand | E1: Product/Service | F1: Agency | G1: Country | H1: Subcategory | I1: Image URL | J1: YouTube ID | K1: Campaign Group | L1: Entry URL
A2: 1 | B2: Gold | C2: IKEA HIDDEN TAGS | D2: IKEA | E2: IKEA | F2: UZINA | G2: Portugal | H2: Data Storytelling | I2: https://ascentialcdn.filespin.io/api/v1/conversion/237ade5924eb407898bf58d19f58a52a | J2: oKWkHqlt7yA | L2: https://www.lovethework.com/work/entries/ikea-hidden-tags-753885
A3: 2 | B3: Gold | C3: SATO 2531 | D3: ASUNIWA | E3: THINK NAME PROJECT | F3: DENTSU DIGITAL | G3: Japan | H3: Cultural Engagement | I3: https://ascentialcdn.filespin.io/api/v1/conversion/e23ba1fc24004021856268a0ee6b44d9 | J3: BW5T0gC6o3o | L3: https://www.lovethework.com/work/entries/sato-2531-754250
A4: 3 | B4: Gold | C4: ACKO TAILOR TEST | D4: ACKO | E4: HEALTH INSURANCE | F4: LEO | G4: India | H4: Creative Data Collection & Research | I4: https://ascentialcdn.filespin.io/api/v1/conversion/a8a20a31dcb844ebad5ef04afca8370b | J4: alezIXsk0So | L4: https://www.lovethework.com/work/entries/acko-tailor-test-754081
A5: 4 | B5: Silver | C5: E.L.F. BEAUTY "SO MANY DICKS" | D5: E.L.F. BEAUTY | F5: E.L.F. BEAUTY | H5: Use of Humour | I5: https://ascentialcdn.filespin.io/api/v1/conversion/64d76bdbc8f54be7a59e700d5332b2a6 | J5: -koo15C3nYI | L5: https://www.lovethework.com/work/entries/elf-beauty-so-many-dicks-753999
A6: 5 | B6: Silver | C6: DROPS OF HOPE | D6: KIMBERLY-CLARK | E6: POISE | F6: FCB NEW YORK | G6: United States | H6: Data-Driven Consumer Product | I6: https://ascentialcdn.filespin.io/api/v1/conversion/d3b1ef914a9640f7b0b0389b64d37fd2 | J6: vimeo:1092193619 | L6: https://www.lovethework.com/work/entries/drops-of-hope-753816
A7: 6 | B7: Silver | C7: HEALTH TRACKER | D7: ELEA LABORATORY | E7: ELEA LABORATORY | F7: VML | G7: Argentina | H7: Cultural Engagement | I7: https://ascentialcdn.filespin.io/api/v1/conversion/dc840a1ede4e49ceba65f229ae4ced69 | J7: uMCZkFghs_w | L7: https://www.lovethework.com/work/entries/health-tracker-754213
A8: 7 | B8: Silver | C8: STREETNAV | D8: STREETCO | E8: STREETNAV | F8: HAVAS PARIS | G8: France | H8: Use of Real-Time Data | I8: https://ascentialcdn.filespin.io/api/v1/conversion/e94bf22aa9464e848abb53d498481dc1 | J8: vimeo:1093372618 | L8: https://www.lovethework.com/work/entries/streetnav-754079
A9: 8 | B9: Silver | C9: PIXVERTISING | D9: BURGER KING | E9: BK FRANGUINHOS | F9: ALMAPBBDO | G9: Brazil | H9: Data-Driven Targeting | I9: https://ascentialcdn.filespin.io/api/v1/conversion/cfd7900b28e941bc9f0945581daf896f | J9: vimeo:1081470031 | L9: https://www.lovethework.com/work/entries/pixvertising-761869
A10: 9 | B10: Silver | C10: THE AMAZON GREENVENTORY | D10: NATURA | E10: INSTITUTO NATTURA | F10: AFRICA CREATIVE DDB | G10: Brazil | H10: Data Technology | I10: https://ascentialcdn.filespin.io/api/v1/conversion/8f27d4982c9f44a0ae99fa41531bda8e | J10: vimeo:1094885157 | L10: https://www.lovethework.com/work/entries/the-amazon-greenventory-754084
A11: 10 | B11: Silver | C11: BREASTMILK MONEY | D11: HERCONOMY | E11: HERCONOMY | F11: SERVICEPLAN GERMANY | G11: Germany | H11: Single-Market Campaign | I11: https://ascentialcdn.filespin.io/api/v1/conversion/73ea0e639f6747c68cf8460abe2f02bb | J11: vimeo:1094309200 | L11: https://www.lovethework.com/work/entries/breastmilk-money-754148
A12: 11 | B12: Bronze | C12: RECIPE FOR GROWTH | D12: IFOOD | E12: IFOOD B2B | F12: DM9 | G12: Brazil | H12: Data Integration | I12: https://ascentialcdn.filespin.io/api/v1/conversion/06ac79ad1b9840bdb3df3269a42d0933 | J12: vimeo:1080197730 | L12: https://www.lovethework.com/work/entries/recipe-for-growth-754115
A13: 12 | B13: Bronze | C13: DISCONNECT | D13: AIR FRANCE | E13: AIR FRANCE HOLIDAYS | F13: TBWA\PARIS | G13: France | H13: Data Visualisation | I13: https://ascentialcdn.filespin.io/api/v1/conversion/6fbd1db8f0384e92b6c363cfc1ba9bec | J13: htsdJ3-K3N4 | L13: https://www.lovethework.com/work/entries/disconnect-753762
A14: 13 | B14: Bronze | C14: IKEA HIDDEN TAGS | D14: IKEA | E14: IKEA | F14: UZINA | G14: Portugal | H14: Market Disruption | I14: https://ascentialcdn.filespin.io/api/v1/conversion/237ade5924eb407898bf58d19f58a52a | J14: oKWkHqlt7yA | L14: https://www.lovethework.com/work/entries/ikea-hidden-tags-754342
A15: 14 | B15: Bronze | C15: THE MISSING PORTRAITS | D15: PIRACANJUBA | E15: MILK | F15: AMPFY | G15: Brazil | H15: Corporate Purpose & Social Responsibility | I15: https://ascentialcdn.filespin.io/api/v1/conversion/32d357cad3624b9489965e9886948447 | J15: vimeo:1077737553 | L15: https://www.lovethework.com/work/entries/the-missing-portraits-754176
A16: 15 | B16: Bronze | C16: LIFE DONOR CARD | D16: MASTERCARD | E16: LIFE DONOR FEATURE | F16: MRM GERMANY | G16: Germany | H16: Data-Driven Consumer Product | I16: https://ascentialcdn.filespin.io/api/v1/conversion/d4f1b0f66c5e4ae7ad17037a6aa198f7 | J16: pe-7cdkH2dA | L16: https://www.lovethework.com/work/entries/life-donor-card-759724
A17: 16 | B17: Bronze | C17: HUMANIMAL TOURISM | D17: PROCOLOMBIA | E17: COLOMBIA, THE COUNTRY OF BEAUTY | F17: DDB COLOMBIA | G17: Colombia | H17: Data-Enhanced Creativity | I17: https://ascentialcdn.filespin.io/api/v1/conversion/baf91a99fe954d17a2d2b48558a76a34 | J17: 1r6DMx0FOYk | L17: https://www.lovethework.com/work/entries/humanimal-tourism-753838
A18: 17 | B18: Bronze | C18: THE SOCIAL FEED | D18: HUNGERSTATION | E18: FOOD DELIVERY APP | F18: VML | G18: United Arab Emirates | H18: Data-Driven Targeting | I18: https://ascentialcdn.filespin.io/api/v1/conversion/f79ebb4926094729b16cf44d9e9f7d4f | J18: vimeo:1075735593 | L18: https://www.lovethework.com/work/entries/the-social-feed-753950

Sheet Creative Commerce
A1: # | B1: Tier | C1: Campaign | D1: Brand | E1: Product/Service | F1: Agency | G1: Country | H1: Subcategory | I1: Image URL | J1: YouTube ID | K1: Campaign Group | L1: Entry URL
A2: 1 | B2: Grand Prix | C2: PRESERVED PROMOS | D2: ZIPLOC | E2: ZIPLOC | F2: VML | G2: United States | H2: Brand Strategy | I2: https://ascentialcdn.filespin.io/api/v1/conversion/8223f25b769b40e3b665c4ec19e2e12c | J2: F9CTRsV3N7k | L2: https://www.lovethework.com/work/entries/preserved-promos-756451
A3: 2 | B3: Gold | C3: RECIPE FOR GROWTH | D3: IFOOD | E3: IFOOD B2B | F3: DM9 | G3: Brazil | H3: Consumer Services/Business to Business | I3: https://ascentialcdn.filespin.io/api/v1/conversion/06ac79ad1b9840bdb3df3269a42d0933 | J3: vimeo:1080197730 | L3: https://www.lovethework.com/work/entries/recipe-for-growth-756123
A4: 3 | B4: Gold | C4: SAD KAMA-CHAN | D4: B&Q | E4: BAR B Q PLAZA | F4: GREY THAILAND | G4: Thailand | H4: Customer Acquisition & Retention | I4: https://ascentialcdn.filespin.io/api/v1/conversion/b1a090f7c816487f8dcee01d4c656df9 | J4: h7MYlQFAKMg | L4: https://www.lovethework.com/work/entries/sad-kama-chan-756446
A5: 4 | B5: Gold | C5: LUCKY YATRA | D5: INDIAN RAILWAYS | E5: RAILWAY SERVICE | F5: FCB INDIA | G5: India | H5: Customer Acquisition & Retention | I5: https://ascentialcdn.filespin.io/api/v1/conversion/81cf5ad6f9074f6589edcf4736a3552b | J5: 19fzAvuFq0I | L5: https://www.lovethework.com/work/entries/lucky-yatra-756377
A6: 5 | B6: Silver | C6: FOOTBALL IS FOR FOOD | D6: UBER EATS | E6: UBER EATS | F6: SPECIAL | G6: United States | H6: Travel, Leisure, Retail, Restaurants & Fast-Food Chains | I6: https://ascentialcdn.filespin.io/api/v1/conversion/23d7c7eb3b1845ab821b2444f4366440 | J6: Mi_cxUyqH4Q | L6: https://www.lovethework.com/work/entries/football-is-for-food-756070
A7: 6 | B7: Silver | C7: MAKEUP PAYMENT | D7: MASTERCARD | E7: MASTERCARD | F7: MRM | G7: Brazil | H7: Innovative use of Commerce Channel | I7: https://ascentialcdn.filespin.io/api/v1/conversion/65f21a7641c4411ab901d5cc5854564a | J7: izZ-HPCDzy4 | L7: https://www.lovethework.com/work/entries/makeup-payment-756226
A8: 7 | B8: Silver | C8: COUPON RAIN | D8: MERCADO LIVRE | E8: MERCADO LIVRE | F8: GUT | G8: Brazil | H8: Travel, Leisure, Retail, Restaurants & Fast-Food Chains | I8: https://ascentialcdn.filespin.io/api/v1/conversion/8782875c907847289e66a9d52a2b2ec8 | J8: vimeo:1093414319 | L8: https://www.lovethework.com/work/entries/coupon-rain-756095
A9: 8 | B9: Silver | C9: THE SOCIAL FEED | D9: HUNGERSTATION | E9: FOOD DELIVERY APP | F9: VML | G9: United Arab Emirates | H9: Social Behaviour | I9: https://ascentialcdn.filespin.io/api/v1/conversion/ed346dbf026441888562409343c9c149 | J9: vimeo:1075735593 | L9: https://www.lovethework.com/work/entries/the-social-feed-756367
A10: 9 | B10: Silver | C10: PRIZE ON THE BONE | D10: KFC | E10: KFC ICE-CREAM | F10: DM9 | G10: Brazil | H10: Social Behaviour | I10: https://ascentialcdn.filespin.io/api/v1/conversion/32ef7021bdbd4c4392fa51fb240d45e6 | J10: h4Kl5THlsYw | L10: https://www.lovethework.com/work/entries/prize-on-the-bone-756514
A11: 10 | B11: Silver | C11: PRICE PACKS | D11: PENNY | E11: FOOD/NON-FOOD | F11: SERVICEPLAN GERMANY | G11: Germany | H11: Retail Media | I11: https://ascentialcdn.filespin.io/api/v1/conversion/67b6df2a0fe64deeb274c91d50040c54 | J11: wXx6z3mDnVc | L11: https://www.lovethework.com/work/entries/price-packs-756267
A12: 11 | B12: Silver | C12: ORANGE - SAFER PHONE | D12: ORANGE | E12: SAFER PHONES | F12: PUBLICIS CONSEIL | G12: France | H12: Consumer Services/Business to Business | I12: https://ascentialcdn.filespin.io/api/v1/conversion/cb56a9988125417f960278fdeea26a5f | J12: fvFMlQwQJNk | L12: https://www.lovethework.com/work/entries/orange-safer-phone-756150
A13: 12 | B13: Silver | C13: U UP? | D13: IKEA | E13: IKEA | F13: RETHINK | G13: Canada | H13: Use of Humour | I13: https://ascentialcdn.filespin.io/api/v1/conversion/1d6f8cfcad1b47c9beaa5f403844ec8a | J13: VT02JDQuMxM | L13: https://www.lovethework.com/work/entries/u-up-756513
... A21: 20 | B21: Bronze | C21: KLEENEX SCORE | D21: KIMBERLY-CLARK | E21: KLEENEX | F21: VML | G21: United States | H21: Innovative use of Commerce Channel | I21: https://ascentialcdn.filespin.io/api/v1/conversion/b71f0dff73f3455abef2899f0b1aeb49 | J21: hKBNKbhMwZw | L21: https://www.lovethework.com/work/entries/kleenex-score-756290

Sheet Entertainment
A1: # | B1: Tier | C1: Campaign | D1: Brand | E1: Product/Service | F1: Agency | G1: Country | H1: Subcategory | I1: Image URL | J1: YouTube ID | K1: Campaign Group | L1: Entry URL
A2: 1 | B2: Grand Prix | C2: NIGHT FISHING | D2: HYUNDAI | E2: IONIQ | F2: INNOCEAN | G2: South Korea | H2: Fiction Film: 5-30 minutes | I2: digital-presentation-images/entertainment-hyundai-night-fishing.webp | J2: BTcsn4aLOkQ | L2: https://www.lovethework.com/work/entries/night-fishing-767309
A3: 2 | B3: Gold | C3: THE FINAL COPY OF ILON SPECHT | D3: L'OREAL | E3: L'ORÃAL PARIS | F3: McCANN | G3: France | H3: Non-Fiction Film: 5-30 minutes | I3: digital-presentation-images/entertainment-loreal-the-final-copy-of-ilon-specht.webp | J3: vimeo:1094956645 | L3: https://www.lovethework.com/work/entries/the-final-copy-of-ilon-specht-766871
A4: 3 | B4: Gold | C4: HAALAND PAYBACK TIME | D4: CLASH OF CLANS | E4: CLASH OF CLANS | F4: DAVID | G4: United States | H4: Audience Engagement/Distribution Strategy | I4: https://ascentialcdn.filespin.io/api/v1/conversion/e56e744cd3594eceb82733246e9035b2 | J4: TcQ--NtSQ9s | L4: https://www.lovethework.com/work/entries/haaland-payback-time-766835
A5: 4 | B5: Gold | C5: CAPTION WITH INTENTION | D5: ACADEMY OF MOTION PICTURE ARTS & SCIENCES - RAKISH - CHICAGO HEARING SOCIETY | E5: CLOSED CAPTIONING | F5: FCB CHICAGO | G5: United States | H5: Diversity & Inclusion in Entertainment | I5: https://ascentialcdn.filespin.io/api/v1/conversion/3a7cf992b94648e7abc8a97fc02fb04b | J5: F48khKZhKHM | L5: https://www.lovethework.com/work/entries/caption-with-intention-767270
A6: 5 | B6: Gold | C6: DUNGEONS&DRAGONS: THE LOST EPISODE | D6: HASBRO | E6: TOYS | F6: OGILVY | G6: Brazil | H6: Influencer & Co-Creation | I6: digital-presentation-images/entertainment-hasbro-dungeons-and-dragons-the-lost-episode.webp | J6: vimeo:1080276069 | L6: https://www.lovethework.com/work/entries/dungeonsdragons-the-lost-episode-767102
A7: 6 | B7: Gold | C7: TIDE COLLATERAL STAIN STORIES | D7: TIDE | E7: TIDE OXI BOOST | F7: SAATCHI & SAATCHI | G7: United States | H7: Brand Partnerships, Sponsorships & Collaborations | I7: https://ascentialcdn.filespin.io/api/v1/conversion/55473142d6864b37b0a59f44ba97046b | J7: vimeo:1078053795 | L7: https://www.lovethework.com/work/entries/tide-collateral-stain-stories-767268
A8: 7 | B8: Silver | C8: LAP OF LEGENDS | D8: AB INBEV - MICHELOB ULTRA | E8: MICHELOB ULTRA | F8: FCB NEW YORK | G8: United States | H8: Innovation in Branded Content | I8: https://ascentialcdn.filespin.io/api/v1/conversion/00bc8da7a7464d6c8f4154a6b1e3cc23 | J8: vimeo:943372451 | L8: https://www.lovethework.com/work/entries/lap-of-legends-767038
A9: 8 | B9: Silver | C9: CAN'T UNSEE IT | D9: HEINZ KETCHUP & MUSTARD | E9: KRAFT HEINZ | F9: RETHINK | G9: Canada | H9: Brand Partnerships, Sponsorships & Collaborations | I9: https://ascentialcdn.filespin.io/api/v1/conversion/3db7ec7e31b7459bafa082009489d40e | J9: itiHi3WYcSs | L9: https://www.lovethework.com/work/entries/cant-unsee-it-767337
A10: 9 | B10: Silver | C10: OREO SQUARE COOKIE | D10: MONDELEZ INTERNATIONAL | E10: OREO | F10: SAATCHI & SAATCHI | G10: Germany | H10: Audience Engagement/Distribution Strategy | I10: https://ascentialcdn.filespin.io/api/v1/conversion/76013060c8dd4eaab1a92bf04d89af79 | J10: vimeo:1068186645 | L10: https://www.lovethework.com/work/entries/oreo-square-cookie-767454
A11: 10 | B11: Silver | C11: CAPTION WITH INTENTION | D11: ACADEMY OF MOTION PICTURE ARTS & SCIENCES - RAKISH - CHICAGO HEARING SOCIETY | E11: CLOSED CAPTIONING | F11: FCB CHICAGO | G11: United States | H11: Cultural Engagement | I11: https://ascentialcdn.filespin.io/api/v1/conversion/3a7cf992b94648e7abc8a97fc02fb04b | J11: F48khKZhKHM | L11: https://www.lovethework.com/work/entries/caption-with-intention-767304
A12: 11 | B12: Silver | C12: THE FINAL COPY OF ILON SPECHT | D12: L'OREAL | E12: L'ORÃAL PARIS | F12: McCANN | G12: France | H12: Diversity & Inclusion in Entertainment | I12: digital-presentation-images/entertainment-loreal-the-final-copy-of-ilon-specht.webp | J12: vimeo:1094956645 | L12: https://www.lovethework.com/work/entries/the-final-copy-of-ilon-specht-766850
A13: 12 | B13: Silver | C13: OLYMPIC GAMES OPENING CEREMONY PARIS 2024 | D13: PARIS 2024 | E13: PARIS 2024 | F13: PANAME 24 | G13: France | H13: Diversity & Inclusion in Entertainment | I13: https://ascentialcdn.filespin.io/api/v1/conversion/60aa1888e5b6444381b060dc1801de84 | J13: vimeo:1093757553 | L13: https://www.lovethework.com/work/entries/olympic-games-opening-ceremony-paris-2024-767406
... A23: 22 | B23: Bronze | C23: STARRING BARS | D23: HEINEKEN | E23: HEINEKEN | F23: LEPUB | G23: Italy | H23: Brand Partnerships, Sponsorships & Collaborations | I23: https://ascentialcdn.filespin.io/api/v1/conversion/6544f095e71a47a39d27334e2404e951 | J23: VNq1oogkrYk | L23: https://www.lovethework.com/work/entries/starring-bars-767438

Sheet Entertainment Lions for Sport
A1: # | B1: Tier | C1: Campaign | D1: Brand | E1: Product/Service | F1: Agency | G1: Country | H1: Subcategory | I1: Image URL | J1: YouTube ID | K1: Campaign Group | L1: Entry URL
A2: 1 | B2: Grand Prix | C2: HAALAND PAYBACK TIME | D2: CLASH OF CLANS | E2: CLASH OF CLANS | F2: DAVID | G2: United States | H2: Partnerships with Sports Talent | I2: https://ascentialcdn.filespin.io/api/v1/conversion/0ab9c1eb4c5a4e82b68ff5fcca75da6b | J2: TcQ--NtSQ9s | L2: https://www.lovethework.com/work/entries/haaland-payback-time-762223
A3: 2 | B3: Gold | C3: OLYMPIC GAMES OPENING CEREMONY PARIS 2024 | D3: PARIS 2024 | E3: PARIS 2024 | F3: PANAME 24 | G3: France | H3: Broadcast/Live Streaming | I3: https://ascentialcdn.filespin.io/api/v1/conversion/60aa1888e5b6444381b060dc1801de84 | J3: vimeo:1093757553 | L3: https://www.lovethework.com/work/entries/olympic-games-opening-ceremony-paris-2024-757241
A4: 3 | B4: Gold | C4: SIGNED BY FANATICS | D4: FANATICS | E4: Licensed Sports Merchandise | F4: FANATICS | G4: United States | H4: Esports & Gaming | I4: https://ascentialcdn.filespin.io/api/v1/conversion/6dec2b71e9e0467cb429446b1f864686 | J4: vimeo:1094224675 | L4: https://www.lovethework.com/work/entries/signed-by-fanatics-757314
A5: 4 | B5: Gold | C5: KYIKATEJÊ | D5: GAVIÃO KYIKATEJÊ FOOTBALL CLUB, AREA 23 | E5: GAVIÃO KYIKATEJÃ FOOTBALL CLUB | F5: AN IPG HEALTH COMPANY | G5: United States | H5: Film Series and Audio | I5: digital-presentation-images/entertainment-lions-for-sport-gaviao-kyikateje-football-club-kyikateje.webp | J5: vimeo:1080359037 | L5: https://www.lovethework.com/work/entries/kyikatej-757331
A6: 5 | B6: Gold | C6: THE 4TH JUDGE | D6: THE RING | E6: BOXING EVENT | F6: BIGTIME CREATIVE SHOP | G6: Saudi Arabia | H6: Innovation in Sport | I6: https://ascentialcdn.filespin.io/api/v1/conversion/564dea338e9e42018a7f0c9b66595cae | J6: vimeo:1056470221 | L6: https://www.lovethework.com/work/entries/the-4th-judge-762406
A7: 6 | B7: Gold | C7: OBSESSION | D7: RIYADH SEASON | E7: BOXING FIGHT | F7: BIGTIME CREATIVE SHOP | G7: Saudi Arabia | H7: Use of Humour | I7: digital-presentation-images/entertainment-lions-for-sport-riyadh-season-obsession.webp | J7: PdcUQwAtDDs | L7: https://www.lovethework.com/work/entries/obsession-763910
A8: 7 | B8: Silver | C8: PAID THROUGH PARENTS | D8: COORS BREWING COMPANY | E8: MOLSON COORS | F8: RETHINK | G8: Canada | H8: Brand Partnerships, Sponsorships & Collaborations | I8: https://ascentialcdn.filespin.io/api/v1/conversion/a5629a97973948f688643981b63ac56e | J8: 8urf8-B-xrE | L8: https://www.lovethework.com/work/entries/paid-through-parents-757385
A9: 8 | B9: Silver | C9: RUNNING IN FEAR | D9: ALMA PRETA | E9: ALMA PRETA | F9: LEW'LARA\TBWA | G9: Brazil | H9: Diversity & Inclusion in Sport | I9: https://ascentialcdn.filespin.io/api/v1/conversion/091d74f6176f4334bcedd28604ff10a5 | J9: mgBubkLmF-g | L9: https://www.lovethework.com/work/entries/running-in-fear-757711
A10: 9 | B10: Silver | C10: THE 4TH JUDGE | D10: THE RING | E10: BOXING EVENT | F10: BIGTIME CREATIVE SHOP | G10: Saudi Arabia | H10: Sports Live Experience | I10: https://ascentialcdn.filespin.io/api/v1/conversion/564dea338e9e42018a7f0c9b66595cae | J10: vimeo:1056470221 | L10: https://www.lovethework.com/work/entries/the-4th-judge-762326
A11: 10 | B11: Silver | C11: AVANI'S GOLD | D11: BRITANNIA MARIE GOLD | E11: BRITANNIA MARIE GOLD | F11: TALENTED | G11: India | H11: Brand Storytelling | I11: https://ascentialcdn.filespin.io/api/v1/conversion/e0e7f0a8eeed48888d3d57f241eb99ae | J11: dz9sYI3dZ-0 | L11: https://www.lovethework.com/work/entries/avanis-gold-757226
A12: 11 | B12: Silver | C12: HAALAND PAYBACK TIME | D12: CLASH OF CLANS | E12: CLASH OF CLANS | F12: DAVID | G12: United States | H12: Esports & Gaming | I12: https://ascentialcdn.filespin.io/api/v1/conversion/0ab9c1eb4c5a4e82b68ff5fcca75da6b | J12: TcQ--NtSQ9s | L12: https://www.lovethework.com/work/entries/haaland-payback-time-762343
A13: 12 | B13: Silver | C13: KYIKATEJÊ | D13: GAVIÃO KYIKATEJÊ FOOTBALL CLUB, AREA 23 | E13: GAVIÃO KYIKATEJÃ FOOTBALL CLUB | F13: AN IPG HEALTH COMPANY | G13: United States | H13: Diversity & Inclusion in Sport | I13: digital-presentation-images/entertainment-lions-for-sport-gaviao-kyikateje-football-club-kyikateje.webp | J13: vimeo:1080359037 | L13: https://www.lovethework.com/work/entries/kyikatej-757692
... A27: 26 | B27: Bronze | C27: FIELDS OF GLORY | D27: PILSEN BEER | E27: PILSEN BEER | F27: MONKS | G27: Colombia | H27: Brand Partnerships, Sponsorships & Collaborations | I27: https://ascentialcdn.filespin.io/api/v1/conversion/3c8c2a1d775049aeb067fb493759f83d | J27: 3nAP3n43rok | L27: https://www.lovethework.com/work/entries/fields-of-glory-757481

Sheet Creative Strategy
A1: # | B1: Tier | C1: Campaign | D1: Brand | E1: Product/Service | F1: Agency | G1: Country | H1: Subcategory | I1: Image URL | J1: YouTube ID | K1: Campaign Group | L1: Entry URL
A2: 1 | B2: Grand Prix | C2: REAL BEAUTY: HOW A SOAP BRAND CREATED A GLOBAL SELF-ESTEEM MOVEMENT | D2: DOVE | E2: DOVE | F2: OGILVY UK | G2: United Kingdom | H2: Long-Term Brand Platform | I2: digital-presentation-images/creative-strategy-dove-real-beauty-how-a-soap-brand-created-a-global-self-esteem-movement.webp | J2: puQ0PNZ1W-A | L2: https://www.lovethework.com/work/entries/real-beauty-how-a-soap-brand-created-a-global-self-esteem-movement-757207
A3: 2 | B3: Gold | C3: SATO 2531 | D3: ASUNIWA | E3: THINK NAME PROJECT | F3: DENTSU DIGITAL | G3: Japan | H3: Data & Analytics | I3: digital-presentation-images/creative-strategy-asuniwa-sato-2531.webp | J3: BW5T0gC6o3o | L3: https://www.lovethework.com/work/entries/sato-2531-756616
A4: 3 | B4: Gold | C4: HUMANIMAL TOURISM | D4: PROCOLOMBIA | E4: COLOMBIA, THE COUNTRY OF BEAUTY | F4: DDB COLOMBIA | G4: Colombia | H4: Data & Analytics | I4: digital-presentation-images/creative-strategy-procolombia-humanimal-tourism.webp | J4: 1r6DMx0FOYk | L4: https://www.lovethework.com/work/entries/humanimal-tourism-756682
A5: 4 | B5: Gold | C5: AXA - THREE WORDS | D5: AXA | E5: INSURANCE | F5: PUBLICIS CONSEIL | G5: France | H5: Products/Services | I5: digital-presentation-images/creative-strategy-axa-axa-three-words.webp | J5: pY-03zuV7mE | L5: https://www.lovethework.com/work/entries/axa-three-words-757080
A6: 5 | B6: Gold | C6: THE NEW PRESIDENT | D6: ANNAHAR NEWSPAPER | E6: ANNAHAR NEWSPAPER | F6: IMPACT BBDO | G6: United Arab Emirates | H6: Media/Entertainment | I6: https://ascentialcdn.filespin.io/api/v1/conversion/04e3ef953a454b9da10f1982fa8553b3 | J6: MeCjFylJMVo | L6: https://www.lovethework.com/work/entries/the-new-president-756636
A7: 6 | B7: Gold | C7: PEDIGREE CARAMELO | D7: PEDIGREE | E7: PEDIGREE | F7: ALMAPBBDO | G7: Brazil | H7: Brand Strategy | I7: digital-presentation-images/creative-strategy-pedigree-caramelo.webp | J7: prMM0H9psRs | L7: https://www.lovethework.com/work/entries/pedigree-caramelo-762215
A8: 7 | B8: Silver | C8: CHOOSE UBER | D8: HEETCH | E8: HEETCH | F8: BETC | G8: France | H8: Brave Brands | I8: https://ascentialcdn.filespin.io/api/v1/conversion/fd2b448479ca41b7aa08b7d8a4bd8749 | J8: l9rO0yGTLEM | L8: https://www.lovethework.com/work/entries/choose-uber-762197
A9: 8 | B9: Silver | C9: ANNAHAR'S ACTIVE JOURNALISM | D9: ANNAHAR | E9: ANNAHAR | F9: IMPACT BBDO | G9: United Arab Emirates | H9: Long-Term Brand Platform | I9: https://ascentialcdn.filespin.io/api/v1/conversion/b4e46a523b114724a7376a0c7e970774 | J9: vimeo:1094885200 | L9: https://www.lovethework.com/work/entries/annahars-active-journalism-757177
A10: 9 | B10: Silver | C10: DAISY VS SCAMMERS | D10: O2 | E10: DAISY VS SCAMMERS | F10: VCCP | G10: United Kingdom | H10: Breakthrough on a Budget | I10: digital-presentation-images/creative-strategy-o2-daisy-vs-scammers.webp | J10: tnfhe_XMg7U | L10: https://www.lovethework.com/work/entries/daisy-vs-scammers-756893
A11: 10 | B11: Silver | C11: FOUND IN TRANSLATION | D11: MEDALLA LIGHT | E11: MEDALLA LIGHT | F11: DDB LATINA PUERTO RICO | G11: Puerto Rico | H11: Cultural Engagement | I11: digital-presentation-images/creative-strategy-medalla-light-found-in-translation.webp | J11: O_uAjIgBx2g | L11: https://www.lovethework.com/work/entries/found-in-translation-757072
A12: 11 | B12: Silver | C12: THE LAST BARF BAG | D12: DRAMAMINE | E12: DRAMAMINE | F12: FCB CHICAGO | G12: United States | H12: Healthcare | I12: digital-presentation-images/creative-strategy-dramamine-the-last-barf-bag.webp | J12: QEJe_2ygBzQ | L12: https://www.lovethework.com/work/entries/the-last-barf-bag-756641
A13: 12 | B13: Silver | C13: IT'S A CHEETOS THING | D13: CHEETOS | PEPSICO | E13: CHEETOS | F13: GOODBY SILVERSTEIN & PARTNERS | G13: United States | H13: Long-Term Brand Platform | I13: digital-presentation-images/creative-strategy-cheetos-pepsico-its-a-cheetos-thing.webp | J13: vimeo:1094791063 | L13: https://www.lovethework.com/work/entries/its-a-cheetos-thing-757167
... A29: 28 | B29: Bronze | C29: SATO 2531 | D29: ASUNIWA | E29: THINK NAME PROJECT | F29: DENTSU DIGITAL | G29: Japan | H29: Cultural Engagement | I29: digital-presentation-images/creative-strategy-asuniwa-sato-2531.webp | J29: BW5T0gC6o3o | L29: https://www.lovethework.com/work/entries/sato-2531-757065

Sheet Industry Craft
A1: # | B1: Tier | C1: Campaign | D1: Brand | E1: Product/Service | F1: Agency | G1: Country | H1: Subcategory | I1: Image URL | J1: YouTube ID | K1: Campaign Group | L1: Entry URL
A2: 1 | B2: Grand Prix | C2: NIGRUM CORPUS | D2: IDOMED | E2: NIGRUM CORPUS | F2: ARTPLAN | G2: Brazil | H2: Art Direction: Print & Publishing | I2: https://ascentialcdn.filespin.io/api/v1/conversion/bf5407e59cfa412f991854f10cadc2f2 | J2: vimeo:1089083708 | L2: https://www.lovethework.com/work/entries/nigrum-corpus-755517
A3: 2 | B3: Gold | C3: PROJECT 4270 | D3: BANCO DE CHILE | E3: BANCO DE CHILE | F3: BBDO CHILE | G3: Chile | H3: Photography: Brand & Communications Design | I3: https://ascentialcdn.filespin.io/api/v1/conversion/49a6511e16b04d3a992e7af24cead47a | J3: ge_gHOV-RZc | L3: https://www.lovethework.com/work/entries/project-4270-755469
A4: 3 | B4: Gold | C4: EYE SCAN | D4: 1001 OPTOMETRY | E4: 1001 OPTOMETRY | F4: VML | G4: Australia | H4: Art Direction: Outdoor | I4: https://ascentialcdn.filespin.io/api/v1/conversion/0d649f054bbc45eb8338454f58477357 | J4: e1py_XZAMkk | K4: 1001-optometry-art-direction-outdoor | L4: https://www.lovethework.com/work/entries/eye-scan-755297
A5: 4 | B5: Gold | C5: EYE TEST | D5: 1001 OPTOMETRY | E5: 1001 OPTOMETRY | F5: VML | G5: Australia | H5: Art Direction: Outdoor | I5: digital-presentation-images/industry-craft-1001-optometry-eye-test.webp | J5: e1py_XZAMkk | K5: 1001-optometry-art-direction-outdoor | L5: https://www.lovethework.com/work/entries/eye-test-755288
A6: 5 | B6: Gold | C6: EYECARE | D6: 1001 OPTOMETRY | E6: 1001 OPTOMETRY | F6: VML | G6: Australia | H6: Art Direction: Outdoor | I6: https://ascentialcdn.filespin.io/api/v1/conversion/1414d4463a6843cf997e70a4225294ad | J6: e1py_XZAMkk | K6: 1001-optometry-art-direction-outdoor | L6: https://www.lovethework.com/work/entries/eyecare-755309
A7: 6 | B7: Gold | C7: WINNING ISN'T COMFORTABLE | D7: NIKE | E7: NIKE | F7: WIEDEN+KENNEDY | G7: United States | H7: Copywriting: Brand & Communications Design | I7: https://ascentialcdn.filespin.io/api/v1/conversion/3550c1fc27e344ca95537ef31e739800 | J7: FFFmnfdBrm8 | L7: https://www.lovethework.com/work/entries/winning-isnt-comfortable-755643
A8: 7 | B8: Gold | C8: NO LABELS | D8: NIKKA WHISKY | E8: NIKKA WHISKY | F8: DENTSU INC. | G8: Japan | H8: Photography: Brand & Communications Design | I8: https://ascentialcdn.filespin.io/api/v1/conversion/298920c22d6d4405bd030b3c48358045 | J8: vimeo:1094008740 | L8: https://www.lovethework.com/work/entries/no-labels-755428
A9: 8 | B9: Silver | C9: THE PHILHARMONIC PRINTS – FOYER WINDOWS, 1ST FLOOR | D9: BERLINER PHILHARMONIKER | E9: BERLINER PHILHARMONIKER | F9: SCHOLZ & FRIENDS | G9: Germany | H9: Art Direction: Outdoor | I9: https://ascentialcdn.filespin.io/api/v1/conversion/45b82704ea3c485b85b739da362c39ed | J9: vimeo:1093696994 | K9: berliner-philharmoniker-art-direction-outdoor | L9: https://www.lovethework.com/work/entries/the-philharmonic-prints-foyer-windows-1st-floor-762038
A10: 9 | B10: Silver | C10: MOCTEZUMA — CEMENT REIMAGINED IN MEXICO | D10: MOCTEZUMA | E10: MOCTEZUMA CEMENT | F10: BRANDS&PEOPLE | G10: Mexico | H10: Art Direction: Packaging Design | I10: https://ascentialcdn.filespin.io/api/v1/conversion/45acab20ec964b83b71a1ef010683ff4 | J10: DTHrH8UT9Ow | L10: https://www.lovethework.com/work/entries/moctezuma-cement-reimagined-in-mexico-762817
A11: 10 | B11: Silver | C11: DESIGNING PARIS 2024 | D11: COJOP 2024 | E11: PARIS 2024 OLYMPIC GAMES | F11: W CONRAN DESIGN | G11: France | H11: Art Direction: Brand & Communications Design | I11: https://ascentialcdn.filespin.io/api/v1/conversion/d08dfedd3b1440c495f9825ba37be9ee | J11: b-00yk-YunY | L11: https://www.lovethework.com/work/entries/designing-paris-2024-755182
A12: 11 | B12: Silver | C12: MADE TO SHARE | D12: CADBURY | E12: CADBURY DAIRY MILK | F12: VCCP | G12: United Kingdom | H12: Copywriting: Packaging Design | I12: https://ascentialcdn.filespin.io/api/v1/conversion/e8adc13b9108423d81f397fa0733aba6 | J12: 4GIFbq2eeFg | L12: https://www.lovethework.com/work/entries/made-to-share-764634
A13: 12 | B13: Silver | C13: YOU MUST BE HUMAN | D13: WORLDCOIN | E13: WORLD ID | F13: adam&eveBerlin | G13: Germany | H13: Copywriting: Outdoor | I13: https://ascentialcdn.filespin.io/api/v1/conversion/afbd21854dee4741933864bfb260b620 | J13: Gw_U4uH5-9g | L13: https://www.lovethework.com/work/entries/you-must-be-human-764585
A14: 13 | B14: Silver | C14: 60 YEARS OF FILM | D14: CHICAGO INTERNATIONAL FILM FESTIVAL | E14: CHICAGO INTERNATIONAL FILM FESTIVAL | F14: OGILVY | G14: United States | H14: Art Direction: Brand & Communications Design | I14: https://ascentialcdn.filespin.io/api/v1/conversion/9ae725d9e1774872a4971b3b6e62fbbb | L14: https://www.lovethework.com/work/entries/60-years-of-film-761969
A15: 14 | B15: Silver | C15: THE PHILHARMONIC PRINTS – STAGE FLOOR, GREAT HALL | D15: BERLINER PHILHARMONIKER | E15: BERLINER PHILHARMONIKER | F15: SCHOLZ & FRIENDS | G15: Germany | H15: Art Direction: Outdoor | I15: https://ascentialcdn.filespin.io/api/v1/conversion/f59ad983232a4d4185656043a643b86d | J15: vimeo:1093696994 | K15: berliner-philharmoniker-art-direction-outdoor | L15: https://www.lovethework.com/work/entries/the-philharmonic-prints-stage-floor-great-hall-762059
A16: 15 | B16: Bronze | C16: BOAT | D16: CORNETTO | E16: CORNETTO ICE CREAM | F16: LOLA MULLENLOWE | G16: Spain | H16: Art Direction: Outdoor | I16: https://ascentialcdn.filespin.io/api/v1/conversion/3a177c8b37754037a19ddf0d99c858db | J16: hWhvFLwHOlE | K16: cornetto-art-direction-outdoor | L16: https://www.lovethework.com/work/entries/boat-764631
A17: 16 | B17: Bronze | C17: PROTECTOR OF THE CHALICE | D17: STELLA ARTOIS | E17: STELLA ARTOIS | F17: GREY | G17: United Kingdom | H17: Art Direction: Print & Publishing | I17: https://ascentialcdn.filespin.io/api/v1/conversion/a33c9462c05d4330895b056745b6a602 | K17: stella-artois-art-direction-print-publishing | L17: https://www.lovethework.com/work/entries/protector-of-the-chalice-755403
A18: 17 | B18: Bronze | C18: WINIS FONT | D18: WINIS | E18: WINIS CANDY | F18: D14S | G18: Mexico | H18: Art Direction: Brand & Communications Design | I18: https://ascentialcdn.filespin.io/api/v1/conversion/bddc09c58f164186b2e60a6ff81be5d1 | J18: nSdGQxDXGSs | L18: https://www.lovethework.com/work/entries/winis-font-763701
A19: 18 | B19: Bronze | C19: 855-HOW-TO-QUIT-(OPIOIDS) | D19: ANZEN HEALTH | E19: 855-HOW-TO-QUIT-HELPLINE | F19: SERVICEPLAN GERMANY | G19: Germany | H19: Art Direction: Brand & Communications Design | I19: https://ascentialcdn.filespin.io/api/v1/conversion/8f5ea045b19848018f457f855087bd79 | J19: I_xvPLZ9DDk | L19: https://www.lovethework.com/work/entries/855-how-to-quit-opioids-755234
A20: 19 | B20: Bronze | C20: MAKE LOVE LAST - LIVING ROOM | D20: VIATRIS | E20: VIAGRA | F20: OGILVY | G20: China | H20: Photography: Outdoor | I20: digital-presentation-images/industry-craft-viatris-make-love-last-living-room.webp | J20: vimeo:1086963204 | K20: viatris-photography-outdoor | L20: https://www.lovethework.com/work/entries/make-love-last-living-room-755540
A21: 20 | B21: Bronze | C21: 'THE SHINING' | D21: COCA-COLA | E21: COCA-COLA | F21: VML | G21: United States | H21: Art Direction: Print & Publishing | I21: https://ascentialcdn.filespin.io/api/v1/conversion/5e0c4fda3f3d4bc2ad2e0d8b2247d936 | J21: vimeo:1124237531 | K21: coca-cola-art-direction-print-publishing | L21: https://www.lovethework.com/work/entries/the-shining-755543
A22: 21 | B22: Bronze | C22: MAKE LOVE LAST - BEDROOM | D22: VIATRIS | E22: VIAGRA | F22: OGILVY | G22: China | H22: Photography: Outdoor | I22: https://ascentialcdn.filespin.io/api/v1/conversion/c1c1d7e736414c30b0c7dd8125ee00de | J22: vimeo:1086963204 | K22: viatris-photography-outdoor | L22: https://www.lovethework.com/work/entries/make-love-last-bedroom-755520
A23: 22 | B23: Bronze | C23: TENNESSEE SOUND SITES | D23: TENNESSEE DEPARTMENT OF TOURIST DEVELOPMENT | E23: TENNESSEE DEPARTMENT OF TOURIST DEVELOPMENT | F23: VML | G23: United States | H23: Copywriting: Excellence in Image Description | I23: https://ascentialcdn.filespin.io/api/v1/conversion/eb513fac29984db2811524e932026062 | J23: cE9pTxrtkjk | L23: https://www.lovethework.com/work/entries/tennessee-sound-sites-755571
A24: 23 | B24: Bronze | C24: SURFER | D24: CORNETTO | E24: CORNETTO ICE CREAM | F24: LOLA MULLENLOWE | G24: Spain | H24: Art Direction: Outdoor | I24: https://ascentialcdn.filespin.io/api/v1/conversion/9ceaf650a007496f90b6d5670786b4df | J24: hWhvFLwHOlE | K24: cornetto-art-direction-outdoor | L24: https://www.lovethework.com/work/entries/surfer-764652
A25: 24 | B25: Bronze | C25: 'EXTREME METAPHORS' | D25: COCA-COLA | E25: COCA-COLA | F25: VML | G25: United States | H25: Art Direction: Print & Publishing | I25: https://ascentialcdn.filespin.io/api/v1/conversion/e7e539cb5808438292eda4ab47fb950f | J25: vimeo:1124237531 | K25: coca-cola-art-direction-print-publishing | L25: https://www.lovethework.com/work/entries/extreme-metaphors-755369
A26: 25 | B26: Bronze | C26: 'A HOUSE FOR MR. BISWAS' | D26: COCA-COLA | E26: COCA-COLA | F26: VML | G26: United States | H26: Art Direction: Print & Publishing | I26: https://ascentialcdn.filespin.io/api/v1/conversion/9c2384ef085943848ac188cd6d5d9a43 | J26: vimeo:1124237531 | K26: coca-cola-art-direction-print-publishing | L26: https://www.lovethework.com/work/entries/a-house-for-mr-biswas-755553
A27: 26 | B27: Bronze | C27: WAVES | D27: CORNETTO | E27: CORNETTO ICE CREAM | F27: LOLA MULLENLOWE | G27: Spain | H27: Art Direction: Outdoor | I27: https://ascentialcdn.filespin.io/api/v1/conversion/35c567148f6e40e1a267849bde62ba92 | J27: hWhvFLwHOlE | K27: cornetto-art-direction-outdoor | L27: https://www.lovethework.com/work/entries/waves-764642
A28: 27 | B28: Bronze | C28: FLAGS OF UNITY | D28: AMREF | E28: AMREF | F28: EDELMAN | G28: United Kingdom | H28: Art Direction: Brand & Communications Design | I28: https://ascentialcdn.filespin.io/api/v1/conversion/9614d02c7bc4416ba1536c73770f5d8e | J28: Vddqdo02OOQ | L28: https://www.lovethework.com/work/entries/flags-of-unity-755285
A29: 28 | B29: Bronze | C29: THE SHAKESPEARE BIC | D29: BIC | E29: BIC CRYSTAL PEN | F29: VML | G29: Brazil | H29: Art Direction: Print & Publishing | I29: digital-presentation-images/industry-craft-bic-the-shakespeare-bic.webp | J29: 5ngNVTeyi4g | L29: https://www.lovethework.com/work/entries/the-shakespeare-bic-755424
A30: 29 | B30: Bronze | C30: WINTER TAKES ON COLORS | D30: MCDONALD'S POLSKA | E30: DRWALA BURGER (LIMITED TIMED OFFER) | F30: DDB WARSAW | G30: Poland | H30: Art Direction: Outdoor | I30: digital-presentation-images/industry-craft-mcdonalds-polska-winter-takes-on-colors.webp | J30: qcSHtBgAB6o | L30: https://www.lovethework.com/work/entries/winter-takes-on-colors-755528
A31: 30 | B31: Bronze | C31: HAPPINESS WITHIN CHAOS | D31: STELLA ARTOIS | E31: STELLA ARTOIS | F31: GREY | G31: United Kingdom | H31: Art Direction: Print & Publishing | I31: https://ascentialcdn.filespin.io/api/v1/conversion/882ea591b6fa40b29a529180b71afa65 | K31: stella-artois-art-direction-print-publishing | L31: https://www.lovethework.com/work/entries/happiness-within-chaos-755413

Sheet Health & Wellness
A1: # | B1: Tier | C1: Campaign | D1: Brand | E1: Product/Service | F1: Agency | G1: Country | H1: Subcategory | I1: Image URL | J1: YouTube ID | K1: Campaign Group | L1: Entry URL
A2: 1 | B2: Grand Prix | C2: VASELINE VERIFIED | D2: UNILEVER | E2: VASELINE | F2: OGILVY | G2: Singapore | H2: Social & Creator - OTC Applications | I2: https://ascentialcdn.filespin.io/api/v1/conversion/faf0755b0d4e4594ad93cb75d6288e3d | J2: vimeo:1082798104 | L2: https://www.lovethework.com/work/entries/vaseline-verified-753151
A3: 2 | B3: Gold | C3: THE COUNT | D3: SICKKIDS FOUNDATION | E3: SICKKIDS FOUNDATION | F3: FCB TORONTO | G3: Canada | H3: Film Craft: Use of Music/Sound Design - Fundraising & Advocacy | I3: digital-presentation-images/health-and-wellness-sickkids-foundation-the-count.webp | J3: qNF34ZROR8s | L3: https://www.lovethework.com/work/entries/the-count-759678
A4: 3 | B4: Gold | C4: GROUP THERAPY | D4: AXA | E4: AXA | F4: VML | G4: France | H4: Entertainment - Brand-Led Education & Awareness | I4: digital-presentation-images/health-and-wellness-axa-group-therapy.webp | J4: cH8-sNMfrOM | L4: https://www.lovethework.com/work/entries/group-therapy-753332
A5: 4 | B5: Gold | C5: SIGHTWALKS | D5: CEMENTO SOL | E5: CEMENT | F5: CIRCUS GREY | G5: Peru | H5: Outdoor: Ambient - Brand-Led Education & Awareness | I5: https://ascentialcdn.filespin.io/api/v1/conversion/96cab410285c45ed905a8377e0cc25f5 | J5: IRuDOllWc-E | L5: https://www.lovethework.com/work/entries/sightwalks-758841
A6: 5 | B6: Gold | C6: ZIP CODE EXAM | D6: ZIP CODE EXAM , AREA 23 | E6: ZIP CODE EXAM | F6: AN IPG HEALTH COMPANY | G6: United States | H6: Creative Data - Non-profit/Foundation-led Education & Awareness | I6: https://ascentialcdn.filespin.io/api/v1/conversion/fcac93d33c3d4b1c93da6b13d3e32b5e | J6: 2f0k9hGHLuA | L6: https://www.lovethework.com/work/entries/zip-code-exam-763308
A7: 6 | B7: Gold | C7: THE BEST PLACE IN THE WORLD TO HAVE HERPES | D7: NEW ZEALAND HERPES FOUNDATION | E7: NEW ZEALAND HERPES FOUNDATION | F7: FINCH | G7: Australia | H7: Entertainment - Non-profit/Foundation-led Education & Awareness | I7: https://ascentialcdn.filespin.io/api/v1/conversion/5d4b1b0582c5428bafb14fcc9670d1dc | J7: vimeo:1083074994 | L7: https://www.lovethework.com/work/entries/the-best-place-in-the-world-to-have-herpes-753429
A8: 7 | B8: Gold | C8: NIGRUM CORPUS | D8: IDOMED | E8: NIGRUM CORPUS | F8: ARTPLAN | G8: Brazil | H8: Industry Craft: Art Direction - Brand-Led Education & Awareness | I8: https://ascentialcdn.filespin.io/api/v1/conversion/2a553b0447c74fe5a2affb443a416633 | J8: vimeo:1089083708 | L8: https://www.lovethework.com/work/entries/nigrum-corpus-759635
A9: 8 | B9: Silver | C9: ZIP CODE EXAM | D9: ZIP CODE EXAM , AREA 23 | E9: ZIP CODE EXAM | F9: AN IPG HEALTH COMPANY | G9: United States | H9: Integrated - Non-profit/Foundation-led Education & Awareness | I9: https://ascentialcdn.filespin.io/api/v1/conversion/ab087ed95b3a43e88ff6b9ef28d02df5 | J9: 2f0k9hGHLuA | L9: https://www.lovethework.com/work/entries/zip-code-exam-765197
A10: 9 | B10: Silver | C10: MEMENTO BEER | D10: ABRACERVA | E10: NON-ALCOHOLIC BEER | F10: OGILVY HEALTH | G10: United States | H10: Healthcare Product Innovation - Nutraceuticals | I10: https://ascentialcdn.filespin.io/api/v1/conversion/976392be2e5d4a0fbac33fda02182549 | J10: vimeo:1099664585 | L10: https://www.lovethework.com/work/entries/memento-beer-752967
A11: 10 | B11: Silver | C11: NAGA SAINT EYE TEST | D11: EYEBETES FOUNDATION | E11: EYE TEST SERVICES | F11: GODREJ CREATIVE LAB | G11: India | H11: Direct - Non-profit/Foundation-led Education & Awareness | I11: https://ascentialcdn.filespin.io/api/v1/conversion/5097b08d039c468999082882e3dc18f4 | J11: vimeo:1107064614 | L11: https://www.lovethework.com/work/entries/naga-saint-eye-test-753527
A12: 11 | B12: Silver | C12: THE MIND GUARDIAN | D12: SAMSUNG | E12: SAMSUNG | F12: CHEIL WORLDWIDE | G12: Spain | H12: Use of Technology - Health & Wellness Tech | I12: https://ascentialcdn.filespin.io/api/v1/conversion/006b57346ea04abda2e417e9ec9c5e39 | J12: UeoOgsVrEE4 | L12: https://www.lovethework.com/work/entries/the-mind-guardian-753085
A13: 12 | B13: Silver | C13: THE RAREST STARS SHINE BRIGHTEST | D13: MONTEFIORE EINSTEIN | E13: MONTEFIORE EINSTEIN | F13: ALTO | G13: United States | H13: Film: Cinema, TV and Digital Film Content - Health Services & Facilities | I13: digital-presentation-images/health-and-wellness-montefiore-einstein-the-rarest-stars-shine-brightest.webp | J13: vimeo:1056957344 | L13: https://www.lovethework.com/work/entries/the-rarest-stars-shine-brightest-753653
... A34: 33 | B34: Bronze | C34: THE RAREST STARS SHINE BRIGHTEST | D34: MONTEFIORE EINSTEIN | E34: MONTEFIORE EINSTEIN | F34: ALTO | G34: United States | H34: Film Craft: Script - Health Services & Facilities | I34: digital-presentation-images/health-and-wellness-montefiore-einstein-the-rarest-stars-shine-brightest.webp | J34: vimeo:1056957344 | L34: https://www.lovethework.com/work/entries/the-rarest-stars-shine-brightest-753581

Sheet PR
A1: # | B1: Tier | C1: Campaign | D1: Brand | E1: Product/Service | F1: Agency | G1: Country | H1: Subcategory | I1: Image URL | J1: YouTube ID | K1: Campaign Group | L1: Entry URL
A2: 1 | B2: Grand Prix | C2: LUCKY YATRA | D2: INDIAN RAILWAYS | E2: RAILWAY SERVICE | F2: FCB INDIA | G2: India | H2: Travel, Leisure, Retail, Restaurants & Fast-Food Chains | I2: https://ascentialcdn.filespin.io/api/v1/conversion/ef118ab5982a4092aa78da671a82d86d | J2: 19fzAvuFq0I | L2: https://www.lovethework.com/work/entries/lucky-yatra-749405
A3: 2 | B3: Gold | C3: THE PARENTAL LEAVE MORTGAGE | D3: NORDEA | E3: THE PARENTAL LEAVE MORTGAGE | F3: NORD DDB | G3: Sweden | H3: Consumer Services/Business to Business | I3: https://ascentialcdn.filespin.io/api/v1/conversion/a8b9edfd44de47b893b950770030cf54 | J3: 9xzGRtPDwCU | L3: https://www.lovethework.com/work/entries/the-parental-leave-mortgage-749615
A4: 3 | B4: Gold | C4: LUCKY YATRA | D4: INDIAN RAILWAYS | E4: RAILWAY SERVICE | F4: FCB INDIA | G4: India | H4: Local Brand | I4: https://ascentialcdn.filespin.io/api/v1/conversion/6ce681a1873344eba0bc91e5d14a4997 | J4: 19fzAvuFq0I | L4: https://www.lovethework.com/work/entries/lucky-yatra-750264
A5: 4 | B5: Gold | C5: HAALAND PAYBACK TIME | D5: CLASH OF CLANS | E5: CLASH OF CLANS | F5: DAVID | G5: United States | H5: Innovative Use of Influencers/Creators | I5: https://ascentialcdn.filespin.io/api/v1/conversion/e56e744cd3594eceb82733246e9035b2 | J5: TcQ--NtSQ9s | L5: https://www.lovethework.com/work/entries/haaland-payback-time-749773
A6: 5 | B6: Gold | C6: NUTTER BUTTER, YOU GOOD? | D6: NUTTER BUTTER | E6: NUTTER BUTTER COOKIE | F6: DENTSU CREATIVE | G6: United States | H6: Content Creation & Production | I6: https://ascentialcdn.filespin.io/api/v1/conversion/6876d84d5b5142e19c9d97302718d0f2 | J6: AzhCsGOqfyg | L6: https://www.lovethework.com/work/entries/nutter-butter-you-good-749742
A7: 6 | B7: Gold | C7: AXA - THREE WORDS | D7: AXA | E7: INSURANCE | F7: PUBLICIS CONSEIL | G7: France | H7: Consumer Services/Business to Business | I7: https://ascentialcdn.filespin.io/api/v1/conversion/e1a85ff134e545c7b049791151432028 | J7: pY-03zuV7mE | L7: https://www.lovethework.com/work/entries/axa-three-words-749672
A8: 7 | B8: Gold | C8: PROGRESSO SOUP DROPS | D8: PROGRESSO | E8: PROGRESSO CANNED SOUPS | F8: EDELMAN | G8: United States | H8: Media Relations | I8: https://ascentialcdn.filespin.io/api/v1/conversion/8a8d409a0e954a6b8f0df7b07bba8cc9 | J8: vimeo:1094573277 | L8: https://www.lovethework.com/work/entries/progresso-soup-drops-749792
A9: 8 | B9: Gold | C9: SUN RESERVE | D9: CORONA | E9: CORONA | F9: GREY | G9: Brazil | H9: Use of Events & Stunts | I9: https://ascentialcdn.filespin.io/api/v1/conversion/652b705dcecc4cb7a72c76e4e22c80e5 | J9: vimeo:1091835567 | L9: https://www.lovethework.com/work/entries/sun-reserve-749967
A10: 9 | B10: Gold | C10: DAISY VS SCAMMERS | D10: O2 | E10: DAISY VS SCAMMERS | F10: VCCP | G10: United Kingdom | H10: Use of Technology | I10: https://ascentialcdn.filespin.io/api/v1/conversion/6f38aa2f9e1c4c1c906cc1fb6b7c7e8b | J10: tnfhe_XMg7U | L10: https://www.lovethework.com/work/entries/daisy-vs-scammers-750173
A11: 10 | B11: Silver | C11: OLYMPIC CURRY | D11: MCDONALD'S | E11: CURRY SAUCE | F11: DDB PARIS | G11: France | H11: Social Engagement | I11: https://ascentialcdn.filespin.io/api/v1/conversion/b8993a8a561d47fe9b9f126b8fbb45ce | J11: tOs7DlcDX0U | L11: https://www.lovethework.com/work/entries/olympic-curry-749727
A12: 11 | B12: Silver | C12: SATO 2531 | D12: ASUNIWA | E12: THINK NAME PROJECT | F12: DENTSU DIGITAL | G12: Japan | H12: Research, Data & Analytics | I12: https://ascentialcdn.filespin.io/api/v1/conversion/32b2b247e87144d9837c4fa1252873da | J12: BW5T0gC6o3o | L12: https://www.lovethework.com/work/entries/sato-2531-749858
A13: 12 | B13: Silver | C13: 36 MONTHS | D13: 36 MONTHS | E13: 36 MONTHS | F13: SUPERMASSIVE | G13: Australia | H13: PR Effectiveness | I13: https://ascentialcdn.filespin.io/api/v1/conversion/cdd8c63860a0458e9216b7b4bf571de5 | J13: KXjKyTfgps8 | L13: https://www.lovethework.com/work/entries/36-months-749925
... A45: 44 | B45: Bronze | C45: SATO 2531 | D45: ASUNIWA | E45: THINK NAME PROJECT | F45: DENTSU DIGITAL | G45: Japan | H45: Single-Market Campaign | I45: https://ascentialcdn.filespin.io/api/v1/conversion/fe9e00109f57461bb9f36f9c845a8be1 | J45: BW5T0gC6o3o | L45: https://www.lovethework.com/work/entries/sato-2531-750198

Sheet Print & Publishing
A1: # | B1: Tier | C1: Campaign | D1: Brand | E1: Product/Service | F1: Agency | G1: Country | H1: Subcategory | I1: Image URL | J1: YouTube ID | K1: Campaign Group | L1: Entry URL
A2: 1 | B2: Grand Prix | C2: PRICE PACKS | D2: PENNY | E2: FOOD/NON-FOOD | F2: SERVICEPLAN GERMANY | G2: Germany | H2: Market Disruption | I2: https://ascentialcdn.filespin.io/api/v1/conversion/67b6df2a0fe64deeb274c91d50040c54 | J2: wXx6z3mDnVc | L2: https://www.lovethework.com/work/entries/price-packs-740125
A3: 2 | B3: Gold | C3: INK OF DEMOCRACY | D3: TIMES OF INDIA GROUP | E3: ELECTION APPEAL | F3: HAVAS | G3: India | H3: Corporate Purpose & Social Responsibility | I3: digital-presentation-images/print-and-publishing-times-of-india-group-ink-of-democracy.webp | J3: Y04IsSy9fCI | L3: https://www.lovethework.com/work/entries/ink-of-democracy-740050
A4: 3 | B4: Gold | C4: HOLI | D4: DOVE | E4: DOVE SOAP | F4: OGILVY | G4: United States | H4: Consumer Goods | I4: https://ascentialcdn.filespin.io/api/v1/conversion/8487f504004046b3b4f39c80f9542955 | J4: vimeo:1083687587 | K4: dove-consumer-goods | L4: https://www.lovethework.com/work/entries/holi-739718
A5: 4 | B5: Gold | C5: ST. PATRICK'S DAY | D5: DOVE | E5: DOVE SOAP | F5: OGILVY | G5: United States | H5: Consumer Goods | I5: https://ascentialcdn.filespin.io/api/v1/conversion/372489df63044fcf8bfb5e5cca943bfe | J5: vimeo:1083687587 | K5: dove-consumer-goods | L5: https://www.lovethework.com/work/entries/st-patricks-day-739704
A6: 5 | B6: Gold | C6: HAPPINESS WITHIN CHAOS | D6: STELLA ARTOIS | E6: STELLA ARTOIS | F6: GREY | G6: United Kingdom | H6: Consumer Goods | I6: https://ascentialcdn.filespin.io/api/v1/conversion/882ea591b6fa40b29a529180b71afa65 | K6: stella-artois-philosophical | L6: https://www.lovethework.com/work/entries/happiness-within-chaos-739654
A7: 6 | B7: Gold | C7: NEW YEAR'S | D7: DOVE | E7: DOVE SOAP | F7: OGILVY | G7: United States | H7: Consumer Goods | I7: https://ascentialcdn.filespin.io/api/v1/conversion/38e5adf42b364346bf882ff41160aabc | J7: vimeo:1083687587 | K7: dove-consumer-goods | L7: https://www.lovethework.com/work/entries/new-years-739696
A8: 7 | B8: Gold | C8: MARDI GRAS | D8: DOVE | E8: DOVE SOAP | F8: OGILVY | G8: United States | H8: Consumer Goods | I8: https://ascentialcdn.filespin.io/api/v1/conversion/616e9779606e4684a96c828d12a9b7a0 | J8: vimeo:1083687587 | K8: dove-consumer-goods | L8: https://www.lovethework.com/work/entries/mardi-gras-739712
A9: 8 | B9: Gold | C9: CARNAVAL | D9: DOVE | E9: DOVE SOAP | F9: OGILVY | G9: United States | H9: Consumer Goods | I9: https://ascentialcdn.filespin.io/api/v1/conversion/3bc75956d7df4f839632c72343fb5cb5 | J9: vimeo:1083687587 | K9: dove-consumer-goods | L9: https://www.lovethework.com/work/entries/carnaval-739726
A10: 9 | B10: Gold | C10: THE SIP OF SANCTUARY | D10: STELLA ARTOIS | E10: STELLA ARTOIS | F10: GREY | G10: United Kingdom | H10: Consumer Goods | I10: https://ascentialcdn.filespin.io/api/v1/conversion/bc046e548975443980453424bc30515a | K10: stella-artois-philosophical | L10: https://www.lovethework.com/work/entries/the-sip-of-sanctuary-739632
A11: 10 | B11: Gold | C11: PROTECTOR OF THE CHALICE | D11: STELLA ARTOIS | E11: STELLA ARTOIS | F11: GREY | G11: United Kingdom | H11: Consumer Goods | I11: https://ascentialcdn.filespin.io/api/v1/conversion/a33c9462c05d4330895b056745b6a602 | K11: stella-artois-philosophical | L11: https://www.lovethework.com/work/entries/protector-of-the-chalice-739644
A12: 11 | B12: Silver | C12: ROSES | D12: OREO | E12: OREO | F12: LEPUB BOGOTA | G12: Colombia | H12: Consumer Goods | I12: https://ascentialcdn.filespin.io/api/v1/conversion/7e2d8fe4c7af49f0b2003ab42f27074e | J12: p_3AcLnU1A8 | K12: oreo-consumer-goods | L12: https://www.lovethework.com/work/entries/roses-764508
A13: 12 | B13: Silver | C13: TOILET PAPER | D13: OREO | E13: OREO | F13: LEPUB BOGOTA | G13: Colombia | H13: Consumer Goods | I13: https://ascentialcdn.filespin.io/api/v1/conversion/96ea34877f1644f4a22d867dfa8e2f5d | J13: p_3AcLnU1A8 | K13: oreo-consumer-goods | L13: https://www.lovethework.com/work/entries/toilet-paper-764491
A14: 13 | B14: Silver | C14: NOT EVERY SMILE STARTS AS A SMILE | D14: COLGATE | E14: COLGATE | F14: VML | G14: France | H14: Social Behaviour | I14: https://ascentialcdn.filespin.io/api/v1/conversion/7795062110544927acc4f73eedfb3d7d | J14: vimeo:1099341785 | L14: https://www.lovethework.com/work/entries/not-every-smile-starts-as-a-smile-740106
A15: 14 | B15: Silver | C15: NOTES ON NOTES | D15: CAPITAL BANK | E15: CAPITAL BANK LOANS | F15: ADPRO& | G15: Jordan | H15: Social Behaviour | I15: https://ascentialcdn.filespin.io/api/v1/conversion/26f992b0fc0e4479b962853921264524 | J15: vimeo:1093833076 | L15: https://www.lovethework.com/work/entries/notes-on-notes-739979
A16: 15 | B16: Silver | C16: PUBLIC TRANSPORT | D16: KITKAT | E16: KITKAT | F16: VML | G16: Czech Republic | H16: Consumer Goods | I16: https://ascentialcdn.filespin.io/api/v1/conversion/5faffc268ac047f7a20b5bf0e2fb5e1a | J16: ByGNQ3wEbEY | K16: kitkat-consumer-goods | L16: https://www.lovethework.com/work/entries/public-transport-760550
A17: 16 | B17: Silver | C17: STREET | D17: KITKAT | E17: KITKAT | F17: VML | G17: Czech Republic | H17: Consumer Goods | I17: https://ascentialcdn.filespin.io/api/v1/conversion/1d6b4cb3e726479c8a6b03da24a5d79e | J17: ByGNQ3wEbEY | K17: kitkat-consumer-goods | L17: https://www.lovethework.com/work/entries/street-760556
A18: 17 | B18: Silver | C18: CROWD | D18: KITKAT | E18: KITKAT | F18: VML | G18: Czech Republic | H18: Consumer Goods | I18: https://ascentialcdn.filespin.io/api/v1/conversion/f6a6e5cb949d4b8fa071221329aa94bf | J18: ByGNQ3wEbEY | K18: kitkat-consumer-goods | L18: https://www.lovethework.com/work/entries/crowd-760545
A19: 18 | B19: Silver | C19: GAME DAY | D19: STELLA ARTOIS | E19: STELLA ARTOIS | F19: OGILVY | G19: United States | H19: Consumer Goods | I19: https://ascentialcdn.filespin.io/api/v1/conversion/7bfaee649e4b417698823553cddf194e | J19: HLbAbQdJTtQ | K19: stella-artois-occasions | L19: https://www.lovethework.com/work/entries/game-day-739606
A20: 19 | B20: Silver | C20: BIRTHDAY PARTY | D20: STELLA ARTOIS | E20: STELLA ARTOIS | F20: OGILVY | G20: United States | H20: Consumer Goods | I20: https://ascentialcdn.filespin.io/api/v1/conversion/7bfaee649e4b417698823553cddf194e | J20: kYb25YZDQ-E | K20: stella-artois-occasions | L20: https://www.lovethework.com/work/entries/birthday-party-739588
A21: 20 | B21: Silver | C21: DINNER | D21: STELLA ARTOIS | E21: STELLA ARTOIS | F21: OGILVY | G21: United States | H21: Consumer Goods | I21: https://ascentialcdn.filespin.io/api/v1/conversion/7bfaee649e4b417698823553cddf194e | J21: bKyHQlIq-dQ | K21: stella-artois-occasions | L21: https://www.lovethework.com/work/entries/dinner-739600
A22: 21 | B22: Silver | C22: BANANAS | D22: OREO | E22: OREO | F22: LEPUB BOGOTA | G22: Colombia | H22: Consumer Goods | I22: https://ascentialcdn.filespin.io/api/v1/conversion/2e8876adc7f74c79b691fdfab21733d3 | J22: p_3AcLnU1A8 | K22: oreo-consumer-goods | L22: https://www.lovethework.com/work/entries/bananas-764516
A23: 22 | B23: Silver | C23: EGGS | D23: OREO | E23: OREO | F23: LEPUB BOGOTA | G23: Colombia | H23: Consumer Goods | I23: https://ascentialcdn.filespin.io/api/v1/conversion/bde69bf2e7be40499498d5c2b091ec54 | J23: p_3AcLnU1A8 | K23: oreo-consumer-goods | L23: https://www.lovethework.com/work/entries/eggs-764497
A24: 23 | B24: Silver | C24: THE SHAKESPEARE BIC | D24: BIC | E24: BIC CRYSTAL PEN | F24: VML | G24: Brazil | H24: Innovative and adapted use of Print & Publishing | I24: https://ascentialcdn.filespin.io/api/v1/conversion/3bc3455889f14af89ad13e749464c1f2 | J24: 5ngNVTeyi4g | L24: https://www.lovethework.com/work/entries/the-shakespeare-bic-740046
A25: 24 | B25: Silver | C25: DUCK | D25: OREO | E25: OREO | F25: LEPUB BOGOTA | G25: Colombia | H25: Consumer Goods | I25: https://ascentialcdn.filespin.io/api/v1/conversion/2b000adce52c43929b343bdac9dd757a | J25: p_3AcLnU1A8 | K25: oreo-consumer-goods | L25: https://www.lovethework.com/work/entries/duck-764523
A26: 25 | B26: Silver | C26: CORONA ECLIPSE | D26: CORONA | E26: CORONA | F26: DAVID | G26: United States | H26: Social Behaviour | I26: https://ascentialcdn.filespin.io/api/v1/conversion/f853d90cf7e444e99add88e4dc3a069b | J26: ViJvHO9BxvU | L26: https://www.lovethework.com/work/entries/corona-eclipse-740137
A27: 26 | B27: Bronze | C27: JORDAN 23 | D27: NBA INDIA | E27: BASKETBALL | F27: LEO | G27: United Arab Emirates | H27: Travel, Leisure, Retail, Restaurants & Fast-Food Chains | I27: https://ascentialcdn.filespin.io/api/v1/conversion/c5b031a5911b4850a76ea7fd56dbea94 | J27: mp4:https://video.adsoftheworld.com/ibifauwq5kyl1e6ba8ooyoj4clnb.mp4 | K27: nba-india-travel-leisure-retail-restaurants-fast-food-chains | L27: https://www.lovethework.com/work/entries/jordan-23-739924
A28: 27 | B28: Bronze | C28: RUNNING | D28: DIRT IS GOOD | E28: PERSIL | F28: MULLENLOWE UK | G28: United Kingdom | H28: Consumer Goods | I28: https://ascentialcdn.filespin.io/api/v1/conversion/7f9c50afbfc4459aa7a6bc82ca0b9c86 | J28: invT2-ON-k4 | K28: dirt-is-good-consumer-goods | L28: https://www.lovethework.com/work/entries/running-739716
A29: 28 | B29: Bronze | C29: WAVES | D29: CORNETTO | E29: CORNETTO ICE CREAM | F29: LOLA MULLENLOWE | G29: Spain | H29: Consumer Goods | I29: https://ascentialcdn.filespin.io/api/v1/conversion/35c567148f6e40e1a267849bde62ba92 | J29: hWhvFLwHOlE | K29: cornetto-consumer-goods | L29: https://www.lovethework.com/work/entries/waves-758582
A30: 29 | B30: Bronze | C30: HISTORY OUTNUMBERED | D30: HISTORY CHANNEL | E30: HISTORY CHANNEL | F30: DENTSU CREATIVE | G30: Portugal | H30: Corporate Purpose & Social Responsibility | I30: https://ascentialcdn.filespin.io/api/v1/conversion/07c2f6587e874a9db8f1446fd7f9d520 | J30: W29029BIbvY | L30: https://www.lovethework.com/work/entries/history-outnumbered-760429
A31: 30 | B31: Bronze | C31: WINDSURF | D31: CORNETTO | E31: CORNETTO ICE CREAM | F31: LOLA MULLENLOWE | G31: Spain | H31: Consumer Goods | I31: https://ascentialcdn.filespin.io/api/v1/conversion/2f9ebcc7b9ec4ad9a4dcf79bd56fa88b | J31: hWhvFLwHOlE | K31: cornetto-consumer-goods | L31: https://www.lovethework.com/work/entries/windsurf-758599
A32: 31 | B32: Bronze | C32: SHAQ 34 | D32: NBA INDIA | E32: BASKETBALL | F32: LEO | G32: United Arab Emirates | H32: Travel, Leisure, Retail, Restaurants & Fast-Food Chains | I32: https://ascentialcdn.filespin.io/api/v1/conversion/e7cc0c06262e42b19cab333197725351 | J32: mp4:https://video.adsoftheworld.com/ibifauwq5kyl1e6ba8ooyoj4clnb.mp4 | K32: nba-india-travel-leisure-retail-restaurants-fast-food-chains | L32: https://www.lovethework.com/work/entries/shaq-34-739934
A33: 32 | B33: Bronze | C33: KICK BOXING | D33: DIRT IS GOOD | E33: PERSIL | F33: MULLENLOWE UK | G33: United Kingdom | H33: Consumer Goods | I33: https://ascentialcdn.filespin.io/api/v1/conversion/38843c3e975e4cdfb57d5df8c625382d | J33: invT2-ON-k4 | K33: dirt-is-good-consumer-goods | L33: https://www.lovethework.com/work/entries/kick-boxing-739728
A34: 33 | B34: Bronze | C34: LEBRON 6 | D34: NBA INDIA | E34: BASKETBALL | F34: LEO | G34: United Arab Emirates | H34: Travel, Leisure, Retail, Restaurants & Fast-Food Chains | I34: https://ascentialcdn.filespin.io/api/v1/conversion/c9a1239df73f4604809221939576d7f1 | J34: mp4:https://video.adsoftheworld.com/ibifauwq5kyl1e6ba8ooyoj4clnb.mp4 | K34: nba-india-travel-leisure-retail-restaurants-fast-food-chains | L34: https://www.lovethework.com/work/entries/lebron-6-739952
A35: 34 | B35: Bronze | C35: FOUND IN TRANSLATION | D35: MEDALLA LIGHT | E35: MEDALLA LIGHT | F35: DDB LATINA PUERTO RICO | G35: Puerto Rico | H35: Cultural Engagement | I35: https://ascentialcdn.filespin.io/api/v1/conversion/e7509fe94193449ab6656099498b127b | J35: O_uAjIgBx2g | L35: https://www.lovethework.com/work/entries/found-in-translation-740061
A36: 35 | B36: Bronze | C36: DIVER | D36: CORNETTO | E36: CORNETTO ICE CREAM | F36: LOLA MULLENLOWE | G36: Spain | H36: Consumer Goods | I36: https://ascentialcdn.filespin.io/api/v1/conversion/e42388f28bfb41c7ad9b20fe7d0d6982 | J36: hWhvFLwHOlE | K36: cornetto-consumer-goods | L36: https://www.lovethework.com/work/entries/diver-758726
A37: 36 | B37: Bronze | C37: EYE - SHOT ON FABER-CASTELL | D37: FABER CASTELL | E37: FABER-CASTELL | F37: DAVID | G37: Brazil | H37: Consumer Goods | I37: https://ascentialcdn.filespin.io/api/v1/conversion/13a4275fa0744f33abce7c940e31f041 | J37: vimeo:946365669 | K37: faber-castell-consumer-goods | L37: https://www.lovethework.com/work/entries/eye-shot-on-faber-castell-739620
A38: 37 | B38: Bronze | C38: BOAT | D38: CORNETTO | E38: CORNETTO ICE CREAM | F38: LOLA MULLENLOWE | G38: Spain | H38: Consumer Goods | I38: https://ascentialcdn.filespin.io/api/v1/conversion/3a177c8b37754037a19ddf0d99c858db | J38: hWhvFLwHOlE | K38: cornetto-consumer-goods | L38: https://www.lovethework.com/work/entries/boat-758573
A39: 38 | B39: Bronze | C39: LEMON - SHOT ON FABER-CASTELL | D39: FABER CASTELL | E39: FABER-CASTELL | F39: DAVID | G39: Brazil | H39: Consumer Goods | I39: https://ascentialcdn.filespin.io/api/v1/conversion/3a49c191a12941509feeea5c2f551a2b | J39: vimeo:946365669 | K39: faber-castell-consumer-goods | L39: https://www.lovethework.com/work/entries/lemon-shot-on-faber-castell-739605
A40: 39 | B40: Bronze | C40: SURFER | D40: CORNETTO | E40: CORNETTO ICE CREAM | F40: LOLA MULLENLOWE | G40: Spain | H40: Consumer Goods | I40: https://ascentialcdn.filespin.io/api/v1/conversion/9ceaf650a007496f90b6d5670786b4df | J40: hWhvFLwHOlE | K40: cornetto-consumer-goods | L40: https://www.lovethework.com/work/entries/surfer-758590
A41: 40 | B41: Bronze | C41: KOBE 8 | D41: NBA INDIA | E41: BASKETBALL | F41: LEO | G41: United Arab Emirates | H41: Travel, Leisure, Retail, Restaurants & Fast-Food Chains | I41: https://ascentialcdn.filespin.io/api/v1/conversion/d693c1e769a741a4b475d5ec8a7e89a1 | J41: mp4:https://video.adsoftheworld.com/ibifauwq5kyl1e6ba8ooyoj4clnb.mp4 | K41: nba-india-travel-leisure-retail-restaurants-fast-food-chains | L41: https://www.lovethework.com/work/entries/kobe-8-739945
A42: 41 | B42: Bronze | C42: SCHOLARSHIP IN BOOKS | D42: UNIASSELVI | E42: SCHOLARSHIPS | F42: BETC HAVAS | G42: Brazil | H42: Corporate Purpose & Social Responsibility | I42: https://ascentialcdn.filespin.io/api/v1/conversion/9dcab7bc84b744cea2a588c2b63f30c2 | J42: vimeo:1093833192 | L42: https://www.lovethework.com/work/entries/scholarship-in-books-740104
A43: 42 | B43: Bronze | C43: PUBIC SERVICE ANNOUNCEMENT | D43: KIEHL'S | E43: KIEHLâS DERMATOLOGIST BRANDâS INTIMATE CARE LINE-UP INCLUDING INGROWN HAIR & TONE CORRECTIVE DROPS. | F43: MARCEL | G43: France | H43: Cultural Engagement | I43: digital-presentation-images/print-and-publishing-kiehls-public-service-announcement.webp | J43: HhChMlLE2QU | L43: https://www.lovethework.com/work/entries/pubic-service-announcement-760516
A44: 43 | B44: Bronze | C44: COFFEE - SHOT ON FABER-CASTELL | D44: FABER CASTELL | E44: FABER-CASTELL | F44: DAVID | G44: Brazil | H44: Consumer Goods | I44: https://ascentialcdn.filespin.io/api/v1/conversion/2d1f419e936b4d0ea17e3840fa1b8a50 | J44: vimeo:946365669 | K44: faber-castell-consumer-goods | L44: https://www.lovethework.com/work/entries/coffee-shot-on-faber-castell-739612
A45: 44 | B45: Bronze | C45: FOOTBALL | D45: DIRT IS GOOD | E45: PERSIL | F45: MULLENLOWE UK | G45: United Kingdom | H45: Consumer Goods | I45: https://ascentialcdn.filespin.io/api/v1/conversion/9d66925a6eb0418eb99f0354abd04b27 | J45: invT2-ON-k4 | K45: dirt-is-good-consumer-goods | L45: https://www.lovethework.com/work/entries/football-739709
A46: 45 | B46: Bronze | C46: COUPON RAIN | D46: MERCADO LIVRE | E46: MERCADO LIVRE | F46: GUT | G46: Brazil | H46: Single-Market Campaign | I46: https://ascentialcdn.filespin.io/api/v1/conversion/36fd55aacbed488286697152f0a3eeb3 | J46: vimeo:1093414319 | L46: https://www.lovethework.com/work/entries/coupon-rain-760474
A47: 46 | B47: Bronze | C47: THE FREEDOM EDITION | D47: SOCIETY | E47: SOCIETY | F47: BETC | G47: France | H47: Corporate Purpose & Social Responsibility | I47: https://ascentialcdn.filespin.io/api/v1/conversion/e09e1f0a06fc44109db762800cac9584 | J47: WK6ONFfbUvI | L47: https://www.lovethework.com/work/entries/the-freedom-edition-740070

Sheet Social & Creator
A1: # | B1: Tier | C1: Campaign | D1: Brand | E1: Product/Service | F1: Agency | G1: Country | H1: Subcategory | I1: Image URL | J1: YouTube ID | K1: Campaign Group | L1: Entry URL
A2: 1 | B2: Grand Prix | C2: VASELINE VERIFIED | D2: UNILEVER | E2: VASELINE | F2: OGILVY | G2: Singapore | H2: Community Building | I2: https://ascentialcdn.filespin.io/api/v1/conversion/faf0755b0d4e4594ad93cb75d6288e3d | J2: vimeo:1082798104 | L2: https://www.lovethework.com/work/entries/vaseline-verified-742887
A3: 2 | B3: Gold | C3: NAVY SUBREDDIT HUNT | D3: U.S. NAVY | E3: U.S. NAVY RECRUITMENT INITIATIVE | F3: VML | G3: United States | H3: Audience Targeting/Engagement Strategies | I3: https://ascentialcdn.filespin.io/api/v1/conversion/acedbde3eb964175b899c5e90a584d7a | J3: 1qkvD-Vpqp4 | L3: https://www.lovethework.com/work/entries/navy-subreddit-hunt-742520
A4: 3 | B4: Gold | C4: RESALE | D4: BUDWEISER | E4: BEER | F4: AFRICA CREATIVE DDB | G4: Brazil | H4: Innovative Engagement of Community | I4: https://ascentialcdn.filespin.io/api/v1/conversion/abd9a65dba9c44ab8abe0ea46a3db71c | J4: vimeo:1079571158 | L4: https://www.lovethework.com/work/entries/resale-742723
A5: 4 | B5: Gold | C5: U UP? | D5: IKEA | E5: IKEA | F5: RETHINK | G5: Canada | H5: Use of Humour | I5: https://ascentialcdn.filespin.io/api/v1/conversion/1d6f8cfcad1b47c9beaa5f403844ec8a | J5: VT02JDQuMxM | L5: https://www.lovethework.com/work/entries/u-up-743199
A6: 5 | B6: Gold | C6: REDDITOR EDIT | D6: SKODA | E6: Å KODA OCTAVIA | F6: LEO | G6: United Kingdom | H6: Co-Creation & User Generated Content | I6: https://ascentialcdn.filespin.io/api/v1/conversion/7581a597717542d6b5b354f2ffcb56a5 | J6: KmLMtKsmwqA | L6: https://www.lovethework.com/work/entries/redditor-edit-743155
A7: 6 | B7: Gold | C7: ERASE VALENTINE'S DAY | D7: MONDELEZ INTERNATIONAL | E7: CADBURY 5 STAR CHOCOLATE | F7: OGILVY | G7: India | H7: Use of Humour | I7: https://ascentialcdn.filespin.io/api/v1/conversion/a64caaaecf144955a62b435827fff0e3 | J7: _9bU3wT71Ac | L7: https://www.lovethework.com/work/entries/erase-valentines-day-743287
A8: 7 | B8: Gold | C8: OLYMPIC CURRY | D8: MCDONALD'S | E8: CURRY SAUCE | F8: DDB PARIS | G8: France | H8: Real-Time Response | I8: https://ascentialcdn.filespin.io/api/v1/conversion/b8993a8a561d47fe9b9f126b8fbb45ce | J8: tOs7DlcDX0U | L8: https://www.lovethework.com/work/entries/olympic-curry-742518
A9: 8 | B9: Gold | C9: NUTTER BUTTER, YOU GOOD? | D9: NUTTER BUTTER | E9: NUTTER BUTTER COOKIE | F9: DENTSU CREATIVE | G9: United States | H9: Breakthrough on a Budget | I9: https://ascentialcdn.filespin.io/api/v1/conversion/6876d84d5b5142e19c9d97302718d0f2 | J9: AzhCsGOqfyg | L9: https://www.lovethework.com/work/entries/nutter-butter-you-good-743552
A10: 9 | B10: Silver | C10: ONE SECOND ADS | D10: BUDWEISER | E10: BEER | F10: AFRICA CREATIVE DDB | G10: Brazil | H10: Content Placement | I10: digital-presentation-images/social-and-creator-budweiser-one-second-ads.webp | J10: d-mtDQXtR6I | K10: budweiser-one-second-ads | L10: https://www.lovethework.com/work/entries/one-second-ads-759513
A11: 10 | B11: Silver | C11: THE DEATH OF DUO | D11: DUOLINGO | E11: DUOLINGO | F11: DUOLINGO | G11: United States | H11: Community Management | I11: https://ascentialcdn.filespin.io/api/v1/conversion/f4109c89080c4d6b8170e479b78d5160 | J11: vimeo:1094581252 | L11: https://www.lovethework.com/work/entries/the-death-of-duo-742331
A12: 11 | B12: Silver | C12: GULF OF MEXICO (BAR) | D12: TECATE | E12: TECATE LIGHT | F12: LEPUB | G12: Mexico | H12: Market Disruption | I12: https://ascentialcdn.filespin.io/api/v1/conversion/afa88aa8421b41a18c68b9863bb6926c | J12: vimeo:1092263623 | L12: https://www.lovethework.com/work/entries/gulf-of-mexico-bar-743548
A13: 12 | B13: Silver | C13: REDDITOR EDIT | D13: SKODA | E13: Å KODA OCTAVIA | F13: LEO | G13: United Kingdom | H13: Audience Targeting/Engagement Strategies | I13: https://ascentialcdn.filespin.io/api/v1/conversion/7581a597717542d6b5b354f2ffcb56a5 | J13: KmLMtKsmwqA | L13: https://www.lovethework.com/work/entries/redditor-edit-742379
A14: 13 | B14: Silver | C14: FIZZOOKA | D14: PERFETTI VAN MELLE | E14: MENTOS | F14: BBH | G14: United Kingdom | H14: Creator Collaboration | I14: https://ascentialcdn.filespin.io/api/v1/conversion/f5ffbe1532054f85b7f9f9b7fba1f1ee | J14: TgjfKovV888 | L14: https://www.lovethework.com/work/entries/fizzooka-742654
A15: 14 | B15: Silver | C15: SEVERANCE S2 - INTEGRATED CAMPAIGN | D15: APPLE | E15: ORIGINAL SERIES ON APPLE TV+ | F15: APPLE | G15: United States | H15: Multi-Platform Social Campaign | I15: https://ascentialcdn.filespin.io/api/v1/conversion/c0034932e80d4cb1aa654cc85c066b7e | J15: QPJtgjoqtdw | L15: https://www.lovethework.com/work/entries/severance-s2-integrated-campaign-743040
A16: 15 | B16: Silver | C16: TIDE COLLATERAL STAIN STORIES | D16: TIDE | E16: TIDE OXI BOOST | F16: SAATCHI & SAATCHI | G16: United States | H16: Brand Storytelling | I16: https://ascentialcdn.filespin.io/api/v1/conversion/2e880efa163040b884c55c34c5aa79f9 | J16: vimeo:1078053795 | L16: https://www.lovethework.com/work/entries/tide-collateral-stain-stories-742510
A17: 16 | B17: Silver | C17: RETRO INFLUENCERS | D17: SKOL | E17: SKOL | F17: GUT | G17: Brazil | H17: Co-Creation & User Generated Content | I17: https://ascentialcdn.filespin.io/api/v1/conversion/16704911a39145c09f1ae466143b410d | J17: FKLnmbWukt0 | L17: https://www.lovethework.com/work/entries/retro-influencers-743091
A18: 17 | B18: Silver | C18: LAY'S BAR CRAWL | D18: LAY'S | E18: LAY'S | F18: SLAP GLOBAL | G18: Argentina | H18: Multi-Platform Social Campaign | I18: https://ascentialcdn.filespin.io/api/v1/conversion/cc887f9119c440728c26ede9e95b1ad2 | J18: HHZjLH4UCS0 | L18: https://www.lovethework.com/work/entries/lays-bar-crawl-743116
A19: 18 | B19: Silver | C19: NAME THIS OREO | D19: OREO | E19: OREO | F19: VML | G19: United States | H19: Creator Collaboration | I19: digital-presentation-images/social-and-creator-oreo-name-this-oreo.webp | J19: vimeo:1078732737 | L19: https://www.lovethework.com/work/entries/name-this-oreo-765219
A20: 19 | B20: Silver | C20: NAME THIS OREO | D20: OREO | E20: OREO | F20: VML | G20: United States | H20: Social Listening & Insight | I20: digital-presentation-images/social-and-creator-oreo-name-this-oreo.webp | J20: vimeo:1078732737 | L20: https://www.lovethework.com/work/entries/name-this-oreo-765219
A21: 20 | B21: Silver | C21: CALL OF DISCOUNTS | D21: MERCADO LIVRE | E21: MERCADO LIVRE | F21: GUT | G21: Brazil | H21: Content Placement | I21: https://ascentialcdn.filespin.io/api/v1/conversion/fffcddb9a87d448bbc386fd70d215d5e | J21: vimeo:1093409251 | L21: https://www.lovethework.com/work/entries/call-of-discounts-742896
A22: 21 | B22: Silver | C22: VASELINE VERIFIED | D22: UNILEVER | E22: VASELINE | F22: OGILVY | G22: Singapore | H22: Healthcare | I22: https://ascentialcdn.filespin.io/api/v1/conversion/faf0755b0d4e4594ad93cb75d6288e3d | J22: vimeo:1082798104 | L22: https://www.lovethework.com/work/entries/vaseline-verified-742181
... A43: 42 | B43: Bronze | C43: SNICKERS AI | D43: SNICKERS | E43: SNICKERS | F43: T&PM | G43: United Kingdom | H43: Co-Creation & User Generated Content | I43: https://ascentialcdn.filespin.io/api/v1/conversion/86bcac60e3f648c7881b028c2d9d2273 | J43: VlRy84v2mXw | L43: https://www.lovethework.com/work/entries/snickers-ai-743048
A44: 43 | B44: Bronze | C44: ONE SECOND ADS | D44: BUDWEISER | E44: BEER | F44: AFRICA CREATIVE DDB | G44: Brazil | H44: Innovative Engagement of Community | I44: digital-presentation-images/social-and-creator-budweiser-one-second-ads.webp | J44: d-mtDQXtR6I | K44: budweiser-one-second-ads | L44: https://www.lovethework.com/work/entries/one-second-ads-759545
A45: 44 | B45: Bronze | C45: CAMDEN STOUT - HONEST REVIEWS | D45: CAMDEN TOWN BREWERY | E45: CAMDEN STOUT | F45: ABINBEV | G45: Belgium | H45: Audience Targeting/Engagement Strategies | I45: https://ascentialcdn.filespin.io/api/v1/conversion/02e1b78a1ce94d84bee44bf8a707550e | J45: vimeo:1077904091 | L45: https://www.lovethework.com/work/entries/camden-stout-honest-reviews-742275
A46: 45 | B46: Bronze | C46: U UP? | D46: IKEA | E46: IKEA | F46: RETHINK | G46: Canada | H46: Breakthrough on a Budget | I46: https://ascentialcdn.filespin.io/api/v1/conversion/1d6f8cfcad1b47c9beaa5f403844ec8a | J46: VT02JDQuMxM | L46: https://www.lovethework.com/work/entries/u-up-743427
A47: 46 | B47: Bronze | C47: BURGER TO KING | D47: BURGER KING, HAPPINESS | E47: BURGER KING | F47: AN FCB ALLIANCE | G47: Belgium | H47: Innovative Engagement of Community | I47: https://ascentialcdn.filespin.io/api/v1/conversion/9c71f6e2352b428784f91e8247db714e | J47: RQVaoU4CGRk | L47: https://www.lovethework.com/work/entries/burger-to-king-760741
A48: 47 | B48: Bronze | C48: THE FLIPPER | D48: HEINEKEN | E48: HEINEKEN | F48: LEPUB | G48: Netherlands | H48: Creator Collaboration | I48: https://ascentialcdn.filespin.io/api/v1/conversion/5e630b6d1a8d43d494544038884723b7 | J48: vimeo:1083152151 | L48: https://www.lovethework.com/work/entries/the-flipper-760602
A49: 48 | B49: Bronze | C49: TRACKING BAD BUNNY | D49: RIMAS MUSIC | E49: BAD BUNNY | F49: DDB LATINA PUERTO RICO | G49: Puerto Rico | H49: Cultural Engagement | I49: https://ascentialcdn.filespin.io/api/v1/conversion/12a3c9e0c6e948eeaa5543a2fedda2c2 | J49: hPLaT_JT9Zw | L49: https://www.lovethework.com/work/entries/tracking-bad-bunny-759002
A50: 49 | B50: Bronze | C50: THE BLACK DOG(S) | D50: SECONDE CHANCE | E50: SECONDE CHANCE | F50: BETC | G50: France | H50: Breakthrough on a Budget | I50: https://ascentialcdn.filespin.io/api/v1/conversion/30aec1c3378c43f3845d46d7e83d4bf5 | J50: eh7nvB91vaM | L50: https://www.lovethework.com/work/entries/the-black-dogs-743512
A51: 50 | B51: Bronze | C51: BASSI VS MEN'S FACEWASH | D51: GARNIER L'OREAL | E51: FACEWASH | F51: BBH INDIA | G51: India | H51: Use of Humour | I51: https://ascentialcdn.filespin.io/api/v1/conversion/f324b2259303465985c6298914501fea | J51: vimeo:1084518468 | L51: https://www.lovethework.com/work/entries/bassi-vs-mens-facewash-743479

Sheet Direct
A1: # | B1: Tier | C1: Campaign | D1: Brand | E1: Product/Service | F1: Agency | G1: Country | H1: Subcategory | I1: Image URL | J1: YouTube ID | K1: Campaign Group | L1: Entry URL
A2: 1 | B2: Grand Prix | C2: AXA - THREE WORDS | D2: AXA | E2: INSURANCE | F2: PUBLICIS CONSEIL | G2: France | H2: Market Disruption | I2: https://ascentialcdn.filespin.io/api/v1/conversion/e1a85ff134e545c7b049791151432028 | J2: pY-03zuV7mE | L2: https://www.lovethework.com/work/entries/axa-three-words-744768
A3: 2 | B3: Gold | C3: COUPON RAIN | D3: MERCADO LIVRE | E3: MERCADO LIVRE | F3: GUT | G3: Brazil | H3: Travel, Leisure, Retail, Restaurants & Fast-Food Chains | I3: https://ascentialcdn.filespin.io/api/v1/conversion/b99de0a05bc54707b1426d24706b518b | J3: vimeo:1093414319 | L3: https://www.lovethework.com/work/entries/coupon-rain-758980
A4: 3 | B4: Gold | C4: U UP? | D4: IKEA | E4: IKEA | F4: RETHINK | G4: Canada | H4: Breakthrough on a Budget | I4: https://ascentialcdn.filespin.io/api/v1/conversion/1d6f8cfcad1b47c9beaa5f403844ec8a | J4: VT02JDQuMxM | L4: https://www.lovethework.com/work/entries/u-up-744634
A5: 4 | B5: Gold | C5: PRICE PACKS | D5: PENNY | E5: FOOD/NON-FOOD | F5: SERVICEPLAN GERMANY | G5: Germany | H5: Experience Design | I5: https://ascentialcdn.filespin.io/api/v1/conversion/67b6df2a0fe64deeb274c91d50040c54 | J5: wXx6z3mDnVc | L5: https://www.lovethework.com/work/entries/price-packs-744245
A6: 5 | B6: Gold | C6: FOOTBALL IS FOR FOOD | D6: UBER EATS | E6: UBER EATS | F6: SPECIAL | G6: United States | H6: Use of Humour | I6: https://ascentialcdn.filespin.io/api/v1/conversion/bdc3e17665e54318a6a9b4e6705f40a7 | J6: Mi_cxUyqH4Q | L6: https://www.lovethework.com/work/entries/football-is-for-food-744614
A7: 6 | B7: Gold | C7: LIDLIZE | D7: LIDL | E7: RETAIL | F7: MARCEL | G7: France | H7: Travel, Leisure, Retail, Restaurants & Fast-Food Chains | I7: https://ascentialcdn.filespin.io/api/v1/conversion/f979928ea0a14ad7a4df5b301de95a0e | J7: mba6sPCSX_8 | L7: https://www.lovethework.com/work/entries/lidlize-760060
A8: 7 | B8: Gold | C8: PRIZE ON THE BONE | D8: KFC | E8: KFC ICE-CREAM | F8: DM9 | G8: Brazil | H8: Launch/Relaunch | I8: https://ascentialcdn.filespin.io/api/v1/conversion/32ef7021bdbd4c4392fa51fb240d45e6 | J8: h4Kl5THlsYw | L8: https://www.lovethework.com/work/entries/prize-on-the-bone-744551
A9: 8 | B9: Gold | C9: LUCKY YATRA | D9: INDIAN RAILWAYS | E9: RAILWAY SERVICE | F9: FCB INDIA | G9: India | H9: Local Brand | I9: https://ascentialcdn.filespin.io/api/v1/conversion/baed08eef7b94a6cabcd62dedb653704 | J9: 19fzAvuFq0I | L9: https://www.lovethework.com/work/entries/lucky-yatra-744460
A10: 9 | B10: Gold | C10: IKEA HIDDEN TAGS | D10: IKEA | E10: IKEA | F10: UZINA | G10: Portugal | H10: Small-Scale Media | I10: https://ascentialcdn.filespin.io/api/v1/conversion/237ade5924eb407898bf58d19f58a52a | J10: oKWkHqlt7yA | L10: https://www.lovethework.com/work/entries/ikea-hidden-tags-743744
A11: 10 | B11: Gold | C11: POTTY-TUNITIES | D11: ANGEL SOFT | E11: ANGEL SOFT TOILET PAPER | F11: GREY | G11: United States | H11: Use of Broadcast | I11: https://ascentialcdn.filespin.io/api/v1/conversion/d1fbeead5aeb4909a43f4920061be696 | J11: eAh8JA18QJA | L11: https://www.lovethework.com/work/entries/potty-tunities-743937
A12: 11 | B12: Gold | C12: PRESERVED PROMOS | D12: ZIPLOC | E12: ZIPLOC | F12: VML | G12: United States | H12: Use of Real-Time Data | I12: https://ascentialcdn.filespin.io/api/v1/conversion/8223f25b769b40e3b665c4ec19e2e12c | J12: F9CTRsV3N7k | L12: https://www.lovethework.com/work/entries/preserved-promos-744127
A13: 12 | B13: Silver | C13: BREASTMILK MONEY | D13: HERCONOMY | E13: HERCONOMY | F13: SERVICEPLAN GERMANY | G13: Germany | H13: Cultural Engagement | I13: https://ascentialcdn.filespin.io/api/v1/conversion/73ea0e639f6747c68cf8460abe2f02bb | J13: vimeo:1094309200 | L13: https://www.lovethework.com/work/entries/breastmilk-money-744959
... A60: 59 | B60: Bronze | C60: DAISY VS SCAMMERS | D60: O2 | E60: DAISY VS SCAMMERS | F60: VCCP | G60: United Kingdom | H60: New Realities & Emerging Tech | I60: https://ascentialcdn.filespin.io/api/v1/conversion/1e451eb4b5bc4d44a6946bac225c6e96 | J60: tnfhe_XMg7U | L60: https://www.lovethework.com/work/entries/daisy-vs-scammers-744081

Sheet Titanium
A1: # | B1: Tier | C1: Campaign | D1: Brand | E1: Product/Service | F1: Agency | G1: Country | H1: Subcategory | I1: Image URL | J1: YouTube ID | K1: Campaign Group | L1: Entry URL
A2: 1 | B2: Titanium Grand Prix | C2: AXA - THREE WORDS | D2: AXA | E2: INSURANCE | F2: PUBLICIS CONSEIL | G2: France | H2: Titanium | I2: https://ascentialcdn.filespin.io/api/v1/conversion/e1a85ff134e545c7b049791151432028 | J2: pY-03zuV7mE | L2: https://www.lovethework.com/work/entries/axa-three-words-748384
A3: 2 | B3: Titanium | C3: PEDIGREE CARAMELO | D3: PEDIGREE | E3: PEDIGREE | F3: ALMAPBBDO | G3: Brazil | H3: Titanium | I3: https://ascentialcdn.filespin.io/api/v1/conversion/61f3c230a91e417397304be1d6a0ef2d | J3: prMM0H9psRs | L3: https://www.lovethework.com/work/entries/pedigree-caramelo-758945
A4: 3 | B4: Titanium | C4: VASELINE VERIFIED | D4: UNILEVER | E4: VASELINE | F4: OGILVY | G4: Singapore | H4: Titanium | I4: https://ascentialcdn.filespin.io/api/v1/conversion/faf0755b0d4e4594ad93cb75d6288e3d | J4: vimeo:1082798104 | L4: https://www.lovethework.com/work/entries/vaseline-verified-758815
A5: 4 | B5: Titanium | C5: CAPTION WITH INTENTION | D5: ACADEMY OF MOTION PICTURE ARTS & SCIENCES - RAKISH - CHICAGO HEARING SOCIETY | E5: CLOSED CAPTIONING | F5: FCB CHICAGO | G5: United States | H5: Titanium | I5: https://ascentialcdn.filespin.io/api/v1/conversion/ec33dea7945841b0a0833542b60f5b36 | J5: F48khKZhKHM | L5: https://www.lovethework.com/work/entries/caption-with-intention-748572

Sheet Digital Craft
A1: # | B1: Tier | C1: Campaign | D1: Brand | E1: Product/Service | F1: Agency | G1: Country | H1: Subcategory | I1: Image URL | J1: YouTube ID | K1: Campaign Group | L1: Entry URL
A2: 1 | B2: Grand Prix | C2: CAPTION WITH INTENTION | D2: ACADEMY OF MOTION PICTURE ARTS & SCIENCES - RAKISH - CHICAGO HEARING SOCIETY | E2: CLOSED CAPTIONING | F2: FCB CHICAGO | G2: United States | H2: UX & Journey Design | I2: https://ascentialcdn.filespin.io/api/v1/conversion/3a8020f6426f40968730b5a8c68a0b35 | J2: F48khKZhKHM | L2: https://www.lovethework.com/work/entries/caption-with-intention-754389
A3: 2 | B3: Gold | C3: TREE CORRESPONDENTS | D3: HYUNDAI | E3: HYUNDAI IONIQ FOREST | F3: FCB NEW YORK | G3: United States | H3: Data Storytelling | I3: https://ascentialcdn.filespin.io/api/v1/conversion/82542e7381744bb783bb6c60f2929b2c | J3: vimeo:1092193263 | L3: https://www.lovethework.com/work/entries/tree-correspondents-762045
A4: 3 | B4: Gold | C4: CAPTION WITH INTENTION | D4: ACADEMY OF MOTION PICTURE ARTS & SCIENCES - RAKISH - CHICAGO HEARING SOCIETY | E4: CLOSED CAPTIONING | F4: FCB CHICAGO | G4: United States | H4: Innovative Use of Technology | I4: https://ascentialcdn.filespin.io/api/v1/conversion/6e437af497a34d6bbc71738a2b9c581b | J4: F48khKZhKHM | L4: https://www.lovethework.com/work/entries/caption-with-intention-754831
A5: 4 | B5: Gold | C5: TREE CORRESPONDENTS | D5: HYUNDAI | E5: HYUNDAI IONIQ FOREST | F5: FCB NEW YORK | G5: United States | H5: Curation of Data | I5: https://ascentialcdn.filespin.io/api/v1/conversion/82542e7381744bb783bb6c60f2929b2c | J5: vimeo:1092193263 | L5: https://www.lovethework.com/work/entries/tree-correspondents-762045
A6: 5 | B6: Silver | C6: THE SHADED ROUTE | D6: HUNGERSTATION | E6: HUNGERSTATION DELIVERY APP | F6: VML | G6: Saudi Arabia | H6: Real-Time Usage & Targeting | I6: https://ascentialcdn.filespin.io/api/v1/conversion/a5387631458b48648c6dba4b21efb3d0 | J6: 5cGxg-wRzsE | L6: https://www.lovethework.com/work/entries/the-shaded-route-754725
A7: 6 | B7: Silver | C7: TREE CORRESPONDENTS | D7: HYUNDAI | E7: HYUNDAI IONIQ FOREST | F7: FCB NEW YORK | G7: United States | H7: Technological Achievement in Digital Craft | I7: https://ascentialcdn.filespin.io/api/v1/conversion/82542e7381744bb783bb6c60f2929b2c | J7: vimeo:1092193263 | L7: https://www.lovethework.com/work/entries/tree-correspondents-762150
A8: 7 | B8: Silver | C8: IN HOT WATER | D8: WORLD WILDLIFE FUND (WWF) | E8: WWF | F8: NOMINT | G8: United Kingdom | H8: Motion Graphics Design & Animation | I8: https://ascentialcdn.filespin.io/api/v1/conversion/f2ca9488d23e45d5b432ce4a6c2e8f08 | J8: vimeo:1028875237 | L8: https://www.lovethework.com/work/entries/in-hot-water-754526
A9: 8 | B9: Silver | C9: SALTANAT LIGHT | D9: CITIX | E9: CITIX | F9: GFORCE | G9: Kazakhstan | H9: Real-Time Contextual Content | I9: https://ascentialcdn.filespin.io/api/v1/conversion/68f2c53ebcea42bd9ab7b58852b5aa95 | J9: POZJDa6y23g | L9: https://www.lovethework.com/work/entries/saltanat-light-764174
A10: 9 | B10: Silver | C10: DAISY VS SCAMMERS | D10: O2 | E10: DAISY VS SCAMMERS | F10: VCCP | G10: United Kingdom | H10: Innovative Use of Technology | I10: https://ascentialcdn.filespin.io/api/v1/conversion/2d7855910ffa41a78e83fffe11540c7b | J10: tnfhe_XMg7U | L10: https://www.lovethework.com/work/entries/daisy-vs-scammers-754726
A11: 10 | B11: Bronze | C11: ALLEVIA POLLEN PASSPORT | D11: Opella-Allegra | E11: ALLEGRA | F11: MRM WORLDWIDE | G11: Spain | H11: Data Visualisation | I11: https://ascentialcdn.filespin.io/api/v1/conversion/5bdbab28251f44eda6fdb7d90fe1a6eb | J11: vimeo:1080313277 | L11: https://www.lovethework.com/work/entries/allevia-pollen-passport-754613
A12: 11 | B12: Bronze | C12: APPLE 100 BEST ALBUMS | D12: APPLE | E12: APPLE MUSIC | F12: TBWA\MEDIA ARTS LAB | G12: United States | H12: Digital Illustration & Image Design | I12: https://ascentialcdn.filespin.io/api/v1/conversion/c56cee379a1249b9912bbe50964ff0d2 | J12: vimeo:1039756308 | L12: https://www.lovethework.com/work/entries/apple-100-best-albums-754412
A13: 12 | B13: Bronze | C13: THE ODYSSEY OF WILSON | D13: VIVO | E13: Telephone Company | F13: AFRICA CREATIVE DDB | G13: Brazil | H13: Data Storytelling | I13: https://ascentialcdn.filespin.io/api/v1/conversion/d824fa39d9d94210af54fc45e5e11735 | J13: vimeo:1082349787 | L13: https://www.lovethework.com/work/entries/the-odissey-of-wilson-754689
... A18: 17 | B18: Bronze | C18: INTERFACE OF HUMANITY POWERED BY NTT | D18: NTT HUMAN INFORMATICS LABORATORIES | E18: NTT HUMAN INFORMATICS LABORATORIES | F18: DENTSU INC. | G18: Japan | H18: UX & Journey Design | I18: https://ascentialcdn.filespin.io/api/v1/conversion/15acf37ec83847ee82067e734a40a3de | J18: 9Yv1aq_N-Ss | L18: https://www.lovethework.com/work/entries/interface-of-humanity-powered-by-ntt-754473

Sheet Health Grand Prix for Good
A1: # | B1: Tier | C1: Campaign | D1: Brand | E1: Product/Service | F1: Agency | G1: Country | H1: Subcategory | I1: Image URL | J1: YouTube ID | K1: Campaign Group | L1: Entry URL
A2: 1 | B2: Grand Prix | C2: THE BEST PLACE IN THE WORLD TO HAVE HERPES | D2: NEW ZEALAND HERPES FOUNDATION | E2: NEW ZEALAND HERPES FOUNDATION | F2: FINCH | G2: Australia | H2: Lions Health Grand Prix for Good | I2: digital-presentation-images/lions-health-grand-prix-for-good-new-zealand-herpes-foundation-the-best-place-in-the-world-to-have-herpes.webp | J2: vimeo:1083074994 | L2: https://www.lovethework.com/work/entries/the-best-place-in-the-world-to-have-herpes-767496
