Workbook

Sheet Summary
A1: BRAIN CANNESDY — WINNERS DATABASE
A2: Awards summary · auto-generated by scripts/rebuild_summary.py · 2026-06-26
A4: TOTALS BY YEAR
A5: Year | B5: Grand Prix | C5: Gold | D5: Silver | E5: Bronze | F5: Titanium | G5: Total
A6: 2025 | B6: 34 | C6: 148 | D6: 278 | E6: 414 | F6: 4 | G6: 878
A7: 2026 | B7: 25 | C7: 91 | D7: 171 | E7: 272 | F7: 0 | G7: 559
A8: All years | B8: 59 | C8: 239 | D8: 449 | E8: 686 | F8: 4 | G8: 1437
A10: BY CATEGORY (all years)
A11: Category | B11: Grand Prix | C11: Gold | D11: Silver | E11: Bronze | F11: Titanium | G11: Total
A12: Creative Brand | B12: =COUNTIF('Creative Brand'!$B:$B,"Grand Prix") | C12: =COUNTIF('Creative Brand'!$B:$B,"Gold") | D12: =COUNTIF('Creative Brand'!$B:$B,"Silver") | E12: =COUNTIF('Creative Brand'!$B:$B,"Bronze") | F12: =COUNTIF('Creative Brand'!$B:$B,"Titanium Grand Prix")+COUNTIF('Creative Brand'!$B:$B,"Titanium") | G12: =SUM(B12:F12)
A13: Audio & Radio | B13: =COUNTIF('Audio & Radio'!$B:$B,"Grand Prix") | C13: =COUNTIF('Audio & Radio'!$B:$B,"Gold") | D13: =COUNTIF('Audio & Radio'!$B:$B,"Silver") | E13: =COUNTIF('Audio & Radio'!$B:$B,"Bronze") | F13: =COUNTIF('Audio & Radio'!$B:$B,"Titanium Grand Prix")+COUNTIF('Audio & Radio'!$B:$B,"Titanium") | G13: =SUM(B13:F13)
A14: Film | B14: =COUNTIF('Film'!$B:$B,"Grand Prix") | C14: =COUNTIF('Film'!$B:$B,"Gold") | D14: =COUNTIF('Film'!$B:$B,"Silver") | E14: =COUNTIF('Film'!$B:$B,"Bronze") | F14: =COUNTIF('Film'!$B:$B,"Titanium Grand Prix")+COUNTIF('Film'!$B:$B,"Titanium") | G14: =SUM(B14:F14)
A15: Outdoor | B15: =COUNTIF('Outdoor'!$B:$B,"Grand Prix") | C15: =COUNTIF('Outdoor'!$B:$B,"Gold") | D15: =COUNTIF('Outdoor'!$B:$B,"Silver") | E15: =COUNTIF('Outdoor'!$B:$B,"Bronze") | F15: =COUNTIF('Outdoor'!$B:$B,"Titanium Grand Prix")+COUNTIF('Outdoor'!$B:$B,"Titanium") | G15: =SUM(B15:F15)
A16: Print & Publishing | B16: =COUNTIF('Print & Publishing'!$B:$B,"Grand Prix") | C16: =COUNTIF('Print & Publishing'!$B:$B,"Gold") | D16: =COUNTIF('Print & Publishing'!$B:$B,"Silver") | E16: =COUNTIF('Print & Publishing'!$B:$B,"Bronze") | F16: =COUNTIF('Print & Publishing'!$B:$B,"Titanium Grand Prix")+COUNTIF('Print & Publishing'!$B:$B,"Titanium") | G16: =SUM(B16:F16)
A17: Design | B17: =COUNTIF('Design'!$B:$B,"Grand Prix") | C17: =COUNTIF('Design'!$B:$B,"Gold") | D17: =COUNTIF('Design'!$B:$B,"Silver") | E17: =COUNTIF('Design'!$B:$B,"Bronze") | F17: =COUNTIF('Design'!$B:$B,"Titanium Grand Prix")+COUNTIF('Design'!$B:$B,"Titanium") | G17: =SUM(B17:F17)
A18: Digital Craft | B18: =COUNTIF('Digital Craft'!$B:$B,"Grand Prix") | C18: =COUNTIF('Digital Craft'!$B:$B,"Gold") | D18: =COUNTIF('Digital Craft'!$B:$B,"Silver") | E18: =COUNTIF('Digital Craft'!$B:$B,"Bronze") | F18: =COUNTIF('Digital Craft'!$B:$B,"Titanium Grand Prix")+COUNTIF('Digital Craft'!$B:$B,"Titanium") | G18: =SUM(B18:F18)
A19: Film Craft | B19: =COUNTIF('Film Craft'!$B:$B,"Grand Prix") | C19: =COUNTIF('Film Craft'!$B:$B,"Gold") | D19: =COUNTIF('Film Craft'!$B:$B,"Silver") | E19: =COUNTIF('Film Craft'!$B:$B,"Bronze") | F19: =COUNTIF('Film Craft'!$B:$B,"Titanium Grand Prix")+COUNTIF('Film Craft'!$B:$B,"Titanium") | G19: =SUM(B19:F19)
A20: Industry Craft | B20: =COUNTIF('Industry Craft'!$B:$B,"Grand Prix") | C20: =COUNTIF('Industry Craft'!$B:$B,"Gold") | D20: =COUNTIF('Industry Craft'!$B:$B,"Silver") | E20: =COUNTIF('Industry Craft'!$B:$B,"Bronze") | F20: =COUNTIF('Industry Craft'!$B:$B,"Titanium Grand Prix")+COUNTIF('Industry Craft'!$B:$B,"Titanium") | G20: =SUM(B20:F20)
A21: Creative B2B | B21: =COUNTIF('Creative B2B'!$B:$B,"Grand Prix") | C21: =COUNTIF('Creative B2B'!$B:$B,"Gold") | D21: =COUNTIF('Creative B2B'!$B:$B,"Silver") | E21: =COUNTIF('Creative B2B'!$B:$B,"Bronze") | F21: =COUNTIF('Creative B2B'!$B:$B,"Titanium Grand Prix")+COUNTIF('Creative B2B'!$B:$B,"Titanium") | G21: =SUM(B21:F21)
A22: Creative Data | B22: =COUNTIF('Creative Data'!$B:$B,"Grand Prix") | C22: =COUNTIF('Creative Data'!$B:$B,"Gold") | D22: =COUNTIF('Creative Data'!$B:$B,"Silver") | E22: =COUNTIF('Creative Data'!$B:$B,"Bronze") | F22: =COUNTIF('Creative Data'!$B:$B,"Titanium Grand Prix")+COUNTIF('Creative Data'!$B:$B,"Titanium") | G22: =SUM(B22:F22)
A23: Direct | B23: =COUNTIF('Direct'!$B:$B,"Grand Prix") | C23: =COUNTIF('Direct'!$B:$B,"Gold") | D23: =COUNTIF('Direct'!$B:$B,"Silver") | E23: =COUNTIF('Direct'!$B:$B,"Bronze") | F23: =COUNTIF('Direct'!$B:$B,"Titanium Grand Prix")+COUNTIF('Direct'!$B:$B,"Titanium") | G23: =SUM(B23:F23)
A24: Media | B24: =COUNTIF('Media'!$B:$B,"Grand Prix") | C24: =COUNTIF('Media'!$B:$B,"Gold") | D24: =COUNTIF('Media'!$B:$B,"Silver") | E24: =COUNTIF('Media'!$B:$B,"Bronze") | F24: =COUNTIF('Media'!$B:$B,"Titanium Grand Prix")+COUNTIF('Media'!$B:$B,"Titanium") | G24: =SUM(B24:F24)
A25: PR | B25: =COUNTIF('PR'!$B:$B,"Grand Prix") | C25: =COUNTIF('PR'!$B:$B,"Gold") | D25: =COUNTIF('PR'!$B:$B,"Silver") | E25: =COUNTIF('PR'!$B:$B,"Bronze") | F25: =COUNTIF('PR'!$B:$B,"Titanium Grand Prix")+COUNTIF('PR'!$B:$B,"Titanium") | G25: =SUM(B25:F25)
A26: Social & Creator | B26: =COUNTIF('Social & Creator'!$B:$B,"Grand Prix") | C26: =COUNTIF('Social & Creator'!$B:$B,"Gold") | D26: =COUNTIF('Social & Creator'!$B:$B,"Silver") | E26: =COUNTIF('Social & Creator'!$B:$B,"Bronze") | F26: =COUNTIF('Social & Creator'!$B:$B,"Titanium Grand Prix")+COUNTIF('Social & Creator'!$B:$B,"Titanium") | G26: =SUM(B26:F26)
A27: Entertainment | B27: =COUNTIF('Entertainment'!$B:$B,"Grand Prix") | C27: =COUNTIF('Entertainment'!$B:$B,"Gold") | D27: =COUNTIF('Entertainment'!$B:$B,"Silver") | E27: =COUNTIF('Entertainment'!$B:$B,"Bronze") | F27: =COUNTIF('Entertainment'!$B:$B,"Titanium Grand Prix")+COUNTIF('Entertainment'!$B:$B,"Titanium") | G27: =SUM(B27:F27)
A28: Entertainment Lions for Gaming | B28: =COUNTIF('Entertainment Lions for Gaming'!$B:$B,"Grand Prix") | C28: =COUNTIF('Entertainment Lions for Gaming'!$B:$B,"Gold") | D28: =COUNTIF('Entertainment Lions for Gaming'!$B:$B,"Silver") | E28: =COUNTIF('Entertainment Lions for Gaming'!$B:$B,"Bronze") | F28: =COUNTIF('Entertainment Lions for Gaming'!$B:$B,"Titanium Grand Prix")+COUNTIF('Entertainment Lions for Gaming'!$B:$B,"Titanium") | G28: =SUM(B28:F28)
A29: Entertainment Lions for Music | B29: =COUNTIF('Entertainment Lions for Music'!$B:$B,"Grand Prix") | C29: =COUNTIF('Entertainment Lions for Music'!$B:$B,"Gold") | D29: =COUNTIF('Entertainment Lions for Music'!$B:$B,"Silver") | E29: =COUNTIF('Entertainment Lions for Music'!$B:$B,"Bronze") | F29: =COUNTIF('Entertainment Lions for Music'!$B:$B,"Titanium Grand Prix")+COUNTIF('Entertainment Lions for Music'!$B:$B,"Titanium") | G29: =SUM(B29:F29)
A30: Entertainment Lions for Sport | B30: =COUNTIF('Entertainment Lions for Sport'!$B:$B,"Grand Prix") | C30: =COUNTIF('Entertainment Lions for Sport'!$B:$B,"Gold") | D30: =COUNTIF('Entertainment Lions for Sport'!$B:$B,"Silver") | E30: =COUNTIF('Entertainment Lions for Sport'!$B:$B,"Bronze") | F30: =COUNTIF('Entertainment Lions for Sport'!$B:$B,"Titanium Grand Prix")+COUNTIF('Entertainment Lions for Sport'!$B:$B,"Titanium") | G30: =SUM(B30:F30)
A31: Brand Experience & Activation | B31: =COUNTIF('Brand Experience & Activation'!$B:$B,"Grand Prix") | C31: =COUNTIF('Brand Experience & Activation'!$B:$B,"Gold") | D31: =COUNTIF('Brand Experience & Activation'!$B:$B,"Silver") | E31: =COUNTIF('Brand Experience & Activation'!$B:$B,"Bronze") | F31: =COUNTIF('Brand Experience & Activation'!$B:$B,"Titanium Grand Prix")+COUNTIF('Brand Experience & Activation'!$B:$B,"Titanium") | G31: =SUM(B31:F31)
A32: Creative Business Transformation | B32: =COUNTIF('Creative Bus. Transformation'!$B:$B,"Grand Prix") | C32: =COUNTIF('Creative Bus. Transformation'!$B:$B,"Gold") | D32: =COUNTIF('Creative Bus. Transformation'!$B:$B,"Silver") | E32: =COUNTIF('Creative Bus. Transformation'!$B:$B,"Bronze") | F32: =COUNTIF('Creative Bus. Transformation'!$B:$B,"Titanium Grand Prix")+COUNTIF('Creative Bus. Transformation'!$B:$B,"Titanium") | G32: =SUM(B32:F32)
A33: Creative Commerce | B33: =COUNTIF('Creative Commerce'!$B:$B,"Grand Prix") | C33: =COUNTIF('Creative Commerce'!$B:$B,"Gold") | D33: =COUNTIF('Creative Commerce'!$B:$B,"Silver") | E33: =COUNTIF('Creative Commerce'!$B:$B,"Bronze") | F33: =COUNTIF('Creative Commerce'!$B:$B,"Titanium Grand Prix")+COUNTIF('Creative Commerce'!$B:$B,"Titanium") | G33: =SUM(B33:F33)
A34: Innovation | B34: =COUNTIF('Innovation'!$B:$B,"Grand Prix") | C34: =COUNTIF('Innovation'!$B:$B,"Gold") | D34: =COUNTIF('Innovation'!$B:$B,"Silver") | E34: =COUNTIF('Innovation'!$B:$B,"Bronze") | F34: =COUNTIF('Innovation'!$B:$B,"Titanium Grand Prix")+COUNTIF('Innovation'!$B:$B,"Titanium") | G34: =SUM(B34:F34)
A35: Luxury | B35: =COUNTIF('Luxury'!$B:$B,"Grand Prix") | C35: =COUNTIF('Luxury'!$B:$B,"Gold") | D35: =COUNTIF('Luxury'!$B:$B,"Silver") | E35: =COUNTIF('Luxury'!$B:$B,"Bronze") | F35: =COUNTIF('Luxury'!$B:$B,"Titanium Grand Prix")+COUNTIF('Luxury'!$B:$B,"Titanium") | G35: =SUM(B35:F35)
A36: Glass: The Lion for Change | B36: =COUNTIF('Glass - The Lion for Change'!$B:$B,"Grand Prix") | C36: =COUNTIF('Glass - The Lion for Change'!$B:$B,"Gold") | D36: =COUNTIF('Glass - The Lion for Change'!$B:$B,"Silver") | E36: =COUNTIF('Glass - The Lion for Change'!$B:$B,"Bronze") | F36: =COUNTIF('Glass - The Lion for Change'!$B:$B,"Titanium Grand Prix")+COUNTIF('Glass - The Lion for Change'!$B:$B,"Titanium") | G36: =SUM(B36:F36)
A37: Grand Prix for Good | B37: =COUNTIF('Grand Prix for Good'!$B:$B,"Grand Prix") | C37: =COUNTIF('Grand Prix for Good'!$B:$B,"Gold") | D37: =COUNTIF('Grand Prix for Good'!$B:$B,"Silver") | E37: =COUNTIF('Grand Prix for Good'!$B:$B,"Bronze") | F37: =COUNTIF('Grand Prix for Good'!$B:$B,"Titanium Grand Prix")+COUNTIF('Grand Prix for Good'!$B:$B,"Titanium") | G37: =SUM(B37:F37)
A38: Sustainable Development Goals | B38: =COUNTIF('Sustainable Development Goals'!$B:$B,"Grand Prix") | C38: =COUNTIF('Sustainable Development Goals'!$B:$B,"Gold") | D38: =COUNTIF('Sustainable Development Goals'!$B:$B,"Silver") | E38: =COUNTIF('Sustainable Development Goals'!$B:$B,"Bronze") | F38: =COUNTIF('Sustainable Development Goals'!$B:$B,"Titanium Grand Prix")+COUNTIF('Sustainable Development Goals'!$B:$B,"Titanium") | G38: =SUM(B38:F38)
A39: Health & Wellness | B39: =COUNTIF('Health & Wellness'!$B:$B,"Grand Prix") | C39: =COUNTIF('Health & Wellness'!$B:$B,"Gold") | D39: =COUNTIF('Health & Wellness'!$B:$B,"Silver") | E39: =COUNTIF('Health & Wellness'!$B:$B,"Bronze") | F39: =COUNTIF('Health & Wellness'!$B:$B,"Titanium Grand Prix")+COUNTIF('Health & Wellness'!$B:$B,"Titanium") | G39: =SUM(B39:F39)
A40: Lions Health Grand Prix for Good | B40: =COUNTIF('Health Grand Prix for Good'!$B:$B,"Grand Prix") | C40: =COUNTIF('Health Grand Prix for Good'!$B:$B,"Gold") | D40: =COUNTIF('Health Grand Prix for Good'!$B:$B,"Silver") | E40: =COUNTIF('Health Grand Prix for Good'!$B:$B,"Bronze") | F40: =COUNTIF('Health Grand Prix for Good'!$B:$B,"Titanium Grand Prix")+COUNTIF('Health Grand Prix for Good'!$B:$B,"Titanium") | G40: =SUM(B40:F40)
A41: Pharma | B41: =COUNTIF('Pharma'!$B:$B,"Grand Prix") | C41: =COUNTIF('Pharma'!$B:$B,"Gold") | D41: =COUNTIF('Pharma'!$B:$B,"Silver") | E41: =COUNTIF('Pharma'!$B:$B,"Bronze") | F41: =COUNTIF('Pharma'!$B:$B,"Titanium Grand Prix")+COUNTIF('Pharma'!$B:$B,"Titanium") | G41: =SUM(B41:F41)
A42: Creative Effectiveness | B42: =COUNTIF('Creative Effectiveness'!$B:$B,"Grand Prix") | C42: =COUNTIF('Creative Effectiveness'!$B:$B,"Gold") | D42: =COUNTIF('Creative Effectiveness'!$B:$B,"Silver") | E42: =COUNTIF('Creative Effectiveness'!$B:$B,"Bronze") | F42: =COUNTIF('Creative Effectiveness'!$B:$B,"Titanium Grand Prix")+COUNTIF('Creative Effectiveness'!$B:$B,"Titanium") | G42: =SUM(B42:F42)
A43: Creative Strategy | B43: =COUNTIF('Creative Strategy'!$B:$B,"Grand Prix") | C43: =COUNTIF('Creative Strategy'!$B:$B,"Gold") | D43: =COUNTIF('Creative Strategy'!$B:$B,"Silver") | E43: =COUNTIF('Creative Strategy'!$B:$B,"Bronze") | F43: =COUNTIF('Creative Strategy'!$B:$B,"Titanium Grand Prix")+COUNTIF('Creative Strategy'!$B:$B,"Titanium") | G43: =SUM(B43:F43)
A44: Titanium | B44: =COUNTIF('Titanium'!$B:$B,"Grand Prix") | C44: =COUNTIF('Titanium'!$B:$B,"Gold") | D44: =COUNTIF('Titanium'!$B:$B,"Silver") | E44: =COUNTIF('Titanium'!$B:$B,"Bronze") | F44: =COUNTIF('Titanium'!$B:$B,"Titanium Grand Prix")+COUNTIF('Titanium'!$B:$B,"Titanium") | G44: =SUM(B44:F44)
A45: TOTAL | B45: =SUM(B12:B44) | C45: =SUM(C12:C44) | D45: =SUM(D12:D44) | E45: =SUM(E12:E44) | F45: =SUM(F12:F44) | G45: =SUM(G12:G44)
A47: TOP 25 BRANDS BY TOTAL LIONS
A48: Rank | B48: Brand | C48: Grand Prix | D48: Gold | E48: Silver | F48: Bronze | G48: Titanium | H48: Total
A49: 1 | B49: Heineken | C49: 1 | D49: 7 | E49: 7 | F49: 18 | G49: 0 | H49: 33
A50: 2 | B50: Apple | C50: 2 | D50: 5 | E50: 10 | F50: 11 | G50: 0 | H50: 28
A51: 3 | B51: IKEA | C51: 0 | D51: 8 | E51: 6 | F51: 11 | G51: 0 | H51: 25
A52: 4 | B52: Coca-Cola | C52: 0 | D52: 3 | E52: 5 | F52: 16 | G52: 0 | H52: 24
A53: 5 | B53: McDonald's | C53: 0 | D53: 4 | E53: 5 | F53: 13 | G53: 0 | H53: 22
A54: 6 | B54: KitKat | C54: 4 | D54: 4 | E54: 7 | F54: 6 | G54: 0 | H54: 21
A55: 7 | B55: Dove | C55: 3 | D55: 5 | E55: 4 | F55: 7 | G55: 0 | H55: 19
A56: 8 | B56: Oreo | C56: 0 | D56: 3 | E56: 10 | F56: 5 | G56: 0 | H56: 18
A57: 9 | B57: Mercado Livre | C57: 2 | D57: 2 | E57: 7 | F57: 6 | G57: 0 | H57: 17
A58: 10 | B58: Stella Artois | C58: 0 | D58: 6 | E58: 4 | F58: 7 | G58: 0 | H58: 17
A59: 11 | B59: Penny | C59: 1 | D59: 3 | E59: 3 | F59: 8 | G59: 0 | H59: 15
A60: 12 | B60: Vaseline | C60: 0 | D60: 2 | E60: 5 | F60: 8 | G60: 0 | H60: 15
... A73: 25 | B73: Telstra | C73: 1 | D73: 3 | E73: 1 | F73: 3 | G73: 0 | H73: 8

Sheet Creative Brand
A1: Year | B1: Tier | C1: Campaign | D1: Brand | E1: Product/Service | F1: Agency | G1: Country | H1: Subcategory | I1: Image URL | J1: YouTube ID | K1: Campaign Group | L1: Entry URL | M1: Description | N1: Keywords
A2: 2026 | B2: Grand Prix | C2: ABInBev: Creativity at Scale | D2: ABInBev | E2: Beer | F2: Anheuser-Busch InBev | G2: Belgium | H2: A01 - Talent & Workplace Culture | I2: https://ascentialcdn.filespin.io/api/v1/conversion/6313b7c3fac0443297698d064dc6d5ed | L2: https://www.lovethework.com/work/entries/abinbev-creativity-at-scale-792758 | M2: AB InBev's entry in the inaugural Creative Brand category, which judges the systems, culture and capabilities behind a brand's creative output rather than any single campaign. It lays out how the world's largest brewer turned creativity into a repeatable, company-wide discipline — shared creative principles, talent development and consistent ways of working embedded across its portfolio of beer brands and dozens of markets, so award-level work becomes a structured, ongoing growth capability rather than a one-off. | N2: creative-brand, talent, workplace-culture, creative-transformation, marketing-operations, organizational-culture, beer, alcohol, abinbev, global, belgium
A3: 2026 | B3: Gold | C3: Mastercard | D3: Mastercard | E3: Mastercard | F3: Mastercard | G3: United States | H3: A02 - Collaboration and Partnership Models | I3: https://ascentialcdn.filespin.io/api/v1/conversion/d6b76a71d79a4ae68f925ead9e28a8eb | L3: https://www.lovethework.com/work/entries/mastercard-779685 | M3: Mastercard's entry in the new Creative Brand category, recognising the operating model behind its marketing rather than a single execution. It centres on how the brand is built through long-term collaboration and partnership — sponsorships, cultural platforms and co-creation with outside organisations — turning those relationships into a consistent, repeatable system for staying culturally relevant and extending the brand across markets over time. | N3: creative-brand, collaboration, partnership, brand-platform, sponsorship, marketing-operations, payments, fintech, financial-services, finance, mastercard, united-states

Sheet Audio & Radio
A1: Year | B1: Tier | C1: Campaign | D1: Brand | E1: Product/Service | F1: Agency | G1: Country | H1: Subcategory | I1: Image URL | J1: YouTube ID | K1: Campaign Group | L1: Entry URL | M1: Description | N1: Keywords
A2: 2025 | B2: Grand Prix | C2: One Second Ads | D2: Budweiser | E2: Beer | F2: Africa Creative DDB | G2: Brazil | H2: B01 - Use of Music | I2: digital-presentation-images/audio-and-radio-budweiser-one-second-ads.webp | J2: RpvlshoKIrE | L2: https://www.lovethework.com/work/entries/one-second-ads-741948 | M2: A series of one-second social media ads built around the opening note or two of globally recognized songs — from Beyoncé and Taylor Swift to The Beatles and Foo Fighters — short enough that true fans could identify the track but too brief to trigger music licensing fees. Budweiser challenged viewers on social media to name the song, rewarding correct guessers with a beer coupon sent via DM, which turned the comment sections into active guessing threads and kept viewers replaying the ads voluntarily. | N2: beer, alcohol, social-media, audio, music, entertainment, short-form-video, brazil, user-participation, mobile
A3: 2025 | B3: Gold | C3: Name This Oreo | D3: Oreo | E3: Oreo | F3: VML | G3: United States | H3: A03 - Voice Activation | I3: digital-presentation-images/audio-and-radio-oreo-name-this-oreo.webp | J3: hRp6cBmbfIw | L3: https://www.lovethework.com/work/entries/name-this-oreo-741853 | M3: A voice-activated web game at namethisoreo.com that turns 'OREO Grammar' — a viral internet meme in which cookie-and-creme combinations are read aloud as sequences of 'O' (cookie) and 'RE' (creme) — into a timed naming challenge. Players speak the correct O-RE sequence for each stacked OREO combination shown on screen, build streaks, and unlock cookie offers. | N3: cookie, snack, food, packaged-goods, cpg, fmcg, voice-game, web-experience, meme-marketing, gamification, audio, united-states
A4: 2025 | B4: Gold | C4: One Second Ads | D4: Budweiser | E4: Beer | F4: Africa Creative DDB | G4: Brazil | H4: A06 - Audio-Led Creativity | I4: digital-presentation-images/audio-and-radio-budweiser-one-second-ads.webp | J4: RpvlshoKIrE | L4: https://www.lovethework.com/work/entries/one-second-ads-741888 | M4: A series of one-second social media ads built around the opening note or two of globally recognized songs — from Beyoncé and Taylor Swift to The Beatles and Foo Fighters — short enough that true fans could identify the track but too brief to trigger music licensing fees. Budweiser challenged viewers on social media to name the song, rewarding correct guessers with a beer coupon sent via DM, which turned the comment sections into active guessing threads and kept viewers replaying the ads voluntarily. | N4: beer, alcohol, social-media, audio, music, entertainment, short-form-video, brazil, user-participation, mobile
A5: 2025 | B5: Gold | C5: The Second Release | D5: Billboard Arabia | E5: Billboard Magazine | F5: SRMG Labs | G5: Saudi Arabia | H5: C03 - Single-Market Campaign | I5: digital-presentation-images/audio-and-radio-billboard-arabia-the-second-release.webp | J5: sH5Jk7ywBLc | L5: https://www.lovethework.com/work/entries/the-second-release-742149 | M5: A vinyl record pressing of 'Etab,' a 1988 Saudi classic by singer Tarouf Abdulkhair Adam Talal (stage name Etab), remastered and re-released in 2024 by Billboard Arabia to mark Saudi National Day — the song's first-ever physical release. | N5: music, entertainment, vinyl, audio, cultural-engagement, saudi-arabia, music-media, re-release, archival
A6: 2025 | B6: Silver | C6: Name This Oreo | D6: Oreo | E6: Oreo | F6: VML | G6: United States | H6: A01 - Use of Audio & Radio as a Medium | I6: digital-presentation-images/audio-and-radio-oreo-name-this-oreo.webp | J6: hRp6cBmbfIw | L6: https://www.lovethework.com/work/entries/name-this-oreo-741778 | M6: A voice-activated web game at namethisoreo.com that turns "OREO Grammar" — a viral internet meme in which cookie-and-creme combinations are read aloud as sequences of "O" (cookie) and "RE" (creme) — into a timed naming challenge. Players speak the correct O-RE sequence for each stacked OREO combination shown on screen, build streaks, and unlock cookie offers. The campaign launched in partnership with TikTok's 2024 Creator of the Year, @OHIOSATOYUBOSS, whose existing OREO Grammar content made him the natural host. | N6: snack, food, packaged-goods, cpg, fmcg, voice-activation, mobile-app, social-influencer, gamification, united-states, tiktok, audio
A7: 2025 | B7: Silver | C7: Fishermen Storytellers | D7: Corona | E7: Beer | F7: Africa Creative DDB | G7: Brazil | H7: A04 - Branded Content/Podcasts | I7: digital-presentation-images/audio-and-radio-corona-fishermen-storytellers.webp | J7: vimeo:1090130974 | L7: https://www.lovethework.com/work/entries/fishermen-storytellers-764514 | M7: A documentary and design project that helps Brazilian fishing communities replace lost income during the annual fishing ban by training fishermen as tour guides for their own folklore. The work culminates in a stop-motion film made from hand-carved wooden scenes and a book bound in salvaged boat wood, fishing nets, and cement. | N7: branded-content, social-good, craft, storytelling, beer, alcohol, brazil, sustainability, stop-motion
A8: 2025 | B8: Silver | C8: 1. High Energy Intern | D8: Fusion Energy Drink | E8: Energy Drink | F8: David | G8: Spain | H8: B03 - Script | I8: https://ascentialcdn.filespin.io/api/v1/storyboard/846afe3e468240929823119e42cf3b99/storyboard_000008.jpg | J8: vimeo:1105218555 | L8: https://www.lovethework.com/work/entries/1-high-energy-intern-762404 | M8: A radio campaign for Fusion Energy Drink that flips the usual category logic: it's not for high-energy people, it's for the people who have to keep up with them. In this spot, 'High-Energy Intern' becomes a lovable but relentless office sunbeam—firing off endless questions, emoji-packed messages, and 'OMG amazing' reactions to even the dullest policy update. Fusion is energy for people who live with people with energy—or in this case, work 40 hours a week directly across from them. | N8: energy-drink, drinks, beverage, radio, audio, humor, workplace, brand-platform
A9: 2025 | B9: Silver | C9: Chill Enough | D9: Coors Brewing Company | E9: Coors Light | F9: Alma Advertising Agency | G9: United States | H9: B04 - Casting & Performance | I9: digital-presentation-images/audio-and-radio-coors-light-chill-enough.webp | J9: vimeo:1086177966 | L9: https://www.lovethework.com/work/entries/chill-enough-762433 | M9: A radio campaign in which voiceover announcers recorded their scripts while fully submerged in ice plunge baths — the physical discomfort of the cold translating directly into audible distress, bleeps, and involuntary reactions in the final spots. The stunt mirrors Coors Light's cold-activated can, whose mountain label turns blue only when the beer reaches ice-cold temperature. | N9: beer, alcohol, radio, casting-and-performance, stunt, united-states, audio, brand-feature
A10: 2025 | B10: Silver | C10: Burger to King | D10: Burger King | E10: Burger King | F10: Happiness, an FCB Alliance | G10: Belgium | H10: C02 - Challenger Brand | I10: digital-presentation-images/audio-and-radio-burger-king-burger-to-king.webp | J10: RQVaoU4CGRk | L10: https://www.lovethework.com/work/entries/burger-to-king-763482 | M10: A loophole in EA FC25's AI commentary system, which dynamically reads every real player's name aloud, exploited by Burger King. Fans were coached via influencers and social posts to build Ultimate Team squads using real FC25 players actually named 'Burger' (e.g. Wouter Burger, Stoke City) and 'King' (e.g. Joshua King, Toulouse), so that whenever the ball moved between them, the automated in-game commentator called out 'Burger... King' — without EA Sports' involvement. | N10: qsr, fast-food, restaurant, food, gaming, video-games, entertainment, football, soccer, sport, audio, in-game, social-media, ambient, hijack
A11: 2025 | B11: Silver | C11: The Second Release | D11: Billboard Arabia | E11: Billboard Magazine | F11: SRMG Labs | G11: Saudi Arabia | H11: C04 - Social Behaviour | I11: digital-presentation-images/audio-and-radio-billboard-arabia-the-second-release.webp | J11: sH5Jk7ywBLc | L11: https://www.lovethework.com/work/entries/the-second-release-742142 | M11: A vinyl record pressing of "Etab," a 1988 Saudi classic by singer Tarouf Abdulkhair Adam Talal (stage name Etab), remastered and re-released in 2024 by Billboard Arabia to mark Saudi National Day — the song's first-ever physical release. The packaging, designed by SRMG Labs in Riyadh, pairs archival black-and-white portrait photography with neon-green Arabic and Latin typography across the sleeve, inner labels, and inserts. | N11: billboard-magazine, music, entertainment, vinyl, packaging, arabic-typography, heritage, saudi-arabia, single-market-campaign, print
A12: 2025 | B12: Silver | C12: From Hurt to Hit | D12: Brahma | E12: Beer | F12: Africa Creative DDB | G12: Brazil | H12: C05 - Use of Humour | I12: https://ascentialcdn.filespin.io/api/v1/conversion/2c4c0601d34e42cf931304cf072f6fa8 | J12: vimeo:1081566541 | L12: https://www.lovethework.com/work/entries/from-hurt-to-hit-742107 | M12: A campaign built around the Brazilian sertanejo tradition of writing songs about heartbreak: Brahma collected real emotional stories from consumers and turned them into sertanejo tracks, connecting the brand to the country's most popular music genre through the raw material of personal pain. In Brazil, where alcohol advertising operates under a "dark market" restriction that bans direct product promotion, associating with music culture is one of the few open channels — making the emotional honesty of the mechanic both the creative idea and the regulatory workaround. | N12: beer, alcohol, audio, music, entertainment, sertanejo, humor, brazil, branded-content, user-generated-content
A13: 2025 | B13: Silver | C13: Me Feat. Me | D13: Nosotras | E13: Nosotras | F13: DDB Chile | G13: Chile | H13: C09 - Cultural Engagement | I13: https://ascentialcdn.filespin.io/api/v1/conversion/a6ac5c5dd4fc4487966ae01ac52f95ff | J13: KBcSEzHf5DA | L13: https://www.lovethework.com/work/entries/me-feat-me-742031 | M13: A music track in which Nosotras recruited women to collaborate with themselves — each artist featured as both the lead and the featured act, credited as "Me feat. Me" — to express self-confidence as a solo identity rather than one defined in relation to others. The format borrowed the standard music-industry "feat." credit convention to make the idea literal: the only collaborator worth naming is yourself. | N13: feminine-hygiene, audio, music, entertainment, cultural-engagement, womens-empowerment, chile
... A22: 2025 | B22: Bronze | C22: Sounds Right | D22: Museum for the United Nations - UN Live | E22: Music | F22: AKQA | G22: Denmark | H22: C07 - Corporate Purpose & Social Responsibility | I22: digital-presentation-images/audio-and-radio-museum-for-the-united-nations-sounds-right.webp | J22: 5newTxSZ9bU | L22: https://www.lovethework.com/work/entries/sounds-right-759882 | M22: A Spotify initiative, developed by AKQA for Museum for the United Nations – UN Live, that registers NATURE as an official credited artist on the platform — so that existing songs featuring natural soundscapes, from artists including V of BTS, David Bowie, Brian Eno, AURORA, and Ellie Goulding, list NATURE as a collaborator with its own verified artist profile. Streaming royalties attributed to NATURE's credit are directed toward nature conservation funding. | N22: music, entertainment, streaming, tv, spotify, mobile-app, conservation, public-service, corporate-social-responsibility, denmark, akqa
A23: 2025 | B23: Silver | C23: 2. High Energy Boyfriend | D23: Fusion Energy Drink | F23: David | G23: Spain | H23: B03 - Script | I23: https://ascentialcdn.filespin.io/api/v1/storyboard/846afe3e468240929823119e42cf3b99/storyboard_000008.jpg | J23: vimeo:1105218613 | M23: A radio campaign for Fusion Energy Drink that flips the usual category logic: it's not for high-energy people, it's for the people who have to keep up with them. In this spot, 'High-Energy Boyfriend' becomes a lovable but exhausting social tornado—filling your apartment with friends, turning every weekend into an event, and somehow volunteering you both for Dimitri's wedding and a neighbor's pregnant cat. Fusion is energy for people who live with people with energy—and their friends, and their friends' friends. | N23: energy-drink, drinks, beverage, radio, audio, humor, brand-platform
A24: 2025 | B24: Silver | C24: 3. High Energy Dad | D24: Fusion Energy Drink | F24: David | G24: Spain | H24: B03 - Script | I24: https://ascentialcdn.filespin.io/api/v1/storyboard/846afe3e468240929823119e42cf3b99/storyboard_000008.jpg | J24: vimeo:1105218658 | M24: A radio campaign for Fusion Energy Drink that flips the usual category logic: it's not for high-energy people, it's for the people who have to keep up with them. In this spot, 'High-Energy Dad' becomes a lovable but exhausting force of nature—turning errands, chores and life lessons into full-body cardio. Fusion is energy for people who live with people with energy. | N24: energy-drink, drinks, beverage, radio, audio, humor, family, brand-platform
A25: 2025 | B25: Silver | C25: Cold Detector | D25: Coors Brewing Company | F25: Alma Advertising Agency | G25: United States | H25: B04 - Casting & Performance | I25: digital-presentation-images/audio-and-radio-coors-light-chill-enough.webp | J25: vimeo:1086178012 | M25: A radio campaign in which voiceover announcers recorded their scripts while submerged in ice plunge baths — a live demonstration of the cold the Coors Light cold-activated can is designed to signal. The physical shock of the ice water produced involuntary reactions, bleeps, and audibly frozen delivery across three finished spots. | N25: beer, alcohol, radio, casting, united-states, audio, experiential-production, cold-activation, packaging-tie-in
A26: 2025 | B26: Silver | C26: Mountain Cold | D26: Coors Brewing Company | F26: Alma Advertising Agency | G26: United States | H26: B04 - Casting & Performance | I26: digital-presentation-images/audio-and-radio-coors-light-chill-enough.webp | J26: vimeo:1086178036 | M26: A radio campaign in which voiceover announcers record Coors Light scripts from inside an ice plunge — submerged to the shoulders in ice-cold water for the duration of each take. Three spots were produced, each capturing the involuntary reactions, strained delivery, and bleeped expletives of announcers trying to maintain professional composure while experiencing the same cold the brand's color-changing mountain label is designed to signal. | N26: beer, alcohol, radio, casting-and-performance, stunt, united-states, audio, coors-light
A27: 2025 | B27: Bronze | C27: Spill the Tea | D27: Hansa Pilsener | F27: Joe Public | G27: South Africa | H27: B03 - Script | I27: https://ascentialcdn.filespin.io/api/v1/storyboard/0bca684772274dd9a6e2c0c6cd401876/storyboard_000008.jpg | J27: vimeo:1032236549 | M27: A radio campaign from Hansa Pilsner, which positions itself as the beer for grown men by lovingly roasting younger guys and their try-hard trends—from 'spill the tea' to gaming streams, sneaker collecting and ASMR sleep videos. The spot builds a funny exclusionary platform: there may be 'a beer for you,' but Hansa is reserved for men with a little more life experience. | N27: beer, alcohol, radio, audio, humor, south-africa, brand-platform
A28: 2025 | B28: Bronze | C28: Okrrr | D28: Hansa Pilsener | F28: Joe Public | G28: South Africa | H28: B03 - Script | I28: https://ascentialcdn.filespin.io/api/v1/storyboard/0bca684772274dd9a6e2c0c6cd401876/storyboard_000008.jpg | J28: vimeo:1022471976 | M28: A radio campaign from Hansa Pilsner, which positions itself as the beer for grown men by lovingly roasting younger guys and their try-hard trends—from personal brands, oversized fits, TikTok challenges, and get-ready-with-me culture. The spot builds a funny exclusionary platform: there may be 'a beer for you,' but Hansa is reserved for men with a little more life experience. | N28: beer, alcohol, radio, audio, humor, south-africa, brand-platform
A29: 2026 | B29: Grand Prix | C29: Coquí Alarmed | D29: Hyundai Puerto Rico | E29: Hyundai | F29: BBDO Puerto Rico | G29: Puerto Rico | H29: C03 - Single-Market Campaign | I29: https://ascentialcdn.filespin.io/api/v1/conversion/6d4d0b7e5bcc4ec58a29958dcba0a0c2 | J29: 55knFa5zP6g | L29: https://www.lovethework.com/work/entries/coqu-alarmed-780472 | M29: After a tourist complained online about the noise of Puerto Rico's coquí, Hyundai replaced the standard lock and unlock chirp in its rental cars at Avis, Enterprise and Charlie Car Rental with the real recorded call of the tiny tree frog. Neck hangers in each car explained the coquí's place in Puerto Rican identity, turning a functional alert sound into a piece of national pride. | N29: automotive, cars, transport, car-rental, vehicles, audio, sound-design, sonic-branding, cultural-identity, tourism, travel, wildlife, nature, hyundai, puerto-rico
A30: 2026 | B30: Gold | C30: Sleep Talk Reviews | D30: IKEA | E30: IKEA | F30: Rethink | G30: Canada | H30: A06 - Audio-Led Creativity | I30: https://ascentialcdn.filespin.io/api/v1/conversion/29d5e6beff5343f4a75840aacad3165f | J30: BNAfX0lKSjg | L30: https://www.lovethework.com/work/entries/sleep-talk-reviews-780352 | M30: IKEA invited real sleep talkers to spend the night on its mattresses inside the store, with hidden mics capturing their mumbles, snores and sleep-talk as honest reviews of how deeply they slept. The recordings ran on radio, streaming audio, social and out-of-home, reframing deep sleep itself as proof of comfort. | N30: furniture, home, homeware, retail, mattresses, bedding, audio, sound-recording, product-reviews, sleep, ikea, canada
A31: 2026 | B31: Gold | C31: Searching For Birds On Wires | D31: Abradee | E31: Institutional | F31: Africa Creative | G31: Brazil | H31: B01 - Use of Music | I31: https://ascentialcdn.filespin.io/api/v1/conversion/5b453c1cca9944e59a8d6df49dabd9f2 | J31: vimeo:1202133381 | L31: https://www.lovethework.com/work/entries/searching-for-birds-on-wires-780318 | M31: For Brazil's electricity-distribution association, Africa Creative turned photographs of birds perched on power lines into music, reading each bird's position on the wires as a note on a musical staff and composing an original piece from the patterns the birds formed. | N31: energy, electricity, utilities, power, institutional, audio, music, entertainment, composition, birds, nature, power-lines, abradee, brazil
A32: 2026 | B32: Silver | C32: A Mother's Commentary | D32: Reporters Without Borders (RSF) | E32: Press Freedom Advocacy | F32: The Good Company | G32: France | H32: A01 - Use of Audio & Radio as a Medium | I32: https://ascentialcdn.filespin.io/api/v1/conversion/e5b4c80d95974dff83d0dba8bc80f740 | J32: a4ZCQDgxW0U | L32: https://www.lovethework.com/work/entries/a-mothers-commentary-780310 | M32: During a Paris Saint-Germain match on beIN Sports, the broadcast's live commentary cut out at the seventh minute - one minute for each year of his sentence - and was replaced by the voice of Sylvie Godard, mother of detained French sports journalist Christophe Gleizes. She spoke to viewers and then to her son, who can only follow football from his Algerian prison cell, as part of RSF's push for his release. | N32: non-profit, ngo, not-for-profit, charity, social-good, press-freedom, journalism, human-rights, advocacy, audio, radio, broadcast, entertainment, sports, football, soccer, sport, rsf, france
A33: 2026 | B33: Silver | C33: The Unofficial Official Sound Of F1 | D33: Sting | E33: Sting | F33: Leo India | G33: India | H33: C02 - Challenger Brand | I33: https://ascentialcdn.filespin.io/api/v1/conversion/c8ed916715884400910e742f565dc00e | J33: MteFVMaD-0M | L33: https://www.lovethework.com/work/entries/the-unofficial-official-sound-of-f1-774255 | M33: To launch Sting's Formula 1 partnership, the brand seized on a fan observation that an F1 engine's roar sounds like the word 'Sting.' DJ Armin van Buuren claimed he could hear 'Stinggg' hidden in the engine noise, sparking remixes and debate, and the idea extended into a track built from real race audio. | N33: beverage, drinks, energy-drink, soft-drink, audio, sound, music, entertainment, sports, motorsport, sport, racing, formula-1, sponsorship, sting, india
A34: 2026 | B34: Silver | C34: Could Have Been A Heineken | D34: Heineken | E34: Heineken Beer | F34: LePub | G34: Italy | H34: C04 - Social Behaviour | I34: https://ascentialcdn.filespin.io/api/v1/conversion/325cbd01df444a49a6a09ac2bc5dd3fa | J34: vimeo:1203492482 | L34: https://www.lovethework.com/work/entries/could-have-been-a-heineken-780519 | M34: To nudge people off endless voice notes and back into face-to-face conversation, Heineken let users forward any voice message longer than three minutes to a private WhatsApp bot. The bot replied 'Could have been a Heineken' with a voucher for a free beer and suggestions for nearby bars. | N34: beer, alcohol, beverage, drinks, audio, voice-messaging, messaging, technology, social-connection, heineken, italy
A35: 2026 | B35: Silver | C35: Doorbell Ads | D35: Mercado Libre | E35: Mercado Libre | F35: GUT | G35: Argentina | H35: C06 - Breakthrough on a Budget | I35: https://ascentialcdn.filespin.io/api/v1/conversion/7b5cd9b3d33e45f7a2d41fc540a4f415 | J35: vimeo:1187878678 | L35: https://www.lovethework.com/work/entries/doorbell-ads-780499 | M35: Mercado Libre bought radio spots as short as a doorbell chime and placed them to run last in the ad break, so the brief 'ding' reframed every commercial before it: whatever had just been advertised could be found on Mercado Libre. | N35: ecommerce, retail, online-shopping, marketplace, shopping, audio, radio, media-placement, mercado-libre, argentina
A36: 2026 | B36: Silver | C36: The Yangzhou Qiao Bei Musical Suite | D36: Yangzhou Municipal Bureau of Culture, Radio, TV and Tourism, China | E36: To Promote Bathhouse Culture and the City of Yangzhou | F36: TBWA\China | G36: China | H36: D04 - Travel, Leisure, Retail, Restaurants & Fast-Food Chains | I36: https://www.brandinginasia.com/wp-content/uploads/2026/05/Yangzhou-Qiao-Bei-Musical-Suite_board-copy.webp | J36: 2mH41-1bJVA | L36: https://www.lovethework.com/work/entries/the-yangzhou-qiao-bei-musical-suite-778657 | M36: TBWA China turned the towels of Yangzhou's 1,200-year-old Qiao Bei back-tapping bath ritual into percussion instruments, recording four original 'towel percussion' compositions from the massage rhythms. An NFC chip in the towel packaging let people unlock the music and learn the rhythms at home, promoting the city's bathhouse heritage and tourism. | N36: tourism, travel, government, culture, heritage, audio, music, entertainment, percussion, sound, china, yangzhou
A37: 2026 | B37: Bronze | C37: Played By Humans | D37: Jazz Is Dead | E37: Played By Humans | F37: TBWA\Chiat\Day | G37: United States | H37: B01 - Use of Music | I37: https://i.ytimg.com/vi/bz1r-JIEdzU/maxresdefault.jpg | J37: 1lZ696Kd6ic | L37: https://www.lovethework.com/work/entries/played-by-humans-774278 | M37: In response to AI-generated tracks flooding streaming platforms, Jazz Is Dead and TBWA\Chiat\Day created 'Played By Humans,' a stamp of authenticity and public verification platform that lets artists and listeners certify music as human-made. It launched with a documentary short and a human-made cover of an AI-generated song. | N37: music, entertainment, arts, culture, audio, ai, technology, artificial-intelligence, authenticity, verification, jazz-is-dead, united-states
A38: 2026 | B38: Bronze | C38: Healing Era | D38: Hansa Pilsener | E38: Hansa Pilsener | F38: Joe Public | G38: South Africa | H38: B03 - Script | I38: https://ascentialcdn.filespin.io/api/v1/storyboard/3e5b42d9dfa54b8da6f479b1e9630e4e/storyboard_000008.jpg | J38: cjAwhbK_ZBQ | L38: https://www.lovethework.com/work/entries/healing-era-780405 | M38: Part of Hansa Pilsener's over-30s 'You Deserve a Beer' platform, this radio script - voiced by South African comedian Mojak in an epic, affirming locker-room style - appears to celebrate Gen Z's 'healing era' of self-care as hard work, before a dry twist concludes they deserve a beer, just not a Hansa. | N38: beer, alcohol, beverage, drinks, audio, radio, script, humour, comedy, gen-z, hansa-pilsener, south-africa
A39: 2026 | B39: Bronze | C39: The Hustle | D39: Hansa Pilsener | E39: Hansa Pilsener | F39: Joe Public | G39: South Africa | H39: B03 - Script | I39: https://ascentialcdn.filespin.io/api/v1/storyboard/3ea2629528df4e4a87566afecb98c392/storyboard_000008.jpg | J39: cqUa2mLcc5o | L39: https://www.lovethework.com/work/entries/the-hustle-780321 | M39: Part of Hansa Pilsener's over-30s 'You Deserve a Beer' platform, this radio script - voiced by comedian Mojak in a grand, motivational tone - mock-celebrates Gen Z's idea of 'the hustle' as hard work, before a dry twist lands that they deserve a beer, just not a Hansa. | N39: beer, alcohol, beverage, drinks, audio, radio, script, humour, comedy, gen-z, hansa-pilsener, south-africa
A40: 2026 | B40: Bronze | C40: Delulu Is The Solulu | D40: Hansa Pilsener | E40: Hansa Pilsener | F40: Joe Public | G40: South Africa | H40: B03 - Script | I40: https://ascentialcdn.filespin.io/api/v1/storyboard/fdf7d8da65e240369ca734caac94542b/storyboard_000008.jpg | J40: mI3rWxtcblQ | L40: https://www.lovethework.com/work/entries/delulu-is-the-solulu-780328 | M40: Part of Hansa Pilsener's over-30s 'You Deserve a Beer' platform, this radio script leans on the Gen Z phrase 'delulu is the solulu,' voiced by comedian Mojak as a heroic affirmation of manifesting as effort, before the dry twist that they deserve a beer, just not a Hansa. | N40: beer, alcohol, beverage, drinks, audio, radio, script, humour, comedy, gen-z, slang, hansa-pilsener, south-africa
... A45: 2026 | B45: Bronze | C45: Bedtime Donations | D45: Royal Society For Blind Children | E45: Bedtime Donations App | F45: Innocean | G45: Germany | H45: D07 - Not-for-Profit / Charity / Government | I45: https://ascentialcdn.filespin.io/api/v1/conversion/f4c9dafd39714b8c96da0d7dd9e055ea | J45: nw12Kyu0wqQ | L45: https://www.lovethework.com/work/entries/bedtime-donations-780400 | M45: Innocean Berlin and the Royal Society for Blind Children built the Bedtime Donations app: when a parent reads a story from its library aloud, safe AI turns the reading into a free audiobook for blind and vision-impaired children to listen to anytime, crowdsourcing a growing library of bedtime stories. | N45: non-profit, charity, ngo, not-for-profit, social-good, accessibility, blindness, disability, children, audio, audiobooks, app, ai, technology, rsbc, germany

Sheet Film
A1: Year | B1: Tier | C1: Campaign | D1: Brand | E1: Product/Service | F1: Agency | G1: Country | H1: Subcategory | I1: Image URL | J1: YouTube ID | K1: Campaign Group | L1: Entry URL | M1: Description | N1: Keywords
A2: 2025 | B2: Grand Prix | C2: Paris Paralympics 2024: Considering What? | D2: Channel 4 | E2: Channel 4 | F2: Channel 4 | G2: United Kingdom | H2: A05 - Media/Entertainment | I2: digital-presentation-images/film-channel-4-paris-paralympic-2024-considering-what.webp | J2: bUs_mNTNwvE | L2: https://www.lovethework.com/work/entries/paris-paralympics-2024-considering-what-738686 | M2: A Channel 4 campaign for the Paris 2024 Paralympic Games, made by in-house agency 4Creative and production company Biscuit Filmworks, built around the patronising language real viewers use about Paralympic athletes — phrases like "she's incredibly fast for someone in a wheelchair" and "amazing... considering" — which appeared as OOH billboards with the condescending caveats crossed out by the athletes' actual sporting achievements. On social, the same treatment was flipped: patronising comments typically aimed at Paralympians were redirected at non-disabled Olympians, exposing the double standard. The campaign responded to research showing that 60% of viewers still watch the Paralympics primarily to see athletes "overcome" their disabilities rather than compete as elite sportspeople. | N2: broadcaster, ooh, social-media, paralympics, disability, sport, film, cinema, entertainment, united-kingdom, 4creative
A3: 2025 | B3: Grand Prix | C3: The Final Copy of Ilon Specht | D3: L'oréal Paris | E3: L'oréal Paris | F3: McCANN | G3: France | H3: F07 - Corporate Purpose & Social Responsibility | I3: digital-presentation-images/film-loreal-paris-the-final-copy-of-ilona-specht.webp | J3: vimeo:1094956645 | L3: https://www.lovethework.com/work/entries/the-final-copy-of-ilon-specht-739568 | M3: An 18-minute documentary released on International Women's Day across Prime Video, AMC+, and YouTube, telling the story of Ilon Specht — the copywriter who wrote "Because I'm Worth It" for L'Oréal Paris in 1973 — through an intimate, deathbed-style account. Made by McCann Paris with Proudfoot's Breakwater Studios and production company Traverse 32, the film launched across 20+ countries alongside OOH, screenings, and interactive installations, leaving the original tagline's four words entirely unchanged. | N3: cosmetics, personal-care, beauty, documentary, film, entertainment, cinema, ooh, interactive-installation, streaming, tv, france, corporate-purpose, womens-rights, branded-content, social-media
A4: 2025 | B4: Gold | C4: Find Your Friends | D4: Apple | E4: Precision Finding | F4: Apple | G4: United States | H4: B01 - Consumer Goods | I4: digital-presentation-images/film-apple-find-your-friends.webp | J4: vimeo:1068530073 | L4: https://www.lovethework.com/work/entries/find-your-friends-738592 | M4: A film shot at a Star Wars fan convention in which a lone attendee, dressed in Mandalorian armor, uses the Precision Finding feature on his iPhone 15 to locate his friends in a crowd of identically helmeted cosplayers. Designed and released on May 4th as a love letter to the fan community, the film's sound was built at Skywalker Sound and background signage was seeded with details for fans to decode. | N4: smartphone, film, cinema, entertainment, precision-finding, fan-culture, star-wars, cosplay, united-states, sound-design, casting
A5: 2025 | B5: Gold | C5: Never Just a Period | D5: Bodyform | E5: Bodyform | F5: AMV BBDO | G5: United Kingdom | H5: B02 - Healthcare | I5: digital-presentation-images/film-bodyform-never-just-a-period.webp | J5: EQW59KR3c4U | L5: https://www.lovethework.com/work/entries/never-just-a-period-738863 | M5: A film and integrated campaign for Bodyform/Libresse, created by AMV BBDO London, that dramatises the gap between what women are told about their bodies and what they actually experience — staging rarely discussed moments like getting a period while breastfeeding, large perimenopausal clots, and periods that disappear for months after stopping contraception. An online conversation thread prompted audiences with "What do you wish you'd been told?", opening a space for women+ to share experiences spanning first period to last. | N5: femcare, film, cinema, entertainment, integrated-campaign, healthcare, womens-health, social, united-kingdom, menstrual-health, amv-bbdo
A6: 2025 | B6: Gold | C6: Let There Be Cake | D6: KFC Thailand | E6: KFC 40th | F6: Bananas | G6: South Africa | H6: B04 - Travel, Leisure, Retail, Restaurants & Fast-Food Chains | I6: https://ascentialcdn.filespin.io/api/v1/storyboard/880f481b580e4ddbb51427137d8c2233/storyboard_000008.jpg | J6: YDaAgeyVXiw | L6: https://www.lovethework.com/work/entries/let-there-be-cake-759113 | M6: A 40th anniversary film for KFC Thailand that reimagines the brand's milestone as a cake-centric celebration, produced by Bananas Johannesburg and Brains & Brawn Bangkok. The spot uses the visual and ritual language of a birthday cake — candles, layers, the act of cutting — to mark four decades of KFC in Thailand. | N6: qsr, fast-food, restaurant, food, film, cinema, entertainment, brand-anniversary, thailand, birthday, celebration, south-africa
A7: 2025 | B7: Gold | C7: The Last Birthday | D7: Association Valentin Haüy | E7: Non Profit Organization - Defense of the Rights of Blind and Visually Impaired People | F7: Josiane | G7: France | H7: B07 - Not-For-Profit / Charity / Government | I7: digital-presentation-images/film-association-valentin-hauy-the-last-birthday.webp | J7: E4mGmGE8fC0 | L7: https://www.lovethework.com/work/entries/the-last-birthday-739026 | M7: A dark-comedy film set at a birthday party where guests approaching 60 frantically attempt to destroy their own eyesight — scored to Charles Aznavour's "Ces yeux-là" — built to expose a French law that cuts off disability assistance to anyone who loses their sight after age 60. The film was banned from both TV and YouTube before circulating online, produced by Josiane and Hiersoir for the Association Valentin Haüy. | N7: non-profit, online-film, disability-rights, france, public-health, dark-comedy, advocacy, visual-impairment
A8: 2025 | B8: Gold | C8: Telstra - Better on a Better Network | D8: Telstra | E8: Telstra | F8: Bear Meets Eagle on Fire | G8: Australia | H8: F03 - Single-Market Campaign | I8: digital-presentation-images/film-telstra-telstra-better-on-a-better-network.webp | J8: L8wOtakkr28 | L8: https://www.lovethework.com/work/entries/telstra-better-on-a-better-network-739331 | M8: A suite of 26 short films, each set in a different lesser-known regional town or remote area of Australia, brought to life through 56 puppets voiced by 42 actors — each film representing a local story and community that benefits from Telstra's network coverage. The spots aired across Channel 9's Olympics and Paralympics broadcast, replacing the single repeated sponsor spot with a rotating cast of regional characters and landscapes. | N8: telecommunications, film, cinema, entertainment, puppets, craft, regional, australia, broadcast, olympics, sport, multi-spot
A9: 2025 | B9: Gold | C9: The Best Place in the World to Have Herpes | D9: New Zealand Herpes Foundation | E9: New Zealand Herpes Foundation | F9: Finch | G9: Australia | H9: F05 - Use of Humour | I9: digital-presentation-images/film-new-zealand-herpes-foundation-the-best-place-in-the-world-to-have-herpes.webp | J9: vimeo:1081954251 | L9: https://www.lovethework.com/work/entries/the-best-place-in-the-world-to-have-herpes-739431 | M9: A tourism-style campaign for the New Zealand Herpes Foundation, created by Finch in Sydney and Motion Sickness in Auckland, that repositioned herpes stigma reduction as a matter of national pride — framing it as a competition New Zealand could win. A live Herpes Stigma Index on the campaign website tracked New Zealand's ranking against 77 other countries, while a five-lesson "Herpes Destigmatisation Course" used humour to walk participants through misconceptions, awarding points that contributed to the national leaderboard position. The work drew on the fact that 30% of New Zealanders diagnosed with herpes experience depressive or suicidal thoughts, and that the virus — despite being common and largely harmless — is rarely discussed openly. | N9: public-health, digital, health-education, humour, new-zealand, australia, e-learning, website, stigma, ooh
A10: 2025 | B10: Gold | C10: Brian Cox Goes to College | D10: Uber One | E10: Uber One for Students | F10: Special | G10: United States | H10: F05 - Use of Humour | I10: digital-presentation-images/film-uber-one-brian-cox-goes-to-college.webp | J10: vimeo:1035756667 | L10: https://www.lovethework.com/work/entries/brian-cox-goes-to-college-739411 | M10: A TV spot for Uber One's student membership tier that casts 78-year-old Brian Cox — playing a gruff, curmudgeonly version of himself — as an unlikely college student willing to re-enroll just to access $4.99/month perks: $0 delivery fees, 10% off orders, and 6% cash back on rides. The joke is that the deal is so good it makes even a billionaire actor consider going back to campus, with Cox's talent for playing cantankerous authority lending the premise a dry, self-aware irony. | N10: ride-hailing, film, cinema, entertainment, humor, celebrity-casting, student-audience, subscription, united-states, uber-eats, food-delivery, food, restaurant, ecommerce, retail, online-shopping
A11: 2025 | B11: Gold | C11: Group Therapy | D11: AXA | E11: AXA | F11: VML | G11: France | H11: F05 - Use of Humour | I11: digital-presentation-images/film-axa-group-therapy.webp | J11: vimeo:1158349533 | L11: https://www.lovethework.com/work/entries/group-therapy-739424 | M11: A feature-length documentary produced with Kevin Hart's Hartbeat company, in which six comedians — Mike Birbiglia, Nicole Byer, Gary Gulman, London Hughes, Tig Notaro, and Atsuko Okatsuka — participate in a candid group therapy session led by Neil Patrick Harris, built on the insight that comedians routinely process personal pain in front of audiences. Released on Prime Video and supported by a multimedia campaign across Twitch, Fire TV, and Meta, it anchors a global AXA initiative directing viewers to a free Mind Health Self-Check tool — motivated by survey findings that only 4 in 10 people with preventable mental health conditions seek professional help, and that 39% of 18–24 year-olds experience severe anxiety, stress, or depression. | N11: health-insurance, documentary, film, entertainment, cinema, mental-health, healthcare, medical, comedy, prime-video, streaming, tv, global, public-health, branded-content
A12: 2025 | B12: Silver | C12: Flock | D12: Apple | E12: iPhone | F12: TBWA\Media Arts Lab | G12: United States | H12: A01 - Consumer Goods | I12: digital-presentation-images/film-apple-flock.webp | J12: vimeo:1006144786 | L12: https://www.lovethework.com/work/entries/flock-738495 | M12: A dystopian short film, made by TBWA\Media Arts Lab, in which surveillance cameras built to look like birds and bats — pigeons, seagulls, ravens, owls, and bats, each crafted as physical models before being composited into live-action footage — hunt people's browsing data across everyday online moments. Safari's privacy protections intervene to scatter the flock, drawing a contrast between iPhone and browsers that monetize every click, swipe, and scroll. | N12: iphone, consumer-electronics, film, cinema, entertainment, privacy, vfx, creature-design, united-states, safari, online-tracking
A13: 2025 | B13: Silver | C13: Jordan Can't Ban Greatness | D13: Nike | E13: Nike | F13: Wieden+Kennedy | G13: United States | H13: A01 - Consumer Goods | I13: digital-presentation-images/film-nike-jordan-cant-ban-greatness.webp | J13: vimeo:1053855569 | L13: https://www.lovethework.com/work/entries/jordan-cant-ban-greatness-738501 | M13: A staged "ban" rollout launched on NBA Christmas Day 2024, using the 40th anniversary of the NBA's 1985 fine on the Air Jordan I as its premise — asking what the world would look like if Nike had never paid it. Over the following weeks, Jordan Brand's own Instagram account disappeared, Air Jordans were pulled from Nike.com, Jalen Hurts was positioned as fined by the NFL for wearing "unapproved colors," the Jumpman was blacked out on Michael Jordan's Chicago statue, lyrics referencing Air Jordan were removed from Genius, the shoe was banned from NBA2K, a Jordan NASCAR wrap carried a "Banned" theme, and the Jumpman logo was projected into the sky via drone show above the Jordan Brand fan fest in Oakland. | N13: footwear, integrated-campaign, social-media, stunt, sports-marketing, united-states, basketball, film, cinema, entertainment
... A53: 2025 | B53: Bronze | C53: Skin | D53: Raça Magazine | E53: Institutional | F53: LePub | G53: Brazil | H53: F09 - Cultural Engagement | I53: digital-presentation-images/film-raca-magazine-skin.webp | J53: vimeo:1088284685 | L53: https://www.lovethework.com/work/entries/skin-739661 | M53: A print and film ad for RAÇA Magazine, Brazil's Black press publication, built around the handwritten testimony of Carlos Palmeira — a Brazilian man with vitiligo whose skin shifted from completely Black to completely White, a condition affecting 0.009% of Brazilians. His account, written in his own hand and overlaid across his portrait, describes how the same people who once profiled, ignored, or feared him began treating him with warmth as his pigmentation changed — a firsthand account of racism operating through appearance alone. | N53: print, film, cinema, entertainment, magazine, anti-racism, brazil, handwritten, institutional, racial-equity, portrait
A54: 2026 | B54: Gold | C54: Hope | D54: IKEA | E54: IKEA Home Furnishings | F54: TRY | G54: Norway | H54: A01 - Consumer Goods | I54: https://ascentialcdn.filespin.io/api/v1/storyboard/05eb6c2bef6f405cb9e64fa464be0ee5/storyboard_000008.jpg | J54: vimeo:1096194558 | M54: Part of a TRY, Oslo print series for IKEA built on sharp copywriting and art direction, the 'Hope' execution turns an everyday domestic moment into a crafted home-furnishings ad. | N54: ikea, home furnishings, furniture, home, retail, print, copywriting, art direction, design, try, oslo, norway
A55: 2026 | B55: Gold | C55: Mornings | D55: IKEA | E55: IKEA Home Furnishings | F55: TRY | G55: Norway | H55: A01 - Consumer Goods | I55: https://ascentialcdn.filespin.io/api/v1/storyboard/b73a8e6bb7864c92bfc36217a62b9e07/storyboard_000008.jpg | J55: vimeo:1096194558 | M55: Part of a TRY, Oslo print series for IKEA built on sharp copywriting and art direction, the 'Mornings' execution turns an everyday domestic moment into a crafted home-furnishings ad. | N55: ikea, home furnishings, furniture, home, retail, print, copywriting, art direction, design, try, oslo, norway
A56: 2026 | B56: Gold | C56: Picky | D56: IKEA | E56: IKEA Home Furnishings | F56: TRY | G56: Norway | H56: A01 - Consumer Goods | I56: https://ascentialcdn.filespin.io/api/v1/storyboard/0bf25309251246599f87bd442bae7502/storyboard_000008.jpg | J56: vimeo:1096194558 | M56: Part of a TRY, Oslo print series for IKEA built on sharp copywriting and art direction, the 'Picky' execution turns an everyday domestic moment into a crafted home-furnishings ad. | N56: ikea, home furnishings, furniture, home, retail, print, copywriting, art direction, design, try, oslo, norway
A57: 2026 | B57: Gold | C57: Awake | D57: IKEA | E57: IKEA Home Furnishings | F57: TRY | G57: Norway | H57: A01 - Consumer Goods | I57: https://ascentialcdn.filespin.io/api/v1/storyboard/cbd032d6bd4d42cc843cc6b8ae5595f0/storyboard_000008.jpg | J57: vimeo:1096194558 | M57: One of IKEA's run of brand films from TRY built on simple, recognisable moments of life at home, where an everyday domestic scene becomes a quiet reminder of how the home shapes daily life. | N57: ikea, home furnishings, home, family, everyday life, furniture, norway, slice of life
A58: 2026 | B58: Bronze | C58: Slide | D58: Apple | E58: iPhone 17 | F58: Apple | G58: United States | H58: A01 - Consumer Goods | I58: https://i.ytimg.com/vi/PBrYMBacnyM/maxresdefault.jpg | J58: vimeo:1168177137 | L58: https://www.lovethework.com/work/entries/slide-780526 | M58: A demonstration film for the iPhone 17's Ceramic Shield 2 scratch resistance. Across a tense, wordless business negotiation, an iPhone 17 Pro is slid face-down back and forth along a long boardroom table, turning a durability claim into a single sustained piece of tabletop tension. | N58: apple, iphone, smartphone, technology, product demo, durability, screen, negotiation
A59: 2026 | B59: Silver | C59: A Critter Carol | D59: Apple | E59: iPhone | F59: TBWA\Media Arts Lab | G59: United States | H59: A01 - Consumer Goods | I59: https://beastgrip.com/cdn/shop/articles/shot-on-iphone-17-pro-a-critter-carol-beastgrip-gear-behind-the-magic_10ea192b-ee14-4514-915e-2d46daad1ef4.jpg | J59: h7v2YtzPag4 | L59: https://www.lovethework.com/work/entries/a-critter-carol-782154 | M59: Apple's holiday 'Shot on iPhone' film: after a hiker drops an iPhone in a snowy forest, a group of handmade puppet critters — a raccoon, bear, owl, deer and others — find it and film themselves in a joyful musical number celebrating friendship and craft. Directed by Mark Molloy. (Cross-Channel Storytelling entry.) | N59: apple, iphone, smartphone, technology, holiday, christmas, puppets, animation, film, cinema, entertainment, storytelling, cross-channel, music, digital craft, tbwa media arts lab, united states
A60: 2026 | B60: Bronze | C60: Never Over | D60: Eli Lilly | E60: Eli Lilly | F60: Wieden+Kennedy | G60: United States | H60: A02 - Healthcare | I60: https://qtxasset.com/quartz/qcloud5/media/image/lilly-neverover.jpg | J60: CtxdhnieTCQ | L60: https://www.lovethework.com/work/entries/never-over-780835 | M60: A short film that draws a parallel between Olympic sport and scientific research, setting the relentless, never-finished pursuit of athletic greatness against the equally unending work of medical discovery. | N60: eli lilly, pharma, healthcare, olympics, sport, science, research, perseverance
A61: 2026 | B61: Bronze | C61: Good Days | D61: Lilly | E61: Pharma | F61: Wieden+Kennedy | G61: United States | H61: A02 - Healthcare | I61: https://ascentialcdn.filespin.io/api/v1/storyboard/907717afa6174727846d909d942e5a11/storyboard_000008.jpg | J61: vimeo:1150526756 | L61: https://www.lovethework.com/work/entries/good-days-776865 | M61: A short film about Alzheimer's that dramatises the stark, unpredictable contrast between the good and bad days people living with the disease experience, holding the two against each other to convey how much an ordinary good day can mean. | N61: lilly, pharma, healthcare, alzheimers, dementia, memory, caregiving, awareness
A62: 2026 | B62: Gold | C62: No Project Without Drama | D62: Hornbach | E62: Home Improvement Superstore | F62: Heimat\TBWA | G62: Germany | H62: A04 - Travel, Leisure, Retail, Restaurants & Fast-Food Chains | I62: https://i.ytimg.com/vi/FN5yqNreuTU/maxresdefault.jpg | J62: OOgaqXlaH2Q | M62: A cinematic homage to the beauty and chaos of do-it-yourself life for German home-improvement retailer Hornbach, treating ordinary renovation projects with movie-grade tension, scale and craft. | N62: hornbach, home improvement, diy, retail, hardware store, germany, film, cinema, entertainment, direction, sound design, production design, achievement in production, film craft, heimat tbwa, drama
A63: 2026 | B63: Bronze | C63: Tableau | D63: John Lewis | E63: John Lewis | F63: Saatchi & Saatchi | G63: United Kingdom | H63: A04 - Travel, Leisure, Retail, Restaurants & Fast-Food Chains | I63: https://ascentialcdn.filespin.io/api/v1/storyboard/2be90f6054584758b96b99e0381a6947/storyboard_000008.jpg | L63: https://www.lovethework.com/work/entries/tableau-773408 | M63: Marking 100 years of John Lewis's 'Never Knowingly Undersold' promise, a highly choreographed single moving portrait that turns a century of British life into one continuous tableau. | N63: john lewis, retail, department store, christmas, britain, heritage, saatchi saatchi, somesuch, production design, licensed music, use of licensed adapted music, achievement in production, film craft, united kingdom
A64: 2026 | B64: Bronze | C64: Unloved | D64: Intermarché | E64: Retail | F64: Romance | G64: France | H64: A04 - Travel, Leisure, Retail, Restaurants & Fast-Food Chains | I64: https://ascentialcdn.filespin.io/api/v1/storyboard/f840ad18f88245f099c2cb8cb59c3dc5/storyboard_000008.jpg | J64: 2p62no4LBg8 | L64: https://www.lovethework.com/work/entries/unloved-773428 | M64: A two-and-a-half-minute Christmas film for supermarket Intermarche, created by Romance, telling the story of an unloved wolf shunned by the forest who finds belonging by learning to eat well. Blending live action and 3D animation, 'Le Mal-Aime' sells a heartfelt holiday tale about healthy eating rather than the produce itself. | N64: intermarche, retail, supermarket, grocery, healthy eating, nutrition, healthcare, france, christmas, film, cinema, entertainment, animation, storytelling, wolf, romance, bronze
A65: 2026 | B65: Bronze | C65: Bring a Book to Life | D65: Amazon | E65: Amazon Books | F65: Droga5 | G65: United Kingdom | H65: A05 - Media/Entertainment | I65: https://ascentialcdn.filespin.io/api/v1/storyboard/d18719e0933443d7bebd1a7fdd001889/storyboard_000008.jpg | J65: vimeo:1103797486 | L65: https://www.lovethework.com/work/entries/bring-a-book-to-life-773361 | M65: A campaign for Amazon Books and Kindle built on the idea that a story doesn't move on its own; it needs the reader's imagination to give it life. The film takes viewers on a visual adventure through thrillers, romances and historic tales as readers conjure them into being. | N65: amazon, books, kindle, reading, imagination, publishing, literature, retail
A66: 2026 | B66: Bronze | C66: Bullet Machine | D66: La Unión Newspaper and Article 19 | E66: La Unión Newspaper and Article 19 | F66: Grey | G66: Mexico | H66: A05 - Media/Entertainment | I66: https://ascentialcdn.filespin.io/api/v1/conversion/df6cf4fa9847452db1e19199cd182928 | J66: 9vpZNqaMVaQ | L66: https://www.lovethework.com/work/entries/bullet-machine-776914 | M66: Released to coincide with World Press Freedom Day, a short film for La Unión Newspaper and Article 19 exposing how violence against journalists in Mexico also threatens their families and communities. | N66: article 19, la union, journalism, press freedom, mexico, human rights, violence, social cause, sound design, direction, film craft, grey, world press freedom day
A67: 2026 | B67: Bronze | C67: Dish | D67: OpenAI | E67: ChatGPT | F67: Isle of Any | G67: United States | H67: A06 - Consumer Services/Business to Business | I67: https://ascentialcdn.filespin.io/api/v1/storyboard/2e6f760af8624a3bbe2776efef6b2c2e/storyboard_000008.jpg | J67: vimeo:1135476314 | L67: https://www.lovethework.com/work/entries/dish-780559 | M67: Part of ChatGPT's first large-scale brand campaign: short, cinematic films shot on 35mm that each end like a movie's final scene and rely on the viewer's knowledge of cinema to fill in what came before. 'Dish' follows a character using ChatGPT to cook. | N67: openai, chatgpt, ai, technology, artificial intelligence, cooking, cinematic, film series
A68: 2026 | B68: Bronze | C68: Pull Up | D68: OpenAI | E68: ChatGPT | F68: Isle of Any | G68: United States | H68: A06 - Consumer Services/Business to Business | I68: https://ascentialcdn.filespin.io/api/v1/storyboard/e6ee7a2d8238436f8c0f02cc0ab2e9a3/storyboard_000008.jpg | J68: IqC3YrIzbQw | L68: https://www.lovethework.com/work/entries/pull-up-773350 | M68: Part of ChatGPT's first large-scale brand campaign: short, cinematic films shot on 35mm that each end like a movie's final scene and trust the audience to imagine the rest. 'Pull Up' shows ChatGPT lending a hand to an everyday moment. | N68: openai, chatgpt, ai, technology, artificial intelligence, cinematic, film series
A69: 2026 | B69: Bronze | C69: Trip | D69: OpenAI | E69: ChatGPT | F69: Isle of Any | G69: United States | H69: A06 - Consumer Services/Business to Business | I69: https://ascentialcdn.filespin.io/api/v1/storyboard/d70b203a977b4daca0bd57bcad94e4f8/storyboard_000008.jpg | J69: vimeo:1122948088 | L69: https://www.lovethework.com/work/entries/trip-780560 | M69: Part of ChatGPT's first large-scale brand campaign: short, cinematic films shot on 35mm. 'Trip' follows a character using ChatGPT to plan and navigate travel, ending at the journey's final beat and leaving the audience to picture the rest. | N69: openai, chatgpt, ai, technology, artificial intelligence, travel, tourism, cinematic, film series
A70: 2026 | B70: Bronze | C70: In Good Time | D70: Uber | E70: Service / Automotive | F70: Mother | G70: United States | H70: A06 - Consumer Services/Business to Business | I70: https://i.ytimg.com/vi/CafQC20v8Kw/maxresdefault.jpg | J70: vimeo:1127387388 | L70: https://www.lovethework.com/work/entries/in-good-time-780298 | M70: A long-form film that turns Uber's ride tracker into a storytelling device, counting down the fleeting moments before each ride arrives as it follows a couple through a slice-of-life love story from a suburban bar to a life-changing moment outside a costume party. | N70: uber, ride hailing, transport, love story, suburbs, slice of life, eta, technology
A71: 2026 | B71: Grand Prix | C71: Can I Get a Six Pack Quickly? | D71: Claude | E71: Claude | F71: Mother London | G71: United Kingdom | H71: A06 - Consumer Services/Business to Business | I71: https://ascentialcdn.filespin.io/api/v1/storyboard/0d44bcbacd244b2bb8c30a2604f3a64b/storyboard_000008.jpg | J71: NuEXYfbV_PA | M71: One of Claude's first brand films, a darkly comedic spot in which a man struggling with pull-ups asks a muscular stranger how to get a six pack quickly, only for the stranger to start shoving ads into his replies; a pointed jab at AI assistants that blur the line between helping and selling. | N71: claude, anthropic, ai, technology, artificial intelligence, advertising, humour, super bowl
A72: 2026 | B72: Grand Prix | C72: How Can I Communicate Better With My Mom? | D72: Claude | E72: Claude | F72: Mother London | G72: United Kingdom | H72: A06 - Consumer Services/Business to Business | I72: https://ascentialcdn.filespin.io/api/v1/storyboard/a2e0a30e8993406ab779e1b13e17ee28/storyboard_000008.jpg | J72: 8ZnGqg87FEo | M72: One of Claude's first brand films, named after a real question people ask AI. The darkly comedic spot imagines what happens when an assistant built to help is instead primed to sell, exposing the risk of ads creeping into AI answers. | N72: claude, anthropic, ai, technology, artificial intelligence, advertising, humour, super bowl
A73: 2026 | B73: Bronze | C73: Help! | D73: Santalucía | E73: Santalucía Insurance | F73: Oriol Villar | G73: Spain | H73: A06 - Consumer Services/Business to Business | I73: https://i.ytimg.com/vi/eGqMrzR9Z3c/maxresdefault.jpg | J73: vimeo:1204811319 | L73: https://www.lovethework.com/work/entries/help-778437 | M73: A film for Spanish insurer Santalucia from Oriol Villar that dramatises a moment of need to make the case for the reassurance and support an insurer is meant to provide. | N73: santalucia, insurance, financial-services, finance, spain, financial services, support, reassurance
A74: 2026 | B74: Silver | C74: L'Ultimo Uomo Reale ("The Last Real Man") | D74: Team One | E74: Luxury Resale Authentication | F74: Team One | G74: United States | H74: B01 - Consumer Goods | I74: https://ascentialcdn.filespin.io/api/v1/storyboard/7ec728894e3b4d52904dc3236ff69c4c/storyboard_000008.jpg | J74: bAivc_GuTTA | L74: https://www.lovethework.com/work/entries/lultimo-uomo-reale-the-last-real-man-780570 | M74: An AI-generated film for luxury resale-authentication brand The RealReal that pokes fun at the pitfalls of AI while celebrating what's 'real'; entered in AI Craft. | N74: the realreal, team one, luxury, resale, authentication, ai, technology, artificial intelligence, ai craft, generative, film craft, united states
A75: 2026 | B75: Gold | C75: I Think of You Dying | D75: Life360 | E75: Life360 | F75: Alto | G75: United States | H75: B01 - Consumer Goods | I75: https://i.vimeocdn.com/video/2010937384-516d276f3ecaa7e95ecdc6d192f631ac4356ecf8e8b686f7c92c4d33f3dc9c96-d | M75: A fiction short film with an original composition for the family-safety app Life360, built around the anxious what-ifs a parent runs through about a loved one's safety — the kind of worry the app is designed to ease. | N75: life360, app, technology, family safety, location tracking, music, entertainment, original composition, song, fiction film, alto, united states, bronze
A76: 2026 | B76: Bronze | C76: Mother Strike | D76: Snack Jack | E76: Snack Jack Ring | F76: Hanami Food | G76: Thailand | H76: B01 - Consumer Goods | I76: https://agenda-note.com/files/user/202604090007_2.png | J76: MU6XGbpTAQY | M76: A film for Thai snack brand Snack Jack Ring from Hanami Food that plays a everyday domestic standoff for comic effect to put its product at the centre of the moment. | N76: snack jack, snacks, food, thailand, humour, family, consumer goods
A77: 2026 | B77: Bronze | C77: A Critter Carol | D77: Apple | E77: iPhone | F77: TBWA\Media Arts Lab | G77: United States | H77: B01 - Consumer Goods | I77: https://beastgrip.com/cdn/shop/articles/shot-on-iphone-17-pro-a-critter-carol-beastgrip-gear-behind-the-magic_10ea192b-ee14-4514-915e-2d46daad1ef4.jpg | J77: h7v2YtzPag4 | L77: https://www.lovethework.com/work/entries/a-critter-carol-782155 | M77: Apple's holiday 'Shot on iPhone' film: after a hiker drops an iPhone in a snowy forest, a group of handmade puppet critters — a raccoon, bear, owl, deer and others — find it and film themselves in a joyful musical number celebrating friendship and craft. Directed by Mark Molloy. (Cross-Channel Storytelling entry.) | N77: apple, iphone, smartphone, technology, holiday, christmas, puppets, animation, film, cinema, entertainment, storytelling, cross-channel, music, digital craft, tbwa media arts lab, united states
A78: 2026 | B78: Bronze | C78: Love Hurts | D78: Vaseline | E78: Vaseline | F78: Ogilvy Singapore | G78: Singapore | H78: B02 - Healthcare | I78: https://ascentialcdn.filespin.io/api/v1/storyboard/6cc46c323ad24662a60e2bb0be9ed9b7/storyboard_000008.jpg | J78: wlFdNOZvpFc | L78: https://www.lovethework.com/work/entries/love-hurts-782296 | M78: A film built on a ritual familiar across many families: a parent or grandparent applying Vaseline to a child's face whether the child likes it or not. It frames this small, stubborn, often-resisted gesture as an everyday, unspoken act of care and protection. | N78: vaseline, petroleum jelly, skincare, personal-care, beauty, family, care, ritual, parenting, singapore
A79: 2026 | B79: Bronze | C79: No Project Without Drama | D79: Hornbach | E79: Home Improvement Superstore | F79: Heimat\TBWA | G79: Germany | H79: B04 - Travel, Leisure, Retail, Restaurants & Fast-Food Chains | I79: https://i.ytimg.com/vi/FN5yqNreuTU/maxresdefault.jpg | J79: OOgaqXlaH2Q | M79: A cinematic homage to the beauty and chaos of do-it-yourself life for German home-improvement retailer Hornbach, treating ordinary renovation projects with movie-grade tension, scale and craft. | N79: hornbach, home improvement, diy, retail, hardware store, germany, film, cinema, entertainment, direction, sound design, production design, achievement in production, film craft, heimat tbwa, drama
A80: 2026 | B80: Silver | C80: Drop In | D80: Electronic Arts | E80: EA Skate | F80: Uncommon Creative Studio | G80: United States | H80: B05 - Media/Entertainment | I80: https://i.ytimg.com/vi/DeGXanmlJ_0/maxresdefault.jpg | J80: 6FNbP64LKmk | L80: https://www.lovethework.com/work/entries/drop-in-773514 | M80: A relaunch film for EA's Skate after a 15-year hiatus, made with and for the skate community; produced by Riff Raff Films and directed by The Sacred Egg, recognized for its editing. | N80: electronic arts, ea skate, gaming, video-games, entertainment, video game, skateboarding, skate, editing, uncommon creative studio, riff raff films, film craft, united states, community
A81: 2026 | B81: Silver | C81: Your Way Out | D81: Coinbase | E81: Coinbase | F81: Isle of Any | G81: United States | H81: B06 - Consumer Services/Business to Business | I81: https://ascentialcdn.filespin.io/api/v1/storyboard/6e7a83cdcdca4cb386c0bcec3dcb9870/storyboard_000008.jpg | J81: spmjIn5NaV0 | L81: https://www.lovethework.com/work/entries/your-way-out-773483 | M81: A film for Coinbase that challenges perceptions of the traditional financial system using video-game aesthetics: a character navigates and escapes a rigged, game-like world, framing crypto as the way out. (Film Craft Grand Prix; also won across Direction, Production Design, Achievement in Production and Script.) | N81: coinbase, crypto, cryptocurrency, finance, financial system, video game, gaming aesthetics, film, cinema, entertainment, direction, production design, achievement in production, film craft, grand prix, isle of any, united states
A82: 2026 | B82: Bronze | C82: Mafia | D82: Purga Studio | E82: AI Production Company | F82: Gut | G82: Mexico | H82: B06 - Consumer Services/Business to Business | I82: https://i.ytimg.com/vi/lc_CGwfNsvQ/maxresdefault.jpg | J82: vimeo:1182109710 | L82: https://www.lovethework.com/work/entries/mafia-780898 | M82: Part of 'Lorem Ipsum,' a trilogy marking the launch of AI production house Purga Films. The film stages a high-end, cinematic mafia drama in which characters perform with full dramatic weight, yet every line of dialogue is built from placeholder filler text; a provocation about the illusion of polished execution. | N82: purga studio, ai, technology, artificial intelligence, production, film craft, mafia, lorem ipsum, mexico
A83: 2026 | B83: Bronze | C83: Samurai | D83: Purga Studio | E83: AI Production Company | F83: Gut | G83: Mexico | H83: B06 - Consumer Services/Business to Business | I83: https://i.ytimg.com/vi/trGqIa1RZTg/maxresdefault.jpg | J83: vimeo:1182110177 | L83: https://www.lovethework.com/work/entries/samurai-780899 | M83: Part of 'Lorem Ipsum,' a trilogy marking the launch of AI production house Purga Films. The film stages a high-end, cinematic samurai drama in which characters perform with full dramatic weight, yet every line of dialogue is built from placeholder filler text; a provocation about the illusion of polished execution. | N83: purga studio, ai, technology, artificial intelligence, production, film craft, samurai, lorem ipsum, mexico
A84: 2026 | B84: Bronze | C84: Western | D84: Purga Studio | E84: AI Production Company | F84: Gut | G84: Mexico | H84: B06 - Consumer Services/Business to Business | I84: https://i.ytimg.com/vi/srE_ud-g8r0/maxresdefault.jpg | J84: vimeo:1182110488 | L84: https://www.lovethework.com/work/entries/western-780900 | M84: Part of 'Lorem Ipsum,' a trilogy marking the launch of AI production house Purga Films. The film stages a high-end, cinematic Western in which characters perform with full dramatic weight, yet every line of dialogue is built from placeholder filler text; a provocation about the illusion of polished execution. | N84: purga studio, ai, technology, artificial intelligence, production, film craft, western, lorem ipsum, mexico
A85: 2026 | B85: Silver | C85: Unfading Love | D85: Thai Life Insurance | E85: Thai Life Insurance | F85: Ogilvy | G85: Thailand | H85: B06 - Consumer Services/Business to Business | I85: https://ascentialcdn.filespin.io/api/v1/storyboard/c4235b7ba5a44d10bde3e3d6470f9bae/storyboard_000008.jpg | J85: vimeo:1150774030 | L85: https://www.lovethework.com/work/entries/unfading-love-780902 | M85: A film for Thai Life Insurance that prioritises cinematic storytelling over advertising convention, telling the story of a mother living with Alzheimer's and her grown son who has asthma as a meditation on how parents never stop caring for their children. | N85: thai life insurance, insurance, financial-services, finance, thailand, alzheimers, family, parenting, care, cinematic
A86: 2026 | B86: Bronze | C86: Beat Cancer Off | D86: Fuck Cancer | E86: Beat Cancer Off | F86: VML | G86: United States | H86: B07 - Not-for-Profit / Charity / Government | I86: https://ascentialcdn.filespin.io/api/v1/conversion/e10de6b252874bff954d07054112fa2a | J86: vimeo:1179609250 | L86: https://www.lovethework.com/work/entries/beat-cancer-off-780906 | M86: An original crooner-style song and film for the charity Fuck Cancer that strings together global euphemisms for male masturbation to raise prostate-health awareness — using irreverent humour, grounded in the scientific link between frequent ejaculation and lower prostate-cancer risk, to make men more willing to talk about and act on their health. | N86: fuck cancer, charity, non-profit, health, mens-health, prostate cancer, cancer awareness, music, entertainment, song, humour, vml, united states, gold
A87: 2026 | B87: Gold | C87: Apple Music x Bad Bunny Halftime Show - Shot on iPhone | D87: Apple | E87: Bad Bunny Super Bowl | F87: HPLA | G87: United States | H87: C01 - Viral Film | I87: digital-presentation-images/film-apple-bad-bunny-halftime-show-shot-on-iphone.webp | J87: G6FuWd4wNd8 | K87: badbunny-shot-on-iphone | M87: A 'Shot on iPhone' film capturing fans' reactions to Bad Bunny's Super Bowl halftime show, assembled from footage shot by photographers and cinematographers using iPhone across many locations and time zones, from Puerto Rico outward, to document a global cultural moment as it was felt around the world. | N87: apple, apple music, iphone, bad bunny, super bowl, music, entertainment, halftime, shot on iphone, culture
A88: 2026 | B88: Bronze | C88: Original Forever | D88: Adidas | E88: Adidas Originals | F88: Johannes Leonardo | G88: United States | H88: D01 - Screens & Events | I88: https://ascentialcdn.filespin.io/api/v1/conversion/7c69e0ddd6ef4e4c8949df7dc8e40429 | L88: https://www.lovethework.com/work/entries/original-forever-773587 | M88: The Entertainment Lions Grand Prix. For adidas Originals, Johannes Leonardo built a cultural partnership around the reunion of British rock band Oasis, tying the band's enduring 'original' status to the brand's heritage line and weaving adidas into one of the year's biggest music moments. | N88: adidas, adidas originals, sportswear, apparel, footwear, sneakers, fashion, consumer goods, united states, united kingdom, oasis, music, entertainment, band, reunion, brand partnership, collaboration, culture, johannes leonardo, grand prix
A89: 2026 | B89: Gold | C89: A Time and a Place | D89: Claude | E89: Claude | F89: Mother London | G89: United Kingdom | H89: F02 - Challenger Brand | I89: https://resized-media.entries.clios.com/companies/141675/media/c35f4ca9-48e7-4488-ff89-08de69f995ed-xlarge.jpg.webp | M89: For Anthropic's Claude, Mother imagined a near-future in which AI answers come sponsored — a pointed jab at rivals introducing ads into their chatbots. Four darkly comedic films, each named after a real question people ask AI about health, relationships or work, show a very human moment interrupted by an ad-supported chatbot response, positioning Claude as the assistant that keeps advertising out of the conversation. | N89: claude, anthropic, ai, technology, artificial intelligence, chatbot, software, tech, united kingdom, united states, advertising, ad-free, films, comedy, super bowl, challenger brand, brand strategy, creative strategy, mother, silver
A90: 2026 | B90: Silver | C90: Tableau | D90: John Lewis | E90: John Lewis | F90: Saatchi & Saatchi | G90: United Kingdom | H90: F03 - Single-Market Campaign | I90: https://ascentialcdn.filespin.io/api/v1/storyboard/2be90f6054584758b96b99e0381a6947/storyboard_000008.jpg | L90: https://www.lovethework.com/work/entries/tableau-773507 | M90: Marking 100 years of John Lewis's 'Never Knowingly Undersold' promise, a highly choreographed single moving portrait that turns a century of British life into one continuous tableau. | N90: john lewis, retail, department store, christmas, britain, heritage, saatchi saatchi, somesuch, production design, licensed music, use of licensed adapted music, achievement in production, film craft, united kingdom
A91: 2026 | B91: Bronze | C91: The Mexican Dream - The Work | D91: Indio | E91: Indio Beer | F91: Ogilvy | G91: Mexico | H91: F03 - Single-Market Campaign | I91: https://ascentialcdn.filespin.io/api/v1/storyboard/02865df39c1e4fd283baca7ecccfa9f4/storyboard_000008.jpg | J91: vimeo:1197514785 | L91: https://www.lovethework.com/work/entries/the-mexican-dream-the-work-781885 | M91: A film for Indio beer that reframes the 'American Dream' as something built on Mexican dreams, portraying Mexican resilience and hustle as the real engine behind the aspiration. | N91: indio, beer, alcohol, mexico, national pride, resilience, immigration, culture
A92: 2026 | B92: Bronze | C92: Who’s Waiting for You? | D92: Cerveza Victoria | E92: Cerveza Victoria | F92: Wieden+Kennedy | G92: Mexico | H92: F03 - Single-Market Campaign | I92: https://resized-media.entries.clios.com/companies/141437/media/9e902c01-f315-4959-00c0-08de69f995ee-xlarge.jpg.webp | L92: https://www.lovethework.com/work/entries/whos-waiting-for-you-782321 | M92: For Mexican beer brand Cerveza Victoria, Wieden+Kennedy Mexico created a short fiction film rooted in emotional storytelling and local culture, using the question 'Who's waiting for you?' to dramatise the people and homecomings that give a night out its meaning. | N92: cerveza victoria, beer, alcohol, drinks, beverage, fmcg, mexico, fiction film, short film, storytelling, emotional, culture, homecoming, entertainment, wieden kennedy, gold
A93: 2026 | B93: Bronze | C93: First School Poo | D93: Andrex | E93: Andrex | F93: Kimberly-Clark | G93: United Kingdom | H93: F03 - Single-Market Campaign | I93: https://ascentialcdn.filespin.io/api/v1/conversion/2970e06d192c4cdf8075574a6e83e958 | J93: vimeo:1084183002 | L93: https://www.lovethework.com/work/entries/first-school-poo-793461 | M93: A film tackling the taboo of children being afraid to poo at school. It opens on a boy in class, mortified after an accidental fart, to dramatise how many kids hold it in at school and make the case for comfort and confidence around an everyday bodily function. | N93: andrex, toilet paper, kimberly-clark, children, school, taboo, humour, health
A94: 2026 | B94: Bronze | C94: Love Hurts | D94: Vaseline | E94: Vaseline | F94: Ogilvy Singapore | G94: Singapore | H94: F04 - Social Behaviour | I94: https://ascentialcdn.filespin.io/api/v1/storyboard/6cc46c323ad24662a60e2bb0be9ed9b7/storyboard_000008.jpg | J94: wlFdNOZvpFc | L94: https://www.lovethework.com/work/entries/love-hurts-773643 | M94: A film built on a ritual familiar across many families: a parent or grandparent applying Vaseline to a child's face whether the child likes it or not. It frames this small, stubborn, often-resisted gesture as an everyday, unspoken act of care and protection. | N94: vaseline, petroleum jelly, skincare, personal-care, beauty, family, care, ritual, parenting, singapore
A95: 2026 | B95: Silver | C95: First School Poo | D95: Andrex | E95: Andrex | F95: Kimberly-Clark | G95: United Kingdom | H95: F04 - Social Behaviour | I95: https://ascentialcdn.filespin.io/api/v1/conversion/2970e06d192c4cdf8075574a6e83e958 | J95: vimeo:1084183002 | L95: https://www.lovethework.com/work/entries/first-school-poo-793471 | M95: A film tackling the taboo of children being afraid to poo at school. It opens on a boy in class, mortified after an accidental fart, to dramatise how many kids hold it in at school and make the case for comfort and confidence around an everyday bodily function. | N95: andrex, toilet paper, kimberly-clark, children, school, taboo, humour, health
A96: 2026 | B96: Silver | C96: After Shit Happened Service | D96: Shield Insurance | E96: Shield Insurance | F96: VML | G96: Thailand | H96: F05 - Use of Humour | I96: https://ascentialcdn.filespin.io/api/v1/storyboard/045a091430be44d791d894348f00f6e3/storyboard_000008.jpg | J96: vimeo:1177559337 | L96: https://www.lovethework.com/work/entries/after-shit-happened-service-773623 | M96: A darkly comic film for Shield Insurance built around the messy aftermath when things go wrong, using humour to argue for the value of being covered after the unexpected happens. | N96: shield insurance, insurance, financial-services, finance, thailand, humour, financial services, protection
A97: 2026 | B97: Silver | C97: I Think of You Dying | D97: Life360 | E97: Life360 | F97: Alto | G97: United States | H97: F05 - Use of Humour | I97: https://i.vimeocdn.com/video/2010937384-516d276f3ecaa7e95ecdc6d192f631ac4356ecf8e8b686f7c92c4d33f3dc9c96-d | L97: https://www.lovethework.com/work/entries/i-think-of-you-dying-773484 | M97: A fiction short film with an original composition for the family-safety app Life360, built around the anxious what-ifs a parent runs through about a loved one's safety — the kind of worry the app is designed to ease. | N97: life360, app, technology, family safety, location tracking, music, entertainment, original composition, song, fiction film, alto, united states, bronze
A98: 2026 | B98: Bronze | C98: The Kaprao Criminals | D98: KFC Thailand | E98: Kaprao Crispy Chicken Rice Bowl | F98: Wolf BKK | G98: Thailand | H98: F05 - Use of Humour | I98: https://ascentialcdn.filespin.io/api/v1/conversion/11e80619841d44a1a16a761dba652bc7 | L98: https://www.lovethework.com/work/entries/the-kaprao-criminals-773694 | M98: A casting-led comedic film for KFC Thailand's Kaprao Crispy Chicken Rice Bowl. | N98: kfc, fast food, qsr, fast-food, restaurant, food, thailand, kaprao, chicken, humor, casting, film craft, wolf bkk
A99: 2026 | B99: Silver | C99: Beat Cancer Off | D99: Fuck Cancer | E99: Beat Cancer Off | F99: VML | G99: United States | H99: F05 - Use of Humour | I99: https://ascentialcdn.filespin.io/api/v1/conversion/e10de6b252874bff954d07054112fa2a | J99: vimeo:1179609250 | L99: https://www.lovethework.com/work/entries/beat-cancer-off-781693 | M99: An original crooner-style song and film for the charity Fuck Cancer that strings together global euphemisms for male masturbation to raise prostate-health awareness — using irreverent humour, grounded in the scientific link between frequent ejaculation and lower prostate-cancer risk, to make men more willing to talk about and act on their health. | N99: fuck cancer, charity, non-profit, health, mens-health, prostate cancer, cancer awareness, music, entertainment, song, humour, vml, united states, gold
A100: 2026 | B100: Gold | C100: Based on a True Story | D100: Missing People | E100: Missing People | F100: BBH | G100: United Kingdom | H100: F05 - Use of Humour | I100: https://ascentialcdn.filespin.io/api/v1/storyboard/5bc0d8305a464d9b899a4aae1d0ef94c/storyboard_000008.jpg | J100: vimeo:1199684705 | M100: A film for the charity Missing People that challenges society's voracious, disconnected consumption of true-crime entertainment, reclaiming the narrative around real missing-person cases from the genre that turns them into content. | N100: missing people, charity, non-profit, true crime, awareness, social, missing persons
A101: 2026 | B101: Silver | C101: For Papa! | D101: Instacart | E101: Instacart Online Grocery Delivery | F101: McCann New York + BBDO + Local Produce | G101: United States | H101: F05 - Use of Humour | I101: https://ascentialcdn.filespin.io/api/v1/conversion/b5d8515d763b461097bfa2881636035f | J101: G-k2qTGwwc4 | L101: https://www.lovethework.com/work/entries/for-papa-777867 | M101: A casting-led, emotional film for Instacart grocery delivery, credited to McCann New York with BBDO Chicago and Local Produce San Francisco. | N101: instacart, grocery, retail, delivery, ecommerce, online-shopping, food, casting, film craft, mccann new york, bbdo, local produce, united states, emotional
A102: 2026 | B102: Silver | C102: I'm Not Remarkable | D102: Apple | E102: Accessibility | F102: Apple | G102: United States | H102: F07 - Corporate Purpose & Social Responsibility | I102: https://i.ytimg.com/vi/KmFPWxjmnqE/maxresdefault.jpg | L102: https://www.lovethework.com/work/entries/im-not-remarkable-780956 | M102: A musical short film for Apple, released around the International Day of Persons with Disabilities, built as a full college-musical anthem performed entirely by deaf and disabled students from around the world. The original song — written by Tim Minchin and performed by the cast — showcases Apple's accessibility features including Magnifier for Mac, Braille Access and Accessibility Reader while putting a large disabled ensemble centre stage. | N102: apple, accessibility, technology, consumer-electronics, music, entertainment, musical, song, disability, deaf, inclusion, diversity, tim minchin, short film, united states, gold
A103: 2026 | B103: Gold | C103: Bullet Machine | D103: La Unión Newspaper and Article 19 | E103: La Unión Newspaper and Article 19 | F103: Grey | G103: Mexico | H103: F07 - Corporate Purpose & Social Responsibility | I103: https://ascentialcdn.filespin.io/api/v1/conversion/df6cf4fa9847452db1e19199cd182928 | J103: 9vpZNqaMVaQ | M103: Released to coincide with World Press Freedom Day, a short film for La Unión Newspaper and Article 19 exposing how violence against journalists in Mexico also threatens their families and communities. | N103: article 19, la union, journalism, press freedom, mexico, human rights, violence, social cause, sound design, direction, film craft, grey, world press freedom day
A104: 2026 | B104: Gold | C104: Your Way Out | D104: Coinbase | E104: Coinbase | F104: Isle of Any | G104: United States | H104: F08 - Market Disruption | I104: https://ascentialcdn.filespin.io/api/v1/storyboard/6e7a83cdcdca4cb386c0bcec3dcb9870/storyboard_000008.jpg | J104: spmjIn5NaV0 | M104: A film for Coinbase that challenges perceptions of the traditional financial system using video-game aesthetics: a character navigates and escapes a rigged, game-like world, framing crypto as the way out. (Film Craft Grand Prix; also won across Direction, Production Design, Achievement in Production and Script.) | N104: coinbase, crypto, cryptocurrency, finance, financial system, video game, gaming aesthetics, film, cinema, entertainment, direction, production design, achievement in production, film craft, grand prix, isle of any, united states
A105: 2026 | B105: Silver | C105: A Time and a Place | D105: Claude | E105: Claude | F105: Mother London | G105: United Kingdom | H105: F08 - Market Disruption | I105: https://resized-media.entries.clios.com/companies/141675/media/c35f4ca9-48e7-4488-ff89-08de69f995ed-xlarge.jpg.webp | J105: UOdh90TqXPY | M105: For Anthropic's Claude, Mother imagined a near-future in which AI answers come sponsored — a pointed jab at rivals introducing ads into their chatbots. Four darkly comedic films, each named after a real question people ask AI about health, relationships or work, show a very human moment interrupted by an ad-supported chatbot response, positioning Claude as the assistant that keeps advertising out of the conversation. | N105: claude, anthropic, ai, technology, artificial intelligence, chatbot, software, tech, united kingdom, united states, advertising, ad-free, films, comedy, super bowl, challenger brand, brand strategy, creative strategy, mother, silver
A106: 2026 | B106: Silver | C106: AXA – Nothing Stops Women's Rugby | D106: AXA France | E106: Partnership AXA x Women's Rugby | F106: Publicis Conseil | G106: France | H106: F09 - Cultural Engagement | I106: https://ascentialcdn.filespin.io/api/v1/conversion/2a6b2b4859824eca99522c5972d31625 | L106: https://www.lovethework.com/work/entries/axa-nothing-stops-womens-rugby-776209 | M106: A three-minute manifesto film aired on France Télévisions, directed by Julien & Quentin, championing women's rugby as a fight against stereotypes and AXA's stance on women's rights. | N106: axa, insurance, financial-services, finance, womens rugby, sport, rugby, women, gender, france, editing, publicis conseil, film craft, manifesto

Sheet Outdoor
A1: Year | B1: Tier | C1: Campaign | D1: Brand | E1: Product/Service | F1: Agency | G1: Country | H1: Subcategory | I1: Image URL | J1: YouTube ID | K1: Campaign Group | L1: Entry URL | M1: Description | N1: Keywords
A2: 2025 | B2: Grand Prix | C2: Crowd | D2: KitKat | E2: KitKat | F2: VML | G2: Czech Republic | H2: A01 - Consumer Goods | I2: https://ascentialcdn.filespin.io/api/v1/conversion/6dc8ee87b55d449f88c8f8a0868b533a | J2: ByGNQ3wEbEY | L2: https://www.lovethework.com/work/entries/crowd-740225 | M2: A series of out-of-home placements across Czech Republic public transport and streets that use existing crowds of commuters and pedestrians as the visual content of the ad — positioning densely packed people as the reason to take a break. Each execution frames the surrounding crowd through the KitKat creative, making the real-world environment the message. | N2: chocolate, ooh, public-transport, street, czech-republic, ambient, experiential, consumer-goods, cpg, fmcg
A3: 2025 | B3: Grand Prix | C3: Public Transport | D3: KitKat | E3: KitKat | F3: VML | G3: Czech Republic | H3: A01 - Consumer Goods | I3: https://ascentialcdn.filespin.io/api/v1/conversion/9b1fc196d863402282277d81f4bdf031 | J3: ByGNQ3wEbEY | L3: https://www.lovethework.com/work/entries/public-transport-758659 | M3: An outdoor campaign across Czech Republic crowd, public transport, and street placements that depicted commuters and passersby in everyday phone-scrolling situations — but with KitKat bars swapped in place of their smartphones. The images required no explanation: the brand's longstanding "take a break" idea made literal by replacing the object people most compulsively reach for. | N3: snack, food, packaged-goods, cpg, fmcg, ooh, public-transport, street, czech-republic, print, photography, brand-awareness
A4: 2025 | B4: Grand Prix | C4: Street | D4: KitKat | E4: KitKat | F4: VML | G4: Czech Republic | H4: A01 - Consumer Goods | I4: https://ascentialcdn.filespin.io/api/v1/conversion/ad97fbb0d50649118006eac4d5a902a7 | J4: ByGNQ3wEbEY | L4: https://www.lovethework.com/work/entries/street-758667 | M4: Outdoor installations across Czech Republic streets and public transport placements that replaced the expected KitKat branding with images of crowds of people — all looking down at their phones. The work revived the "Have a break, have a KitKat" line without stating it, letting the behavior of the crowd make the case for putting the phone down. | N4: snack, food, packaged-goods, cpg, fmcg, ooh, public-transport, street, czech-republic, consumer-goods, phone-behavior, outdoor-installation
A5: 2025 | B5: Grand Prix | C5: Olympic Games Opening Ceremony Paris 2024 | D5: Paris 2024 | E5: Paris 2024 | F5: Paname 24 | G5: France | H5: C04 - Live Advertising and Events | I5: https://ascentialcdn.filespin.io/api/v1/conversion/60aa1888e5b6444381b060dc1801de84 | J5: t8o4ulxT1Cc | L5: https://www.lovethework.com/work/entries/olympic-games-opening-ceremony-paris-2024-740923 | M5: The official opening ceremony of the Paris 2024 Olympics, produced for the IOC and Paris 2024 by the Paname 24 collective — the first Olympic opener staged outside a stadium, sending 6,800 athletes down the Seine on 85 boats and ending with a hot-air-balloon cauldron lifted above the city. | N5: live-event, olympics, sport, ceremony, paris, large-scale, broadcast, entertainment, partnership, france
A6: 2025 | B6: Gold | C6: The Sip of Sanctuary | D6: Stella Artois | E6: Stella Artois | F6: Grey | G6: United Kingdom | H6: A01 - Consumer Goods | I6: https://ascentialcdn.filespin.io/api/v1/conversion/bc046e548975443980453424bc30515a | L6: https://www.lovethework.com/work/entries/the-sip-of-sanctuary-740333 | M6: A print campaign for Stella Artois, created by Grey London, built around three posters — "The Sip of Sanctuary," "Protector of the Chalice," and "Happiness Within Chaos" — each depicting the Stella Artois chalice as a refuge of calm amid surrounding disorder or threat. The imagery uses the glass itself as the visual anchor, framing a quiet moment of stillness as something worth protecting. | N6: beer, alcohol, print, poster, visual-storytelling, united-kingdom, illustration, campaign
A7: 2025 | B7: Gold | C7: Protector of the Chalice | D7: Stella Artois | E7: Stella Artois | F7: Grey | G7: United Kingdom | H7: A01 - Consumer Goods | I7: https://ascentialcdn.filespin.io/api/v1/conversion/a33c9462c05d4330895b056745b6a602 | L7: https://www.lovethework.com/work/entries/protector-of-the-chalice-740342 | M7: A series of posters by Grey London depicting people drinking a Stella Artois pint in crowded, chaotic surroundings — the chalice held steady and upright as the world presses in around it. Each execution frames the glass as a personal sanctuary, the one still point in a scene of noise and compression. | N7: beer, alcohol, print, ooh, poster, united-kingdom, illustration, consumer-goods, cpg, fmcg
A8: 2025 | B8: Gold | C8: Happiness Within Chaos | D8: Stella Artois | E8: Stella Artois | F8: Grey | G8: United Kingdom | H8: A01 - Consumer Goods | I8: https://ascentialcdn.filespin.io/api/v1/conversion/882ea591b6fa40b29a529180b71afa65 | L8: https://www.lovethework.com/work/entries/happiness-within-chaos-740351 | M8: A print campaign by Grey London that places a Stella Artois chalice — and the calm of drinking from it — inside visually hectic scenes, contrasting the stillness of the glass against surrounding disorder. Each execution in the series isolates the moment of a sip as a pocket of quiet amid crowds, noise, and clutter. | N8: beer, alcohol, print, ooh, united-kingdom, campaign-series, illustration, consumer-goods, cpg, fmcg
A9: 2025 | B9: Gold | C9: Fries | D9: Heinz | E9: Heinz | F9: Wieden+Kennedy | G9: United Kingdom | H9: B01 - Consumer Goods | I9: https://ascentialcdn.filespin.io/api/v1/conversion/9e7a10af468b4293bb13624b6ac695d7 | J9: vimeo:1167690695 | L9: https://www.lovethework.com/work/entries/fries-740416 | M9: A print and outdoor campaign from Wieden+Kennedy London that strips the Heinz label down to its iconic keystone frame, filling it with close-up photography of the brand's classic food pairings — fries, chips, and toast — with no product name required. The work leans on the idea that after 156 years, Heinz's associations are so ingrained in British culture that the pairings alone are enough to trigger recognition of the condiment. | N9: condiment, print, ooh, photography, brand-identity, united-kingdom, food-pairing, minimalism
A10: 2025 | B10: Gold | C10: Chips | D10: Heinz | E10: Heinz | F10: Wieden+Kennedy | G10: United Kingdom | H10: B01 - Consumer Goods | I10: https://ascentialcdn.filespin.io/api/v1/conversion/98502860304b486096f96cbacf35f7ac | J10: vimeo:1167690695 | L10: https://www.lovethework.com/work/entries/chips-740534 | M10: An outdoor campaign across major UK cities that swaps the word "Heinz" out of the brand's long-running "It Has to Be Heinz" tagline and replaces it with the food that completes the pairing — "It Has to Be Chips," "It Has to Be Toast," "It Has to Be Fries." Each execution centers on a single Heinz product shot alongside its instinctive companion, built on the idea that certain food combinations have become so fixed in British taste memory that either half of the pair can cue the brand. Produced by Studio Philotheus Nisch, Berlin. | N10: condiment, ooh, print, united-kingdom, campaign, food, copywriting, brand-tagline
A11: 2025 | B11: Gold | C11: Toast | D11: Heinz | E11: Heinz | F11: Wieden+Kennedy | G11: United Kingdom | H11: B01 - Consumer Goods | I11: https://ascentialcdn.filespin.io/api/v1/conversion/19b79ceaf445400d88e358d61316e067 | J11: vimeo:1167690695 | L11: https://www.lovethework.com/work/entries/toast-740549 | M11: A print and outdoor campaign of extreme close-up images pairing Heinz products with the British foods they're most associated with — fries, chips, and toast — shot to trigger sensory food memories rather than show full meals. Created by Wieden+Kennedy London, the work runs nationwide across the United Kingdom as a masterbrand campaign built on the observation that Heinz is inseparable from the taste of specific everyday foods. | N11: condiment, print, ooh, food-photography, masterbrand, united-kingdom, consumer-goods, cpg, fmcg
A12: 2025 | B12: Gold | C12: Scratch & Sniff | D12: Axe/Lynx | E12: Deodorant | F12: Lola MullenLowe | G12: Spain | H12: C01 - Displays | I12: https://ascentialcdn.filespin.io/api/v1/conversion/a4189a00c22b49558f6796c1b0fdf90c | J12: L5RfU7Jmoug | L12: https://www.lovethework.com/work/entries/scratch-sniff-740665 | M12: Scratch-and-sniff OOH panels placed in ambient locations to launch Axe/Lynx's new Lower Body Spray — a fine fragrance designed specifically for the groin area. The displays invited passersby to scratch the panel and smell the product, turning a taboo self-checking habit into a direct fragrance sampling mechanic. | N12: deodorant, personal-care, beauty, ooh, ambient, experiential, scent, sampling, spain, displays
A13: 2025 | B13: Gold | C13: Shades of Red | D13: Coca-Cola | E13: Coca-Cola Company | F13: David | G13: Spain | H13: C03 - Special Build | I13: https://ascentialcdn.filespin.io/api/v1/conversion/b9b1ac806434448cb6648aa308f263db | J13: vimeo:1083484983 | L13: https://www.lovethework.com/work/entries/shades-of-red-740785 | M13: A program that retired 12,700 sun-faded red awnings from Mexico's small 'tiendita' corner stores and replaced them. Each shop's old awning was repurposed into branded billboards and merch, and Coca-Cola pressed a limited run of cans whose label color matched the exact, faded shade of red on each shop's awning. | N13: retail, ooh, packaging, partnership, small-business, mexico, beverage, drinks, single-market
A14: 2025 | B14: Gold | C14: Missed Birthdays | D14: Itv X Calm | E14: Itv X Calm | F14: adam&eveDDB | G14: United Kingdom | H14: C04 - Live Advertising and Events | I14: https://ascentialcdn.filespin.io/api/v1/conversion/238b3e3f0aab4c3fa9adf2b23d50eab3 | J14: ifZVZ4fX4gg | L14: https://www.lovethework.com/work/entries/missed-birthdays-740958 | M14: A live television moment built around a birthday cake — on what would have been Evelyn's 18th birthday, ITV broadcast a real-time celebration of a young person who died by suicide, with the candles, the cake, and the empty chair making visible the birthdays that families of suicide victims never get to mark. Created with mental health charity CALM (Campaign Against Living Miserably), the broadcast directed viewers to CALM's tools for supporting young people who may be struggling. | N14: live-advertising, television, mental-health, healthcare, medical, suicide-prevention, public-service, united-kingdom, charity, broadcast, entertainment
A15: 2025 | B15: Gold | C15: Tracking Bad Bunny | D15: Rimas Music | E15: Bad Bunny | F15: DDB Latina Puerto Rico | G15: Puerto Rico | H15: C05 - Interactive Experiences | I15: https://ascentialcdn.filespin.io/api/v1/conversion/8c433c0437494277a7cb3b8c1148b82c | J15: -3Aq3u6EJZ4 | L15: https://www.lovethework.com/work/entries/tracking-bad-bunny-759229 | M15: A GPS-based scavenger hunt built around Bad Bunny's album release that sent fans to physical locations across Puerto Rico, using the artist's real-time movements as waypoints in a digital tracking experience. Created by DDB Latina Puerto Rico for Rimas Music, the mechanic turned the island itself into the stage for the launch. | N15: music, entertainment, interactive-experience, gps, scavenger-hunt, mobile, puerto-rico, album-launch, fan-engagement
A16: 2025 | B16: Gold | C16: Gulf of Mexico (Bar) | D16: Tecate | E16: Tecate Light | F16: LePub | G16: Mexico | H16: E01 - Local Brand | I16: https://ascentialcdn.filespin.io/api/v1/conversion/afa88aa8421b41a18c68b9863bb6926c | J16: TFbAS7weMR8 | L16: https://www.lovethework.com/work/entries/gulf-of-mexico-bar-741350 | M16: A floating bar built on a boat in the Gulf of Mexico, accessible only by sea and named 'Golfo de México' — a response to a U.S. proposal to rename the gulf the 'Gulf of America.' To pair, Tecate launched a special-edition Tecate Light brewed with salt harvested from the disputed waters. | N16: ooh, brand-stunt, political-commentary, beer, alcohol, packaging, mexico, branded-venue, special-edition
A17: 2025 | B17: Gold | C17: Price Packs | D17: Penny | E17: Food/Non-Food | F17: Serviceplan Germany | G17: Germany | H17: E02 - Challenger Brand | I17: https://ascentialcdn.filespin.io/api/v1/conversion/67b6df2a0fe64deeb274c91d50040c54 | J17: cnAXR4lk6R0 | L17: https://www.lovethework.com/work/entries/price-packs-741243 | M17: A packaging redesign for five Penny staples — oatmeal, toast, salt, crisps, mayonnaise — that swaps standard product graphics for the locked-in low price rendered enormous on the front of the pack. The shelf becomes its own price-stability ad, with the same visual extended to outdoor across all 2,100 stores. | N17: packaging, retail, ooh, supermarket, grocery, design, price, germany, market-disruption
A18: 2025 | B18: Gold | C18: Lucky Yatra | D18: Indian Railways | E18: Railway Service | F18: FCB India | G18: India | H18: E04 - Social Behaviour | I18: https://ascentialcdn.filespin.io/api/v1/conversion/7771593e59654e55b2c0654f5d61ec8e | J18: IYJlZRbvMEw | L18: https://www.lovethework.com/work/entries/lucky-yatra-741463 | M18: A loyalty program built into the ticketing system of Indian Railways: every valid ticket carries a unique number that's auto-entered into daily and weekly cash prize draws. Designed to turn ticketless travel — an entrenched habit on one of the world's largest rail networks — into a paid behavior worth doing. | N18: railway-service, loyalty-program, public-service, mobile-app, india, gamification, ticketing
A19: 2025 | B19: Silver | C19: Windsurf | D19: Cornetto | E19: Cornetto Ice Cream | F19: Lola MullenLowe | G19: Spain | H19: B01 - Consumer Goods | I19: https://ascentialcdn.filespin.io/api/v1/conversion/2f9ebcc7b9ec4ad9a4dcf79bd56fa88b | J19: hWhvFLwHOlE | L19: https://www.lovethework.com/work/entries/windsurf-740535 | M19: A series of outdoor print ads for Cornetto in Spain, each built around the shape of an unwrapped Cornetto cone used as the central graphic element — the wafer tip and chocolate base forming the hull of a boat, the body of a windsurfer, the arc of a wave, and the silhouette of a diver. Each execution in the "Unwrap It" campaign uses only the product's own geometry to construct a summer scene, with no additional illustration. | N19: ice-cream, ooh, print, outdoor, illustration, spain, summer, product-as-image, graphic-design
A20: 2025 | B20: Silver | C20: Surfer | D20: Cornetto | E20: Cornetto Ice Cream | F20: Lola MullenLowe | G20: Spain | H20: B01 - Consumer Goods | I20: https://ascentialcdn.filespin.io/api/v1/conversion/9ceaf650a007496f90b6d5670786b4df | J20: hWhvFLwHOlE | L20: https://www.lovethework.com/work/entries/surfer-740546 | M20: A graphic print series for Cornetto ice cream in which the wrapper of a half-unwrapped cone doubles as a visual element of a summer scene — a sail, a wave, a surfer's board, a diver's arc. Each execution uses only the product and its packaging to complete the image, with no additional illustration. | N20: ice-cream, print, ooh, packaging, outdoor, graphic-design, spain, consumer-goods, cpg, fmcg
... A53: 2025 | B53: Bronze | C53: Price Packs - Toast | D53: Penny | E53: Food/Non-Food | F53: Serviceplan Germany | G53: Germany | H53: A04 - Travel, Leisure, Retail, Restaurants & Fast-Food Chains | I53: https://ascentialcdn.filespin.io/api/v1/conversion/0f62d161bf704e03bcece90e78e11d29 | J53: cnAXR4lk6R0 | L53: https://www.lovethework.com/work/entries/price-packs-toast-740385 | M53: A retail packaging campaign for Penny in Germany that uses the physical pack design of everyday food products to communicate price. Created by Serviceplan Germany, the campaign turns the toast packaging itself into the price message, making shelf-level value visible without requiring a separate promotional label or display. | N53: retail, packaging, food, grocery, germany, price-communication, ooh, serviceplan
A54: 2025 | B54: Bronze | C54: The Sip of Sanctuary | D54: Stella Artois | E54: Stella Artois | F54: Grey | G54: United Kingdom | H54: B01 - Consumer Goods | I54: https://ascentialcdn.filespin.io/api/v1/conversion/bc046e548975443980453424bc30515a | L54: https://www.lovethework.com/work/entries/the-sip-of-sanctuary-740553 | M54: A print campaign for Stella Artois, created by Grey London, built around three posters — "The Sip of Sanctuary," "Protector of the Chalice," and "Happiness Within Chaos" — each depicting the Stella Artois chalice as a refuge of calm amid surrounding disorder or threat. The imagery uses the glass itself as the visual anchor, framing a quiet moment of stillness as something worth protecting. | N54: beer, alcohol, print, poster, visual-storytelling, united-kingdom, illustration, campaign
A55: 2025 | B55: Bronze | C55: Happiness Within Chaos | D55: Stella Artois | E55: Stella Artois | F55: Grey | G55: United Kingdom | H55: B01 - Consumer Goods | I55: https://ascentialcdn.filespin.io/api/v1/conversion/882ea591b6fa40b29a529180b71afa65 | L55: https://www.lovethework.com/work/entries/happiness-within-chaos-740366 | M55: A print campaign by Grey London that places a Stella Artois chalice — and the calm of drinking from it — inside visually hectic scenes, contrasting the stillness of the glass against surrounding disorder. Each execution in the series isolates the moment of a sip as a pocket of quiet amid crowds, noise, and clutter. | N55: beer, alcohol, print, ooh, united-kingdom, campaign-series, illustration, consumer-goods, cpg, fmcg
A56: 2025 | B56: Bronze | C56: Protector of the Chalice | D56: Stella Artois | E56: Stella Artois | F56: Grey | G56: United Kingdom | H56: B01 - Consumer Goods | I56: https://ascentialcdn.filespin.io/api/v1/conversion/a33c9462c05d4330895b056745b6a602 | L56: https://www.lovethework.com/work/entries/protector-of-the-chalice-740439 | M56: A series of posters by Grey London depicting people drinking a Stella Artois pint in crowded, chaotic surroundings — the chalice held steady and upright as the world presses in around it. Each execution frames the glass as a personal sanctuary, the one still point in a scene of noise and compression. | N56: beer, alcohol, print, ooh, poster, united-kingdom, illustration, consumer-goods, cpg, fmcg
A57: 2025 | B57: Bronze | C57: Likes | D57: History Channel | E57: History Channel | F57: Dentsu Creative | G57: Portugal | H57: B05 - Media/Entertainment | I57: https://ascentialcdn.filespin.io/api/v1/conversion/9e6eef6a84b640f9b2da45ad47d321c9 | J57: W29029BIbvY | L57: https://www.lovethework.com/work/entries/likes-763469 | M57: An OOH, print, and TV campaign that places a single social media data point — 1,856 likes on a comment reading "We miss you, Hitler" — alongside present-day statistics: 33,963 racial hate crimes in Germany in 2024 and 162 neo-Nazi marches in six months. The juxtaposition uses live, sourced numbers to argue that the distance between historical atrocity and the present is shorter than it appears. | N57: history-channel, media-entertainment, ooh, print, television, social-data, portugal, germany, public-awareness
A58: 2025 | B58: Bronze | C58: Marches | D58: History Channel | E58: History Channel | F58: Dentsu Creative | G58: Portugal | H58: B05 - Media/Entertainment | I58: https://ascentialcdn.filespin.io/api/v1/conversion/848c6f5fe00a4cc2be171136fcd87b87 | J58: W29029BIbvY | L58: https://www.lovethework.com/work/entries/marches-763480 | M58: A set of outdoor displays placed along Portuguese streets where historical marches — the traditional Lisbon neighborhood processions — take place, pairing real crime-scene locations with History Channel's true-crime programming slate. The displays position the march routes themselves as evidence of the crimes covered in the channel's shows. | N58: history-channel, media-entertainment, ooh, true-crime, portugal, displays, street-level
A59: 2025 | B59: Bronze | C59: Crimes | D59: History Channel | E59: History Channel | F59: Dentsu Creative | G59: Portugal | H59: B05 - Media/Entertainment | I59: https://ascentialcdn.filespin.io/api/v1/conversion/2aba4c2194414c37b9cf328c0dcc193f | J59: W29029BIbvY | L59: https://www.lovethework.com/work/entries/crimes-763490 | M59: A series of out-of-home displays placed at real-world crime scenes — or locations tied to historical crimes — in Portugal, using physical signage to surface the History Channel's crime-related programming at the sites where those events actually occurred. The campaign was created by Dentsu Creative Lisbon. | N59: history-channel, media-entertainment, ooh, displays, portugal, true-crime, site-specific
A60: 2025 | B60: Bronze | C60: Signs from Heaven | D60: Pangu Cloud | E60: Pangu Meteorological Model | F60: Ogilvy | G60: China | H60: C01 - Displays | I60: https://ascentialcdn.filespin.io/api/v1/conversion/09dbff10bf5e4eaeae2d578fe9cc19b0 | J60: CLTN81ECv6E | L60: https://www.lovethework.com/work/entries/signs-from-heaven-740708 | M60: An early-warning system built for remote fishing communities and villages in Madagascar, using Pangu Cloud's AI-powered meteorological model to detect incoming storms and deliver life-saving weather alerts before they strike. Because thousands of fishermen and villagers die each year from storms they had no advance notice of, the alerts were distributed through local channels accessible to communities with no reliable digital infrastructure. | N60: meteorological-model, ai, technology, public-safety, ooh, madagascar, china, early-warning, weather
A61: 2025 | B61: Bronze | C61: Smile 20 | D61: Goody's Pain Powder | E61: Goody's Pain Powder | F61: FCB Chicago | G61: United States | H61: C02 - Interactive/Dynamic Digital Screens | I61: https://ascentialcdn.filespin.io/api/v1/conversion/102f0d648c284c6e98ed2de341d6a49d | J61: vimeo:1081666376 | L61: https://www.lovethework.com/work/entries/smile-20-740676 | M61: An AI-powered digital screen placed at Mile 20 of the Knoxville Marathon — the point where runners hit "the wall" — that detected each runner's face and overlaid a smile filter in real time, prompting an involuntary physical smile during one of the race's most painful stretches. The placement responds to a specific constraint: runners are medically advised not to take NSAIDs like Goody's Pain Powder mid-race, so the brand offered an alternative form of relief at the moment it couldn't offer its actual product. | N61: pain-relief, ooh, dynamic-digital-screens, ai, technology, face-detection, experiential, running, united-states, sports-marketing
A62: 2025 | B62: Bronze | C62: Carrefoursa - Ghost Town | D62: CarrefourSA | E62: Retail | F62: TBWA\Istanbul | G62: Turkey | H62: C03 - Special Build | I62: https://ascentialcdn.filespin.io/api/v1/conversion/7aeda253bc4a4f4e8c659c64a4721596 | J62: 0tKFbogECr4 | L62: https://www.lovethework.com/work/entries/carrefoursa-ghost-town-740781 | M62: To expose the threat of abandoned 'ghost nets,' CarrefourSA collected them from the sea and draped them across Ocaklar, turning the Turkish fishing village into a haunting vision of the ghost town it could become. The installation made the invisible crisis impossible to ignore, while a training program and digital platform helped educate thousands of fishermen on protecting sustainable seafood and coastal livelihoods. | N62: retail, supermarket, grocery, ooh, sustainability, environment, social-good, turkey, partnership, installation
A63: 2025 | B63: Bronze | C63: Chai Bansuri - the Tea Flute | D63: Unilever | E63: Brooke Bond Taj Mahal Tea | F63: Ogilvy | G63: India | H63: C04 - Live Advertising and Events | I63: https://ascentialcdn.filespin.io/api/v1/conversion/b79b43804eae486ea54374794321d26f | J63: rUaCL7lrVa4 | L63: https://www.lovethework.com/work/entries/chai-bansuri-the-tea-flute-740791 | M63: A 500-litre kettle engineered to play the flute — steam from brewing Taj Mahal Tea was channeled through a bansuri while mechanized fingers worked the finger holes to produce live music. The installation draws on Taj Mahal Tea's long association with classical Indian music, using the act of brewing itself as the instrument. | N63: tea, live-event, installation, india, classical-music, ogilvy, experiential, branded-entertainment
A64: 2025 | B64: Bronze | C64: Worst Children's Library | D64: Samsung | E64: Samsung | F64: DDB New Zealand | G64: New Zealand | H64: C05 - Interactive Experiences | I64: https://ascentialcdn.filespin.io/api/v1/conversion/0e92a3c97dfe4f05b663ae448b0f27d4 | J64: vimeo:1105993323 | L64: https://www.lovethework.com/work/entries/worst-childrens-library-740810 | M64: A real school library at Auckland Normal Intermediate stripped of its usual books and replaced with 1,160 hand-bound titles — each one a piece of harmful digital content that children have actually encountered online. Topics ranged from toxic masculinity to self-harm to animal cruelty, catalogued in a custom 'Dewey Decimal System of Harm,' with parents invited to walk the shelves. | N64: social-good, online-safety, education, exhibition, kids, new-zealand, partnership, behaviour-change
A65: 2025 | B65: Bronze | C65: Mayo Exchange | D65: Hellmann's | E65: Hellmann's Mayonnaise | F65: Edelman | G65: United Kingdom | H65: C05 - Interactive Experiences | I65: https://ascentialcdn.filespin.io/api/v1/conversion/2f963ba6e5b3402fb58a7907daa78953 | J65: 4NpEnDNRwc0 | L65: https://www.lovethework.com/work/entries/mayo-exchange-740956 | M65: A pop-up condiment currency exchange run across 62 locations in the United Kingdom, where Hellmann's invited ketchup owners to physically hand in their bottles in exchange for Hellmann's Mayonnaise. The exchange framing — staffed counters, branded currency signage — positioned mayo as the superior condiment by treating ketchup as a currency worth trading away. | N65: mayonnaise, experiential, ooh, pop-up, condiment, united-kingdom, retail-activation, interactive-experience
A66: 2025 | B66: Bronze | C66: Touchboards Discount | D66: Itaú Unibanco | E66: Bank | F66: Africa Creative DDB | G66: Brazil | H66: C05 - Interactive Experiences | I66: https://ascentialcdn.filespin.io/api/v1/conversion/e14b84bfe13a475898db5ad4b54d8a97 | J66: vimeo:1136599182 | L66: https://www.lovethework.com/work/entries/touchboards-discount-740763 | M66: For Black Friday, Itaú Shop turned missed shots during a major Brazilian championship match into instant marketplace discounts. Using touch-enabled boards around the field, every ball that hit the ads unlocked deals on fan-favorite items like TVs, jerseys and soccer balls, transforming bad plays into rewarding moments for fans in the stadium and at home. | N66: banking, financial-services, finance, fintech, sport, football, soccer, ooh, interactive, brazil, retail-promo, real-time
A67: 2025 | B67: Bronze | C67: Followers Store | D67: New Balance | E67: New Balance | F67: LePub | G67: Brazil | H67: C06 - Transit | I67: https://ascentialcdn.filespin.io/api/v1/conversion/3f6078e96a9a4e17acada7c2ad04d652 | J67: uYskstOPF4U | L67: https://www.lovethework.com/work/entries/followers-store-741098 | M67: A geo-fenced sales window for an exclusive São Paulo FC jersey, unlockable on the New Balance app only for fans physically near the team bus as it traveled to Morumbi Stadium ahead of a Brazilian Championship match. Outside that travel window, the jersey was unbuyable; inside it, fans had minutes to pre-order before the bus passed. | N67: ecommerce, retail, online-shopping, geolocation, football, soccer, sport, brazil, app, partnership
A68: 2025 | B68: Bronze | C68: Lucky Yatra | D68: Indian Railways | E68: Railway Service | F68: FCB India | G68: India | H68: C06 - Transit | I68: https://ascentialcdn.filespin.io/api/v1/conversion/cf238077a73e4204aff7e28913d98b1d | J68: IYJlZRbvMEw | L68: https://www.lovethework.com/work/entries/lucky-yatra-741094 | M68: A loyalty program built into the ticketing system of Indian Railways: every valid ticket carries a unique number that's auto-entered into daily and weekly cash prize draws. Designed to turn ticketless travel — an entrenched habit on one of the world's largest rail networks — into a paid behavior worth doing. | N68: railway-service, loyalty-program, public-service, mobile-app, india, gamification, ticketing
... A82: 2026 | B82: Silver | C82: Bahamas | D82: British Airways | E82: British Airways | F82: Uncommon Creative Studio | G82: United Kingdom | H82: A04 - Travel, Leisure, Retail, Restaurants & Fast-Food Chains | I82: https://ascentialcdn.filespin.io/api/v1/conversion/0718b5a0a0e847d29275452cbc3a3f24 | J82: 5nPuWpFyaN0 | L82: https://www.lovethework.com/work/entries/bahamas-773804 | M82: Part of British Airways' destination poster series by Uncommon, using spare typographic lines and the airline's window motif to capture the particular feeling of flying to the Bahamas. | N82: british airways, airline, travel, tourism, aviation, destination, posters, billboard, typography, copywriting, uncommon, united kingdom
A83: 2026 | B83: Silver | C83: Blizzard As Usual 1 | D83: Tim Hortons | E83: Tim Hortons Coffee | F83: GUT | G83: Canada | H83: A04 - Travel, Leisure, Retail, Restaurants & Fast-Food Chains | I83: https://ascentialcdn.filespin.io/api/v1/conversion/f20b6f66d22c4bedbf73b3c5f7eb8d34 | L83: https://www.lovethework.com/work/entries/blizzard-as-usual-1-781812 | M83: An execution in Tim Hortons' "Blizzard As Usual" outdoor series, positioning the coffee chain as the dependable Canadian fixture that stays open and keeps people going through the worst winter weather. | N83: tim hortons, coffee, qsr, fast-food, restaurant, food, fast food, winter, weather, outdoor, canada, gut
A84: 2026 | B84: Silver | C84: Blizzard As Usual 2 | D84: Tim Hortons | E84: Tim Hortons Coffee | F84: GUT | G84: Canada | H84: A04 - Travel, Leisure, Retail, Restaurants & Fast-Food Chains | I84: https://ascentialcdn.filespin.io/api/v1/conversion/2ef70d835b8742c3a3ddd0baafd338f9 | L84: https://www.lovethework.com/work/entries/blizzard-as-usual-2-781813 | M84: An execution in Tim Hortons' "Blizzard As Usual" outdoor series, positioning the coffee chain as the dependable Canadian fixture that stays open and keeps people going through the worst winter weather. | N84: tim hortons, coffee, qsr, fast-food, restaurant, food, fast food, winter, weather, outdoor, canada, gut
A85: 2026 | B85: Silver | C85: Blizzard As Usual 3 | D85: Tim Hortons | E85: Tim Hortons Coffee | F85: GUT | G85: Canada | H85: A04 - Travel, Leisure, Retail, Restaurants & Fast-Food Chains | I85: https://ascentialcdn.filespin.io/api/v1/conversion/9a3f8f3c2518439587bff77df6f2e6c1 | L85: https://www.lovethework.com/work/entries/blizzard-as-usual-3-781814 | M85: An execution in Tim Hortons' "Blizzard As Usual" outdoor series, positioning the coffee chain as the dependable Canadian fixture that stays open and keeps people going through the worst winter weather. | N85: tim hortons, coffee, qsr, fast-food, restaurant, food, fast food, winter, weather, outdoor, canada, gut
A86: 2026 | B86: Bronze | C86: Listening | D86: KitKat | E86: KitKat | F86: VML | G86: United Kingdom | H86: B01 - Consumer Goods | I86: https://ascentialcdn.filespin.io/api/v1/conversion/0ae3f31aa29747fead886298ba298f4a | J86: Dr7pQhIHtjw | L86: https://www.lovethework.com/work/entries/listening-773895 | M86: An execution in KitKat's "Have a Break" poster series, turning the bar's four-finger form into a quiet moment of listening. | N86: kitkat, chocolate, confectionery, candy, snack, packaged-goods, food, cpg, fmcg, have a break, posters, billboard, art direction, vml, united kingdom
A87: 2026 | B87: Bronze | C87: Strumming | D87: KitKat | E87: KitKat | F87: VML | G87: United Kingdom | H87: B01 - Consumer Goods | I87: https://ascentialcdn.filespin.io/api/v1/conversion/d25487359a99417dae16fef5d80c7ed3 | J87: Dr7pQhIHtjw | L87: https://www.lovethework.com/work/entries/strumming-773904 | M87: An execution in KitKat's "Have a Break" poster series, turning the bar's four-finger form into a moment of strumming a guitar. | N87: kitkat, chocolate, confectionery, candy, snack, packaged-goods, food, cpg, fmcg, have a break, posters, billboard, art direction, vml, united kingdom
A88: 2026 | B88: Bronze | C88: Reading | D88: KitKat | E88: KitKat | F88: VML | G88: United Kingdom | H88: B01 - Consumer Goods | I88: https://ascentialcdn.filespin.io/api/v1/conversion/7781b13d20634ffbbd3f30fbd692d9cb | J88: Dr7pQhIHtjw | L88: https://www.lovethework.com/work/entries/reading-773910 | M88: An execution in KitKat's "Have a Break" poster series, turning the bar's four-finger form into a moment of reading. | N88: kitkat, chocolate, confectionery, candy, snack, packaged-goods, food, cpg, fmcg, have a break, posters, billboard, art direction, vml, united kingdom
A89: 2026 | B89: Bronze | C89: Daydreaming | D89: KitKat | E89: KitKat | F89: VML | G89: United Kingdom | H89: B01 - Consumer Goods | I89: https://ascentialcdn.filespin.io/api/v1/conversion/09bc532278ac434382b29be611fcfbcd | J89: Dr7pQhIHtjw | L89: https://www.lovethework.com/work/entries/daydreaming-773916 | M89: An execution in KitKat's "Have a Break" poster series, turning the bar's four-finger form into a moment of daydreaming. | N89: kitkat, chocolate, confectionery, candy, snack, packaged-goods, food, cpg, fmcg, have a break, posters, billboard, art direction, vml, united kingdom
A90: 2026 | B90: Bronze | C90: New York | D90: British Airways | E90: British Airways | F90: Uncommon Creative Studio | G90: United Kingdom | H90: B04 - Travel, Leisure, Retail, Restaurants & Fast-Food Chains | I90: https://ascentialcdn.filespin.io/api/v1/conversion/e046424d59624f868cc948c68204b629 | J90: 5nPuWpFyaN0 | L90: https://www.lovethework.com/work/entries/new-york-773929 | M90: Part of British Airways' destination poster series by Uncommon, using spare typographic lines and the airline's window motif to capture the particular feeling of flying to New York. | N90: british airways, airline, travel, tourism, aviation, destination, posters, billboard, typography, copywriting, uncommon, united kingdom
A91: 2026 | B91: Bronze | C91: The Pyrenees | D91: British Airways | E91: British Airways | F91: Uncommon Creative Studio | G91: United Kingdom | H91: B04 - Travel, Leisure, Retail, Restaurants & Fast-Food Chains | I91: https://ascentialcdn.filespin.io/api/v1/conversion/f6d5816b7ded4af5977fe1410d33e3a4 | J91: 5nPuWpFyaN0 | L91: https://www.lovethework.com/work/entries/the-pyrenees-773780 | M91: Part of British Airways' destination poster series by Uncommon, using spare typographic lines and the airline's window motif to capture the particular feeling of flying to the Pyrenees. | N91: british airways, airline, travel, tourism, aviation, destination, posters, billboard, typography, copywriting, uncommon, united kingdom
A92: 2026 | B92: Bronze | C92: Abuja | D92: British Airways | E92: British Airways | F92: Uncommon Creative Studio | G92: United Kingdom | H92: B04 - Travel, Leisure, Retail, Restaurants & Fast-Food Chains | I92: https://ascentialcdn.filespin.io/api/v1/conversion/8b33ac1c62494a3db5d7edb0ace06d76 | J92: 5nPuWpFyaN0 | L92: https://www.lovethework.com/work/entries/abuja-780691 | M92: Part of British Airways' destination poster series by Uncommon, using spare typographic lines and the airline's window motif to capture the particular feeling of flying to Abuja. | N92: british airways, airline, travel, tourism, aviation, destination, posters, billboard, typography, copywriting, uncommon, united kingdom
A93: 2026 | B93: Gold | C93: Gig | D93: McDonald's | E93: McDonald's | F93: Leo | G93: United Kingdom | H93: B04 - Travel, Leisure, Retail, Restaurants & Fast-Food Chains | I93: https://ascentialcdn.filespin.io/api/v1/conversion/2871e116e8e84821ad316ed7313291fa | J93: Xzm_7YZ1sy8 | L93: https://www.lovethework.com/work/entries/gig-781129 | M93: An execution in McDonald's UK poster series capturing the universally relatable urge to grab a McDonald's after a big night out — here, after a gig. | N93: mcdonalds, qsr, fast-food, restaurant, food, fast food, burgers, posters, billboard, humour, insight, leo, united kingdom
A94: 2026 | B94: Gold | C94: Wedding | D94: McDonald's | E94: McDonald's | F94: Leo | G94: United Kingdom | H94: B04 - Travel, Leisure, Retail, Restaurants & Fast-Food Chains | I94: https://ascentialcdn.filespin.io/api/v1/conversion/043c00c89c1040249f0fa8d738cb065c | J94: Xzm_7YZ1sy8 | L94: https://www.lovethework.com/work/entries/wedding-781130 | M94: An execution in McDonald's UK poster series capturing the universally relatable urge to grab a McDonald's after a big occasion — here, after a wedding. | N94: mcdonalds, qsr, fast-food, restaurant, food, fast food, burgers, posters, billboard, humour, insight, leo, united kingdom
A95: 2026 | B95: Gold | C95: Bowling | D95: McDonald's | E95: McDonald's | F95: Leo | G95: United Kingdom | H95: B04 - Travel, Leisure, Retail, Restaurants & Fast-Food Chains | I95: https://ascentialcdn.filespin.io/api/v1/conversion/d15dd5731b41491ea690b4d3ab4a2403 | J95: Xzm_7YZ1sy8 | L95: https://www.lovethework.com/work/entries/bowling-781131 | M95: An execution in McDonald's UK poster series capturing the universally relatable urge to grab a McDonald's after a night out — here, after bowling. | N95: mcdonalds, qsr, fast-food, restaurant, food, fast food, burgers, posters, billboard, humour, insight, leo, united kingdom
A96: 2026 | B96: Bronze | C96: Lime Guides | D96: Corona | E96: Corona | F96: Grey | G96: United States | H96: C01 - Displays | I96: https://ascentialcdn.filespin.io/api/v1/conversion/69614d6489d54169b37f9d4f29af9ce2 | J96: vimeo:1188248881 | L96: https://www.lovethework.com/work/entries/lime-guides-774003 | M96: A Corona outdoor display execution built around the brand's signature lime, using out-of-home placements to reinforce the ritual of a lime-topped Corona. | N96: corona, beer, alcohol, drinks, lime, displays, outdoor, ritual, grey, united states
A97: 2026 | B97: Silver | C97: Discount Chants | D97: Mercado Libre | E97: Mercado Libre | F97: GUT | G97: Argentina | H97: C02 - Interactive/Dynamic Digital Screens | I97: https://ascentialcdn.filespin.io/api/v1/conversion/6f517e3917a04fb19738c49af7c9f4c2 | J97: k2JGGB1tPEA | L97: https://www.lovethework.com/work/entries/discount-chants-781818 | M97: Mercado Libre turned the chants of football crowds into a live discount mechanic, with dynamic digital screens responding to fans' chanting to unlock deals during matches. | N97: mercado libre, ecommerce, retail, online-shopping, marketplace, football, soccer, sport, sports, digital screens, dooh, interactive, gut, argentina
... A129: 2026 | B129: Silver | C129: It Starts Outside | D129: Dirt Is Good | Persil | E129: Persil | F129: Frank | G129: United Kingdom | H129: E09 - Cultural Engagement | I129: https://ascentialcdn.filespin.io/api/v1/conversion/69dc3faab31949dc924a19249afbb55d | J129: 9fkJ8uvZsmM | L129: https://www.lovethework.com/work/entries/it-starts-outside-781842 | M129: Persil's Dirt Is Good partnered with Arsenal Women to encourage young girls to get outside and play, using out-of-home to champion outdoor play despite the mess. | N129: persil, dirt is good, laundry, detergent, fmcg, arsenal, football, soccer, sport, girls, outdoor play, cultural engagement, frank, united kingdom

Sheet Print & Publishing
A1: Year | B1: Tier | C1: Campaign | D1: Brand | E1: Product/Service | F1: Agency | G1: Country | H1: Subcategory | I1: Image URL | J1: YouTube ID | K1: Campaign Group | L1: Entry URL | M1: Description | N1: Keywords
A2: 2025 | B2: Grand Prix | C2: Price Packs | D2: Penny | E2: Food/non-Food | F2: Serviceplan Germany | G2: Germany | H2: Market Disruption | I2: https://ascentialcdn.filespin.io/api/v1/conversion/67b6df2a0fe64deeb274c91d50040c54 | J2: wXx6z3mDnVc | L2: https://www.lovethework.com/work/entries/price-packs-740125 | M2: A packaging redesign for five Penny staples — oatmeal, toast, salt, crisps, mayonnaise — that swaps standard product graphics for the locked-in low price rendered enormous on the front of the pack. The shelf becomes its own price-stability ad, with the same visual extended to outdoor across all 2,100 stores. | N2: packaging, retail, ooh, supermarket, grocery, design, price, germany, market-disruption
A3: 2025 | B3: Gold | C3: Ink of Democracy | D3: Times of India Group | E3: Election Appeal | F3: Havas | G3: India | H3: Corporate Purpose & Social Responsibility | I3: digital-presentation-images/print-and-publishing-times-of-india-group-ink-of-democracy.webp | J3: Y04IsSy9fCI | L3: https://www.lovethework.com/work/entries/ink-of-democracy-740050 | M3: Pages of The Times of India and The Economic Times — India's highest-circulation English-language newspapers — were printed in purple ink instead of black during the 2024 Indian General Elections, mirroring the electoral ink applied to every voter's finger as proof of voting. For every 132 registered voters who had not cast a ballot in the previous election, one purple-ink page was produced, resulting in 2.28 million prints, each functioning as a direct appeal to a specific share of the absent electorate. The campaign was created by Havas Creative India in partnership with The Times of India Group, drawing on the fact that 7,500 litres of electoral ink went unused in 2019 due to low turnout. | N3: newspaper, print, public-service, voter-turnout, india, corporate-purpose, packaging-craft, elections, media-brand
A4: 2025 | B4: Gold | C4: Holi | D4: Dove | E4: Dove Soap | F4: Ogilvy | G4: United States | H4: Consumer Goods | I4: https://ascentialcdn.filespin.io/api/v1/conversion/8487f504004046b3b4f39c80f9542955 | J4: vimeo:1174772200 | L4: https://www.lovethework.com/work/entries/holi-739718 | M4: A print campaign for Dove Beauty Bar built around the "morning after" specific celebrations — the Holi edition shows the bar resting among the vivid, smeared pigment residue left on skin after the festival of colors. Part of Ogilvy's broader "Get Unready" series that counters social media "Get Ready With Me" content by centering the cleansing and removal ritual instead of the application one. The campaign also includes Mardi Gras and Carnaval executions, each using the distinctive aftermath of that celebration as the visual context for the soap's role. | N4: soap, print, beauty, consumer-goods, cpg, fmcg, holiday-campaign, united-states, get-unready, skin-care
A5: 2025 | B5: Gold | C5: St. Patrick's Day | D5: Dove | E5: Dove Soap | F5: Ogilvy | G5: United States | H5: Consumer Goods | I5: https://ascentialcdn.filespin.io/api/v1/conversion/372489df63044fcf8bfb5e5cca943bfe | J5: vimeo:1174772200 | L5: https://www.lovethework.com/work/entries/st-patricks-day-739704 | M5: A cultural extension of Dove's "Get Unready" platform, timed to St. Patrick's Day, inviting people to remove the makeup, glitter, and face paint worn for the holiday using Dove soap. The activation follows the same mechanic as earlier "Get Unready" moments — New Year's Eve, Holi, Carnaval — where high-pigment, high-product celebrations become a natural prompt to show Dove's cleansing in use. | N5: soap, consumer-goods, cpg, fmcg, social, united-states, skincare, personal-care, beauty, seasonal, ogilvy, get-unready
A6: 2025 | B6: Gold | C6: Happiness Within Chaos | D6: Stella Artois | E6: Stella Artois | F6: Grey | G6: United Kingdom | H6: Consumer Goods | I6: https://ascentialcdn.filespin.io/api/v1/conversion/882ea591b6fa40b29a529180b71afa65 | L6: https://www.lovethework.com/work/entries/happiness-within-chaos-739654 | M6: A print campaign by Grey London that places a Stella Artois chalice — and the calm of drinking from it — inside visually hectic scenes, contrasting the stillness of the glass against surrounding disorder. Each execution in the series isolates the moment of a sip as a pocket of quiet amid crowds, noise, and clutter. | N6: beer, alcohol, print, ooh, united-kingdom, campaign-series, illustration, consumer-goods, cpg, fmcg
A7: 2025 | B7: Gold | C7: New Year's | D7: Dove | E7: Dove Soap | F7: Ogilvy | G7: United States | H7: Consumer Goods | I7: https://ascentialcdn.filespin.io/api/v1/conversion/38e5adf42b364346bf882ff41160aabc | J7: vimeo:1174772200 | L7: https://www.lovethework.com/work/entries/new-years-739696 | M7: A multi-phased campaign for Dove's Beauty Bar that launched immediately after midnight on New Year's Eve, positioning the bar soap as a self-care ritual for winding down after life's big moments rather than getting ready for them. Developed by Ogilvy, the "Get Unready" work debuted across the United States with creative centered on the quiet, personal act of washing off the night — leaning into the bar's 65-plus-year presence in the bathroom as a comfort object rather than a beauty step. | N7: soap, consumer-goods, cpg, fmcg, ooh, social, united-states, self-care, new-years, seasonal, multi-platform
A8: 2025 | B8: Gold | C8: Mardi Gras | D8: Dove | E8: Dove Soap | F8: Ogilvy | G8: United States | H8: Consumer Goods | I8: https://ascentialcdn.filespin.io/api/v1/conversion/616e9779606e4684a96c828d12a9b7a0 | J8: vimeo:1174772200 | L8: https://www.lovethework.com/work/entries/mardi-gras-739712 | M8: A print campaign for Dove Soap that uses the visual language of Mardi Gras, Holi, and Carnaval — three festivals defined by the ritualized throwing or covering of color — as a backdrop for the brand's skin-care messaging. Each execution centers on a different celebration, pairing its signature palette and iconography with Dove's positioning around real skin. | N8: dove-soap, print, consumer-goods, cpg, fmcg, united-states, festival, skin-care, campaign, ogilvy
A9: 2025 | B9: Gold | C9: Carnaval | D9: Dove | E9: Dove Soap | F9: Ogilvy | G9: United States | H9: Consumer Goods | I9: https://ascentialcdn.filespin.io/api/v1/conversion/3bc75956d7df4f839632c72343fb5cb5 | J9: vimeo:1174772200 | L9: https://www.lovethework.com/work/entries/carnaval-739726 | M9: A print campaign for Dove Beauty Bar built around three global skin-cleansing festivals — Mardi Gras, Holi, and Carnaval — each execution showing the bar removing the vivid pigments, body paint, and glitter associated with that celebration. The work positions Dove's facial cleansing benefits against the specific, intense residue left by each festival's traditions rather than generic everyday makeup. | N9: soap, print, consumer-goods, cpg, fmcg, festival, beauty, united-states, skincare, personal-care, ogilvy
A10: 2025 | B10: Gold | C10: The Sip of Sanctuary | D10: Stella Artois | E10: Stella Artois | F10: Grey | G10: United Kingdom | H10: Consumer Goods | I10: https://ascentialcdn.filespin.io/api/v1/conversion/bc046e548975443980453424bc30515a | L10: https://www.lovethework.com/work/entries/the-sip-of-sanctuary-739632 | M10: A print campaign for Stella Artois, created by Grey London, built around three posters — "The Sip of Sanctuary," "Protector of the Chalice," and "Happiness Within Chaos" — each depicting the Stella Artois chalice as a refuge of calm amid surrounding disorder or threat. The imagery uses the glass itself as the visual anchor, framing a quiet moment of stillness as something worth protecting. | N10: beer, alcohol, print, poster, visual-storytelling, united-kingdom, illustration, campaign
A11: 2025 | B11: Gold | C11: Protector of the Chalice | D11: Stella Artois | E11: Stella Artois | F11: Grey | G11: United Kingdom | H11: Consumer Goods | I11: https://ascentialcdn.filespin.io/api/v1/conversion/a33c9462c05d4330895b056745b6a602 | L11: https://www.lovethework.com/work/entries/protector-of-the-chalice-739644 | M11: A series of posters by Grey London depicting people drinking a Stella Artois pint in crowded, chaotic surroundings — the chalice held steady and upright as the world presses in around it. Each execution frames the glass as a personal sanctuary, the one still point in a scene of noise and compression. | N11: beer, alcohol, print, ooh, poster, united-kingdom, illustration, consumer-goods, cpg, fmcg
A12: 2025 | B12: Silver | C12: Roses | D12: Oreo | E12: Oreo | F12: LePub Bogota | G12: Colombia | H12: Consumer Goods | I12: https://ascentialcdn.filespin.io/api/v1/conversion/7e2d8fe4c7af49f0b2003ab42f27074e | J12: p_3AcLnU1A8 | L12: https://www.lovethework.com/work/entries/roses-764508 | M12: A print visual from a five-part OREO campaign — Eggs, Roses, Bananas, Duck, and Toilet Paper — in which each image depicts an everyday object or food that has visibly been twisted apart in the same way as an OREO cookie. The series uses the gesture as a universal sign of a considered choice, running under the line "A Decision Was Made Here." | N12: snack, food, packaged-goods, cpg, fmcg, print, ooh, photography, colombia, visual-series, consumer-goods, humor
A13: 2025 | B13: Silver | C13: Toilet Paper | D13: Oreo | E13: Oreo | F13: LePub Bogota | G13: Colombia | H13: Consumer Goods | I13: https://ascentialcdn.filespin.io/api/v1/conversion/96ea34877f1644f4a22d867dfa8e2f5d | J13: p_3AcLnU1A8 | L13: https://www.lovethework.com/work/entries/toilet-paper-764491 | M13: A print campaign that places Oreo cookies inside mundane, everyday objects — toilet paper rolls, egg cartons, rose bouquets, banana bunches, and rubber ducks — as if the cookie naturally belongs there. Each execution uses a clean, precise art direction to let the visual joke land without copy, relying on the familiarity of the Oreo shape to create instant recognition in an unexpected context. | N13: oreo, snack, food, packaged-goods, cpg, fmcg, print, colombia, netherlands, humor, art-direction, consumer-goods
A14: 2025 | B14: Silver | C14: Not Every Smile Starts as a Smile | D14: Colgate | E14: Colgate | F14: VML | G14: France | H14: Social Behaviour | I14: https://ascentialcdn.filespin.io/api/v1/conversion/7795062110544927acc4f73eedfb3d7d | J14: vimeo:1099341785 | L14: https://www.lovethework.com/work/entries/not-every-smile-starts-as-a-smile-740106 | M14: A print campaign for Colgate, created by VML Paris with media handled by Wavemaker, built around the visual observation that many children's genuine smiles begin as something else — a grimace, a pout, a scrunched face mid-brush. The prints capture those in-between expressions to reframe the everyday friction of kids' tooth-brushing as the precursor to the smile itself. | N14: toothpaste, print, kids, oral-care, social-behaviour, france, united-kingdom, photography
A15: 2025 | B15: Silver | C15: Notes on Notes | D15: Capital Bank | E15: Capital Bank Loans | F15: Adpro& | G15: Jordan | H15: Social Behaviour | I15: https://ascentialcdn.filespin.io/api/v1/conversion/26f992b0fc0e4479b962853921264524 | J15: vimeo:1093833076 | L15: https://www.lovethework.com/work/entries/notes-on-notes-739979 | M15: Capital Bank tapped into the Jordanian tradition of writing wishes on money notes, reframing those hopes as goals people could act on with competitive loan rates. The campaign encouraged Jordanians to stop waiting for their dreams to circulate and start making them happen through housing, personal and car loans, driving major lifts in loan interest and traffic. | N15: banking, financial-services, finance, loans, jordan, cultural-engagement, print, integrated
A16: 2025 | B16: Silver | C16: Public Transport | D16: KitKat | E16: Kitkat | F16: VML | G16: Czech Republic | H16: Consumer Goods | I16: https://ascentialcdn.filespin.io/api/v1/conversion/5faffc268ac047f7a20b5bf0e2fb5e1a | J16: ByGNQ3wEbEY | L16: https://www.lovethework.com/work/entries/public-transport-760550 | M16: An outdoor campaign across Czech Republic crowd, public transport, and street placements that depicted commuters and passersby in everyday phone-scrolling situations — but with KitKat bars swapped in place of their smartphones. The images required no explanation: the brand's longstanding "take a break" idea made literal by replacing the object people most compulsively reach for. | N16: snack, food, packaged-goods, cpg, fmcg, ooh, public-transport, street, czech-republic, print, photography, brand-awareness
A17: 2025 | B17: Silver | C17: Street | D17: KitKat | E17: Kitkat | F17: VML | G17: Czech Republic | H17: Consumer Goods | I17: https://ascentialcdn.filespin.io/api/v1/conversion/1d6b4cb3e726479c8a6b03da24a5d79e | J17: ByGNQ3wEbEY | L17: https://www.lovethework.com/work/entries/street-760556 | M17: Outdoor installations across Czech Republic streets and public transport placements that replaced the expected KitKat branding with images of crowds of people — all looking down at their phones. The work revived the "Have a break, have a KitKat" line without stating it, letting the behavior of the crowd make the case for putting the phone down. | N17: snack, food, packaged-goods, cpg, fmcg, ooh, public-transport, street, czech-republic, consumer-goods, phone-behavior, outdoor-installation
A18: 2025 | B18: Silver | C18: Crowd | D18: KitKat | E18: Kitkat | F18: VML | G18: Czech Republic | H18: Consumer Goods | I18: https://ascentialcdn.filespin.io/api/v1/conversion/f6a6e5cb949d4b8fa071221329aa94bf | J18: ByGNQ3wEbEY | L18: https://www.lovethework.com/work/entries/crowd-760545 | M18: A series of out-of-home placements across Czech Republic public transport and streets that use existing crowds of commuters and pedestrians as the visual content of the ad — positioning densely packed people as the reason to take a break. Each execution frames the surrounding crowd through the KitKat creative, making the real-world environment the message. | N18: chocolate, ooh, public-transport, street, czech-republic, ambient, experiential, consumer-goods, cpg, fmcg
A19: 2025 | B19: Silver | C19: Game Day | D19: Stella Artois | E19: Stella Artois | F19: Ogilvy | G19: United States | H19: Consumer Goods | I19: https://ascentialcdn.filespin.io/api/v1/conversion/7bfaee649e4b417698823553cddf194e | J19: HLbAbQdJTtQ | L19: https://www.lovethework.com/work/entries/game-day-739606 | M19: Stella Artois turned the all-too-real party fear of someone stealing your premium beer into a playful print campaign. Hiders Keepers celebrates the classic move of hiding your Stella at house parties, sports gatherings and birthdays so no one else claims it first. | N19: beer, alcohol, print, humor, packaging, social, global
A20: 2025 | B20: Silver | C20: Birthday Party | D20: Stella Artois | E20: Stella Artois | F20: Ogilvy | G20: United States | H20: Consumer Goods | I20: https://ascentialcdn.filespin.io/api/v1/conversion/7bfaee649e4b417698823553cddf194e | J20: kYb25YZDQ-E | L20: https://www.lovethework.com/work/entries/birthday-party-739588 | M20: Stella Artois turned the all-too-real party fear of someone stealing your premium beer into a playful print campaign. Hiders Keepers celebrates the classic move of hiding your Stella at house parties, sports gatherings and birthdays so no one else claims it first. | N20: beer, alcohol, print, humor, packaging, social, global
A21: 2025 | B21: Silver | C21: Dinner | D21: Stella Artois | E21: Stella Artois | F21: Ogilvy | G21: United States | H21: Consumer Goods | I21: https://ascentialcdn.filespin.io/api/v1/conversion/7bfaee649e4b417698823553cddf194e | J21: bKyHQlIq-dQ | L21: https://www.lovethework.com/work/entries/dinner-739600 | M21: Stella Artois turned the all-too-real party fear of someone stealing your premium beer into a playful print campaign. Hiders Keepers celebrates the classic move of hiding your Stella at house parties, sports gatherings and birthdays so no one else claims it first. | N21: beer, alcohol, print, humor, packaging, social, global
A22: 2025 | B22: Silver | C22: Bananas | D22: Oreo | E22: Oreo | F22: LePub Bogota | G22: Colombia | H22: Consumer Goods | I22: https://ascentialcdn.filespin.io/api/v1/conversion/2e8876adc7f74c79b691fdfab21733d3 | J22: p_3AcLnU1A8 | L22: https://www.lovethework.com/work/entries/bananas-764516 | M22: A print execution in the OREO 'A Decision Was Made Here' campaign showing a banana with a distinctive bite taken out of it — the shape of the missing piece unmistakably echoing an OREO cookie. Created by LePub Amsterdam and LePub Bogotá, the series uses everyday objects marked by a familiar crescent bite to imply that someone paused mid-snack to twist, lick, or dunk an OREO instead. | N22: oreo, snack, food, packaged-goods, cpg, fmcg, print, consumer-goods, colombia, netherlands, print-and-publishing
A23: 2025 | B23: Silver | C23: Eggs | D23: Oreo | E23: Oreo | F23: LePub Bogota | G23: Colombia | H23: Consumer Goods | I23: https://ascentialcdn.filespin.io/api/v1/conversion/bde69bf2e7be40499498d5c2b091ec54 | J23: p_3AcLnU1A8 | L23: https://www.lovethework.com/work/entries/eggs-764497 | M23: A print ad for Oreo in which the cookie's familiar black-and-white pattern is revealed inside the cross-section of a cracked egg — the cream filling standing in for the yolk. Part of a campaign series (Eggs, Roses, Bananas, Duck) that hides the Oreo design within everyday objects that share its two-tone structure. | N23: oreo, snack, food, packaged-goods, cpg, fmcg, print, colombia, visual-identity, illustration, consumer-goods
... A66: 2026 | B66: Bronze | C66: It Starts Outside | D66: Dirt Is Good | Persil | E66: Persil | F66: Frank | G66: United Kingdom | H66: Cultural Engagement | I66: https://ascentialcdn.filespin.io/api/v1/conversion/ac57f1401301462a935dab09e3fa96d8 | J66: 9fkJ8uvZsmM | L66: https://www.lovethework.com/work/entries/it-starts-outside-781799 | M66: A print and out-of-home execution by Frank for Unilever's Dirt Is Good (Persil), made with Arsenal Women, encouraging girls to get outside and play and embracing the mess of childhood as part of growing up rather than something to keep clean. | N66: persil, dirt is good, laundry, detergent, cleaning, fmcg, cpg, arsenal, football, soccer, sport, girls, outdoor play, gender equality, print, posters, cultural engagement, frank, united kingdom

Sheet Design
A1: Year | B1: Tier | C1: Campaign | D1: Brand | E1: Product/Service | F1: Agency | G1: Country | H1: Subcategory | I1: Image URL | J1: YouTube ID | K1: Campaign Group | L1: Entry URL | M1: Description | N1: Keywords
A2: 2025 | B2: Grand Prix | C2: Caption with Intention | D2: Academy of Motion Picture Arts & Sciences | E2: Closed Captioning | F2: FCB Chicago | G2: United States | H2: B01 - Inclusive Design | I2: https://ascentialcdn.filespin.io/api/v1/conversion/1a22539ff6e94e288d6a3aa1a3a9ace5 | J2: F48khKZhKHM | L2: https://www.lovethework.com/work/entries/caption-with-intention-758922 | M2: A design system for film and television captions that pairs word-by-word sync with expressive typography — type weight, color, and motion communicate volume, tone, and which character is speaking. Built over six years in partnership with the Deaf and Hard of Hearing community, it was adopted by the Academy as the standard for Oscar submissions and earned a technology Oscar. | N2: accessibility, captioning, film, cinema, entertainment, typography, deaf-and-hard-of-hearing, product-design, inclusion, united-states
A3: 2025 | B3: Gold | C3: AirPods Pro 2 Hearing Aid Feature | D3: Apple | E3: AirPods Pro 2 | F3: Apple | G3: United States | H3: A04 - Product Design | I3: https://ascentialcdn.filespin.io/api/v1/conversion/d124f3704bf34fe8a63e19e8325d9220 | J3: vimeo:1093371918 | L3: https://www.lovethework.com/work/entries/airpods-pro-2-hearing-aid-feature-748829 | M3: A software update to AirPods Pro 2 that adds a clinically validated, over-the-counter hearing aid mode — users complete an in-ear audiogram test on their iPhone, and the earbuds adjust their audio output to compensate for measured hearing loss. The feature launched in the United States, Germany, Japan, and New Zealand, where regulatory frameworks permit software-enabled OTC hearing aids, bypassing the traditional audiology clinic model. | N3: headphones, product-design, hearing-health, mobile-app, united-states, germany, japan, new-zealand, accessibility
A4: 2025 | B4: Gold | C4: Nigrum Corpus | D4: Idomed | E4: Nigrum Corpus | F4: Artplan | G4: Brazil | H4: A06 - Books | I4: https://ascentialcdn.filespin.io/api/v1/conversion/83e9fc2a93254c029a34755ff3c96853 | J4: RCK4iiCB2P0 | L4: https://www.lovethework.com/work/entries/nigrum-corpus-764511 | M4: A medical anatomy book created for Instituto de Educação Médica (IDOMED) that replaces the white-body illustrations standard in medical education with Black bodies, pairing anatomical diagrams with floral patterns to celebrate Black beauty. The book addresses the medical racism embedded in curricula that has historically treated white anatomy as the default human reference. | N4: medical-education, book, illustration, typography, brazil, health-equity, racial-inclusion, print
A5: 2025 | B5: Gold | C5: CarrefourSA - Ghost Town | D5: CarrefourSA | E5: Retail | F5: TBWA\Istanbul | G5: Turkey | H5: A08 - Brand Environment & Experience Design | I5: https://ascentialcdn.filespin.io/api/v1/conversion/a8b0865217084e348df3921cebc7c41f | J5: 0tKFbogECr4 | L5: https://www.lovethework.com/work/entries/carrefoursa-ghost-town-748805 | M5: A special-build installation that turned an abandoned town in Turkey into a full-scale Carrefoursa store — shelves, signage, and product displays staged inside empty, derelict buildings. The build used the ghost town's existing structures as aisles and storefronts, drawing a contrast between emptied communities and the retail presence Carrefoursa brings to populated neighborhoods. | N5: retail, special-build, out-of-home, installation, turkey, experiential, ambient
A6: 2025 | B6: Gold | C6: Spreadbeats | D6: Spotify | E6: Spotify | F6: FCB New York | G6: United States | H6: A09 - Design-Driven Effectiveness | I6: https://ascentialcdn.filespin.io/api/v1/conversion/4ebdb10e5b80456a925dc283ac7e501a | J6: vimeo:1000498095 | L6: https://www.lovethework.com/work/entries/spreadbeats-748953 | M6: A music video coded entirely inside the Excel sales decks Spotify sends to media planners — a character bouncing around the cells of a working spreadsheet, scored to a John Summit track, built using only formulas and conditional formatting. The recipient opens the file expecting numbers and the spreadsheet itself starts performing. | N6: b2b, business, sales-enablement, digital-craft, music, entertainment, spreadsheet, united-states, audio-platform, streaming, tv, design
A7: 2025 | B7: Silver | C7: Spreadbeats | D7: Spotify | E7: Spotify | F7: FCB New York | G7: United States | H7: A07 - Digital Design | I7: https://ascentialcdn.filespin.io/api/v1/conversion/1cc1b629542a4d1db92e5b0d90116de7 | J7: vimeo:1000498095 | L7: https://www.lovethework.com/work/entries/spreadbeats-748925 | M7: A music video coded entirely inside the Excel sales decks Spotify sends to media planners — a character bouncing around the cells of a working spreadsheet, scored to a John Summit track, built using only formulas and conditional formatting. The recipient opens the file expecting numbers and the spreadsheet itself starts performing. | N7: b2b, business, sales-enablement, digital-craft, music, entertainment, spreadsheet, united-states, audio-platform, streaming, tv, design
A8: 2025 | B8: Silver | C8: Price Packs | D8: Penny | E8: Food/Non-Food | F8: Serviceplan Germany | G8: Germany | H8: A09 - Design-Driven Effectiveness | I8: https://ascentialcdn.filespin.io/api/v1/conversion/67b6df2a0fe64deeb274c91d50040c54 | J8: cnAXR4lk6R0 | L8: https://www.lovethework.com/work/entries/price-packs-748846 | M8: A packaging redesign for five Penny staples — oatmeal, toast, salt, crisps, mayonnaise — that swaps standard product graphics for the locked-in low price rendered enormous on the front of the pack. The shelf becomes its own price-stability ad, with the same visual extended to outdoor across all 2,100 stores. | N8: packaging, retail, ooh, supermarket, grocery, design, price, germany, market-disruption
A9: 2025 | B9: Silver | C9: The Shakespeare BIC | D9: Bic | E9: BIC Crystal Pen | F9: VML | G9: Brazil | H9: A11 - Special Editions & Bespoke Items | I9: https://ascentialcdn.filespin.io/api/v1/conversion/352257f3d008491e95e0ccbdfe8a4469 | J9: 5ngNVTeyi4g | L9: https://www.lovethework.com/work/entries/the-shakespeare-bic-749146 | M9: A limited-edition BIC Crystal pen produced to mark the fact that Shakespeare's original manuscripts — including Romeo and Juliet — are lost, making the world's most famous plays exist only in later copies. BIC, whose Crystal is one of the most widely used writing instruments ever made, positioned the pen as the physical counterpart to that absence: the kind of object that keeps handwritten words from disappearing. | N9: ballpoint-pen, special-edition, packaging, print, brazil, writing-instrument, craft, cultural-heritage
A10: 2025 | B10: Silver | C10: Sounds of the Land | D10: Billboard Arabia | E10: Billboard Arabia | F10: SRMG Labs | G10: Saudi Arabia | H10: A14 - Promotional Items/Promotional Printed Media | I10: https://ascentialcdn.filespin.io/api/v1/conversion/19a407ae77ab4664baed61135cc5ae9f | J10: gD1XqvQaMR0 | L10: https://www.lovethework.com/work/entries/sounds-of-the-land-758892 | M10: A 10-track album produced by Billboard Arabia and SRMG Labs in which the topography of Arab landscapes — their terrain, geography, and natural features — is translated into sound. Each track is built from acoustic data drawn from a distinct region of the Arab world, turning the physical land itself into the raw material for music. The album was produced in partnership with gamma., the media and technology company founded by Larry Jackson and Ike Youssef, with packaging designed to reflect the initiative's geographic source material. | N10: music-magazine, packaging, music-marketing, promotional-item, saudi-arabia, united-states, album, nature, design
A11: 2025 | B11: Silver | C11: Code My Crown | D11: Dove | E11: Dove | F11: Edelman | G11: United Kingdom | H11: B01 - Inclusive Design | I11: https://ascentialcdn.filespin.io/api/v1/conversion/dc773a5191b947ea85626af886046a69 | J11: stQ442QJ9pg | L11: https://www.lovethework.com/work/entries/code-my-crown-749303 | M11: A guide and training resource built for game developers that shows how to accurately code Black hair styles and textures inside video game character creators — covering curl patterns, locs, braids, and protective styles that are routinely absent or poorly rendered in mainstream titles. Developed by Dove and Edelman London, it addresses the gap between the diversity of Black hair and the limited, often inaccurate options players encounter when building avatars that look like them. | N11: personal-care, gaming, video-games, entertainment, inclusive-design, developer-tool, united-kingdom, black-hair, digital, representation
A12: 2025 | B12: Silver | C12: 1837 Tiffany Blue Conservation | D12: Tiffany & Co. | E12: Tiffany & Co. | F12: L&C | G12: United States | H12: B02 - Sustainability-Focused Design | I12: https://ascentialcdn.filespin.io/api/v1/conversion/a9e8fdb5892d441587b7c4c55eb3d5fb | J12: npGswWNcZC8 | L12: https://www.lovethework.com/work/entries/1837-tiffany-blue-conservation-749213 | M12: A photography and awareness campaign built around the natural occurrence of Tiffany Blue® in ocean waters across Africa, Australia, and the Caribbean — documenting those specific bodies of water as living proof that the brand's signature color exists in nature. Created with L&C New York, the work ties the 1837 founding color to ocean conservation by treating the shade itself as the thing worth protecting. | N12: luxury-jewelry, sustainability, photography, ocean-conservation, united-states, africa, australia, caribbean, brand-identity
A13: 2025 | B13: Silver | C13: Fixables | D13: Philips | E13: Philips Personal Care | F13: LePub | G13: Netherlands | H13: B02 - Sustainability-Focused Design | I13: https://ascentialcdn.filespin.io/api/v1/conversion/9e978f653c5c45cf903985a90708656d | J13: vimeo:1093399093 | L13: https://www.lovethework.com/work/entries/fixables-761443 | M13: A library of free, downloadable 3D-printable replacement parts for Philips personal care products — broken clips, covers, and components that would otherwise send a device to landfill — developed with 3D printer manufacturer Prusa Research and LePub Amsterdam and Milan. The parts are designed to spec so consumers can print exact replacements at home or through a local print service, extending the life of products already in circulation. | N13: personal-care, sustainability, 3d-printing, product-design, netherlands, repair, consumer-electronics, design-for-behaviour-change
... A58: 2026 | B58: Bronze | C58: The Undropped Kit | D58: ASICS | E58: ASICS | F58: GUT Toronto | G58: United Kingdom | H58: B05 - Design for Behavioural Change | I58: https://ascentialcdn.filespin.io/api/v1/conversion/c0eaaf5e1bb347e4a08da10527da46c8 | J58: gyzNtC_3Fnw | L58: https://www.lovethework.com/work/entries/the-undropped-kit-782365 | M58: A reimagined PE kit from ASICS designed to keep teenage girls in sport. Co-created with more than 2,000 UK girls, athlete Tess Howard and inclusive-sportswear experts, the redesigned kit tackles the discomfort and self-consciousness that drive girls to drop out — using design to change behaviour around participation. | N58: asics, sportswear, pe kit, school, sport, design for behavioural change, girls, participation, inclusive design, gender equality, co-creation, design, golin ketchum, united kingdom

Sheet Digital Craft
A1: Year | B1: Tier | C1: Campaign | D1: Brand | E1: Product/Service | F1: Agency | G1: Country | H1: Subcategory | I1: Image URL | J1: YouTube ID | K1: Campaign Group | L1: Entry URL | M1: Description | N1: Keywords
A2: 2025 | B2: Grand Prix | C2: Caption with Intention | D2: Academy of Motion Picture Arts & Sciences | E2: Closed Captioning | F2: FCB Chicago | G2: United States | H2: UX & Journey Design | I2: https://ascentialcdn.filespin.io/api/v1/conversion/3a8020f6426f40968730b5a8c68a0b35 | J2: F48khKZhKHM | L2: https://www.lovethework.com/work/entries/caption-with-intention-754389 | M2: A caption design system for film and television that moves beyond static white text — word-by-word sync pairs with expressive typography, where type weight, color, and motion signal volume, tone, and speaker identity. Developed by FCB Chicago in close partnership with the Chicago Hearing Society, Rakish, and the Academy of Motion Picture Arts and Sciences, which adopted it as a new standard for cinematic accessibility. | N2: closed-captioning, accessibility, typography, film, cinema, entertainment, societal-innovation, united-states, design-system, deaf-hard-of-hearing
A3: 2025 | B3: Gold | C3: Tree Correspondents | D3: Hyundai | E3: Hyundai Ioniq Forest | F3: FCB New York | G3: United States | H3: Data Storytelling | I3: https://ascentialcdn.filespin.io/api/v1/conversion/82542e7381744bb783bb6c60f2929b2c | J3: vimeo:1109390480 | L3: https://www.lovethework.com/work/entries/tree-correspondents-762045 | M3: A data storytelling campaign in which individual trees — a Silver Fir in Czechia, a Juçara Palm in Brazil, a Tulip Tree in the United States — send first-person audio and written dispatches translated from their real environmental sensor data. Built to mark ten years of Hyundai's IONIQ Forest reforestation initiative, the work was developed with FCB New York and turns ecological monitoring data into voiced field reports narrated by the trees themselves. | N3: automotive, cars, transport, data-storytelling, audio, reforestation, environmental, united-states, brazil, czechia, branded-content
A4: 2025 | B4: Gold | C4: Caption with Intention | D4: Academy of Motion Picture Arts & Sciences | E4: Closed Captioning | F4: FCB Chicago | G4: United States | H4: Innovative Use of Technology | I4: https://ascentialcdn.filespin.io/api/v1/conversion/6e437af497a34d6bbc71738a2b9c581b | J4: F48khKZhKHM | L4: https://www.lovethework.com/work/entries/caption-with-intention-754831 | M4: A caption design system for film and television that moves beyond static white text — word-by-word sync pairs with expressive typography, where type weight, color, and motion signal volume, tone, and speaker identity. Developed by FCB Chicago in close partnership with the Chicago Hearing Society, Rakish, and the Academy of Motion Picture Arts and Sciences, which adopted it as a new standard for cinematic accessibility. | N4: closed-captioning, accessibility, typography, film, cinema, entertainment, societal-innovation, united-states, design-system, deaf-hard-of-hearing
A5: 2025 | B5: Gold | C5: Tree Correspondents | D5: Hyundai | E5: Hyundai Ioniq Forest | F5: FCB New York | G5: United States | H5: Curation of Data | I5: https://ascentialcdn.filespin.io/api/v1/conversion/82542e7381744bb783bb6c60f2929b2c | J5: vimeo:1109390480 | L5: https://www.lovethework.com/work/entries/tree-correspondents-762045 | M5: A data storytelling campaign in which individual trees — a Silver Fir in Czechia, a Juçara Palm in Brazil, a Tulip Tree in the United States — send first-person audio and written dispatches translated from their real environmental sensor data. Built to mark ten years of Hyundai's IONIQ Forest reforestation initiative, the work was developed with FCB New York and turns ecological monitoring data into voiced field reports narrated by the trees themselves. | N5: automotive, cars, transport, data-storytelling, audio, reforestation, environmental, united-states, brazil, czechia, branded-content
A6: 2025 | B6: Silver | C6: The Shaded Route | D6: HungerStation | E6: Hungerstation Delivery App | F6: VML | G6: Saudi Arabia | H6: Real-Time Usage & Targeting | I6: https://ascentialcdn.filespin.io/api/v1/conversion/a5387631458b48648c6dba4b21efb3d0 | J6: 5cGxg-wRzsE | L6: https://www.lovethework.com/work/entries/the-shaded-route-754725 | M6: A routing feature built into the HungerStation delivery app that calculates the shadiest path between pickup and drop-off points across Saudi Arabia — plotting roads and turns that maximize shade cover during each journey. The feature uses real-time sun position data alongside mapped building and infrastructure footprints to dynamically update routes as conditions change throughout the day. | N6: delivery-app, mobile-app, technology, data, real-time, rider-welfare, saudi-arabia, navigation, heat
A7: 2025 | B7: Silver | C7: Tree Correspondents | D7: Hyundai | E7: Hyundai Ioniq Forest | F7: FCB New York | G7: United States | H7: Technological Achievement in Digital Craft | I7: https://ascentialcdn.filespin.io/api/v1/conversion/82542e7381744bb783bb6c60f2929b2c | J7: vimeo:1109390480 | L7: https://www.lovethework.com/work/entries/tree-correspondents-762150 | M7: A data storytelling campaign in which individual trees — a Silver Fir in Czechia, a Juçara Palm in Brazil, a Tulip Tree in the United States — send first-person audio and written dispatches translated from their real environmental sensor data. Built to mark ten years of Hyundai's IONIQ Forest reforestation initiative, the work was developed with FCB New York and turns ecological monitoring data into voiced field reports narrated by the trees themselves. | N7: automotive, cars, transport, data-storytelling, audio, reforestation, environmental, united-states, brazil, czechia, branded-content
A8: 2025 | B8: Silver | C8: In Hot Water | D8: World Wildlife Fund (wwf) | E8: WWF | F8: Nomint | G8: United Kingdom | H8: Motion Graphics Design & Animation | I8: https://ascentialcdn.filespin.io/api/v1/conversion/f2ca9488d23e45d5b432ce4a6c2e8f08 | J8: vimeo:1028875237 | L8: https://www.lovethework.com/work/entries/in-hot-water-754526 | M8: A stop-motion film for WWF, made by NOMINT, shot entirely on a thermal camera — each frame built around 1,000 3D-printed replacement models heated to precise temperatures (accurate to 0.1°C) using ovens, heat guns, and freezing sprays, so that heat itself becomes the visual medium. Because figures began cooling the moment they left the oven, every shot was a race to position and capture each model before its thermal color shifted, with the most complex frames — a boy and a fish overlapping at slightly different temperatures — taking days to complete. The film was scored to a reworked version of Radiohead's "No Surprises," with additional production by Neil Barnes of Leftfield, and launched at COP29. | N8: non-profit, animation, stop-motion, thermal-camera, 3d-printing, ocean-conservation, climate, sustainability, environment, film, cinema, entertainment, united-kingdom, craft
A9: 2025 | B9: Silver | C9: Saltanat Light | D9: Citix | E9: Citix | F9: GForce | G9: Kazakhstan | H9: Real-Time Contextual Content | I9: https://ascentialcdn.filespin.io/api/v1/conversion/68f2c53ebcea42bd9ab7b58852b5aa95 | J9: POZJDa6y23g | L9: https://www.lovethework.com/work/entries/saltanat-light-764174 | M9: A network of digital out-of-home screens across Kazakhstan that dims its brightness in real time whenever a domestic violence call is made nearby — each darkening panel a live signal of an incident in that location. The campaign is named after Saltanat Nukenova, who was killed by her husband, former minister Kuandyk Bishimbayev, who was sentenced to 24 years in prison in May 2024. A companion Telegram bot extends the system, connecting people to available support resources. | N9: digital-out-of-home, ai, technology, domestic-violence, gender-equality, social-good, telegram, ambient, real-time, kazakhstan, citix
A10: 2025 | B10: Silver | C10: Daisy vs Scammers | D10: O2 | E10: Daisy vs Scammers | F10: VCCP | G10: United Kingdom | H10: Innovative Use of Technology | I10: https://ascentialcdn.filespin.io/api/v1/conversion/2d7855910ffa41a78e83fffe11540c7b | J10: tnfhe_XMg7U | L10: https://www.lovethework.com/work/entries/daisy-vs-scammers-754726 | M10: An AI-generated elderly woman named Daisy, built by O2 and VCCP to engage phone scammers in extended, rambling conversations — keeping them on the line and away from real potential victims. Daisy is deployed as a live phone persona, realistic enough to hold fraudsters in lengthy calls while collecting intelligence on active scam scripts, at a time when 7 in 10 people in the UK were being targeted by scammers. | N10: telecommunications, ai, technology, public-safety, conversational-ai, united-kingdom, use-of-technology, consumer-protection, voice
A11: 2025 | B11: Bronze | C11: Allevia Pollen Passport | D11: Opella-Allegra | E11: Allegra | F11: MRM Worldwide | G11: Spain | H11: Data Visualisation | I11: https://ascentialcdn.filespin.io/api/v1/conversion/5bdbab28251f44eda6fdb7d90fe1a6eb | J11: vimeo:1080313277 | L11: https://www.lovethework.com/work/entries/allevia-pollen-passport-754613 | M11: A travel-planning tool launched in January — peak holiday-booking season in the UK — that maps real-time and forecast pollen data against travel destinations, letting users see allergy risk levels before they book a trip. Built on the insight that climate change is extending allergy seasons beyond spring, the passport gave Allegra a presence in winter conversations where allergy brands rarely appear. | N11: allergy-medication, data-visualisation, mobile-app, digital, travel, tourism, spain, united-kingdom, seasonal-health, user-tool
A12: 2025 | B12: Bronze | C12: Apple 100 Best Albums | D12: Apple | E12: Apple Music | F12: TBWA\Media Arts Lab | G12: United States | H12: Digital Illustration & Image Design | I12: https://ascentialcdn.filespin.io/api/v1/conversion/c56cee379a1249b9912bbe50964ff0d2 | J12: vimeo:1039756308 | L12: https://www.lovethework.com/work/entries/apple-100-best-albums-754412 | M12: A series of digitally illustrated still-life compositions ranking 100 albums in Apple Music's canon, each rendering a physical artifact tied to the record — including a recreation of the minivan from Kendrick Lamar's *good kid, m.A.A.d city* (#7) cast in gold — dramatically lit against black to evoke a museum display case. Each piece pairs the object with its ranking number, treating the artifact as a stand-in for the album's cultural weight. The campaign was produced in partnership with Model Citizen, BeGrizzlee, and MNFST. | N12: apple-music, digital-illustration, series, music, entertainment, ooh, art-direction, united-states, streaming, tv
A13: 2025 | B13: Bronze | C13: The Odyssey of Wilson | D13: Vivo | E13: Telephone Company | F13: Africa Creative DDB | G13: Brazil | H13: Data Storytelling | I13: https://ascentialcdn.filespin.io/api/v1/conversion/d824fa39d9d94210af54fc45e5e11735 | J13: vimeo:1082349787 | L13: https://www.lovethework.com/work/entries/the-odissey-of-wilson-754689 | M13: An interactive data-storytelling platform built around Wilson — the volleyball from the film Cast Away — that traces a 450-year simulated ocean drift using real plastic-pollution datasets to show where the ball would travel and what marine damage it would cause along the way. Developed by Africa Creative DDB for Vivo in partnership with the Onda Azul Institute, the experience was timed to coincide with the UN Ocean Conference in Nice and aligned with UN Sustainable Development Goal 14: Life Below Water. | N13: telephone-company, data-storytelling, digital, interactive, ocean-pollution, film-reference, brazil, environmental, un-partnership
... A29: 2026 | B29: Silver | C29: The Birdwatcher | D29: Spoor | E29: AI-Powered Bird Monitoring for Wind Projects | F29: FP7 McCann | G29: United Arab Emirates | H29: Innovative Use of Technology | I29: https://ascentialcdn.filespin.io/api/v1/conversion/9a60a9386d6144adafe502c5491797d6 | J29: DbL7yAqIQaw | L29: https://www.lovethework.com/work/entries/the-birdwatcher-791041 | M29: A digital experience from AI wildlife-monitoring company Spoor that turns complex bird-monitoring data from wind farms into an open, accessible public record, making previously invisible bird activity visible to policymakers, industry and the public to show wind energy and wildlife can coexist. (Innovative Use of Technology entry.) | N29: spoor, wind energy, renewable energy, wildlife, birds, conservation, environment, sustainability, ai, technology, data, innovative use of technology, digital craft, fp7 mccann, united arab emirates

Sheet Film Craft
A1: Year | B1: Tier | C1: Campaign | D1: Brand | E1: Product/Service | F1: Agency | G1: Country | H1: Subcategory | I1: Image URL | J1: YouTube ID | K1: Campaign Group | L1: Entry URL | M1: Description | N1: Keywords
A2: 2025 | B2: Grand Prix | C2: Telstra - Better on a Better Network | D2: Telstra | E2: Telstra | F2: Bear Meets Eagle on Fire | G2: Australia | H2: Animation | I2: digital-presentation-images/film-craft-telstra-telstra-better-on-a-better-network.webp | J2: L8wOtakkr28 | L2: https://www.lovethework.com/work/entries/telstra-better-on-a-better-network-765315 | M2: A suite of 26 short films, each set in a different lesser-known regional town or remote area of Australia, brought to life through 56 puppets voiced by 42 actors — each film representing a local story and community that benefits from Telstra's network coverage. The spots aired across Channel 9's Olympics and Paralympics broadcast, replacing the single repeated sponsor spot with a rotating cast of regional characters and landscapes. | N2: telecommunications, film, cinema, entertainment, puppets, craft, regional, australia, broadcast, olympics, sport, multi-spot
A3: 2025 | B3: Gold | C3: Telstra - Better on a Better Network | D3: Telstra | E3: Telstra | F3: Bear Meets Eagle on Fire | G3: Australia | H3: Production Design/Art Direction | I3: digital-presentation-images/film-craft-telstra-telstra-better-on-a-better-network.webp | J3: L8wOtakkr28 | L3: https://www.lovethework.com/work/entries/telstra-better-on-a-better-network-765311 | M3: A suite of 26 short films, each set in a different lesser-known regional town or remote area of Australia, brought to life through 56 puppets voiced by 42 actors — each film representing a local story and community that benefits from Telstra's network coverage. The spots aired across Channel 9's Olympics and Paralympics broadcast, replacing the single repeated sponsor spot with a rotating cast of regional characters and landscapes. | N3: telecommunications, film, cinema, entertainment, puppets, craft, regional, australia, broadcast, olympics, sport, multi-spot
A4: 2025 | B4: Gold | C4: Considering What? | D4: Channel 4 | E4: Paralympics 2024 | F4: Work Editorial | G4: United Kingdom | H4: Editing | I4: digital-presentation-images/film-channel-4-paris-paralympic-2024-considering-what.webp | J4: bUs_mNTNwvE | L4: https://www.lovethework.com/work/entries/considering-what-765324 | M4: A broadcast and OOH campaign for Channel 4's Paris 2024 Paralympics coverage that crossed out patronising caveats — "She's incredibly fast for someone in a wheelchair," "He's so strong for someone so small" — with the athletes' actual performances, leaving the qualifying phrase struck through on billboards and in social posts. On social, the same condescending framing was applied to non-disabled Olympic athletes to expose how absurd the language sounds when directed at anyone. The film, made with 4Creative, personified the physical forces — gravity, wind, time — that all elite athletes face equally, regardless of disability. | N4: broadcaster, paralympics, ooh, film, cinema, entertainment, social, disability, sports, united-kingdom, typography
A5: 2025 | B5: Gold | C5: Guao Guao | D5: Desperados | E5: Desperados | F5: LePub | G5: Italy | H5: Casting | I5: digital-presentation-images/film-craft-desperados-guao-guao.webp | J5: N58e8-bziA0 | L5: https://www.lovethework.com/work/entries/guao-guao-765356 | M5: An original reggaeton track and brand film made in partnership with Colombian Grammy-winning producer Ovy on the Drums and Venezuelan rapper Micro TDH, created for Desperados — a tequila-infused beer positioned around Latin party culture — to respond to declining out-and-about social behavior among Gen Z in Europe. The brand film was cast entirely with non-Latin talent from Europe, China, India, and Africa to show that the energy of reggaeton crosses cultural identities, with casting as the central creative argument. | N5: beer, alcohol, music, entertainment, film, cinema, casting, reggaeton, europe, branded-content, italy, music-video, latin-culture
A6: 2025 | B6: Gold | C6: Find Your Friends | D6: Apple | E6: Precision Finding | F6: Apple | G6: United States | H6: Use of Licensed/Adapted Music | I6: digital-presentation-images/film-craft-apple-find-your-friends.webp | J6: vimeo:1068530073 | L6: https://www.lovethework.com/work/entries/find-your-friends-765322 | M6: A film shot at a Star Wars fan convention in which a lone attendee, dressed in Mandalorian armor, uses the Precision Finding feature on his iPhone 15 to locate his friends in a crowd of identically helmeted cosplayers. Designed and released on May 4th as a love letter to the fan community, the film's sound was built at Skywalker Sound and background signage was seeded with details for fans to decode. | N6: smartphone, film, cinema, entertainment, precision-finding, fan-culture, star-wars, cosplay, united-states, sound-design, casting
A7: 2025 | B7: Gold | C7: Paris Paralympics 2024: Considering What? | D7: Channel 4 | E7: Channel 4 | F7: Biscuit Filmworks | G7: United Kingdom | H7: Direction | I7: digital-presentation-images/film-channel-4-paris-paralympic-2024-considering-what.webp | J7: 2np3KfLrA_M | L7: https://www.lovethework.com/work/entries/paris-paralympics-2024-considering-what-765981 | M7: A Channel 4 campaign for the Paris 2024 Paralympic Games, made by in-house agency 4Creative and production company Biscuit Filmworks, built around the patronising language real viewers use about Paralympic athletes — phrases like "she's incredibly fast for someone in a wheelchair" and "amazing... considering" — which appeared as OOH billboards with the condescending caveats crossed out by the athletes' actual sporting achievements. On social, the same treatment was flipped: patronising comments typically aimed at Paralympians were redirected at non-disabled Olympians, exposing the double standard. The campaign responded to research showing that 60% of viewers still watch the Paralympics primarily to see athletes "overcome" their disabilities rather than compete as elite sportspeople. | N7: broadcaster, ooh, social-media, paralympics, disability, sport, film, cinema, entertainment, united-kingdom, 4creative
A8: 2025 | B8: Gold | C8: A Tale as Old as Websites | D8: Squarespace | E8: Squarespace | F8: Squarespace | G8: United States | H8: Direction | I8: digital-presentation-images/film-craft-squarespace-a-tale-as-old-as-websites.webp | J8: vimeo:1053465598 | L8: https://www.lovethework.com/work/entries/a-tale-as-old-as-websites-765346 | M8: A Super Bowl spot set in rural Ireland, where Barry Keoghan plays a door-to-door website deliveryman in a bygone era — riding on horseback and by donkey to bring freshly built Squarespace sites to farmers, pub owners, and wool knitters. The campaign extended beyond the game-day ad into short films, movie-style posters, a storybook, and a dedicated website for Keoghan's donkey co-star, Mosley. | N8: website-builder, super-bowl, television, film, cinema, entertainment, united-states, ireland, celebrity, consumer-services, period-setting, entrepreneurship
A9: 2025 | B9: Gold | C9: Donkey | D9: Telstra | E9: Telstra | F9: Revolver | G9: Australia | H9: Direction | I9: digital-presentation-images/film-craft-telstra-donkey.webp | J9: vimeo:1028285893 | L9: https://www.lovethework.com/work/entries/donkey-765344 | M9: A Christmas film following a donkey who accidentally becomes a singing star — touring venues, recording, and performing on stage — before homesickness pulls her back to her family. Directed by Revolver and crafted with Blockhead VFX, Rumble Studios, and The Editors, the spot anchors Telstra's seasonal retail period around the idea that family connection is the point of the holiday. | N9: telecommunications, film, cinema, entertainment, christmas, seasonal, australia, vfx, direction, animal-led
A10: 2025 | B10: Gold | C10: A$ap Rocky - Tailor Swif | D10: A$ap Rocky | E10: A$ap Rocky | F10: Iconoclast | G10: United States | H10: Direction | I10: https://ascentialcdn.filespin.io/api/v1/storyboard/7819511744634f7a81824e1b2a278ae1/storyboard_000008.jpg | J10: 5URefVYaJrA | L10: https://www.lovethework.com/work/entries/aap-rocky-tailor-swif-765317 | M10: A music video for A$AP Rocky's "Tailor Swif" shot on location in Kyiv, Ukraine by directors Vania Heymann and Gal Muggia, blending surreal, meme-sourced imagery with street-level urban scenes. The video was filmed roughly three years before its release, leaked multiple times in the interim, and was completed with VFX by Heymann and cinematography by Denys Lushchyk — a local Ukrainian crew referred to as the #sheltersquad. | N10: music-video, hip-hop, surreal, ukraine, united-states, direction, vfx, entertainment
A11: 2025 | B11: Gold | C11: Renault - Argentina | D11: Renault | E11: Renault E-Tech | F11: Publicis Conseil | G11: France | H11: Cinematography | I11: digital-presentation-images/film-craft-renault-renault-argentina.webp | J11: _n5ZDERgrdc | L11: https://www.lovethework.com/work/entries/renault-argentina-766426 | M11: An audiovisual film shot through the windows of Renault's different models across more than ten locations chosen for their geographic and symbolic spread — from Patagonia's southern landscapes to the picturesque corners of northern Argentina. The campaign draws on official data showing Renaults make up the largest share of cars on Argentina's roads, using that ubiquity to frame the film as a portrait of the country itself. | N11: automotive, cars, transport, film, cinema, entertainment, cinematography, branded-content, argentina, france, publicis-conseil, road-trip, heritage
A12: 2025 | B12: Silver | C12: Guao Guao | D12: Desperados | E12: Desperados | F12: LePub | G12: Italy | H12: Use of Original Music | I12: digital-presentation-images/film-craft-desperados-guao-guao.webp | J12: N58e8-bziA0 | L12: https://www.lovethework.com/work/entries/guao-guao-765357 | M12: An original reggaeton track and brand film made in partnership with Colombian Grammy-winning producer Ovy on the Drums and Venezuelan rapper Micro TDH, created for Desperados — a tequila-infused beer positioned around Latin party culture — to respond to declining out-and-about social behavior among Gen Z in Europe. The brand film was cast entirely with non-Latin talent from Europe, China, India, and Africa to show that the energy of reggaeton crosses cultural identities, with casting as the central creative argument. | N12: beer, alcohol, music, entertainment, film, cinema, casting, reggaeton, europe, branded-content, italy, music-video, latin-culture
A13: 2025 | B13: Silver | C13: Moments | D13: Volvo | E13: Volvo Ex90 | F13: Stendahls | G13: Sweden | H13: Editing | I13: https://ascentialcdn.filespin.io/api/v1/storyboard/346a403fc27b4b2db49c84361f4c8081/storyboard_000008.jpg | J13: cQX-QXxwGvA | L13: https://www.lovethework.com/work/entries/moments-765347 | M13: A film for the Volvo EX90, shot by cinematographer Hoyte van Hoytema, built around brief sensory moments — light, texture, motion — rather than a conventional product narrative. Created by Stendahls in collaboration with production company New Land in Sweden. | N13: automotive, cars, transport, film, cinema, entertainment, branded-content, editing, cinematography, sweden
A14: 2025 | B14: Silver | C14: Nike "sunshine" | D14: Nike | F14: Trafik | H14: Colour Correction/Grading | I14: https://ascentialcdn.filespin.io/api/v1/storyboard/b9ed0aae1ae84082882cb4a1ec460780/storyboard_000008.jpg | J14: vimeo:1010739490 | L14: https://www.lovethework.com/work/entries/nike-sunshine-765328 | M14: A colour-graded film from a series of three — "Sunshine," "Morning," and "Joy" — each shot to capture a distinct emotional texture of running, from the dread before a dawn alarm to the reluctant satisfaction after. Created by Wieden+Kennedy with colour work by Trafik's Daniel de Vue, the films launched timed to marathon season to reflect runners' complicated relationship with the sport. | N14: sportswear, film, cinema, entertainment, colour-grading, running, craft, wieden-kennedy
A15: 2025 | B15: Silver | C15: A Tale as Old as Websites | D15: Squarespace | E15: Squarespace | F15: Squarespace | G15: United States | H15: Casting | I15: digital-presentation-images/film-craft-squarespace-a-tale-as-old-as-websites.webp | J15: vimeo:1053465598 | L15: https://www.lovethework.com/work/entries/a-tale-as-old-as-websites-765331 | M15: A Super Bowl spot set in rural Ireland, where Barry Keoghan plays a door-to-door website deliveryman in a bygone era — riding on horseback and by donkey to bring freshly built Squarespace sites to farmers, pub owners, and wool knitters. The campaign extended beyond the game-day ad into short films, movie-style posters, a storybook, and a dedicated website for Keoghan's donkey co-star, Mosley. | N15: website-builder, super-bowl, television, film, cinema, entertainment, united-states, ireland, celebrity, consumer-services, period-setting, entrepreneurship
A16: 2025 | B16: Silver | C16: Flock | D16: Apple | E16: iPhone | F16: TBWA\Media Arts Lab | G16: United States | H16: Animation | I16: digital-presentation-images/film-craft-apple-flock.webp | J16: vimeo:1006144786 | L16: https://www.lovethework.com/work/entries/flock-765354 | M16: A dystopian short film, made by TBWA\Media Arts Lab, in which surveillance cameras built to look like birds and bats — pigeons, seagulls, ravens, owls, and bats, each crafted as physical models before being composited into live-action footage — hunt people's browsing data across everyday online moments. Safari's privacy protections intervene to scatter the flock, drawing a contrast between iPhone and browsers that monetize every click, swipe, and scroll. | N16: iphone, consumer-electronics, film, cinema, entertainment, privacy, vfx, creature-design, united-states, safari, online-tracking
A17: 2025 | B17: Silver | C17: Moments | D17: Volvo | E17: Volvo Ex90 | F17: Stendahls | G17: Sweden | H17: Cinematography | I17: https://ascentialcdn.filespin.io/api/v1/storyboard/346a403fc27b4b2db49c84361f4c8081/storyboard_000008.jpg | J17: cQX-QXxwGvA | L17: https://www.lovethework.com/work/entries/moments-765347 | M17: A film for the Volvo EX90, shot by cinematographer Hoyte van Hoytema, built around brief sensory moments — light, texture, motion — rather than a conventional product narrative. Created by Stendahls in collaboration with production company New Land in Sweden. | N17: automotive, cars, transport, film, cinema, entertainment, branded-content, editing, cinematography, sweden
A18: 2025 | B18: Silver | C18: In Hot Water | D18: World Wildlife Fund (wwf) | E18: WWF | F18: Nomint | G18: United Kingdom | H18: Animation | I18: digital-presentation-images/film-craft-world-wildlife-fund-wwf-in-hot-water.webp | J18: vimeo:1028875237 | L18: https://www.lovethework.com/work/entries/in-hot-water-765332 | M18: A stop-motion film for WWF, made by NOMINT, shot entirely on a thermal camera — each frame built around 1,000 3D-printed replacement models heated to precise temperatures (accurate to 0.1°C) using ovens, heat guns, and freezing sprays, so that heat itself becomes the visual medium. Because figures began cooling the moment they left the oven, every shot was a race to position and capture each model before its thermal color shifted, with the most complex frames — a boy and a fish overlapping at slightly different temperatures — taking days to complete. The film was scored to a reworked version of Radiohead's "No Surprises," with additional production by Neil Barnes of Leftfield, and launched at COP29. | N18: non-profit, animation, stop-motion, thermal-camera, 3d-printing, ocean-conservation, climate, sustainability, environment, film, cinema, entertainment, united-kingdom, craft
A19: 2025 | B19: Silver | C19: Donkey | D19: Telstra | E19: Telstra | F19: Revolver | G19: Australia | H19: Production Design/Art Direction | I19: digital-presentation-images/film-craft-telstra-donkey.webp | J19: vimeo:1028285893 | L19: https://www.lovethework.com/work/entries/donkey-765336 | M19: A Christmas film following a donkey who accidentally becomes a singing star — touring venues, recording, and performing on stage — before homesickness pulls her back to her family. Directed by Revolver and crafted with Blockhead VFX, Rumble Studios, and The Editors, the spot anchors Telstra's seasonal retail period around the idea that family connection is the point of the holiday. | N19: telecommunications, film, cinema, entertainment, christmas, seasonal, australia, vfx, direction, animal-led
A20: 2025 | B20: Silver | C20: Coffin | D20: Life360 | E20: Life360 | F20: Alto | G20: United States | H20: Direction | I20: https://ascentialcdn.filespin.io/api/v1/storyboard/3cd320dd9fcd4445a86f756e25d0402e/storyboard_000008.jpg | J20: vimeo:1023704952 | L20: https://www.lovethework.com/work/entries/coffin-765342 | M20: A film spot directed by Steve Ayson of MJZ in which a funeral goes catastrophically wrong when a coffin lid flies open and the body rolls out — played as dark comedy to illustrate what happens when families lose track of each other. The ad is one of three executions (alongside Coat and Curfew) created by Alto New York for Life360's "Family-Proof Your Family" platform, each staging a worst-case scenario rooted in the anxieties of family safety apps. | N20: family-safety-app, film, cinema, entertainment, dark-comedy, united-states, direction, alto-new-york, mjz
A21: 2025 | B21: Silver | C21: Renault - Argentina | D21: Renault | E21: Renault E-Tech | F21: Publicis Conseil | G21: France | H21: Production Design/Art Direction | I21: digital-presentation-images/film-craft-renault-renault-argentina.webp | J21: _n5ZDERgrdc | L21: https://www.lovethework.com/work/entries/renault-argentina-765345 | M21: An audiovisual film shot through the windows of Renault's different models across more than ten locations chosen for their geographic and symbolic spread — from Patagonia's southern landscapes to the picturesque corners of northern Argentina. The campaign draws on official data showing Renaults make up the largest share of cars on Argentina's roads, using that ubiquity to frame the film as a portrait of the country itself. | N21: automotive, cars, transport, film, cinema, entertainment, cinematography, branded-content, argentina, france, publicis-conseil, road-trip, heritage
A22: 2025 | B22: Silver | C22: A$ap Rocky - Tailor Swif | D22: A$ap Rocky | E22: A$ap Rocky | F22: Iconoclast | G22: United States | H22: Production Design/Art Direction | I22: https://ascentialcdn.filespin.io/api/v1/storyboard/7819511744634f7a81824e1b2a278ae1/storyboard_000008.jpg | J22: 5URefVYaJrA | L22: https://www.lovethework.com/work/entries/aap-rocky-tailor-swif-765343 | M22: A music video for A$AP Rocky's "Tailor Swif" shot on location in Kyiv, Ukraine by directors Vania Heymann and Gal Muggia, blending surreal, meme-sourced imagery with street-level urban scenes. The video was filmed roughly three years before its release, leaked multiple times in the interim, and was completed with VFX by Heymann and cinematography by Denys Lushchyk — a local Ukrainian crew referred to as the #sheltersquad. | N22: music-video, hip-hop, surreal, ukraine, united-states, direction, vfx, entertainment
A23: 2025 | B23: Silver | C23: Believe in Chicken | D23: KFC | E23: Food (fried Chicken) | F23: Mother | G23: United Kingdom | H23: Use of Original Music | I23: digital-presentation-images/film-craft-kfc-believe-in-chicken.webp | J23: vimeo:958338280 | L23: https://www.lovethework.com/work/entries/believe-in-chicken-765320 | M23: A film set in a surreal, quasi-religious world where devoted chicken believers gather in crowds before a giant rooster atop a stone plinth, competing to win a golden egg — the ultimate prize for the faithful. Directed by Vedran Rupic in partnership with Mother London, the campaign builds a recurring "cult of fandom" universe around KFC's fried chicken, with original music scored to match the epic, ceremonial tone. | N23: qsr, fast-food, restaurant, food, film, cinema, entertainment, original-music, united-kingdom, surrealism, branded-entertainment, cult-branding, fried-chicken
A24: 2025 | B24: Bronze | C24: Flock | D24: Apple | E24: iPhone | F24: TBWA\Media Arts Lab | G24: United States | H24: Editing | I24: digital-presentation-images/film-craft-apple-flock.webp | J24: vimeo:1006144786 | L24: https://www.lovethework.com/work/entries/flock-765363 | M24: A dystopian short film, made by TBWA\Media Arts Lab, in which surveillance cameras built to look like birds and bats — pigeons, seagulls, ravens, owls, and bats, each crafted as physical models before being composited into live-action footage — hunt people's browsing data across everyday online moments. Safari's privacy protections intervene to scatter the flock, drawing a contrast between iPhone and browsers that monetize every click, swipe, and scroll. | N24: iphone, consumer-electronics, film, cinema, entertainment, privacy, vfx, creature-design, united-states, safari, online-tracking
A25: 2025 | B25: Bronze | C25: Everything or Nothing | D25: Riyadh Season | E25: Boxing Fight | F25: Bigtime Creative Shop | G25: Saudi Arabia | H25: Production Design/Art Direction | I25: https://ascentialcdn.filespin.io/api/v1/storyboard/99b51143eb5a45779617eee2310c73e0/storyboard_000008.jpg | J25: vimeo:987240751 | L25: https://www.lovethework.com/work/entries/everything-or-nothing-765340 | M25: A long-form promotional film for Riyadh Season's boxing event, produced by BigTime Creative Shop in Saudi Arabia and ambitious enough in scope to be described as bordering on short-film length. The production design and art direction drove the piece's awards recognition, with the work earning a Grand Prix at Dubai Lynx. | N25: boxing, film, cinema, entertainment, production-design, art-direction, long-form, saudi-arabia, sports-event
